Workbook

Sheet README
A1: Discord Nitro subscription revenue model (portfolio project). All Discord figures are third-party estimates.
A2: Scenario: upside. Generated by nitro_model.excel_export from data/assumptions.csv; mirrors src/nitro_model/cohorts.py.
A3: Flow: Assumptions -> Params -> Curves / Eras / MAU / Prices / FX -> Adds -> Paid, Legacy, React -> Subs -> Revenue -> Checks.
A4: FY2025 is history (base values, Params hist.*). From Params!forecast_start_month_index the scenario's values apply to new sign-ups.
A5: Change inputs only on the Assumptions sheet (yellow cells on Params link there). Params!k_cal is solved in Python.
A6: Active subscribers = SUMPRODUCT(sign-ups to date, reversed survival curve). Cohort_US_NitroM shows one segment as a full triangle.
A7: Prices are fixed in local currency at FY2025 average FX; the FX sheet turns them into USD each month (Params!fx_shock_dir: +1 = USD 10% stronger).

Sheet Assumptions
A1: id | B1: group | C1: segment | D1: scenario | E1: value | F1: unit | G1: low | H1: high | I1: status | J1: source_ids | K1: as_of | L1: notes
A2: model_start_year | B2: timeline | C2: all | D2: all | E2: 2025 | F2: year | I2: design | J2: P01 | K2: 2026-10-27 | L2: FY2025 is the calibration year against public estimates
A3: model_start_month | B3: timeline | C3: all | D3: all | E3: 1 | F3: month | I3: design | J3: P01 | K3: 2026-10-27
A4: horizon_months | B4: timeline | C4: all | D4: all | E4: 72 | F4: months | I4: design | J4: P01 | K4: 2026-10-27 | L4: Jan 2025 to Dec 2030: 12 calibration months + 60 forecast months
A5: mau_jan2025 | B5: mau | C5: all | D5: all | E5: 225 | F5: M users | G5: 200 | H5: 260 | I5: proposed | J5: S06;S02;S03;A01 | K5: 2026-10-27 | L5: Discord says 200M+ (May 2025); trackers say 227.7M (2024) to 250-259M (2025). Start below tracker midpoint: trackers likely mix visits and registered users
A6: mau_share | B6: mau | C6: US_CA | D6: all | E6: 0.31 | F6: share | G6: 0.27 | H6: 0.35 | I6: proposed | J6: S07;A01 | K6: 2026-10-27 | L6: Semrush web traffic US 29.1% plus Canada. Caveat: web traffic misses desktop-app and mobile-app use so regional mix may skew; conv_rate by region absorbs part of the error
A7: mau_share | B7: mau | C7: EUROPE | D7: all | E7: 0.28 | F7: share | G7: 0.22 | H7: 0.32 | I7: proposed | J7: S07;A01 | K7: 2026-10-27 | L7: No direct Europe figure found; judgment from country traffic tail (DE/FR/UK/PL)
A8: mau_share | B8: mau | C8: LATAM | D8: all | E8: 0.14 | F8: share | G8: 0.1 | H8: 0.18 | I8: proposed | J8: S07;A01 | K8: 2026-10-27 | L8: Brazil 7.25% of traffic plus rest of LatAm
A9: mau_share | B9: mau | C9: APAC | D9: all | E9: 0.15 | F9: share | G9: 0.1 | H9: 0.2 | I9: proposed | J9: S07;A01 | K9: 2026-10-27 | L9: India 4.9% of traffic plus Japan/SEA/ANZ
A10: mau_share | B10: mau | C10: ROW | D10: all | E10: 0.12 | F10: share | G10: 0.08 | H10: 0.16 | I10: proposed | J10: S07;A01 | K10: 2026-10-27 | L10: Turkey, Russia, MENA, Africa
A11: mau_growth_2025 | B11: mau | C11: all | D11: all | E11: 0.1 | F11: YoY | G11: 0.06 | H11: 0.14 | I11: proposed | J11: S02;S03;A01 | K11: 2026-10-28 | L11: Tracker YoY 2024-25: 8.7% (Resourcera) to 13.8% (Feedough). Same in every scenario: FY2025 is the calibration year
A12: mau_growth_first | B12: mau | C12: all | D12: base | E12: 0.08 | F12: YoY | G12: 0.05 | H12: 0.11 | I12: proposed | J12: S02;S03;A01 | K12: 2026-10-28 | L12: Applies to 2026, the first forecast year; fades linearly to mau_growth_last by 2030
A13: mau_growth_first | B13: mau | C13: all | D13: upside | E13: 0.11 | F13: YoY | G13: 0.08 | H13: 0.14 | I13: proposed | J13: S02;A01 | K13: 2026-10-28 | L13: Near the high tracker growth rate
A14: mau_growth_first | B14: mau | C14: all | D14: downside | E14: 0.05 | F14: YoY | G14: 0.02 | H14: 0.08 | I14: proposed | J14: A01 | K14: 2026-10-28
A15: mau_growth_last | B15: mau | C15: all | D15: base | E15: 0.04 | F15: YoY | G15: 0.02 | H15: 0.06 | I15: proposed | J15: A01 | K15: 2026-10-27 | L15: Applies to 2030; linear fade from first-year growth
A16: mau_growth_last | B16: mau | C16: all | D16: upside | E16: 0.06 | F16: YoY | G16: 0.04 | H16: 0.08 | I16: proposed | J16: A01 | K16: 2026-10-27
A17: mau_growth_last | B17: mau | C17: all | D17: downside | E17: 0 | F17: YoY | G17: -0.03 | H17: 0.02 | I17: proposed | J17: A01 | K17: 2026-10-27 | L17: Flat MAU by 2030
A18: conv_rate | B18: conversion | C18: US_CA | D18: all | E18: 0.0045 | F18: gross adds / MAU / month | G18: 0.003 | H18: 0.006 | I18: proposed | J18: A01 | K18: 2026-10-27 | L18: Back-solved: ~0.65M gross adds/mo holds ~7.3M subs at a ~13-month blended lifetime. Split by willingness to pay. Recalibrated in M3
A19: conv_rate | B19: conversion | C19: EUROPE | D19: all | E19: 0.0032 | F19: gross adds / MAU / month | G19: 0.002 | H19: 0.0045 | I19: proposed | J19: A01 | K19: 2026-10-27
A20: conv_rate | B20: conversion | C20: LATAM | D20: all | E20: 0.0015 | F20: gross adds / MAU / month | G20: 0.0008 | H20: 0.0025 | I20: proposed | J20: A01 | K20: 2026-10-27
A21: conv_rate | B21: conversion | C21: APAC | D21: all | E21: 0.0018 | F21: gross adds / MAU / month | G21: 0.001 | H21: 0.0028 | I21: proposed | J21: A01 | K21: 2026-10-27
A22: conv_rate | B22: conversion | C22: ROW | D22: all | E22: 0.0015 | F22: gross adds / MAU / month | G22: 0.0008 | H22: 0.0025 | I22: proposed | J22: A01 | K22: 2026-10-27
A23: conv_multiplier | B23: conversion | C23: all | D23: base | E23: 1 | F23: x | I23: design | J23: P01 | K23: 2026-10-27
A24: conv_multiplier | B24: conversion | C24: all | D24: upside | E24: 1.1 | F24: x | G24: 1.05 | H24: 1.2 | I24: proposed | J24: A01 | K24: 2026-10-27
A25: conv_multiplier | B25: conversion | C25: all | D25: downside | E25: 0.9 | F25: x | G25: 0.8 | H25: 0.95 | I25: proposed | J25: A01 | K25: 2026-10-27
A26: plan_mix | B26: mix_plan | C26: NITRO_M | D26: all | E26: 0.45 | F26: share of gross adds | G26: 0.35 | H26: 0.55 | I26: proposed | J26: A01 | K26: 2026-10-27 | L26: No public plan mix. Drives most of the ARPU gap vs list price
A27: plan_mix | B27: mix_plan | C27: NITRO_A | D27: all | E27: 0.15 | F27: share of gross adds | G27: 0.08 | H27: 0.25 | I27: proposed | J27: S15;A01 | K27: 2026-10-27 | L27: Duolingo shows annual share can reach 47-71% when pushed hard; Discord does not push annual that hard
A28: plan_mix | B28: mix_plan | C28: BASIC_M | D28: all | E28: 0.32 | F28: share of gross adds | G28: 0.2 | H28: 0.45 | I28: proposed | J28: A01 | K28: 2026-10-27
A29: plan_mix | B29: mix_plan | C29: BASIC_A | D29: all | E29: 0.08 | F29: share of gross adds | G29: 0.03 | H29: 0.15 | I29: proposed | J29: A01 | K29: 2026-10-27
A30: platform_mix | B30: mix_platform | C30: US_CA|WEB | D30: all | E30: 0.55 | F30: share of gross adds | G30: 0.45 | H30: 0.65 | I30: proposed | J30: A01 | K30: 2026-10-27 | L30: Desktop-first product; web/desktop billing avoids app store fees
A31: platform_mix | B31: mix_platform | C31: US_CA|IOS | D31: all | E31: 0.3 | F31: share of gross adds | G31: 0.2 | H31: 0.4 | I31: proposed | J31: A01 | K31: 2026-10-27 | L31: High iPhone share in US
A32: platform_mix | B32: mix_platform | C32: US_CA|ANDROID | D32: all | E32: 0.15 | F32: share of gross adds | G32: 0.1 | H32: 0.2 | I32: proposed | J32: A01 | K32: 2026-10-27
A33: platform_mix | B33: mix_platform | C33: EUROPE|WEB | D33: all | E33: 0.6 | F33: share of gross adds | G33: 0.5 | H33: 0.7 | I33: proposed | J33: A01 | K33: 2026-10-27
A34: platform_mix | B34: mix_platform | C34: EUROPE|IOS | D34: all | E34: 0.22 | F34: share of gross adds | G34: 0.15 | H34: 0.3 | I34: proposed | J34: A01 | K34: 2026-10-27
A35: platform_mix | B35: mix_platform | C35: EUROPE|ANDROID | D35: all | E35: 0.18 | F35: share of gross adds | G35: 0.12 | H35: 0.25 | I35: proposed | J35: A01 | K35: 2026-10-27
A36: platform_mix | B36: mix_platform | C36: LATAM|WEB | D36: all | E36: 0.55 | F36: share of gross adds | G36: 0.45 | H36: 0.65 | I36: proposed | J36: A01 | K36: 2026-10-27
A37: platform_mix | B37: mix_platform | C37: LATAM|IOS | D37: all | E37: 0.1 | F37: share of gross adds | G37: 0.05 | H37: 0.15 | I37: proposed | J37: A01 | K37: 2026-10-27 | L37: Android-dominant region
A38: platform_mix | B38: mix_platform | C38: LATAM|ANDROID | D38: all | E38: 0.35 | F38: share of gross adds | G38: 0.25 | H38: 0.45 | I38: proposed | J38: A01 | K38: 2026-10-27
A39: platform_mix | B39: mix_platform | C39: APAC|WEB | D39: all | E39: 0.55 | F39: share of gross adds | G39: 0.45 | H39: 0.65 | I39: proposed | J39: A01 | K39: 2026-10-27
A40: platform_mix | B40: mix_platform | C40: APAC|IOS | D40: all | E40: 0.2 | F40: share of gross adds | G40: 0.1 | H40: 0.3 | I40: proposed | J40: A01 | K40: 2026-10-27 | L40: Japan iOS-heavy; India Android-heavy
A41: platform_mix | B41: mix_platform | C41: APAC|ANDROID | D41: all | E41: 0.25 | F41: share of gross adds | G41: 0.15 | H41: 0.35 | I41: proposed | J41: A01 | K41: 2026-10-27
A42: platform_mix | B42: mix_platform | C42: ROW|WEB | D42: all | E42: 0.55 | F42: share of gross adds | G42: 0.45 | H42: 0.65 | I42: proposed | J42: A01 | K42: 2026-10-27
A43: platform_mix | B43: mix_platform | C43: ROW|IOS | D43: all | E43: 0.15 | F43: share of gross adds | G43: 0.1 | H43: 0.2 | I43: proposed | J43: A01 | K43: 2026-10-27
A44: platform_mix | B44: mix_platform | C44: ROW|ANDROID | D44: all | E44: 0.3 | F44: share of gross adds | G44: 0.2 | H44: 0.4 | I44: proposed | J44: A01 | K44: 2026-10-27
A45: churn_m1 | B45: churn | C45: MONTHLY | D45: base | E45: 0.3 | F45: share of cohort | G45: 0.25 | H45: 0.35 | I45: benchmark | J45: S13;S16;A01 | K45: 2026-10-27 | L45: Base = Spotify global average plus RevenueCat app benchmarks. Applies to paid starts (direct or converted trialists); trial drop-off is trial_to_paid
A46: churn_m1 | B46: churn | C46: MONTHLY | D46: upside | E46: 0.22 | F46: share of cohort | G46: 0.18 | H46: 0.26 | I46: benchmark | J46: S14;A01 | K46: 2026-10-27 | L46: Upside = Spotify mature markets (US 1-2% tail)
A47: churn_m1 | B47: churn | C47: MONTHLY | D47: downside | E47: 0.4 | F47: share of cohort | G47: 0.35 | H47: 0.5 | I47: benchmark | J47: S15;S16;A01 | K47: 2026-10-27 | L47: Downside = Duolingo monthly (9% renew at 12 mo) / RevenueCat expensive monthly (6.7%)
A48: churn_m2 | B48: churn | C48: MONTHLY | D48: base | E48: 0.14 | F48: share of survivors | G48: 0.1 | H48: 0.18 | I48: benchmark | J48: S13;S16;A01 | K48: 2026-10-27
A49: churn_m2 | B49: churn | C49: MONTHLY | D49: upside | E49: 0.1 | F49: share of survivors | G49: 0.07 | H49: 0.13 | I49: benchmark | J49: S14;A01 | K49: 2026-10-27
A50: churn_m2 | B50: churn | C50: MONTHLY | D50: downside | E50: 0.2 | F50: share of survivors | G50: 0.15 | H50: 0.25 | I50: benchmark | J50: S15;S16;A01 | K50: 2026-10-27
A51: churn_m3 | B51: churn | C51: MONTHLY | D51: base | E51: 0.09 | F51: share of survivors | G51: 0.06 | H51: 0.12 | I51: benchmark | J51: S13;S16;A01 | K51: 2026-10-27
A52: churn_m3 | B52: churn | C52: MONTHLY | D52: upside | E52: 0.06 | F52: share of survivors | G52: 0.04 | H52: 0.08 | I52: benchmark | J52: S14;A01 | K52: 2026-10-27
A53: churn_m3 | B53: churn | C53: MONTHLY | D53: downside | E53: 0.12 | F53: share of survivors | G53: 0.09 | H53: 0.16 | I53: benchmark | J53: S15;S16;A01 | K53: 2026-10-27
A54: churn_tail | B54: churn | C54: MONTHLY | D54: base | E54: 0.05 | F54: share of survivors / month | G54: 0.039 | H54: 0.06 | I54: benchmark | J54: S13;S14 | K54: 2026-10-27 | L54: Spotify Premium 4.8% (Q4'19) and 3.9% (2021 avg); Nitro is more discretionary so slightly higher
A55: churn_tail | B55: churn | C55: MONTHLY | D55: upside | E55: 0.03 | F55: share of survivors / month | G55: 0.02 | H55: 0.039 | I55: benchmark | J55: S14 | K55: 2026-10-27 | L55: Spotify mature markets 1-2%; Nitro set above that
A56: churn_tail | B56: churn | C56: MONTHLY | D56: downside | E56: 0.08 | F56: share of survivors / month | G56: 0.06 | H56: 0.1 | I56: benchmark | J56: S13;S15 | K56: 2026-10-27 | L56: Early Spotify (7.5% Q4'15); Duolingo monthly 4.5-month average lifetime
A57: annual_renewal_first | B57: churn | C57: ANNUAL | D57: base | E57: 0.45 | F57: share renewing | G57: 0.36 | H57: 0.55 | I57: benchmark | J57: S15;S16 | K57: 2026-10-27 | L57: Duolingo ~40% first renewal; RevenueCat cheap annual up to 36%. Nitro set slightly above as a habit product
A58: annual_renewal_first | B58: churn | C58: ANNUAL | D58: upside | E58: 0.55 | F58: share renewing | G58: 0.45 | H58: 0.65 | I58: benchmark | J58: S15;A01 | K58: 2026-10-27
A59: annual_renewal_first | B59: churn | C59: ANNUAL | D59: downside | E59: 0.35 | F59: share renewing | G59: 0.3 | H59: 0.4 | I59: benchmark | J59: S16 | K59: 2026-10-27
A60: annual_renewal_later | B60: churn | C60: ANNUAL | D60: base | E60: 0.65 | F60: share renewing | G60: 0.55 | H60: 0.75 | I60: proposed | J60: A01 | K60: 2026-10-27 | L60: No public second-renewal data found; tenured renewers are stickier
A61: annual_renewal_later | B61: churn | C61: ANNUAL | D61: upside | E61: 0.75 | F61: share renewing | G61: 0.65 | H61: 0.85 | I61: proposed | J61: A01 | K61: 2026-10-27
A62: annual_renewal_later | B62: churn | C62: ANNUAL | D62: downside | E62: 0.55 | F62: share renewing | G62: 0.45 | H62: 0.65 | I62: proposed | J62: A01 | K62: 2026-10-27
A63: react_rate | B63: reactivation | C63: all | D63: base | E63: 0.015 | F63: share of churned pool / month | G63: 0.005 | H63: 0.03 | I63: proposed | J63: A01 | K63: 2026-10-27 | L63: No public win-back data; churned users within the window return at this rate
A64: react_rate | B64: reactivation | C64: all | D64: upside | E64: 0.02 | F64: share of churned pool / month | G64: 0.01 | H64: 0.03 | I64: proposed | J64: A01 | K64: 2026-10-27
A65: react_rate | B65: reactivation | C65: all | D65: downside | E65: 0.01 | F65: share of churned pool / month | G65: 0.005 | H65: 0.02 | I65: proposed | J65: A01 | K65: 2026-10-27
A66: react_window_months | B66: reactivation | C66: all | D66: all | E66: 24 | F66: months | G66: 12 | H66: 36 | I66: proposed | J66: A01 | K66: 2026-10-27 | L66: Churned users older than this drop out of the pool
A67: react_churn_tail | B67: reactivation | C67: all | D67: all | E67: 0.07 | F67: share of survivors / month | G67: 0.05 | H67: 0.1 | I67: proposed | J67: A01 | K67: 2026-10-27 | L67: Reactivated users rejoin on monthly plans; flatter than new-user month-1 churn but above base tail
A68: open_subs | B68: opening_book | C68: all | D68: all | E68: 6.75 | F68: M subscribers | G68: 6 | H68: 7.3 | I68: derived | J68: S01;S02;S03 | K68: 2026-10-27 | L68: Jan 2025 book = 7.3M mid-2025 / 1.17^0.5 (17% YoY growth per Feedough)
A69: open_plan_mix | B69: opening_book | C69: NITRO_M | D69: all | E69: 0.4 | F69: share | G69: 0.3 | H69: 0.5 | I69: proposed | J69: A01 | K69: 2026-10-27 | L69: Tenured book skews to annual vs gross adds
A70: open_plan_mix | B70: opening_book | C70: NITRO_A | D70: all | E70: 0.22 | F70: share | G70: 0.12 | H70: 0.3 | I70: proposed | J70: A01 | K70: 2026-10-27
A71: open_plan_mix | B71: opening_book | C71: BASIC_M | D71: all | E71: 0.28 | F71: share | G71: 0.2 | H71: 0.4 | I71: proposed | J71: A01 | K71: 2026-10-27
A72: open_plan_mix | B72: opening_book | C72: BASIC_A | D72: all | E72: 0.1 | F72: share | G72: 0.05 | H72: 0.15 | I72: proposed | J72: A01 | K72: 2026-10-27
A73: open_region_mix | B73: opening_book | C73: US_CA | D73: all | E73: 0.45 | F73: share | G73: 0.38 | H73: 0.52 | I73: proposed | J73: A01 | K73: 2026-10-27 | L73: Payers skew to high-income regions vs MAU mix
A74: open_region_mix | B74: opening_book | C74: EUROPE | D74: all | E74: 0.3 | F74: share | G74: 0.25 | H74: 0.35 | I74: proposed | J74: A01 | K74: 2026-10-27
A75: open_region_mix | B75: opening_book | C75: LATAM | D75: all | E75: 0.08 | F75: share | G75: 0.05 | H75: 0.12 | I75: proposed | J75: A01 | K75: 2026-10-27
A76: open_region_mix | B76: opening_book | C76: APAC | D76: all | E76: 0.1 | F76: share | G76: 0.06 | H76: 0.14 | I76: proposed | J76: A01 | K76: 2026-10-27
A77: open_region_mix | B77: opening_book | C77: ROW | D77: all | E77: 0.07 | F77: share | G77: 0.04 | H77: 0.1 | I77: proposed | J77: A01 | K77: 2026-10-27
A78: open_y1_share | B78: opening_book | C78: all | D78: all | E78: 0.35 | F78: share of book in first year of tenure | G78: 0.25 | H78: 0.45 | I78: proposed | J78: A01 | K78: 2026-10-28 | L78: Drives the Apple 30% vs 15% fee split for the opening book only; new cohorts get tenure from the cohort engine
A79: open_churn_tail | B79: opening_book | C79: MONTHLY | D79: all | E79: 0.035 | F79: share / month | G79: 0.025 | H79: 0.05 | I79: benchmark | J79: S13;S14 | K79: 2026-10-27 | L79: Tenured monthly subscribers: between Spotify global (3.9%) and mature (1-2%). Same in every scenario: the opening book keeps base behavior
A80: list_price | B80: pricing | C80: NITRO_M | D80: all | E80: 9.99 | F80: USD / month | I80: verified | J80: S08;S09 | K80: 2026-07-01 | L80: US list price; unchanged for years
A81: list_price | B81: pricing | C81: NITRO_A | D81: all | E81: 99.99 | F81: USD / year | I81: verified | J81: S08;S09 | K81: 2026-07-01 | L81: ~17% below 12x monthly
A82: list_price | B82: pricing | C82: BASIC_M | D82: all | E82: 2.99 | F82: USD / month | I82: verified | J82: S08;S09 | K82: 2026-07-01
A83: list_price | B83: pricing | C83: BASIC_A | D83: all | E83: 29.99 | F83: USD / year | I83: verified | J83: S08;S09 | K83: 2026-07-01
A84: price_index | B84: pricing | C84: US_CA | D84: all | E84: 1 | F84: x US price in USD at 2025 avg FX | I84: design | J84: P01 | K84: 2026-10-27 | L84: Reference market
A85: price_index | B85: pricing | C85: EUROPE | D85: all | E85: 1.1 | F85: x US price in USD at 2025 avg FX | G85: 1 | H85: 1.15 | I85: proposed | J85: A01 | K85: 2026-10-27 | L85: Assumes EUR 9.99 VAT-inclusive (~$11.30 at 2025 avg FX). EUR price NOT verified: check at checkout
A86: price_index | B86: pricing | C86: LATAM | D86: all | E86: 0.45 | F86: x US price in USD at 2025 avg FX | G86: 0.3 | H86: 0.6 | I86: proposed | J86: S10;A01 | K86: 2026-10-27 | L86: Localized pricing exists in Brazil per forum posts; level unverified
A87: price_index | B87: pricing | C87: APAC | D87: all | E87: 0.75 | F87: x US price in USD at 2025 avg FX | G87: 0.5 | H87: 1 | I87: proposed | J87: S10;A01 | K87: 2026-10-27 | L87: Japan localized; India reportedly not localized (~INR 850 = ~$10)
A88: price_index | B88: pricing | C88: ROW | D88: all | E88: 0.6 | F88: x US price in USD at 2025 avg FX | G88: 0.3 | H88: 0.8 | I88: proposed | J88: S10;A01 | K88: 2026-10-27 | L88: Turkey ~$3.20 per forum anecdote; RoW blends deep and no discounts
A89: indirect_tax | B89: pricing | C89: US_CA | D89: all | E89: 0 | F89: share of gross price | I89: design | J89: P01 | K89: 2026-10-27 | L89: US sales tax is added on top of list price so it is not in revenue
A90: indirect_tax | B90: pricing | C90: EUROPE | D90: all | E90: 0.167 | F90: share of gross price | G90: 0.15 | H90: 0.18 | I90: proposed | J90: A01 | K90: 2026-10-27 | L90: Prices shown VAT-inclusive. A ~20% VAT rate removes 0.20/1.20 = 16.7% of the gross price; EU rates run 17-27%
A91: indirect_tax | B91: pricing | C91: LATAM | D91: all | E91: 0.12 | F91: share of gross price | G91: 0.05 | H91: 0.2 | I91: proposed | J91: A01 | K91: 2026-10-27 | L91: Digital services taxes vary by country
A92: indirect_tax | B92: pricing | C92: APAC | D92: all | E92: 0.1 | F92: share of gross price | G92: 0.05 | H92: 0.15 | I92: proposed | J92: A01 | K92: 2026-10-27 | L92: Japan consumption tax 10%; India GST 18%
A93: indirect_tax | B93: pricing | C93: ROW | D93: all | E93: 0.1 | F93: share of gross price | G93: 0.05 | H93: 0.2 | I93: proposed | J93: A01 | K93: 2026-10-27
A94: trial_share | B94: promo | C94: all | D94: all | E94: 0.15 | F94: share of gross adds starting on a free trial | G94: 0 | H94: 0.4 | I94: proposed | J94: A01 | K94: 2026-10-28 | L94: Partner promos and free trial months. Trialists pay $0 while in trial, then convert or leave
A95: trial_months | B95: promo | C95: all | D95: all | E95: 1 | F95: months | G95: 1 | H95: 3 | I95: proposed | J95: A01 | K95: 2026-10-28 | L95: Length of the free period
A96: trial_to_paid | B96: promo | C96: all | D96: base | E96: 0.4 | F96: share of trialists converting to paid | G96: 0.25 | H96: 0.6 | I96: proposed | J96: S16;A01 | K96: 2026-10-28 | L96: No public Discord rate. RevenueCat (S16) shows trial conversion clusters at install day but the rate is not in the public preview
A97: trial_to_paid | B97: promo | C97: all | D97: upside | E97: 0.5 | F97: share of trialists converting to paid | G97: 0.25 | H97: 0.6 | I97: proposed | J97: A01 | K97: 2026-10-28
A98: trial_to_paid | B98: promo | C98: all | D98: downside | E98: 0.3 | F98: share of trialists converting to paid | G98: 0.25 | H98: 0.6 | I98: proposed | J98: A01 | K98: 2026-10-28
A99: count_trials_as_subs | B99: promo | C99: all | D99: all | E99: 1 | F99: flag | G99: 0 | H99: 1 | I99: proposed | J99: S13;A01 | K99: 2026-10-28 | L99: Definition: does the 7.3M anchor count trialists? Spotify counts trialists as subscribers (S13). Unknown for the third-party Discord figure
A100: avg_discount | B100: promo | C100: all | D100: all | E100: 0.05 | F100: share of list price | G100: 0 | H100: 0.15 | I100: proposed | J100: A01 | K100: 2026-10-27 | L100: Average discount on paying subscribers (sale pricing; first-month offers)
...

Sheet Params
A1: param | B1: value | C1: linked to
A2: mau0 | B2: =Assumptions!$E$5*1e+06 | C2: mau_jan2025[all]
A3: mau_growth_2025 | B3: =Assumptions!$E$11 | C3: mau_growth_2025[all]
A4: mau_growth_first | B4: =Assumptions!$E$13 | C4: mau_growth_first[all]
A5: mau_growth_last | B5: =Assumptions!$E$16 | C5: mau_growth_last[all]
A6: trial_months | B6: =Assumptions!$E$95 | C6: trial_months[all]
A7: count_trials_as_subs | B7: =Assumptions!$E$99 | C7: count_trials_as_subs[all]
A8: forecast_start_month_index | B8: =Assumptions!$E$122 | C8: forecast_start_month_index[all]
A9: exp_enabled | B9: =Assumptions!$E$129 | C9: exp_enabled[all]
A10: exp_start_month_index | B10: =Assumptions!$E$130 | C10: exp_start_month_index[all]
A11: exp_conv_lift | B11: =Assumptions!$E$131 | C11: exp_conv_lift[all]
A12: exp_churn_change | B12: =Assumptions!$E$132 | C12: exp_churn_change[all]
A13: exp_price_change | B13: =Assumptions!$E$133 | C13: exp_price_change[all]
A14: open_subs | B14: =Assumptions!$E$68*1e+06 | C14: open_subs[all]
A15: open_churn_tail | B15: =Assumptions!$E$79 | C15: open_churn_tail[MONTHLY]
A16: open_y1_share | B16: =Assumptions!$E$78 | C16: open_y1_share[all]
A17: avg_discount | B17: =Assumptions!$E$100 | C17: avg_discount[all]
A18: fee_web | B18: =Assumptions!$E$104 | C18: store_fee[WEB]
A19: fee_ios_y1 | B19: =Assumptions!$E$101 | C19: store_fee[IOS_Y1]
A20: fee_ios_later | B20: =Assumptions!$E$102 | C20: store_fee[IOS_LATER]
A21: fee_android | B21: =Assumptions!$E$103 | C21: store_fee[ANDROID]
A22: cal_target_subs | B22: =Assumptions!$E$134*1e+06 | C22: cal_subs_mid2025[all]
A23: cal_month_index | B23: =Assumptions!$E$135 | C23: cal_month_index[all]
A24: fx_shock | B24: =Assumptions!$E$128 | C24: fx_shock[all]
A25: fx_spot_month_index | B25: =Assumptions!$E$121 | C25: fx_spot_month_index[all]
A26: hist.conv_multiplier | B26: =Assumptions!$E$23 | C26: conv_multiplier[all]
A27: conv_multiplier | B27: =Assumptions!$E$24 | C27: conv_multiplier[all]
A28: hist.trial_share | B28: =Assumptions!$E$94 | C28: trial_share[all]
A29: trial_share | B29: =Assumptions!$E$94 | C29: trial_share[all]
A30: hist.trial_to_paid | B30: =Assumptions!$E$96 | C30: trial_to_paid[all]
A31: trial_to_paid | B31: =Assumptions!$E$97 | C31: trial_to_paid[all]
A32: hist.churn_m1 | B32: =Assumptions!$E$45 | C32: churn_m1[MONTHLY]
A33: churn_m1 | B33: =Assumptions!$E$46 | C33: churn_m1[MONTHLY]
A34: hist.churn_m2 | B34: =Assumptions!$E$48 | C34: churn_m2[MONTHLY]
A35: churn_m2 | B35: =Assumptions!$E$49 | C35: churn_m2[MONTHLY]
A36: hist.churn_m3 | B36: =Assumptions!$E$51 | C36: churn_m3[MONTHLY]
A37: churn_m3 | B37: =Assumptions!$E$52 | C37: churn_m3[MONTHLY]
A38: hist.churn_tail | B38: =Assumptions!$E$54 | C38: churn_tail[MONTHLY]
A39: churn_tail | B39: =Assumptions!$E$55 | C39: churn_tail[MONTHLY]
A40: hist.annual_renewal_first | B40: =Assumptions!$E$57 | C40: annual_renewal_first[ANNUAL]
A41: annual_renewal_first | B41: =Assumptions!$E$58 | C41: annual_renewal_first[ANNUAL]
A42: hist.annual_renewal_later | B42: =Assumptions!$E$60 | C42: annual_renewal_later[ANNUAL]
A43: annual_renewal_later | B43: =Assumptions!$E$61 | C43: annual_renewal_later[ANNUAL]
A44: hist.react_rate | B44: =Assumptions!$E$63 | C44: react_rate[all]
A45: react_rate | B45: =Assumptions!$E$64 | C45: react_rate[all]
A46: hist.react_window_months | B46: =Assumptions!$E$66 | C46: react_window_months[all]
A47: react_window_months | B47: =Assumptions!$E$66 | C47: react_window_months[all]
A48: hist.react_churn_tail | B48: =Assumptions!$E$67 | C48: react_churn_tail[all]
A49: react_churn_tail | B49: =Assumptions!$E$67 | C49: react_churn_tail[all]
A50: cal_rev_low | B50: =Assumptions!$G$137*1000000 | C50: cal_nitro_rev_2025 low
A51: cal_rev_high | B51: =Assumptions!$H$137*1000000 | C51: cal_nitro_rev_2025 high
A52: mau_share[US_CA] | B52: =Assumptions!$E$6 | C52: mau_share[US_CA]
A53: mau_share[EUROPE] | B53: =Assumptions!$E$7 | C53: mau_share[EUROPE]
A54: mau_share[LATAM] | B54: =Assumptions!$E$8 | C54: mau_share[LATAM]
A55: mau_share[APAC] | B55: =Assumptions!$E$9 | C55: mau_share[APAC]
A56: mau_share[ROW] | B56: =Assumptions!$E$10 | C56: mau_share[ROW]
A57: conv_rate[US_CA] | B57: =Assumptions!$E$18 | C57: conv_rate[US_CA]
A58: conv_rate[EUROPE] | B58: =Assumptions!$E$19 | C58: conv_rate[EUROPE]
A59: conv_rate[LATAM] | B59: =Assumptions!$E$20 | C59: conv_rate[LATAM]
A60: conv_rate[APAC] | B60: =Assumptions!$E$21 | C60: conv_rate[APAC]
A61: conv_rate[ROW] | B61: =Assumptions!$E$22 | C61: conv_rate[ROW]
A62: price_index[US_CA] | B62: =Assumptions!$E$84 | C62: price_index[US_CA]
A63: price_index[EUROPE] | B63: =Assumptions!$E$85 | C63: price_index[EUROPE]
A64: price_index[LATAM] | B64: =Assumptions!$E$86 | C64: price_index[LATAM]
A65: price_index[APAC] | B65: =Assumptions!$E$87 | C65: price_index[APAC]
A66: price_index[ROW] | B66: =Assumptions!$E$88 | C66: price_index[ROW]
A67: indirect_tax[US_CA] | B67: =Assumptions!$E$89 | C67: indirect_tax[US_CA]
A68: indirect_tax[EUROPE] | B68: =Assumptions!$E$90 | C68: indirect_tax[EUROPE]
A69: indirect_tax[LATAM] | B69: =Assumptions!$E$91 | C69: indirect_tax[LATAM]
A70: indirect_tax[APAC] | B70: =Assumptions!$E$92 | C70: indirect_tax[APAC]
A71: indirect_tax[ROW] | B71: =Assumptions!$E$93 | C71: indirect_tax[ROW]
A72: open_region_mix[US_CA] | B72: =Assumptions!$E$73 | C72: open_region_mix[US_CA]
A73: open_region_mix[EUROPE] | B73: =Assumptions!$E$74 | C73: open_region_mix[EUROPE]
A74: open_region_mix[LATAM] | B74: =Assumptions!$E$75 | C74: open_region_mix[LATAM]
A75: open_region_mix[APAC] | B75: =Assumptions!$E$76 | C75: open_region_mix[APAC]
A76: open_region_mix[ROW] | B76: =Assumptions!$E$77 | C76: open_region_mix[ROW]
A77: platform_mix[US_CA|WEB] | B77: =Assumptions!$E$30 | C77: platform_mix[US_CA|WEB]
A78: platform_mix[US_CA|IOS] | B78: =Assumptions!$E$31 | C78: platform_mix[US_CA|IOS]
A79: platform_mix[US_CA|ANDROID] | B79: =Assumptions!$E$32 | C79: platform_mix[US_CA|ANDROID]
A80: platform_mix[EUROPE|WEB] | B80: =Assumptions!$E$33 | C80: platform_mix[EUROPE|WEB]
A81: platform_mix[EUROPE|IOS] | B81: =Assumptions!$E$34 | C81: platform_mix[EUROPE|IOS]
A82: platform_mix[EUROPE|ANDROID] | B82: =Assumptions!$E$35 | C82: platform_mix[EUROPE|ANDROID]
A83: platform_mix[LATAM|WEB] | B83: =Assumptions!$E$36 | C83: platform_mix[LATAM|WEB]
A84: platform_mix[LATAM|IOS] | B84: =Assumptions!$E$37 | C84: platform_mix[LATAM|IOS]
A85: platform_mix[LATAM|ANDROID] | B85: =Assumptions!$E$38 | C85: platform_mix[LATAM|ANDROID]
A86: platform_mix[APAC|WEB] | B86: =Assumptions!$E$39 | C86: platform_mix[APAC|WEB]
A87: platform_mix[APAC|IOS] | B87: =Assumptions!$E$40 | C87: platform_mix[APAC|IOS]
A88: platform_mix[APAC|ANDROID] | B88: =Assumptions!$E$41 | C88: platform_mix[APAC|ANDROID]
A89: platform_mix[ROW|WEB] | B89: =Assumptions!$E$42 | C89: platform_mix[ROW|WEB]
A90: platform_mix[ROW|IOS] | B90: =Assumptions!$E$43 | C90: platform_mix[ROW|IOS]
A91: platform_mix[ROW|ANDROID] | B91: =Assumptions!$E$44 | C91: platform_mix[ROW|ANDROID]
A92: plan_mix[NITRO_M] | B92: =Assumptions!$E$26 | C92: plan_mix[NITRO_M]
A93: plan_mix[NITRO_A] | B93: =Assumptions!$E$27 | C93: plan_mix[NITRO_A]
A94: plan_mix[BASIC_M] | B94: =Assumptions!$E$28 | C94: plan_mix[BASIC_M]
A95: plan_mix[BASIC_A] | B95: =Assumptions!$E$29 | C95: plan_mix[BASIC_A]
A96: open_plan_mix[NITRO_M] | B96: =Assumptions!$E$69 | C96: open_plan_mix[NITRO_M]
A97: open_plan_mix[NITRO_A] | B97: =Assumptions!$E$70 | C97: open_plan_mix[NITRO_A]
A98: open_plan_mix[BASIC_M] | B98: =Assumptions!$E$71 | C98: open_plan_mix[BASIC_M]
A99: open_plan_mix[BASIC_A] | B99: =Assumptions!$E$72 | C99: open_plan_mix[BASIC_A]
A100: list_price[NITRO_M] | B100: =Assumptions!$E$80 | C100: list_price[NITRO_M]
...

Sheet Curves
A1: curve | B1: age (months) -> | C1: 0 | D1: 1 | E1: 2 | F1: 3 | G1: 4 | H1: 5 | I1: 6 | J1: 7 | K1: 8 | L1: 9 | M1: 10 | N1: 11 | O1: 12 | P1: 13 | Q1: 14 | R1: 15 | S1: 16 | T1: 17 | U1: 18 | V1: 19 | W1: 20 | X1: 21 | Y1: 22 | Z1: 23 | AA1: 24 | AB1: 25 | AC1: 26 | AD1: 27 | AE1: 28 | AF1: 29 | AG1: 30 | AH1: 31 | AI1: 32 | AJ1: 33 | AK1: 34 | AL1: 35 | AM1: 36 | AN1: 37 | AO1: 38 | AP1: 39 | AQ1: 40 | AR1: 41 | AS1: 42 | AT1: 43 | AU1: 44 | AV1: 45 | AW1: 46 | AX1: 47 | AY1: 48 | AZ1: 49 | BA1: 50 | BB1: 51 | BC1: 52 | BD1: 53 | BE1: 54 | BF1: 55 | BG1: 56 | BH1: 57 | BI1: 58 | BJ1: 59 | BK1: 60 | BL1: 61 | BM1: 62 | BN1: 63 | BO1: 64 | BP1: 65 | BQ1: 66 | BR1: 67 | BS1: 68 | BT1: 69 | BU1: 70 | BV1: 71
A2: Reversed rows run oldest age first so SUMPRODUCT can pair them with sign-ups to date.
A3: @0: history
A4: S_MONTHLY@0 | C4: =1 | D4: =C4*(1-IF(D$1=1,Params!$B$32,IF(D$1=2,Params!$B$34,IF(D$1=3,Params!$B$36,Params!$B$38)))) | E4: =D4*(1-IF(E$1=1,Params!$B$32,IF(E$1=2,Params!$B$34,IF(E$1=3,Params!$B$36,Params!$B$38)))) | F4: =E4*(1-IF(F$1=1,Params!$B$32,IF(F$1=2,Params!$B$34,IF(F$1=3,Params!$B$36,Params!$B$38)))) | G4: =F4*(1-IF(G$1=1,Params!$B$32,IF(G$1=2,Params!$B$34,IF(G$1=3,Params!$B$36,Params!$B$38)))) | H4: =G4*(1-IF(H$1=1,Params!$B$32,IF(H$1=2,Params!$B$34,IF(H$1=3,Params!$B$36,Params!$B$38)))) | I4: =H4*(1-IF(I$1=1,Params!$B$32,IF(I$1=2,Params!$B$34,IF(I$1=3,Params!$B$36,Params!$B$38)))) | J4: =I4*(1-IF(J$1=1,Params!$B$32,IF(J$1=2,Params!$B$34,IF(J$1=3,Params!$B$36,Params!$B$38)))) | K4: =J4*(1-IF(K$1=1,Params!$B$32,IF(K$1=2,Params!$B$34,IF(K$1=3,Params!$B$36,Params!$B$38)))) | ... BV4: =BU4*(1-IF(BV$1=1,Params!$B$32,IF(BV$1=2,Params!$B$34,IF(BV$1=3,Params!$B$36,Params!$B$38))))
A5: S_ANNUAL@0 | C5: =IF(C$1<12,1,Params!$B$40*Params!$B$42^(INT(C$1/12)-1)) | D5: =IF(D$1<12,1,Params!$B$40*Params!$B$42^(INT(D$1/12)-1)) | E5: =IF(E$1<12,1,Params!$B$40*Params!$B$42^(INT(E$1/12)-1)) | F5: =IF(F$1<12,1,Params!$B$40*Params!$B$42^(INT(F$1/12)-1)) | G5: =IF(G$1<12,1,Params!$B$40*Params!$B$42^(INT(G$1/12)-1)) | H5: =IF(H$1<12,1,Params!$B$40*Params!$B$42^(INT(H$1/12)-1)) | I5: =IF(I$1<12,1,Params!$B$40*Params!$B$42^(INT(I$1/12)-1)) | J5: =IF(J$1<12,1,Params!$B$40*Params!$B$42^(INT(J$1/12)-1)) | ... BV5: =IF(BV$1<12,1,Params!$B$40*Params!$B$42^(INT(BV$1/12)-1))
A6: D_MONTHLY@0 | C6: =0 | D6: =C4-D4 | E6: =D4-E4 | F6: =E4-F4 | G6: =F4-G4 | H6: =G4-H4 | I6: =H4-I4 | J6: =I4-J4 | K6: =J4-K4 | ... BV6: =BU4-BV4
A7: D_ANNUAL@0 | C7: =0 | D7: =C5-D5 | E7: =D5-E5 | F7: =E5-F5 | G7: =F5-G5 | H7: =G5-H5 | I7: =H5-I5 | J7: =I5-J5 | K7: =J5-K5 | ... BV7: =BU5-BV5
A8: S_REACT@0 | C8: =(1-Params!$B$48)^C$1 | D8: =(1-Params!$B$48)^D$1 | E8: =(1-Params!$B$48)^E$1 | F8: =(1-Params!$B$48)^F$1 | G8: =(1-Params!$B$48)^G$1 | H8: =(1-Params!$B$48)^H$1 | I8: =(1-Params!$B$48)^I$1 | J8: =(1-Params!$B$48)^J$1 | ... BV8: =(1-Params!$B$48)^BV$1
A9: D_REACT@0 | C9: =0 | D9: =C8-D8 | E9: =D8-E8 | F9: =E8-F8 | G9: =F8-G8 | H9: =G8-H8 | I9: =H8-I8 | J9: =I8-J8 | K9: =J8-K8 | ... BV9: =BU8-BV8
A10: K_REACT@0 | C10: =IF(AND(C$1>=1,C$1<=Params!$B$46),Params!$B$44*(1-Params!$B$44)^(C$1-1),0) | D10: =IF(AND(D$1>=1,D$1<=Params!$B$46),Params!$B$44*(1-Params!$B$44)^(D$1-1),0) | E10: =IF(AND(E$1>=1,E$1<=Params!$B$46),Params!$B$44*(1-Params!$B$44)^(E$1-1),0) | F10: =IF(AND(F$1>=1,F$1<=Params!$B$46),Params!$B$44*(1-Params!$B$44)^(F$1-1),0) | G10: =IF(AND(G$1>=1,G$1<=Params!$B$46),Params!$B$44*(1-Params!$B$44)^(G$1-1),0) | H10: =IF(AND(H$1>=1,H$1<=Params!$B$46),Params!$B$44*(1-Params!$B$44)^(H$1-1),0) | I10: =IF(AND(I$1>=1,I$1<=Params!$B$46),Params!$B$44*(1-Params!$B$44)^(I$1-1),0) | J10: =IF(AND(J$1>=1,J$1<=Params!$B$46),Params!$B$44*(1-Params!$B$44)^(J$1-1),0) | ... BV10: =IF(AND(BV$1>=1,BV$1<=Params!$B$46),Params!$B$44*(1-Params!$B$44)^(BV$1-1),0)
A11: S_MONTHLY_Y1@0 | C11: =IF(C$1<12,C4,0) | D11: =IF(D$1<12,D4,0) | E11: =IF(E$1<12,E4,0) | F11: =IF(F$1<12,F4,0) | G11: =IF(G$1<12,G4,0) | H11: =IF(H$1<12,H4,0) | I11: =IF(I$1<12,I4,0) | J11: =IF(J$1<12,J4,0) | ... BV11: =IF(BV$1<12,BV4,0)
A12: S_ANNUAL_Y1@0 | C12: =IF(C$1<12,C5,0) | D12: =IF(D$1<12,D5,0) | E12: =IF(E$1<12,E5,0) | F12: =IF(F$1<12,F5,0) | G12: =IF(G$1<12,G5,0) | H12: =IF(H$1<12,H5,0) | I12: =IF(I$1<12,I5,0) | J12: =IF(J$1<12,J5,0) | ... BV12: =IF(BV$1<12,BV5,0)
A13: S_REACT_Y1@0 | C13: =IF(C$1<12,C8,0) | D13: =IF(D$1<12,D8,0) | E13: =IF(E$1<12,E8,0) | F13: =IF(F$1<12,F8,0) | G13: =IF(G$1<12,G8,0) | H13: =IF(H$1<12,H8,0) | I13: =IF(I$1<12,I8,0) | J13: =IF(J$1<12,J8,0) | ... BV13: =IF(BV$1<12,BV8,0)
A15: S_MONTHLY@0 reversed | C15: =INDEX($C$4:$BV$4,72) | D15: =INDEX($C$4:$BV$4,71) | E15: =INDEX($C$4:$BV$4,70) | F15: =INDEX($C$4:$BV$4,69) | G15: =INDEX($C$4:$BV$4,68) | H15: =INDEX($C$4:$BV$4,67) | I15: =INDEX($C$4:$BV$4,66) | J15: =INDEX($C$4:$BV$4,65) | K15: =INDEX($C$4:$BV$4,64) | L15: =INDEX($C$4:$BV$4,63) | M15: =INDEX($C$4:$BV$4,62) | N15: =INDEX($C$4:$BV$4,61) | O15: =INDEX($C$4:$BV$4,60) | P15: =INDEX($C$4:$BV$4,59) | Q15: =INDEX($C$4:$BV$4,58) | R15: =INDEX($C$4:$BV$4,57) | S15: =INDEX($C$4:$BV$4,56) | T15: =INDEX($C$4:$BV$4,55) | U15: =INDEX($C$4:$BV$4,54) | V15: =INDEX($C$4:$BV$4,53) | W15: =INDEX($C$4:$BV$4,52) | X15: =INDEX($C$4:$BV$4,51) | Y15: =INDEX($C$4:$BV$4,50) | Z15: =INDEX($C$4:$BV$4,49) | AA15: =INDEX($C$4:$BV$4,48) | AB15: =INDEX($C$4:$BV$4,47) | AC15: =INDEX($C$4:$BV$4,46) | AD15: =INDEX($C$4:$BV$4,45) | AE15: =INDEX($C$4:$BV$4,44) | AF15: =INDEX($C$4:$BV$4,43) | AG15: =INDEX($C$4:$BV$4,42) | AH15: =INDEX($C$4:$BV$4,41) | AI15: =INDEX($C$4:$BV$4,40) | AJ15: =INDEX($C$4:$BV$4,39) | AK15: =INDEX($C$4:$BV$4,38) | AL15: =INDEX($C$4:$BV$4,37) | AM15: =INDEX($C$4:$BV$4,36) | AN15: =INDEX($C$4:$BV$4,35) | AO15: =INDEX($C$4:$BV$4,34) | AP15: =INDEX($C$4:$BV$4,33) | AQ15: =INDEX($C$4:$BV$4,32) | AR15: =INDEX($C$4:$BV$4,31) | AS15: =INDEX($C$4:$BV$4,30) | AT15: =INDEX($C$4:$BV$4,29) | AU15: =INDEX($C$4:$BV$4,28) | AV15: =INDEX($C$4:$BV$4,27) | AW15: =INDEX($C$4:$BV$4,26) | AX15: =INDEX($C$4:$BV$4,25) | AY15: =INDEX($C$4:$BV$4,24) | AZ15: =INDEX($C$4:$BV$4,23) | BA15: =INDEX($C$4:$BV$4,22) | BB15: =INDEX($C$4:$BV$4,21) | BC15: =INDEX($C$4:$BV$4,20) | BD15: =INDEX($C$4:$BV$4,19) | BE15: =INDEX($C$4:$BV$4,18) | BF15: =INDEX($C$4:$BV$4,17) | BG15: =INDEX($C$4:$BV$4,16) | BH15: =INDEX($C$4:$BV$4,15) | BI15: =INDEX($C$4:$BV$4,14) | BJ15: =INDEX($C$4:$BV$4,13) | BK15: =INDEX($C$4:$BV$4,12) | BL15: =INDEX($C$4:$BV$4,11) | BM15: =INDEX($C$4:$BV$4,10) | BN15: =INDEX($C$4:$BV$4,9) | BO15: =INDEX($C$4:$BV$4,8) | BP15: =INDEX($C$4:$BV$4,7) | BQ15: =INDEX($C$4:$BV$4,6) | BR15: =INDEX($C$4:$BV$4,5) | BS15: =INDEX($C$4:$BV$4,4) | BT15: =INDEX($C$4:$BV$4,3) | BU15: =INDEX($C$4:$BV$4,2) | BV15: =INDEX($C$4:$BV$4,1)
A16: S_ANNUAL@0 reversed | C16: =INDEX($C$5:$BV$5,72) | D16: =INDEX($C$5:$BV$5,71) | E16: =INDEX($C$5:$BV$5,70) | F16: =INDEX($C$5:$BV$5,69) | G16: =INDEX($C$5:$BV$5,68) | H16: =INDEX($C$5:$BV$5,67) | I16: =INDEX($C$5:$BV$5,66) | J16: =INDEX($C$5:$BV$5,65) | K16: =INDEX($C$5:$BV$5,64) | L16: =INDEX($C$5:$BV$5,63) | M16: =INDEX($C$5:$BV$5,62) | N16: =INDEX($C$5:$BV$5,61) | O16: =INDEX($C$5:$BV$5,60) | P16: =INDEX($C$5:$BV$5,59) | Q16: =INDEX($C$5:$BV$5,58) | R16: =INDEX($C$5:$BV$5,57) | S16: =INDEX($C$5:$BV$5,56) | T16: =INDEX($C$5:$BV$5,55) | U16: =INDEX($C$5:$BV$5,54) | V16: =INDEX($C$5:$BV$5,53) | W16: =INDEX($C$5:$BV$5,52) | X16: =INDEX($C$5:$BV$5,51) | Y16: =INDEX($C$5:$BV$5,50) | Z16: =INDEX($C$5:$BV$5,49) | AA16: =INDEX($C$5:$BV$5,48) | AB16: =INDEX($C$5:$BV$5,47) | AC16: =INDEX($C$5:$BV$5,46) | AD16: =INDEX($C$5:$BV$5,45) | AE16: =INDEX($C$5:$BV$5,44) | AF16: =INDEX($C$5:$BV$5,43) | AG16: =INDEX($C$5:$BV$5,42) | AH16: =INDEX($C$5:$BV$5,41) | AI16: =INDEX($C$5:$BV$5,40) | AJ16: =INDEX($C$5:$BV$5,39) | AK16: =INDEX($C$5:$BV$5,38) | AL16: =INDEX($C$5:$BV$5,37) | AM16: =INDEX($C$5:$BV$5,36) | AN16: =INDEX($C$5:$BV$5,35) | AO16: =INDEX($C$5:$BV$5,34) | AP16: =INDEX($C$5:$BV$5,33) | AQ16: =INDEX($C$5:$BV$5,32) | AR16: =INDEX($C$5:$BV$5,31) | AS16: =INDEX($C$5:$BV$5,30) | AT16: =INDEX($C$5:$BV$5,29) | AU16: =INDEX($C$5:$BV$5,28) | AV16: =INDEX($C$5:$BV$5,27) | AW16: =INDEX($C$5:$BV$5,26) | AX16: =INDEX($C$5:$BV$5,25) | AY16: =INDEX($C$5:$BV$5,24) | AZ16: =INDEX($C$5:$BV$5,23) | BA16: =INDEX($C$5:$BV$5,22) | BB16: =INDEX($C$5:$BV$5,21) | BC16: =INDEX($C$5:$BV$5,20) | BD16: =INDEX($C$5:$BV$5,19) | BE16: =INDEX($C$5:$BV$5,18) | BF16: =INDEX($C$5:$BV$5,17) | BG16: =INDEX($C$5:$BV$5,16) | BH16: =INDEX($C$5:$BV$5,15) | BI16: =INDEX($C$5:$BV$5,14) | BJ16: =INDEX($C$5:$BV$5,13) | BK16: =INDEX($C$5:$BV$5,12) | BL16: =INDEX($C$5:$BV$5,11) | BM16: =INDEX($C$5:$BV$5,10) | BN16: =INDEX($C$5:$BV$5,9) | BO16: =INDEX($C$5:$BV$5,8) | BP16: =INDEX($C$5:$BV$5,7) | BQ16: =INDEX($C$5:$BV$5,6) | BR16: =INDEX($C$5:$BV$5,5) | BS16: =INDEX($C$5:$BV$5,4) | BT16: =INDEX($C$5:$BV$5,3) | BU16: =INDEX($C$5:$BV$5,2) | BV16: =INDEX($C$5:$BV$5,1)
A17: D_MONTHLY@0 reversed | C17: =INDEX($C$6:$BV$6,72) | D17: =INDEX($C$6:$BV$6,71) | E17: =INDEX($C$6:$BV$6,70) | F17: =INDEX($C$6:$BV$6,69) | G17: =INDEX($C$6:$BV$6,68) | H17: =INDEX($C$6:$BV$6,67) | I17: =INDEX($C$6:$BV$6,66) | J17: =INDEX($C$6:$BV$6,65) | K17: =INDEX($C$6:$BV$6,64) | L17: =INDEX($C$6:$BV$6,63) | M17: =INDEX($C$6:$BV$6,62) | N17: =INDEX($C$6:$BV$6,61) | O17: =INDEX($C$6:$BV$6,60) | P17: =INDEX($C$6:$BV$6,59) | Q17: =INDEX($C$6:$BV$6,58) | R17: =INDEX($C$6:$BV$6,57) | S17: =INDEX($C$6:$BV$6,56) | T17: =INDEX($C$6:$BV$6,55) | U17: =INDEX($C$6:$BV$6,54) | V17: =INDEX($C$6:$BV$6,53) | W17: =INDEX($C$6:$BV$6,52) | X17: =INDEX($C$6:$BV$6,51) | Y17: =INDEX($C$6:$BV$6,50) | Z17: =INDEX($C$6:$BV$6,49) | AA17: =INDEX($C$6:$BV$6,48) | AB17: =INDEX($C$6:$BV$6,47) | AC17: =INDEX($C$6:$BV$6,46) | AD17: =INDEX($C$6:$BV$6,45) | AE17: =INDEX($C$6:$BV$6,44) | AF17: =INDEX($C$6:$BV$6,43) | AG17: =INDEX($C$6:$BV$6,42) | AH17: =INDEX($C$6:$BV$6,41) | AI17: =INDEX($C$6:$BV$6,40) | AJ17: =INDEX($C$6:$BV$6,39) | AK17: =INDEX($C$6:$BV$6,38) | AL17: =INDEX($C$6:$BV$6,37) | AM17: =INDEX($C$6:$BV$6,36) | AN17: =INDEX($C$6:$BV$6,35) | AO17: =INDEX($C$6:$BV$6,34) | AP17: =INDEX($C$6:$BV$6,33) | AQ17: =INDEX($C$6:$BV$6,32) | AR17: =INDEX($C$6:$BV$6,31) | AS17: =INDEX($C$6:$BV$6,30) | AT17: =INDEX($C$6:$BV$6,29) | AU17: =INDEX($C$6:$BV$6,28) | AV17: =INDEX($C$6:$BV$6,27) | AW17: =INDEX($C$6:$BV$6,26) | AX17: =INDEX($C$6:$BV$6,25) | AY17: =INDEX($C$6:$BV$6,24) | AZ17: =INDEX($C$6:$BV$6,23) | BA17: =INDEX($C$6:$BV$6,22) | BB17: =INDEX($C$6:$BV$6,21) | BC17: =INDEX($C$6:$BV$6,20) | BD17: =INDEX($C$6:$BV$6,19) | BE17: =INDEX($C$6:$BV$6,18) | BF17: =INDEX($C$6:$BV$6,17) | BG17: =INDEX($C$6:$BV$6,16) | BH17: =INDEX($C$6:$BV$6,15) | BI17: =INDEX($C$6:$BV$6,14) | BJ17: =INDEX($C$6:$BV$6,13) | BK17: =INDEX($C$6:$BV$6,12) | BL17: =INDEX($C$6:$BV$6,11) | BM17: =INDEX($C$6:$BV$6,10) | BN17: =INDEX($C$6:$BV$6,9) | BO17: =INDEX($C$6:$BV$6,8) | BP17: =INDEX($C$6:$BV$6,7) | BQ17: =INDEX($C$6:$BV$6,6) | BR17: =INDEX($C$6:$BV$6,5) | BS17: =INDEX($C$6:$BV$6,4) | BT17: =INDEX($C$6:$BV$6,3) | BU17: =INDEX($C$6:$BV$6,2) | BV17: =INDEX($C$6:$BV$6,1)
A18: D_ANNUAL@0 reversed | C18: =INDEX($C$7:$BV$7,72) | D18: =INDEX($C$7:$BV$7,71) | E18: =INDEX($C$7:$BV$7,70) | F18: =INDEX($C$7:$BV$7,69) | G18: =INDEX($C$7:$BV$7,68) | H18: =INDEX($C$7:$BV$7,67) | I18: =INDEX($C$7:$BV$7,66) | J18: =INDEX($C$7:$BV$7,65) | K18: =INDEX($C$7:$BV$7,64) | L18: =INDEX($C$7:$BV$7,63) | M18: =INDEX($C$7:$BV$7,62) | N18: =INDEX($C$7:$BV$7,61) | O18: =INDEX($C$7:$BV$7,60) | P18: =INDEX($C$7:$BV$7,59) | Q18: =INDEX($C$7:$BV$7,58) | R18: =INDEX($C$7:$BV$7,57) | S18: =INDEX($C$7:$BV$7,56) | T18: =INDEX($C$7:$BV$7,55) | U18: =INDEX($C$7:$BV$7,54) | V18: =INDEX($C$7:$BV$7,53) | W18: =INDEX($C$7:$BV$7,52) | X18: =INDEX($C$7:$BV$7,51) | Y18: =INDEX($C$7:$BV$7,50) | Z18: =INDEX($C$7:$BV$7,49) | AA18: =INDEX($C$7:$BV$7,48) | AB18: =INDEX($C$7:$BV$7,47) | AC18: =INDEX($C$7:$BV$7,46) | AD18: =INDEX($C$7:$BV$7,45) | AE18: =INDEX($C$7:$BV$7,44) | AF18: =INDEX($C$7:$BV$7,43) | AG18: =INDEX($C$7:$BV$7,42) | AH18: =INDEX($C$7:$BV$7,41) | AI18: =INDEX($C$7:$BV$7,40) | AJ18: =INDEX($C$7:$BV$7,39) | AK18: =INDEX($C$7:$BV$7,38) | AL18: =INDEX($C$7:$BV$7,37) | AM18: =INDEX($C$7:$BV$7,36) | AN18: =INDEX($C$7:$BV$7,35) | AO18: =INDEX($C$7:$BV$7,34) | AP18: =INDEX($C$7:$BV$7,33) | AQ18: =INDEX($C$7:$BV$7,32) | AR18: =INDEX($C$7:$BV$7,31) | AS18: =INDEX($C$7:$BV$7,30) | AT18: =INDEX($C$7:$BV$7,29) | AU18: =INDEX($C$7:$BV$7,28) | AV18: =INDEX($C$7:$BV$7,27) | AW18: =INDEX($C$7:$BV$7,26) | AX18: =INDEX($C$7:$BV$7,25) | AY18: =INDEX($C$7:$BV$7,24) | AZ18: =INDEX($C$7:$BV$7,23) | BA18: =INDEX($C$7:$BV$7,22) | BB18: =INDEX($C$7:$BV$7,21) | BC18: =INDEX($C$7:$BV$7,20) | BD18: =INDEX($C$7:$BV$7,19) | BE18: =INDEX($C$7:$BV$7,18) | BF18: =INDEX($C$7:$BV$7,17) | BG18: =INDEX($C$7:$BV$7,16) | BH18: =INDEX($C$7:$BV$7,15) | BI18: =INDEX($C$7:$BV$7,14) | BJ18: =INDEX($C$7:$BV$7,13) | BK18: =INDEX($C$7:$BV$7,12) | BL18: =INDEX($C$7:$BV$7,11) | BM18: =INDEX($C$7:$BV$7,10) | BN18: =INDEX($C$7:$BV$7,9) | BO18: =INDEX($C$7:$BV$7,8) | BP18: =INDEX($C$7:$BV$7,7) | BQ18: =INDEX($C$7:$BV$7,6) | BR18: =INDEX($C$7:$BV$7,5) | BS18: =INDEX($C$7:$BV$7,4) | BT18: =INDEX($C$7:$BV$7,3) | BU18: =INDEX($C$7:$BV$7,2) | BV18: =INDEX($C$7:$BV$7,1)
A19: S_REACT@0 reversed | C19: =INDEX($C$8:$BV$8,72) | D19: =INDEX($C$8:$BV$8,71) | E19: =INDEX($C$8:$BV$8,70) | F19: =INDEX($C$8:$BV$8,69) | G19: =INDEX($C$8:$BV$8,68) | H19: =INDEX($C$8:$BV$8,67) | I19: =INDEX($C$8:$BV$8,66) | J19: =INDEX($C$8:$BV$8,65) | K19: =INDEX($C$8:$BV$8,64) | L19: =INDEX($C$8:$BV$8,63) | M19: =INDEX($C$8:$BV$8,62) | N19: =INDEX($C$8:$BV$8,61) | O19: =INDEX($C$8:$BV$8,60) | P19: =INDEX($C$8:$BV$8,59) | Q19: =INDEX($C$8:$BV$8,58) | R19: =INDEX($C$8:$BV$8,57) | S19: =INDEX($C$8:$BV$8,56) | T19: =INDEX($C$8:$BV$8,55) | U19: =INDEX($C$8:$BV$8,54) | V19: =INDEX($C$8:$BV$8,53) | W19: =INDEX($C$8:$BV$8,52) | X19: =INDEX($C$8:$BV$8,51) | Y19: =INDEX($C$8:$BV$8,50) | Z19: =INDEX($C$8:$BV$8,49) | AA19: =INDEX($C$8:$BV$8,48) | AB19: =INDEX($C$8:$BV$8,47) | AC19: =INDEX($C$8:$BV$8,46) | AD19: =INDEX($C$8:$BV$8,45) | AE19: =INDEX($C$8:$BV$8,44) | AF19: =INDEX($C$8:$BV$8,43) | AG19: =INDEX($C$8:$BV$8,42) | AH19: =INDEX($C$8:$BV$8,41) | AI19: =INDEX($C$8:$BV$8,40) | AJ19: =INDEX($C$8:$BV$8,39) | AK19: =INDEX($C$8:$BV$8,38) | AL19: =INDEX($C$8:$BV$8,37) | AM19: =INDEX($C$8:$BV$8,36) | AN19: =INDEX($C$8:$BV$8,35) | AO19: =INDEX($C$8:$BV$8,34) | AP19: =INDEX($C$8:$BV$8,33) | AQ19: =INDEX($C$8:$BV$8,32) | AR19: =INDEX($C$8:$BV$8,31) | AS19: =INDEX($C$8:$BV$8,30) | AT19: =INDEX($C$8:$BV$8,29) | AU19: =INDEX($C$8:$BV$8,28) | AV19: =INDEX($C$8:$BV$8,27) | AW19: =INDEX($C$8:$BV$8,26) | AX19: =INDEX($C$8:$BV$8,25) | AY19: =INDEX($C$8:$BV$8,24) | AZ19: =INDEX($C$8:$BV$8,23) | BA19: =INDEX($C$8:$BV$8,22) | BB19: =INDEX($C$8:$BV$8,21) | BC19: =INDEX($C$8:$BV$8,20) | BD19: =INDEX($C$8:$BV$8,19) | BE19: =INDEX($C$8:$BV$8,18) | BF19: =INDEX($C$8:$BV$8,17) | BG19: =INDEX($C$8:$BV$8,16) | BH19: =INDEX($C$8:$BV$8,15) | BI19: =INDEX($C$8:$BV$8,14) | BJ19: =INDEX($C$8:$BV$8,13) | BK19: =INDEX($C$8:$BV$8,12) | BL19: =INDEX($C$8:$BV$8,11) | BM19: =INDEX($C$8:$BV$8,10) | BN19: =INDEX($C$8:$BV$8,9) | BO19: =INDEX($C$8:$BV$8,8) | BP19: =INDEX($C$8:$BV$8,7) | BQ19: =INDEX($C$8:$BV$8,6) | BR19: =INDEX($C$8:$BV$8,5) | BS19: =INDEX($C$8:$BV$8,4) | BT19: =INDEX($C$8:$BV$8,3) | BU19: =INDEX($C$8:$BV$8,2) | BV19: =INDEX($C$8:$BV$8,1)
A20: D_REACT@0 reversed | C20: =INDEX($C$9:$BV$9,72) | D20: =INDEX($C$9:$BV$9,71) | E20: =INDEX($C$9:$BV$9,70) | F20: =INDEX($C$9:$BV$9,69) | G20: =INDEX($C$9:$BV$9,68) | H20: =INDEX($C$9:$BV$9,67) | I20: =INDEX($C$9:$BV$9,66) | J20: =INDEX($C$9:$BV$9,65) | K20: =INDEX($C$9:$BV$9,64) | L20: =INDEX($C$9:$BV$9,63) | M20: =INDEX($C$9:$BV$9,62) | N20: =INDEX($C$9:$BV$9,61) | O20: =INDEX($C$9:$BV$9,60) | P20: =INDEX($C$9:$BV$9,59) | Q20: =INDEX($C$9:$BV$9,58) | R20: =INDEX($C$9:$BV$9,57) | S20: =INDEX($C$9:$BV$9,56) | T20: =INDEX($C$9:$BV$9,55) | U20: =INDEX($C$9:$BV$9,54) | V20: =INDEX($C$9:$BV$9,53) | W20: =INDEX($C$9:$BV$9,52) | X20: =INDEX($C$9:$BV$9,51) | Y20: =INDEX($C$9:$BV$9,50) | Z20: =INDEX($C$9:$BV$9,49) | AA20: =INDEX($C$9:$BV$9,48) | AB20: =INDEX($C$9:$BV$9,47) | AC20: =INDEX($C$9:$BV$9,46) | AD20: =INDEX($C$9:$BV$9,45) | AE20: =INDEX($C$9:$BV$9,44) | AF20: =INDEX($C$9:$BV$9,43) | AG20: =INDEX($C$9:$BV$9,42) | AH20: =INDEX($C$9:$BV$9,41) | AI20: =INDEX($C$9:$BV$9,40) | AJ20: =INDEX($C$9:$BV$9,39) | AK20: =INDEX($C$9:$BV$9,38) | AL20: =INDEX($C$9:$BV$9,37) | AM20: =INDEX($C$9:$BV$9,36) | AN20: =INDEX($C$9:$BV$9,35) | AO20: =INDEX($C$9:$BV$9,34) | AP20: =INDEX($C$9:$BV$9,33) | AQ20: =INDEX($C$9:$BV$9,32) | AR20: =INDEX($C$9:$BV$9,31) | AS20: =INDEX($C$9:$BV$9,30) | AT20: =INDEX($C$9:$BV$9,29) | AU20: =INDEX($C$9:$BV$9,28) | AV20: =INDEX($C$9:$BV$9,27) | AW20: =INDEX($C$9:$BV$9,26) | AX20: =INDEX($C$9:$BV$9,25) | AY20: =INDEX($C$9:$BV$9,24) | AZ20: =INDEX($C$9:$BV$9,23) | BA20: =INDEX($C$9:$BV$9,22) | BB20: =INDEX($C$9:$BV$9,21) | BC20: =INDEX($C$9:$BV$9,20) | BD20: =INDEX($C$9:$BV$9,19) | BE20: =INDEX($C$9:$BV$9,18) | BF20: =INDEX($C$9:$BV$9,17) | BG20: =INDEX($C$9:$BV$9,16) | BH20: =INDEX($C$9:$BV$9,15) | BI20: =INDEX($C$9:$BV$9,14) | BJ20: =INDEX($C$9:$BV$9,13) | BK20: =INDEX($C$9:$BV$9,12) | BL20: =INDEX($C$9:$BV$9,11) | BM20: =INDEX($C$9:$BV$9,10) | BN20: =INDEX($C$9:$BV$9,9) | BO20: =INDEX($C$9:$BV$9,8) | BP20: =INDEX($C$9:$BV$9,7) | BQ20: =INDEX($C$9:$BV$9,6) | BR20: =INDEX($C$9:$BV$9,5) | BS20: =INDEX($C$9:$BV$9,4) | BT20: =INDEX($C$9:$BV$9,3) | BU20: =INDEX($C$9:$BV$9,2) | BV20: =INDEX($C$9:$BV$9,1)
A21: K_REACT@0 reversed | C21: =INDEX($C$10:$BV$10,72) | D21: =INDEX($C$10:$BV$10,71) | E21: =INDEX($C$10:$BV$10,70) | F21: =INDEX($C$10:$BV$10,69) | G21: =INDEX($C$10:$BV$10,68) | H21: =INDEX($C$10:$BV$10,67) | I21: =INDEX($C$10:$BV$10,66) | J21: =INDEX($C$10:$BV$10,65) | K21: =INDEX($C$10:$BV$10,64) | L21: =INDEX($C$10:$BV$10,63) | M21: =INDEX($C$10:$BV$10,62) | N21: =INDEX($C$10:$BV$10,61) | O21: =INDEX($C$10:$BV$10,60) | P21: =INDEX($C$10:$BV$10,59) | Q21: =INDEX($C$10:$BV$10,58) | R21: =INDEX($C$10:$BV$10,57) | S21: =INDEX($C$10:$BV$10,56) | T21: =INDEX($C$10:$BV$10,55) | U21: =INDEX($C$10:$BV$10,54) | V21: =INDEX($C$10:$BV$10,53) | W21: =INDEX($C$10:$BV$10,52) | X21: =INDEX($C$10:$BV$10,51) | Y21: =INDEX($C$10:$BV$10,50) | Z21: =INDEX($C$10:$BV$10,49) | AA21: =INDEX($C$10:$BV$10,48) | AB21: =INDEX($C$10:$BV$10,47) | AC21: =INDEX($C$10:$BV$10,46) | AD21: =INDEX($C$10:$BV$10,45) | AE21: =INDEX($C$10:$BV$10,44) | AF21: =INDEX($C$10:$BV$10,43) | AG21: =INDEX($C$10:$BV$10,42) | AH21: =INDEX($C$10:$BV$10,41) | AI21: =INDEX($C$10:$BV$10,40) | AJ21: =INDEX($C$10:$BV$10,39) | AK21: =INDEX($C$10:$BV$10,38) | AL21: =INDEX($C$10:$BV$10,37) | AM21: =INDEX($C$10:$BV$10,36) | AN21: =INDEX($C$10:$BV$10,35) | AO21: =INDEX($C$10:$BV$10,34) | AP21: =INDEX($C$10:$BV$10,33) | AQ21: =INDEX($C$10:$BV$10,32) | AR21: =INDEX($C$10:$BV$10,31) | AS21: =INDEX($C$10:$BV$10,30) | AT21: =INDEX($C$10:$BV$10,29) | AU21: =INDEX($C$10:$BV$10,28) | AV21: =INDEX($C$10:$BV$10,27) | AW21: =INDEX($C$10:$BV$10,26) | AX21: =INDEX($C$10:$BV$10,25) | AY21: =INDEX($C$10:$BV$10,24) | AZ21: =INDEX($C$10:$BV$10,23) | BA21: =INDEX($C$10:$BV$10,22) | BB21: =INDEX($C$10:$BV$10,21) | BC21: =INDEX($C$10:$BV$10,20) | BD21: =INDEX($C$10:$BV$10,19) | BE21: =INDEX($C$10:$BV$10,18) | BF21: =INDEX($C$10:$BV$10,17) | BG21: =INDEX($C$10:$BV$10,16) | BH21: =INDEX($C$10:$BV$10,15) | BI21: =INDEX($C$10:$BV$10,14) | BJ21: =INDEX($C$10:$BV$10,13) | BK21: =INDEX($C$10:$BV$10,12) | BL21: =INDEX($C$10:$BV$10,11) | BM21: =INDEX($C$10:$BV$10,10) | BN21: =INDEX($C$10:$BV$10,9) | BO21: =INDEX($C$10:$BV$10,8) | BP21: =INDEX($C$10:$BV$10,7) | BQ21: =INDEX($C$10:$BV$10,6) | BR21: =INDEX($C$10:$BV$10,5) | BS21: =INDEX($C$10:$BV$10,4) | BT21: =INDEX($C$10:$BV$10,3) | BU21: =INDEX($C$10:$BV$10,2) | BV21: =INDEX($C$10:$BV$10,1)
A22: S_MONTHLY_Y1@0 reversed | C22: =INDEX($C$11:$BV$11,72) | D22: =INDEX($C$11:$BV$11,71) | E22: =INDEX($C$11:$BV$11,70) | F22: =INDEX($C$11:$BV$11,69) | G22: =INDEX($C$11:$BV$11,68) | H22: =INDEX($C$11:$BV$11,67) | I22: =INDEX($C$11:$BV$11,66) | J22: =INDEX($C$11:$BV$11,65) | K22: =INDEX($C$11:$BV$11,64) | L22: =INDEX($C$11:$BV$11,63) | M22: =INDEX($C$11:$BV$11,62) | N22: =INDEX($C$11:$BV$11,61) | O22: =INDEX($C$11:$BV$11,60) | P22: =INDEX($C$11:$BV$11,59) | Q22: =INDEX($C$11:$BV$11,58) | R22: =INDEX($C$11:$BV$11,57) | S22: =INDEX($C$11:$BV$11,56) | T22: =INDEX($C$11:$BV$11,55) | U22: =INDEX($C$11:$BV$11,54) | V22: =INDEX($C$11:$BV$11,53) | W22: =INDEX($C$11:$BV$11,52) | X22: =INDEX($C$11:$BV$11,51) | Y22: =INDEX($C$11:$BV$11,50) | Z22: =INDEX($C$11:$BV$11,49) | AA22: =INDEX($C$11:$BV$11,48) | AB22: =INDEX($C$11:$BV$11,47) | AC22: =INDEX($C$11:$BV$11,46) | AD22: =INDEX($C$11:$BV$11,45) | AE22: =INDEX($C$11:$BV$11,44) | AF22: =INDEX($C$11:$BV$11,43) | AG22: =INDEX($C$11:$BV$11,42) | AH22: =INDEX($C$11:$BV$11,41) | AI22: =INDEX($C$11:$BV$11,40) | AJ22: =INDEX($C$11:$BV$11,39) | AK22: =INDEX($C$11:$BV$11,38) | AL22: =INDEX($C$11:$BV$11,37) | AM22: =INDEX($C$11:$BV$11,36) | AN22: =INDEX($C$11:$BV$11,35) | AO22: =INDEX($C$11:$BV$11,34) | AP22: =INDEX($C$11:$BV$11,33) | AQ22: =INDEX($C$11:$BV$11,32) | AR22: =INDEX($C$11:$BV$11,31) | AS22: =INDEX($C$11:$BV$11,30) | AT22: =INDEX($C$11:$BV$11,29) | AU22: =INDEX($C$11:$BV$11,28) | AV22: =INDEX($C$11:$BV$11,27) | AW22: =INDEX($C$11:$BV$11,26) | AX22: =INDEX($C$11:$BV$11,25) | AY22: =INDEX($C$11:$BV$11,24) | AZ22: =INDEX($C$11:$BV$11,23) | BA22: =INDEX($C$11:$BV$11,22) | BB22: =INDEX($C$11:$BV$11,21) | BC22: =INDEX($C$11:$BV$11,20) | BD22: =INDEX($C$11:$BV$11,19) | BE22: =INDEX($C$11:$BV$11,18) | BF22: =INDEX($C$11:$BV$11,17) | BG22: =INDEX($C$11:$BV$11,16) | BH22: =INDEX($C$11:$BV$11,15) | BI22: =INDEX($C$11:$BV$11,14) | BJ22: =INDEX($C$11:$BV$11,13) | BK22: =INDEX($C$11:$BV$11,12) | BL22: =INDEX($C$11:$BV$11,11) | BM22: =INDEX($C$11:$BV$11,10) | BN22: =INDEX($C$11:$BV$11,9) | BO22: =INDEX($C$11:$BV$11,8) | BP22: =INDEX($C$11:$BV$11,7) | BQ22: =INDEX($C$11:$BV$11,6) | BR22: =INDEX($C$11:$BV$11,5) | BS22: =INDEX($C$11:$BV$11,4) | BT22: =INDEX($C$11:$BV$11,3) | BU22: =INDEX($C$11:$BV$11,2) | BV22: =INDEX($C$11:$BV$11,1)
A23: S_ANNUAL_Y1@0 reversed | C23: =INDEX($C$12:$BV$12,72) | D23: =INDEX($C$12:$BV$12,71) | E23: =INDEX($C$12:$BV$12,70) | F23: =INDEX($C$12:$BV$12,69) | G23: =INDEX($C$12:$BV$12,68) | H23: =INDEX($C$12:$BV$12,67) | I23: =INDEX($C$12:$BV$12,66) | J23: =INDEX($C$12:$BV$12,65) | K23: =INDEX($C$12:$BV$12,64) | L23: =INDEX($C$12:$BV$12,63) | M23: =INDEX($C$12:$BV$12,62) | N23: =INDEX($C$12:$BV$12,61) | O23: =INDEX($C$12:$BV$12,60) | P23: =INDEX($C$12:$BV$12,59) | Q23: =INDEX($C$12:$BV$12,58) | R23: =INDEX($C$12:$BV$12,57) | S23: =INDEX($C$12:$BV$12,56) | T23: =INDEX($C$12:$BV$12,55) | U23: =INDEX($C$12:$BV$12,54) | V23: =INDEX($C$12:$BV$12,53) | W23: =INDEX($C$12:$BV$12,52) | X23: =INDEX($C$12:$BV$12,51) | Y23: =INDEX($C$12:$BV$12,50) | Z23: =INDEX($C$12:$BV$12,49) | AA23: =INDEX($C$12:$BV$12,48) | AB23: =INDEX($C$12:$BV$12,47) | AC23: =INDEX($C$12:$BV$12,46) | AD23: =INDEX($C$12:$BV$12,45) | AE23: =INDEX($C$12:$BV$12,44) | AF23: =INDEX($C$12:$BV$12,43) | AG23: =INDEX($C$12:$BV$12,42) | AH23: =INDEX($C$12:$BV$12,41) | AI23: =INDEX($C$12:$BV$12,40) | AJ23: =INDEX($C$12:$BV$12,39) | AK23: =INDEX($C$12:$BV$12,38) | AL23: =INDEX($C$12:$BV$12,37) | AM23: =INDEX($C$12:$BV$12,36) | AN23: =INDEX($C$12:$BV$12,35) | AO23: =INDEX($C$12:$BV$12,34) | AP23: =INDEX($C$12:$BV$12,33) | AQ23: =INDEX($C$12:$BV$12,32) | AR23: =INDEX($C$12:$BV$12,31) | AS23: =INDEX($C$12:$BV$12,30) | AT23: =INDEX($C$12:$BV$12,29) | AU23: =INDEX($C$12:$BV$12,28) | AV23: =INDEX($C$12:$BV$12,27) | AW23: =INDEX($C$12:$BV$12,26) | AX23: =INDEX($C$12:$BV$12,25) | AY23: =INDEX($C$12:$BV$12,24) | AZ23: =INDEX($C$12:$BV$12,23) | BA23: =INDEX($C$12:$BV$12,22) | BB23: =INDEX($C$12:$BV$12,21) | BC23: =INDEX($C$12:$BV$12,20) | BD23: =INDEX($C$12:$BV$12,19) | BE23: =INDEX($C$12:$BV$12,18) | BF23: =INDEX($C$12:$BV$12,17) | BG23: =INDEX($C$12:$BV$12,16) | BH23: =INDEX($C$12:$BV$12,15) | BI23: =INDEX($C$12:$BV$12,14) | BJ23: =INDEX($C$12:$BV$12,13) | BK23: =INDEX($C$12:$BV$12,12) | BL23: =INDEX($C$12:$BV$12,11) | BM23: =INDEX($C$12:$BV$12,10) | BN23: =INDEX($C$12:$BV$12,9) | BO23: =INDEX($C$12:$BV$12,8) | BP23: =INDEX($C$12:$BV$12,7) | BQ23: =INDEX($C$12:$BV$12,6) | BR23: =INDEX($C$12:$BV$12,5) | BS23: =INDEX($C$12:$BV$12,4) | BT23: =INDEX($C$12:$BV$12,3) | BU23: =INDEX($C$12:$BV$12,2) | BV23: =INDEX($C$12:$BV$12,1)
A24: S_REACT_Y1@0 reversed | C24: =INDEX($C$13:$BV$13,72) | D24: =INDEX($C$13:$BV$13,71) | E24: =INDEX($C$13:$BV$13,70) | F24: =INDEX($C$13:$BV$13,69) | G24: =INDEX($C$13:$BV$13,68) | H24: =INDEX($C$13:$BV$13,67) | I24: =INDEX($C$13:$BV$13,66) | J24: =INDEX($C$13:$BV$13,65) | K24: =INDEX($C$13:$BV$13,64) | L24: =INDEX($C$13:$BV$13,63) | M24: =INDEX($C$13:$BV$13,62) | N24: =INDEX($C$13:$BV$13,61) | O24: =INDEX($C$13:$BV$13,60) | P24: =INDEX($C$13:$BV$13,59) | Q24: =INDEX($C$13:$BV$13,58) | R24: =INDEX($C$13:$BV$13,57) | S24: =INDEX($C$13:$BV$13,56) | T24: =INDEX($C$13:$BV$13,55) | U24: =INDEX($C$13:$BV$13,54) | V24: =INDEX($C$13:$BV$13,53) | W24: =INDEX($C$13:$BV$13,52) | X24: =INDEX($C$13:$BV$13,51) | Y24: =INDEX($C$13:$BV$13,50) | Z24: =INDEX($C$13:$BV$13,49) | AA24: =INDEX($C$13:$BV$13,48) | AB24: =INDEX($C$13:$BV$13,47) | AC24: =INDEX($C$13:$BV$13,46) | AD24: =INDEX($C$13:$BV$13,45) | AE24: =INDEX($C$13:$BV$13,44) | AF24: =INDEX($C$13:$BV$13,43) | AG24: =INDEX($C$13:$BV$13,42) | AH24: =INDEX($C$13:$BV$13,41) | AI24: =INDEX($C$13:$BV$13,40) | AJ24: =INDEX($C$13:$BV$13,39) | AK24: =INDEX($C$13:$BV$13,38) | AL24: =INDEX($C$13:$BV$13,37) | AM24: =INDEX($C$13:$BV$13,36) | AN24: =INDEX($C$13:$BV$13,35) | AO24: =INDEX($C$13:$BV$13,34) | AP24: =INDEX($C$13:$BV$13,33) | AQ24: =INDEX($C$13:$BV$13,32) | AR24: =INDEX($C$13:$BV$13,31) | AS24: =INDEX($C$13:$BV$13,30) | AT24: =INDEX($C$13:$BV$13,29) | AU24: =INDEX($C$13:$BV$13,28) | AV24: =INDEX($C$13:$BV$13,27) | AW24: =INDEX($C$13:$BV$13,26) | AX24: =INDEX($C$13:$BV$13,25) | AY24: =INDEX($C$13:$BV$13,24) | AZ24: =INDEX($C$13:$BV$13,23) | BA24: =INDEX($C$13:$BV$13,22) | BB24: =INDEX($C$13:$BV$13,21) | BC24: =INDEX($C$13:$BV$13,20) | BD24: =INDEX($C$13:$BV$13,19) | BE24: =INDEX($C$13:$BV$13,18) | BF24: =INDEX($C$13:$BV$13,17) | BG24: =INDEX($C$13:$BV$13,16) | BH24: =INDEX($C$13:$BV$13,15) | BI24: =INDEX($C$13:$BV$13,14) | BJ24: =INDEX($C$13:$BV$13,13) | BK24: =INDEX($C$13:$BV$13,12) | BL24: =INDEX($C$13:$BV$13,11) | BM24: =INDEX($C$13:$BV$13,10) | BN24: =INDEX($C$13:$BV$13,9) | BO24: =INDEX($C$13:$BV$13,8) | BP24: =INDEX($C$13:$BV$13,7) | BQ24: =INDEX($C$13:$BV$13,6) | BR24: =INDEX($C$13:$BV$13,5) | BS24: =INDEX($C$13:$BV$13,4) | BT24: =INDEX($C$13:$BV$13,3) | BU24: =INDEX($C$13:$BV$13,2) | BV24: =INDEX($C$13:$BV$13,1)
A26: @1: forecast
A27: S_MONTHLY@1 | C27: =1 | D27: =C27*(1-IF(D$1=1,Params!$B$33,IF(D$1=2,Params!$B$35,IF(D$1=3,Params!$B$37,Params!$B$39)))) | E27: =D27*(1-IF(E$1=1,Params!$B$33,IF(E$1=2,Params!$B$35,IF(E$1=3,Params!$B$37,Params!$B$39)))) | F27: =E27*(1-IF(F$1=1,Params!$B$33,IF(F$1=2,Params!$B$35,IF(F$1=3,Params!$B$37,Params!$B$39)))) | G27: =F27*(1-IF(G$1=1,Params!$B$33,IF(G$1=2,Params!$B$35,IF(G$1=3,Params!$B$37,Params!$B$39)))) | H27: =G27*(1-IF(H$1=1,Params!$B$33,IF(H$1=2,Params!$B$35,IF(H$1=3,Params!$B$37,Params!$B$39)))) | I27: =H27*(1-IF(I$1=1,Params!$B$33,IF(I$1=2,Params!$B$35,IF(I$1=3,Params!$B$37,Params!$B$39)))) | J27: =I27*(1-IF(J$1=1,Params!$B$33,IF(J$1=2,Params!$B$35,IF(J$1=3,Params!$B$37,Params!$B$39)))) | K27: =J27*(1-IF(K$1=1,Params!$B$33,IF(K$1=2,Params!$B$35,IF(K$1=3,Params!$B$37,Params!$B$39)))) | ... BV27: =BU27*(1-IF(BV$1=1,Params!$B$33,IF(BV$1=2,Params!$B$35,IF(BV$1=3,Params!$B$37,Params!$B$39))))
A28: S_ANNUAL@1 | C28: =IF(C$1<12,1,Params!$B$41*Params!$B$43^(INT(C$1/12)-1)) | D28: =IF(D$1<12,1,Params!$B$41*Params!$B$43^(INT(D$1/12)-1)) | E28: =IF(E$1<12,1,Params!$B$41*Params!$B$43^(INT(E$1/12)-1)) | F28: =IF(F$1<12,1,Params!$B$41*Params!$B$43^(INT(F$1/12)-1)) | G28: =IF(G$1<12,1,Params!$B$41*Params!$B$43^(INT(G$1/12)-1)) | H28: =IF(H$1<12,1,Params!$B$41*Params!$B$43^(INT(H$1/12)-1)) | I28: =IF(I$1<12,1,Params!$B$41*Params!$B$43^(INT(I$1/12)-1)) | J28: =IF(J$1<12,1,Params!$B$41*Params!$B$43^(INT(J$1/12)-1)) | ... BV28: =IF(BV$1<12,1,Params!$B$41*Params!$B$43^(INT(BV$1/12)-1))
A29: D_MONTHLY@1 | C29: =0 | D29: =C27-D27 | E29: =D27-E27 | F29: =E27-F27 | G29: =F27-G27 | H29: =G27-H27 | I29: =H27-I27 | J29: =I27-J27 | K29: =J27-K27 | ... BV29: =BU27-BV27
A30: D_ANNUAL@1 | C30: =0 | D30: =C28-D28 | E30: =D28-E28 | F30: =E28-F28 | G30: =F28-G28 | H30: =G28-H28 | I30: =H28-I28 | J30: =I28-J28 | K30: =J28-K28 | ... BV30: =BU28-BV28
A31: S_REACT@1 | C31: =(1-Params!$B$49)^C$1 | D31: =(1-Params!$B$49)^D$1 | E31: =(1-Params!$B$49)^E$1 | F31: =(1-Params!$B$49)^F$1 | G31: =(1-Params!$B$49)^G$1 | H31: =(1-Params!$B$49)^H$1 | I31: =(1-Params!$B$49)^I$1 | J31: =(1-Params!$B$49)^J$1 | ... BV31: =(1-Params!$B$49)^BV$1
A32: D_REACT@1 | C32: =0 | D32: =C31-D31 | E32: =D31-E31 | F32: =E31-F31 | G32: =F31-G31 | H32: =G31-H31 | I32: =H31-I31 | J32: =I31-J31 | K32: =J31-K31 | ... BV32: =BU31-BV31
A33: K_REACT@1 | C33: =IF(AND(C$1>=1,C$1<=Params!$B$47),Params!$B$45*(1-Params!$B$45)^(C$1-1),0) | D33: =IF(AND(D$1>=1,D$1<=Params!$B$47),Params!$B$45*(1-Params!$B$45)^(D$1-1),0) | E33: =IF(AND(E$1>=1,E$1<=Params!$B$47),Params!$B$45*(1-Params!$B$45)^(E$1-1),0) | F33: =IF(AND(F$1>=1,F$1<=Params!$B$47),Params!$B$45*(1-Params!$B$45)^(F$1-1),0) | G33: =IF(AND(G$1>=1,G$1<=Params!$B$47),Params!$B$45*(1-Params!$B$45)^(G$1-1),0) | H33: =IF(AND(H$1>=1,H$1<=Params!$B$47),Params!$B$45*(1-Params!$B$45)^(H$1-1),0) | I33: =IF(AND(I$1>=1,I$1<=Params!$B$47),Params!$B$45*(1-Params!$B$45)^(I$1-1),0) | J33: =IF(AND(J$1>=1,J$1<=Params!$B$47),Params!$B$45*(1-Params!$B$45)^(J$1-1),0) | ... BV33: =IF(AND(BV$1>=1,BV$1<=Params!$B$47),Params!$B$45*(1-Params!$B$45)^(BV$1-1),0)
A34: S_MONTHLY_Y1@1 | C34: =IF(C$1<12,C27,0) | D34: =IF(D$1<12,D27,0) | E34: =IF(E$1<12,E27,0) | F34: =IF(F$1<12,F27,0) | G34: =IF(G$1<12,G27,0) | H34: =IF(H$1<12,H27,0) | I34: =IF(I$1<12,I27,0) | J34: =IF(J$1<12,J27,0) | ... BV34: =IF(BV$1<12,BV27,0)
A35: S_ANNUAL_Y1@1 | C35: =IF(C$1<12,C28,0) | D35: =IF(D$1<12,D28,0) | E35: =IF(E$1<12,E28,0) | F35: =IF(F$1<12,F28,0) | G35: =IF(G$1<12,G28,0) | H35: =IF(H$1<12,H28,0) | I35: =IF(I$1<12,I28,0) | J35: =IF(J$1<12,J28,0) | ... BV35: =IF(BV$1<12,BV28,0)
A36: S_REACT_Y1@1 | C36: =IF(C$1<12,C31,0) | D36: =IF(D$1<12,D31,0) | E36: =IF(E$1<12,E31,0) | F36: =IF(F$1<12,F31,0) | G36: =IF(G$1<12,G31,0) | H36: =IF(H$1<12,H31,0) | I36: =IF(I$1<12,I31,0) | J36: =IF(J$1<12,J31,0) | ... BV36: =IF(BV$1<12,BV31,0)
A38: S_MONTHLY@1 reversed | C38: =INDEX($C$27:$BV$27,72) | D38: =INDEX($C$27:$BV$27,71) | E38: =INDEX($C$27:$BV$27,70) | F38: =INDEX($C$27:$BV$27,69) | G38: =INDEX($C$27:$BV$27,68) | H38: =INDEX($C$27:$BV$27,67) | I38: =INDEX($C$27:$BV$27,66) | J38: =INDEX($C$27:$BV$27,65) | K38: =INDEX($C$27:$BV$27,64) | L38: =INDEX($C$27:$BV$27,63) | M38: =INDEX($C$27:$BV$27,62) | N38: =INDEX($C$27:$BV$27,61) | O38: =INDEX($C$27:$BV$27,60) | P38: =INDEX($C$27:$BV$27,59) | Q38: =INDEX($C$27:$BV$27,58) | R38: =INDEX($C$27:$BV$27,57) | S38: =INDEX($C$27:$BV$27,56) | T38: =INDEX($C$27:$BV$27,55) | U38: =INDEX($C$27:$BV$27,54) | V38: =INDEX($C$27:$BV$27,53) | W38: =INDEX($C$27:$BV$27,52) | X38: =INDEX($C$27:$BV$27,51) | Y38: =INDEX($C$27:$BV$27,50) | Z38: =INDEX($C$27:$BV$27,49) | AA38: =INDEX($C$27:$BV$27,48) | AB38: =INDEX($C$27:$BV$27,47) | AC38: =INDEX($C$27:$BV$27,46) | AD38: =INDEX($C$27:$BV$27,45) | AE38: =INDEX($C$27:$BV$27,44) | AF38: =INDEX($C$27:$BV$27,43) | AG38: =INDEX($C$27:$BV$27,42) | AH38: =INDEX($C$27:$BV$27,41) | AI38: =INDEX($C$27:$BV$27,40) | AJ38: =INDEX($C$27:$BV$27,39) | AK38: =INDEX($C$27:$BV$27,38) | AL38: =INDEX($C$27:$BV$27,37) | AM38: =INDEX($C$27:$BV$27,36) | AN38: =INDEX($C$27:$BV$27,35) | AO38: =INDEX($C$27:$BV$27,34) | AP38: =INDEX($C$27:$BV$27,33) | AQ38: =INDEX($C$27:$BV$27,32) | AR38: =INDEX($C$27:$BV$27,31) | AS38: =INDEX($C$27:$BV$27,30) | AT38: =INDEX($C$27:$BV$27,29) | AU38: =INDEX($C$27:$BV$27,28) | AV38: =INDEX($C$27:$BV$27,27) | AW38: =INDEX($C$27:$BV$27,26) | AX38: =INDEX($C$27:$BV$27,25) | AY38: =INDEX($C$27:$BV$27,24) | AZ38: =INDEX($C$27:$BV$27,23) | BA38: =INDEX($C$27:$BV$27,22) | BB38: =INDEX($C$27:$BV$27,21) | BC38: =INDEX($C$27:$BV$27,20) | BD38: =INDEX($C$27:$BV$27,19) | BE38: =INDEX($C$27:$BV$27,18) | BF38: =INDEX($C$27:$BV$27,17) | BG38: =INDEX($C$27:$BV$27,16) | BH38: =INDEX($C$27:$BV$27,15) | BI38: =INDEX($C$27:$BV$27,14) | BJ38: =INDEX($C$27:$BV$27,13) | BK38: =INDEX($C$27:$BV$27,12) | BL38: =INDEX($C$27:$BV$27,11) | BM38: =INDEX($C$27:$BV$27,10) | BN38: =INDEX($C$27:$BV$27,9) | BO38: =INDEX($C$27:$BV$27,8) | BP38: =INDEX($C$27:$BV$27,7) | BQ38: =INDEX($C$27:$BV$27,6) | BR38: =INDEX($C$27:$BV$27,5) | BS38: =INDEX($C$27:$BV$27,4) | BT38: =INDEX($C$27:$BV$27,3) | BU38: =INDEX($C$27:$BV$27,2) | BV38: =INDEX($C$27:$BV$27,1)
A39: S_ANNUAL@1 reversed | C39: =INDEX($C$28:$BV$28,72) | D39: =INDEX($C$28:$BV$28,71) | E39: =INDEX($C$28:$BV$28,70) | F39: =INDEX($C$28:$BV$28,69) | G39: =INDEX($C$28:$BV$28,68) | H39: =INDEX($C$28:$BV$28,67) | I39: =INDEX($C$28:$BV$28,66) | J39: =INDEX($C$28:$BV$28,65) | K39: =INDEX($C$28:$BV$28,64) | L39: =INDEX($C$28:$BV$28,63) | M39: =INDEX($C$28:$BV$28,62) | N39: =INDEX($C$28:$BV$28,61) | O39: =INDEX($C$28:$BV$28,60) | P39: =INDEX($C$28:$BV$28,59) | Q39: =INDEX($C$28:$BV$28,58) | R39: =INDEX($C$28:$BV$28,57) | S39: =INDEX($C$28:$BV$28,56) | T39: =INDEX($C$28:$BV$28,55) | U39: =INDEX($C$28:$BV$28,54) | V39: =INDEX($C$28:$BV$28,53) | W39: =INDEX($C$28:$BV$28,52) | X39: =INDEX($C$28:$BV$28,51) | Y39: =INDEX($C$28:$BV$28,50) | Z39: =INDEX($C$28:$BV$28,49) | AA39: =INDEX($C$28:$BV$28,48) | AB39: =INDEX($C$28:$BV$28,47) | AC39: =INDEX($C$28:$BV$28,46) | AD39: =INDEX($C$28:$BV$28,45) | AE39: =INDEX($C$28:$BV$28,44) | AF39: =INDEX($C$28:$BV$28,43) | AG39: =INDEX($C$28:$BV$28,42) | AH39: =INDEX($C$28:$BV$28,41) | AI39: =INDEX($C$28:$BV$28,40) | AJ39: =INDEX($C$28:$BV$28,39) | AK39: =INDEX($C$28:$BV$28,38) | AL39: =INDEX($C$28:$BV$28,37) | AM39: =INDEX($C$28:$BV$28,36) | AN39: =INDEX($C$28:$BV$28,35) | AO39: =INDEX($C$28:$BV$28,34) | AP39: =INDEX($C$28:$BV$28,33) | AQ39: =INDEX($C$28:$BV$28,32) | AR39: =INDEX($C$28:$BV$28,31) | AS39: =INDEX($C$28:$BV$28,30) | AT39: =INDEX($C$28:$BV$28,29) | AU39: =INDEX($C$28:$BV$28,28) | AV39: =INDEX($C$28:$BV$28,27) | AW39: =INDEX($C$28:$BV$28,26) | AX39: =INDEX($C$28:$BV$28,25) | AY39: =INDEX($C$28:$BV$28,24) | AZ39: =INDEX($C$28:$BV$28,23) | BA39: =INDEX($C$28:$BV$28,22) | BB39: =INDEX($C$28:$BV$28,21) | BC39: =INDEX($C$28:$BV$28,20) | BD39: =INDEX($C$28:$BV$28,19) | BE39: =INDEX($C$28:$BV$28,18) | BF39: =INDEX($C$28:$BV$28,17) | BG39: =INDEX($C$28:$BV$28,16) | BH39: =INDEX($C$28:$BV$28,15) | BI39: =INDEX($C$28:$BV$28,14) | BJ39: =INDEX($C$28:$BV$28,13) | BK39: =INDEX($C$28:$BV$28,12) | BL39: =INDEX($C$28:$BV$28,11) | BM39: =INDEX($C$28:$BV$28,10) | BN39: =INDEX($C$28:$BV$28,9) | BO39: =INDEX($C$28:$BV$28,8) | BP39: =INDEX($C$28:$BV$28,7) | BQ39: =INDEX($C$28:$BV$28,6) | BR39: =INDEX($C$28:$BV$28,5) | BS39: =INDEX($C$28:$BV$28,4) | BT39: =INDEX($C$28:$BV$28,3) | BU39: =INDEX($C$28:$BV$28,2) | BV39: =INDEX($C$28:$BV$28,1)
A40: D_MONTHLY@1 reversed | C40: =INDEX($C$29:$BV$29,72) | D40: =INDEX($C$29:$BV$29,71) | E40: =INDEX($C$29:$BV$29,70) | F40: =INDEX($C$29:$BV$29,69) | G40: =INDEX($C$29:$BV$29,68) | H40: =INDEX($C$29:$BV$29,67) | I40: =INDEX($C$29:$BV$29,66) | J40: =INDEX($C$29:$BV$29,65) | K40: =INDEX($C$29:$BV$29,64) | L40: =INDEX($C$29:$BV$29,63) | M40: =INDEX($C$29:$BV$29,62) | N40: =INDEX($C$29:$BV$29,61) | O40: =INDEX($C$29:$BV$29,60) | P40: =INDEX($C$29:$BV$29,59) | Q40: =INDEX($C$29:$BV$29,58) | R40: =INDEX($C$29:$BV$29,57) | S40: =INDEX($C$29:$BV$29,56) | T40: =INDEX($C$29:$BV$29,55) | U40: =INDEX($C$29:$BV$29,54) | V40: =INDEX($C$29:$BV$29,53) | W40: =INDEX($C$29:$BV$29,52) | X40: =INDEX($C$29:$BV$29,51) | Y40: =INDEX($C$29:$BV$29,50) | Z40: =INDEX($C$29:$BV$29,49) | AA40: =INDEX($C$29:$BV$29,48) | AB40: =INDEX($C$29:$BV$29,47) | AC40: =INDEX($C$29:$BV$29,46) | AD40: =INDEX($C$29:$BV$29,45) | AE40: =INDEX($C$29:$BV$29,44) | AF40: =INDEX($C$29:$BV$29,43) | AG40: =INDEX($C$29:$BV$29,42) | AH40: =INDEX($C$29:$BV$29,41) | AI40: =INDEX($C$29:$BV$29,40) | AJ40: =INDEX($C$29:$BV$29,39) | AK40: =INDEX($C$29:$BV$29,38) | AL40: =INDEX($C$29:$BV$29,37) | AM40: =INDEX($C$29:$BV$29,36) | AN40: =INDEX($C$29:$BV$29,35) | AO40: =INDEX($C$29:$BV$29,34) | AP40: =INDEX($C$29:$BV$29,33) | AQ40: =INDEX($C$29:$BV$29,32) | AR40: =INDEX($C$29:$BV$29,31) | AS40: =INDEX($C$29:$BV$29,30) | AT40: =INDEX($C$29:$BV$29,29) | AU40: =INDEX($C$29:$BV$29,28) | AV40: =INDEX($C$29:$BV$29,27) | AW40: =INDEX($C$29:$BV$29,26) | AX40: =INDEX($C$29:$BV$29,25) | AY40: =INDEX($C$29:$BV$29,24) | AZ40: =INDEX($C$29:$BV$29,23) | BA40: =INDEX($C$29:$BV$29,22) | BB40: =INDEX($C$29:$BV$29,21) | BC40: =INDEX($C$29:$BV$29,20) | BD40: =INDEX($C$29:$BV$29,19) | BE40: =INDEX($C$29:$BV$29,18) | BF40: =INDEX($C$29:$BV$29,17) | BG40: =INDEX($C$29:$BV$29,16) | BH40: =INDEX($C$29:$BV$29,15) | BI40: =INDEX($C$29:$BV$29,14) | BJ40: =INDEX($C$29:$BV$29,13) | BK40: =INDEX($C$29:$BV$29,12) | BL40: =INDEX($C$29:$BV$29,11) | BM40: =INDEX($C$29:$BV$29,10) | BN40: =INDEX($C$29:$BV$29,9) | BO40: =INDEX($C$29:$BV$29,8) | BP40: =INDEX($C$29:$BV$29,7) | BQ40: =INDEX($C$29:$BV$29,6) | BR40: =INDEX($C$29:$BV$29,5) | BS40: =INDEX($C$29:$BV$29,4) | BT40: =INDEX($C$29:$BV$29,3) | BU40: =INDEX($C$29:$BV$29,2) | BV40: =INDEX($C$29:$BV$29,1)
A41: D_ANNUAL@1 reversed | C41: =INDEX($C$30:$BV$30,72) | D41: =INDEX($C$30:$BV$30,71) | E41: =INDEX($C$30:$BV$30,70) | F41: =INDEX($C$30:$BV$30,69) | G41: =INDEX($C$30:$BV$30,68) | H41: =INDEX($C$30:$BV$30,67) | I41: =INDEX($C$30:$BV$30,66) | J41: =INDEX($C$30:$BV$30,65) | K41: =INDEX($C$30:$BV$30,64) | L41: =INDEX($C$30:$BV$30,63) | M41: =INDEX($C$30:$BV$30,62) | N41: =INDEX($C$30:$BV$30,61) | O41: =INDEX($C$30:$BV$30,60) | P41: =INDEX($C$30:$BV$30,59) | Q41: =INDEX($C$30:$BV$30,58) | R41: =INDEX($C$30:$BV$30,57) | S41: =INDEX($C$30:$BV$30,56) | T41: =INDEX($C$30:$BV$30,55) | U41: =INDEX($C$30:$BV$30,54) | V41: =INDEX($C$30:$BV$30,53) | W41: =INDEX($C$30:$BV$30,52) | X41: =INDEX($C$30:$BV$30,51) | Y41: =INDEX($C$30:$BV$30,50) | Z41: =INDEX($C$30:$BV$30,49) | AA41: =INDEX($C$30:$BV$30,48) | AB41: =INDEX($C$30:$BV$30,47) | AC41: =INDEX($C$30:$BV$30,46) | AD41: =INDEX($C$30:$BV$30,45) | AE41: =INDEX($C$30:$BV$30,44) | AF41: =INDEX($C$30:$BV$30,43) | AG41: =INDEX($C$30:$BV$30,42) | AH41: =INDEX($C$30:$BV$30,41) | AI41: =INDEX($C$30:$BV$30,40) | AJ41: =INDEX($C$30:$BV$30,39) | AK41: =INDEX($C$30:$BV$30,38) | AL41: =INDEX($C$30:$BV$30,37) | AM41: =INDEX($C$30:$BV$30,36) | AN41: =INDEX($C$30:$BV$30,35) | AO41: =INDEX($C$30:$BV$30,34) | AP41: =INDEX($C$30:$BV$30,33) | AQ41: =INDEX($C$30:$BV$30,32) | AR41: =INDEX($C$30:$BV$30,31) | AS41: =INDEX($C$30:$BV$30,30) | AT41: =INDEX($C$30:$BV$30,29) | AU41: =INDEX($C$30:$BV$30,28) | AV41: =INDEX($C$30:$BV$30,27) | AW41: =INDEX($C$30:$BV$30,26) | AX41: =INDEX($C$30:$BV$30,25) | AY41: =INDEX($C$30:$BV$30,24) | AZ41: =INDEX($C$30:$BV$30,23) | BA41: =INDEX($C$30:$BV$30,22) | BB41: =INDEX($C$30:$BV$30,21) | BC41: =INDEX($C$30:$BV$30,20) | BD41: =INDEX($C$30:$BV$30,19) | BE41: =INDEX($C$30:$BV$30,18) | BF41: =INDEX($C$30:$BV$30,17) | BG41: =INDEX($C$30:$BV$30,16) | BH41: =INDEX($C$30:$BV$30,15) | BI41: =INDEX($C$30:$BV$30,14) | BJ41: =INDEX($C$30:$BV$30,13) | BK41: =INDEX($C$30:$BV$30,12) | BL41: =INDEX($C$30:$BV$30,11) | BM41: =INDEX($C$30:$BV$30,10) | BN41: =INDEX($C$30:$BV$30,9) | BO41: =INDEX($C$30:$BV$30,8) | BP41: =INDEX($C$30:$BV$30,7) | BQ41: =INDEX($C$30:$BV$30,6) | BR41: =INDEX($C$30:$BV$30,5) | BS41: =INDEX($C$30:$BV$30,4) | BT41: =INDEX($C$30:$BV$30,3) | BU41: =INDEX($C$30:$BV$30,2) | BV41: =INDEX($C$30:$BV$30,1)
A42: S_REACT@1 reversed | C42: =INDEX($C$31:$BV$31,72) | D42: =INDEX($C$31:$BV$31,71) | E42: =INDEX($C$31:$BV$31,70) | F42: =INDEX($C$31:$BV$31,69) | G42: =INDEX($C$31:$BV$31,68) | H42: =INDEX($C$31:$BV$31,67) | I42: =INDEX($C$31:$BV$31,66) | J42: =INDEX($C$31:$BV$31,65) | K42: =INDEX($C$31:$BV$31,64) | L42: =INDEX($C$31:$BV$31,63) | M42: =INDEX($C$31:$BV$31,62) | N42: =INDEX($C$31:$BV$31,61) | O42: =INDEX($C$31:$BV$31,60) | P42: =INDEX($C$31:$BV$31,59) | Q42: =INDEX($C$31:$BV$31,58) | R42: =INDEX($C$31:$BV$31,57) | S42: =INDEX($C$31:$BV$31,56) | T42: =INDEX($C$31:$BV$31,55) | U42: =INDEX($C$31:$BV$31,54) | V42: =INDEX($C$31:$BV$31,53) | W42: =INDEX($C$31:$BV$31,52) | X42: =INDEX($C$31:$BV$31,51) | Y42: =INDEX($C$31:$BV$31,50) | Z42: =INDEX($C$31:$BV$31,49) | AA42: =INDEX($C$31:$BV$31,48) | AB42: =INDEX($C$31:$BV$31,47) | AC42: =INDEX($C$31:$BV$31,46) | AD42: =INDEX($C$31:$BV$31,45) | AE42: =INDEX($C$31:$BV$31,44) | AF42: =INDEX($C$31:$BV$31,43) | AG42: =INDEX($C$31:$BV$31,42) | AH42: =INDEX($C$31:$BV$31,41) | AI42: =INDEX($C$31:$BV$31,40) | AJ42: =INDEX($C$31:$BV$31,39) | AK42: =INDEX($C$31:$BV$31,38) | AL42: =INDEX($C$31:$BV$31,37) | AM42: =INDEX($C$31:$BV$31,36) | AN42: =INDEX($C$31:$BV$31,35) | AO42: =INDEX($C$31:$BV$31,34) | AP42: =INDEX($C$31:$BV$31,33) | AQ42: =INDEX($C$31:$BV$31,32) | AR42: =INDEX($C$31:$BV$31,31) | AS42: =INDEX($C$31:$BV$31,30) | AT42: =INDEX($C$31:$BV$31,29) | AU42: =INDEX($C$31:$BV$31,28) | AV42: =INDEX($C$31:$BV$31,27) | AW42: =INDEX($C$31:$BV$31,26) | AX42: =INDEX($C$31:$BV$31,25) | AY42: =INDEX($C$31:$BV$31,24) | AZ42: =INDEX($C$31:$BV$31,23) | BA42: =INDEX($C$31:$BV$31,22) | BB42: =INDEX($C$31:$BV$31,21) | BC42: =INDEX($C$31:$BV$31,20) | BD42: =INDEX($C$31:$BV$31,19) | BE42: =INDEX($C$31:$BV$31,18) | BF42: =INDEX($C$31:$BV$31,17) | BG42: =INDEX($C$31:$BV$31,16) | BH42: =INDEX($C$31:$BV$31,15) | BI42: =INDEX($C$31:$BV$31,14) | BJ42: =INDEX($C$31:$BV$31,13) | BK42: =INDEX($C$31:$BV$31,12) | BL42: =INDEX($C$31:$BV$31,11) | BM42: =INDEX($C$31:$BV$31,10) | BN42: =INDEX($C$31:$BV$31,9) | BO42: =INDEX($C$31:$BV$31,8) | BP42: =INDEX($C$31:$BV$31,7) | BQ42: =INDEX($C$31:$BV$31,6) | BR42: =INDEX($C$31:$BV$31,5) | BS42: =INDEX($C$31:$BV$31,4) | BT42: =INDEX($C$31:$BV$31,3) | BU42: =INDEX($C$31:$BV$31,2) | BV42: =INDEX($C$31:$BV$31,1)
A43: D_REACT@1 reversed | C43: =INDEX($C$32:$BV$32,72) | D43: =INDEX($C$32:$BV$32,71) | E43: =INDEX($C$32:$BV$32,70) | F43: =INDEX($C$32:$BV$32,69) | G43: =INDEX($C$32:$BV$32,68) | H43: =INDEX($C$32:$BV$32,67) | I43: =INDEX($C$32:$BV$32,66) | J43: =INDEX($C$32:$BV$32,65) | K43: =INDEX($C$32:$BV$32,64) | L43: =INDEX($C$32:$BV$32,63) | M43: =INDEX($C$32:$BV$32,62) | N43: =INDEX($C$32:$BV$32,61) | O43: =INDEX($C$32:$BV$32,60) | P43: =INDEX($C$32:$BV$32,59) | Q43: =INDEX($C$32:$BV$32,58) | R43: =INDEX($C$32:$BV$32,57) | S43: =INDEX($C$32:$BV$32,56) | T43: =INDEX($C$32:$BV$32,55) | U43: =INDEX($C$32:$BV$32,54) | V43: =INDEX($C$32:$BV$32,53) | W43: =INDEX($C$32:$BV$32,52) | X43: =INDEX($C$32:$BV$32,51) | Y43: =INDEX($C$32:$BV$32,50) | Z43: =INDEX($C$32:$BV$32,49) | AA43: =INDEX($C$32:$BV$32,48) | AB43: =INDEX($C$32:$BV$32,47) | AC43: =INDEX($C$32:$BV$32,46) | AD43: =INDEX($C$32:$BV$32,45) | AE43: =INDEX($C$32:$BV$32,44) | AF43: =INDEX($C$32:$BV$32,43) | AG43: =INDEX($C$32:$BV$32,42) | AH43: =INDEX($C$32:$BV$32,41) | AI43: =INDEX($C$32:$BV$32,40) | AJ43: =INDEX($C$32:$BV$32,39) | AK43: =INDEX($C$32:$BV$32,38) | AL43: =INDEX($C$32:$BV$32,37) | AM43: =INDEX($C$32:$BV$32,36) | AN43: =INDEX($C$32:$BV$32,35) | AO43: =INDEX($C$32:$BV$32,34) | AP43: =INDEX($C$32:$BV$32,33) | AQ43: =INDEX($C$32:$BV$32,32) | AR43: =INDEX($C$32:$BV$32,31) | AS43: =INDEX($C$32:$BV$32,30) | AT43: =INDEX($C$32:$BV$32,29) | AU43: =INDEX($C$32:$BV$32,28) | AV43: =INDEX($C$32:$BV$32,27) | AW43: =INDEX($C$32:$BV$32,26) | AX43: =INDEX($C$32:$BV$32,25) | AY43: =INDEX($C$32:$BV$32,24) | AZ43: =INDEX($C$32:$BV$32,23) | BA43: =INDEX($C$32:$BV$32,22) | BB43: =INDEX($C$32:$BV$32,21) | BC43: =INDEX($C$32:$BV$32,20) | BD43: =INDEX($C$32:$BV$32,19) | BE43: =INDEX($C$32:$BV$32,18) | BF43: =INDEX($C$32:$BV$32,17) | BG43: =INDEX($C$32:$BV$32,16) | BH43: =INDEX($C$32:$BV$32,15) | BI43: =INDEX($C$32:$BV$32,14) | BJ43: =INDEX($C$32:$BV$32,13) | BK43: =INDEX($C$32:$BV$32,12) | BL43: =INDEX($C$32:$BV$32,11) | BM43: =INDEX($C$32:$BV$32,10) | BN43: =INDEX($C$32:$BV$32,9) | BO43: =INDEX($C$32:$BV$32,8) | BP43: =INDEX($C$32:$BV$32,7) | BQ43: =INDEX($C$32:$BV$32,6) | BR43: =INDEX($C$32:$BV$32,5) | BS43: =INDEX($C$32:$BV$32,4) | BT43: =INDEX($C$32:$BV$32,3) | BU43: =INDEX($C$32:$BV$32,2) | BV43: =INDEX($C$32:$BV$32,1)
A44: K_REACT@1 reversed | C44: =INDEX($C$33:$BV$33,72) | D44: =INDEX($C$33:$BV$33,71) | E44: =INDEX($C$33:$BV$33,70) | F44: =INDEX($C$33:$BV$33,69) | G44: =INDEX($C$33:$BV$33,68) | H44: =INDEX($C$33:$BV$33,67) | I44: =INDEX($C$33:$BV$33,66) | J44: =INDEX($C$33:$BV$33,65) | K44: =INDEX($C$33:$BV$33,64) | L44: =INDEX($C$33:$BV$33,63) | M44: =INDEX($C$33:$BV$33,62) | N44: =INDEX($C$33:$BV$33,61) | O44: =INDEX($C$33:$BV$33,60) | P44: =INDEX($C$33:$BV$33,59) | Q44: =INDEX($C$33:$BV$33,58) | R44: =INDEX($C$33:$BV$33,57) | S44: =INDEX($C$33:$BV$33,56) | T44: =INDEX($C$33:$BV$33,55) | U44: =INDEX($C$33:$BV$33,54) | V44: =INDEX($C$33:$BV$33,53) | W44: =INDEX($C$33:$BV$33,52) | X44: =INDEX($C$33:$BV$33,51) | Y44: =INDEX($C$33:$BV$33,50) | Z44: =INDEX($C$33:$BV$33,49) | AA44: =INDEX($C$33:$BV$33,48) | AB44: =INDEX($C$33:$BV$33,47) | AC44: =INDEX($C$33:$BV$33,46) | AD44: =INDEX($C$33:$BV$33,45) | AE44: =INDEX($C$33:$BV$33,44) | AF44: =INDEX($C$33:$BV$33,43) | AG44: =INDEX($C$33:$BV$33,42) | AH44: =INDEX($C$33:$BV$33,41) | AI44: =INDEX($C$33:$BV$33,40) | AJ44: =INDEX($C$33:$BV$33,39) | AK44: =INDEX($C$33:$BV$33,38) | AL44: =INDEX($C$33:$BV$33,37) | AM44: =INDEX($C$33:$BV$33,36) | AN44: =INDEX($C$33:$BV$33,35) | AO44: =INDEX($C$33:$BV$33,34) | AP44: =INDEX($C$33:$BV$33,33) | AQ44: =INDEX($C$33:$BV$33,32) | AR44: =INDEX($C$33:$BV$33,31) | AS44: =INDEX($C$33:$BV$33,30) | AT44: =INDEX($C$33:$BV$33,29) | AU44: =INDEX($C$33:$BV$33,28) | AV44: =INDEX($C$33:$BV$33,27) | AW44: =INDEX($C$33:$BV$33,26) | AX44: =INDEX($C$33:$BV$33,25) | AY44: =INDEX($C$33:$BV$33,24) | AZ44: =INDEX($C$33:$BV$33,23) | BA44: =INDEX($C$33:$BV$33,22) | BB44: =INDEX($C$33:$BV$33,21) | BC44: =INDEX($C$33:$BV$33,20) | BD44: =INDEX($C$33:$BV$33,19) | BE44: =INDEX($C$33:$BV$33,18) | BF44: =INDEX($C$33:$BV$33,17) | BG44: =INDEX($C$33:$BV$33,16) | BH44: =INDEX($C$33:$BV$33,15) | BI44: =INDEX($C$33:$BV$33,14) | BJ44: =INDEX($C$33:$BV$33,13) | BK44: =INDEX($C$33:$BV$33,12) | BL44: =INDEX($C$33:$BV$33,11) | BM44: =INDEX($C$33:$BV$33,10) | BN44: =INDEX($C$33:$BV$33,9) | BO44: =INDEX($C$33:$BV$33,8) | BP44: =INDEX($C$33:$BV$33,7) | BQ44: =INDEX($C$33:$BV$33,6) | BR44: =INDEX($C$33:$BV$33,5) | BS44: =INDEX($C$33:$BV$33,4) | BT44: =INDEX($C$33:$BV$33,3) | BU44: =INDEX($C$33:$BV$33,2) | BV44: =INDEX($C$33:$BV$33,1)
A45: S_MONTHLY_Y1@1 reversed | C45: =INDEX($C$34:$BV$34,72) | D45: =INDEX($C$34:$BV$34,71) | E45: =INDEX($C$34:$BV$34,70) | F45: =INDEX($C$34:$BV$34,69) | G45: =INDEX($C$34:$BV$34,68) | H45: =INDEX($C$34:$BV$34,67) | I45: =INDEX($C$34:$BV$34,66) | J45: =INDEX($C$34:$BV$34,65) | K45: =INDEX($C$34:$BV$34,64) | L45: =INDEX($C$34:$BV$34,63) | M45: =INDEX($C$34:$BV$34,62) | N45: =INDEX($C$34:$BV$34,61) | O45: =INDEX($C$34:$BV$34,60) | P45: =INDEX($C$34:$BV$34,59) | Q45: =INDEX($C$34:$BV$34,58) | R45: =INDEX($C$34:$BV$34,57) | S45: =INDEX($C$34:$BV$34,56) | T45: =INDEX($C$34:$BV$34,55) | U45: =INDEX($C$34:$BV$34,54) | V45: =INDEX($C$34:$BV$34,53) | W45: =INDEX($C$34:$BV$34,52) | X45: =INDEX($C$34:$BV$34,51) | Y45: =INDEX($C$34:$BV$34,50) | Z45: =INDEX($C$34:$BV$34,49) | AA45: =INDEX($C$34:$BV$34,48) | AB45: =INDEX($C$34:$BV$34,47) | AC45: =INDEX($C$34:$BV$34,46) | AD45: =INDEX($C$34:$BV$34,45) | AE45: =INDEX($C$34:$BV$34,44) | AF45: =INDEX($C$34:$BV$34,43) | AG45: =INDEX($C$34:$BV$34,42) | AH45: =INDEX($C$34:$BV$34,41) | AI45: =INDEX($C$34:$BV$34,40) | AJ45: =INDEX($C$34:$BV$34,39) | AK45: =INDEX($C$34:$BV$34,38) | AL45: =INDEX($C$34:$BV$34,37) | AM45: =INDEX($C$34:$BV$34,36) | AN45: =INDEX($C$34:$BV$34,35) | AO45: =INDEX($C$34:$BV$34,34) | AP45: =INDEX($C$34:$BV$34,33) | AQ45: =INDEX($C$34:$BV$34,32) | AR45: =INDEX($C$34:$BV$34,31) | AS45: =INDEX($C$34:$BV$34,30) | AT45: =INDEX($C$34:$BV$34,29) | AU45: =INDEX($C$34:$BV$34,28) | AV45: =INDEX($C$34:$BV$34,27) | AW45: =INDEX($C$34:$BV$34,26) | AX45: =INDEX($C$34:$BV$34,25) | AY45: =INDEX($C$34:$BV$34,24) | AZ45: =INDEX($C$34:$BV$34,23) | BA45: =INDEX($C$34:$BV$34,22) | BB45: =INDEX($C$34:$BV$34,21) | BC45: =INDEX($C$34:$BV$34,20) | BD45: =INDEX($C$34:$BV$34,19) | BE45: =INDEX($C$34:$BV$34,18) | BF45: =INDEX($C$34:$BV$34,17) | BG45: =INDEX($C$34:$BV$34,16) | BH45: =INDEX($C$34:$BV$34,15) | BI45: =INDEX($C$34:$BV$34,14) | BJ45: =INDEX($C$34:$BV$34,13) | BK45: =INDEX($C$34:$BV$34,12) | BL45: =INDEX($C$34:$BV$34,11) | BM45: =INDEX($C$34:$BV$34,10) | BN45: =INDEX($C$34:$BV$34,9) | BO45: =INDEX($C$34:$BV$34,8) | BP45: =INDEX($C$34:$BV$34,7) | BQ45: =INDEX($C$34:$BV$34,6) | BR45: =INDEX($C$34:$BV$34,5) | BS45: =INDEX($C$34:$BV$34,4) | BT45: =INDEX($C$34:$BV$34,3) | BU45: =INDEX($C$34:$BV$34,2) | BV45: =INDEX($C$34:$BV$34,1)
A46: S_ANNUAL_Y1@1 reversed | C46: =INDEX($C$35:$BV$35,72) | D46: =INDEX($C$35:$BV$35,71) | E46: =INDEX($C$35:$BV$35,70) | F46: =INDEX($C$35:$BV$35,69) | G46: =INDEX($C$35:$BV$35,68) | H46: =INDEX($C$35:$BV$35,67) | I46: =INDEX($C$35:$BV$35,66) | J46: =INDEX($C$35:$BV$35,65) | K46: =INDEX($C$35:$BV$35,64) | L46: =INDEX($C$35:$BV$35,63) | M46: =INDEX($C$35:$BV$35,62) | N46: =INDEX($C$35:$BV$35,61) | O46: =INDEX($C$35:$BV$35,60) | P46: =INDEX($C$35:$BV$35,59) | Q46: =INDEX($C$35:$BV$35,58) | R46: =INDEX($C$35:$BV$35,57) | S46: =INDEX($C$35:$BV$35,56) | T46: =INDEX($C$35:$BV$35,55) | U46: =INDEX($C$35:$BV$35,54) | V46: =INDEX($C$35:$BV$35,53) | W46: =INDEX($C$35:$BV$35,52) | X46: =INDEX($C$35:$BV$35,51) | Y46: =INDEX($C$35:$BV$35,50) | Z46: =INDEX($C$35:$BV$35,49) | AA46: =INDEX($C$35:$BV$35,48) | AB46: =INDEX($C$35:$BV$35,47) | AC46: =INDEX($C$35:$BV$35,46) | AD46: =INDEX($C$35:$BV$35,45) | AE46: =INDEX($C$35:$BV$35,44) | AF46: =INDEX($C$35:$BV$35,43) | AG46: =INDEX($C$35:$BV$35,42) | AH46: =INDEX($C$35:$BV$35,41) | AI46: =INDEX($C$35:$BV$35,40) | AJ46: =INDEX($C$35:$BV$35,39) | AK46: =INDEX($C$35:$BV$35,38) | AL46: =INDEX($C$35:$BV$35,37) | AM46: =INDEX($C$35:$BV$35,36) | AN46: =INDEX($C$35:$BV$35,35) | AO46: =INDEX($C$35:$BV$35,34) | AP46: =INDEX($C$35:$BV$35,33) | AQ46: =INDEX($C$35:$BV$35,32) | AR46: =INDEX($C$35:$BV$35,31) | AS46: =INDEX($C$35:$BV$35,30) | AT46: =INDEX($C$35:$BV$35,29) | AU46: =INDEX($C$35:$BV$35,28) | AV46: =INDEX($C$35:$BV$35,27) | AW46: =INDEX($C$35:$BV$35,26) | AX46: =INDEX($C$35:$BV$35,25) | AY46: =INDEX($C$35:$BV$35,24) | AZ46: =INDEX($C$35:$BV$35,23) | BA46: =INDEX($C$35:$BV$35,22) | BB46: =INDEX($C$35:$BV$35,21) | BC46: =INDEX($C$35:$BV$35,20) | BD46: =INDEX($C$35:$BV$35,19) | BE46: =INDEX($C$35:$BV$35,18) | BF46: =INDEX($C$35:$BV$35,17) | BG46: =INDEX($C$35:$BV$35,16) | BH46: =INDEX($C$35:$BV$35,15) | BI46: =INDEX($C$35:$BV$35,14) | BJ46: =INDEX($C$35:$BV$35,13) | BK46: =INDEX($C$35:$BV$35,12) | BL46: =INDEX($C$35:$BV$35,11) | BM46: =INDEX($C$35:$BV$35,10) | BN46: =INDEX($C$35:$BV$35,9) | BO46: =INDEX($C$35:$BV$35,8) | BP46: =INDEX($C$35:$BV$35,7) | BQ46: =INDEX($C$35:$BV$35,6) | BR46: =INDEX($C$35:$BV$35,5) | BS46: =INDEX($C$35:$BV$35,4) | BT46: =INDEX($C$35:$BV$35,3) | BU46: =INDEX($C$35:$BV$35,2) | BV46: =INDEX($C$35:$BV$35,1)
A47: S_REACT_Y1@1 reversed | C47: =INDEX($C$36:$BV$36,72) | D47: =INDEX($C$36:$BV$36,71) | E47: =INDEX($C$36:$BV$36,70) | F47: =INDEX($C$36:$BV$36,69) | G47: =INDEX($C$36:$BV$36,68) | H47: =INDEX($C$36:$BV$36,67) | I47: =INDEX($C$36:$BV$36,66) | J47: =INDEX($C$36:$BV$36,65) | K47: =INDEX($C$36:$BV$36,64) | L47: =INDEX($C$36:$BV$36,63) | M47: =INDEX($C$36:$BV$36,62) | N47: =INDEX($C$36:$BV$36,61) | O47: =INDEX($C$36:$BV$36,60) | P47: =INDEX($C$36:$BV$36,59) | Q47: =INDEX($C$36:$BV$36,58) | R47: =INDEX($C$36:$BV$36,57) | S47: =INDEX($C$36:$BV$36,56) | T47: =INDEX($C$36:$BV$36,55) | U47: =INDEX($C$36:$BV$36,54) | V47: =INDEX($C$36:$BV$36,53) | W47: =INDEX($C$36:$BV$36,52) | X47: =INDEX($C$36:$BV$36,51) | Y47: =INDEX($C$36:$BV$36,50) | Z47: =INDEX($C$36:$BV$36,49) | AA47: =INDEX($C$36:$BV$36,48) | AB47: =INDEX($C$36:$BV$36,47) | AC47: =INDEX($C$36:$BV$36,46) | AD47: =INDEX($C$36:$BV$36,45) | AE47: =INDEX($C$36:$BV$36,44) | AF47: =INDEX($C$36:$BV$36,43) | AG47: =INDEX($C$36:$BV$36,42) | AH47: =INDEX($C$36:$BV$36,41) | AI47: =INDEX($C$36:$BV$36,40) | AJ47: =INDEX($C$36:$BV$36,39) | AK47: =INDEX($C$36:$BV$36,38) | AL47: =INDEX($C$36:$BV$36,37) | AM47: =INDEX($C$36:$BV$36,36) | AN47: =INDEX($C$36:$BV$36,35) | AO47: =INDEX($C$36:$BV$36,34) | AP47: =INDEX($C$36:$BV$36,33) | AQ47: =INDEX($C$36:$BV$36,32) | AR47: =INDEX($C$36:$BV$36,31) | AS47: =INDEX($C$36:$BV$36,30) | AT47: =INDEX($C$36:$BV$36,29) | AU47: =INDEX($C$36:$BV$36,28) | AV47: =INDEX($C$36:$BV$36,27) | AW47: =INDEX($C$36:$BV$36,26) | AX47: =INDEX($C$36:$BV$36,25) | AY47: =INDEX($C$36:$BV$36,24) | AZ47: =INDEX($C$36:$BV$36,23) | BA47: =INDEX($C$36:$BV$36,22) | BB47: =INDEX($C$36:$BV$36,21) | BC47: =INDEX($C$36:$BV$36,20) | BD47: =INDEX($C$36:$BV$36,19) | BE47: =INDEX($C$36:$BV$36,18) | BF47: =INDEX($C$36:$BV$36,17) | BG47: =INDEX($C$36:$BV$36,16) | BH47: =INDEX($C$36:$BV$36,15) | BI47: =INDEX($C$36:$BV$36,14) | BJ47: =INDEX($C$36:$BV$36,13) | BK47: =INDEX($C$36:$BV$36,12) | BL47: =INDEX($C$36:$BV$36,11) | BM47: =INDEX($C$36:$BV$36,10) | BN47: =INDEX($C$36:$BV$36,9) | BO47: =INDEX($C$36:$BV$36,8) | BP47: =INDEX($C$36:$BV$36,7) | BQ47: =INDEX($C$36:$BV$36,6) | BR47: =INDEX($C$36:$BV$36,5) | BS47: =INDEX($C$36:$BV$36,4) | BT47: =INDEX($C$36:$BV$36,3) | BU47: =INDEX($C$36:$BV$36,2) | BV47: =INDEX($C$36:$BV$36,1)
A49: @2: experiment
A50: S_MONTHLY@2 | C50: =1 | D50: =C50*(1-IF(D$1=1,MIN(1,Params!$B$33*(1+Params!$B$12)),IF(D$1=2,MIN(1,Params!$B$35*(1+Params!$B$12)),IF(D$1=3,MIN(1,Params!$B$37*(1+Params!$B$12)),MIN(1,Params!$B$39*(1+Params!$B$12)))))) | E50: =D50*(1-IF(E$1=1,MIN(1,Params!$B$33*(1+Params!$B$12)),IF(E$1=2,MIN(1,Params!$B$35*(1+Params!$B$12)),IF(E$1=3,MIN(1,Params!$B$37*(1+Params!$B$12)),MIN(1,Params!$B$39*(1+Params!$B$12)))))) | F50: =E50*(1-IF(F$1=1,MIN(1,Params!$B$33*(1+Params!$B$12)),IF(F$1=2,MIN(1,Params!$B$35*(1+Params!$B$12)),IF(F$1=3,MIN(1,Params!$B$37*(1+Params!$B$12)),MIN(1,Params!$B$39*(1+Params!$B$12)))))) | G50: =F50*(1-IF(G$1=1,MIN(1,Params!$B$33*(1+Params!$B$12)),IF(G$1=2,MIN(1,Params!$B$35*(1+Params!$B$12)),IF(G$1=3,MIN(1,Params!$B$37*(1+Params!$B$12)),MIN(1,Params!$B$39*(1+Params!$B$12)))))) | H50: =G50*(1-IF(H$1=1,MIN(1,Params!$B$33*(1+Params!$B$12)),IF(H$1=2,MIN(1,Params!$B$35*(1+Params!$B$12)),IF(H$1=3,MIN(1,Params!$B$37*(1+Params!$B$12)),MIN(1,Params!$B$39*(1+Params!$B$12)))))) | I50: =H50*(1-IF(I$1=1,MIN(1,Params!$B$33*(1+Params!$B$12)),IF(I$1=2,MIN(1,Params!$B$35*(1+Params!$B$12)),IF(I$1=3,MIN(1,Params!$B$37*(1+Params!$B$12)),MIN(1,Params!$B$39*(1+Params!$B$12)))))) | J50: =I50*(1-IF(J$1=1,MIN(1,Params!$B$33*(1+Params!$B$12)),IF(J$1=2,MIN(1,Params!$B$35*(1+Params!$B$12)),IF(J$1=3,MIN(1,Params!$B$37*(1+Params!$B$12)),MIN(1,Params!$B$39*(1+Params!$B$12)))))) | K50: =J50*(1-IF(K$1=1,MIN(1,Params!$B$33*(1+Params!$B$12)),IF(K$1=2,MIN(1,Params!$B$35*(1+Params!$B$12)),IF(K$1=3,MIN(1,Params!$B$37*(1+Params!$B$12)),MIN(1,Params!$B$39*(1+Params!$B$12)))))) | ... BV50: =BU50*(1-IF(BV$1=1,MIN(1,Params!$B$33*(1+Params!$B$12)),IF(BV$1=2,MIN(1,Params!$B$35*(1+Params!$B$12)),IF(BV$1=3,MIN(1,Params!$B$37*(1+Params!$B$12)),MIN(1,Params!$B$39*(1+Params!$B$12))))))
A51: S_ANNUAL@2 | C51: =IF(C$1<12,1,(1-MIN(1,(1-Params!$B$41)*(1+Params!$B$12)))*(1-MIN(1,(1-Params!$B$43)*(1+Params!$B$12)))^(INT(C$1/12)-1)) | D51: =IF(D$1<12,1,(1-MIN(1,(1-Params!$B$41)*(1+Params!$B$12)))*(1-MIN(1,(1-Params!$B$43)*(1+Params!$B$12)))^(INT(D$1/12)-1)) | E51: =IF(E$1<12,1,(1-MIN(1,(1-Params!$B$41)*(1+Params!$B$12)))*(1-MIN(1,(1-Params!$B$43)*(1+Params!$B$12)))^(INT(E$1/12)-1)) | F51: =IF(F$1<12,1,(1-MIN(1,(1-Params!$B$41)*(1+Params!$B$12)))*(1-MIN(1,(1-Params!$B$43)*(1+Params!$B$12)))^(INT(F$1/12)-1)) | G51: =IF(G$1<12,1,(1-MIN(1,(1-Params!$B$41)*(1+Params!$B$12)))*(1-MIN(1,(1-Params!$B$43)*(1+Params!$B$12)))^(INT(G$1/12)-1)) | H51: =IF(H$1<12,1,(1-MIN(1,(1-Params!$B$41)*(1+Params!$B$12)))*(1-MIN(1,(1-Params!$B$43)*(1+Params!$B$12)))^(INT(H$1/12)-1)) | I51: =IF(I$1<12,1,(1-MIN(1,(1-Params!$B$41)*(1+Params!$B$12)))*(1-MIN(1,(1-Params!$B$43)*(1+Params!$B$12)))^(INT(I$1/12)-1)) | J51: =IF(J$1<12,1,(1-MIN(1,(1-Params!$B$41)*(1+Params!$B$12)))*(1-MIN(1,(1-Params!$B$43)*(1+Params!$B$12)))^(INT(J$1/12)-1)) | ... BV51: =IF(BV$1<12,1,(1-MIN(1,(1-Params!$B$41)*(1+Params!$B$12)))*(1-MIN(1,(1-Params!$B$43)*(1+Params!$B$12)))^(INT(BV$1/12)-1))
A52: D_MONTHLY@2 | C52: =0 | D52: =C50-D50 | E52: =D50-E50 | F52: =E50-F50 | G52: =F50-G50 | H52: =G50-H50 | I52: =H50-I50 | J52: =I50-J50 | K52: =J50-K50 | ... BV52: =BU50-BV50
A53: D_ANNUAL@2 | C53: =0 | D53: =C51-D51 | E53: =D51-E51 | F53: =E51-F51 | G53: =F51-G51 | H53: =G51-H51 | I53: =H51-I51 | J53: =I51-J51 | K53: =J51-K51 | ... BV53: =BU51-BV51
A54: S_REACT@2 | C54: =(1-Params!$B$49)^C$1 | D54: =(1-Params!$B$49)^D$1 | E54: =(1-Params!$B$49)^E$1 | F54: =(1-Params!$B$49)^F$1 | G54: =(1-Params!$B$49)^G$1 | H54: =(1-Params!$B$49)^H$1 | I54: =(1-Params!$B$49)^I$1 | J54: =(1-Params!$B$49)^J$1 | ... BV54: =(1-Params!$B$49)^BV$1
A55: D_REACT@2 | C55: =0 | D55: =C54-D54 | E55: =D54-E54 | F55: =E54-F54 | G55: =F54-G54 | H55: =G54-H54 | I55: =H54-I54 | J55: =I54-J54 | K55: =J54-K54 | ... BV55: =BU54-BV54
A56: K_REACT@2 | C56: =IF(AND(C$1>=1,C$1<=Params!$B$47),Params!$B$45*(1-Params!$B$45)^(C$1-1),0) | D56: =IF(AND(D$1>=1,D$1<=Params!$B$47),Params!$B$45*(1-Params!$B$45)^(D$1-1),0) | E56: =IF(AND(E$1>=1,E$1<=Params!$B$47),Params!$B$45*(1-Params!$B$45)^(E$1-1),0) | F56: =IF(AND(F$1>=1,F$1<=Params!$B$47),Params!$B$45*(1-Params!$B$45)^(F$1-1),0) | G56: =IF(AND(G$1>=1,G$1<=Params!$B$47),Params!$B$45*(1-Params!$B$45)^(G$1-1),0) | H56: =IF(AND(H$1>=1,H$1<=Params!$B$47),Params!$B$45*(1-Params!$B$45)^(H$1-1),0) | I56: =IF(AND(I$1>=1,I$1<=Params!$B$47),Params!$B$45*(1-Params!$B$45)^(I$1-1),0) | J56: =IF(AND(J$1>=1,J$1<=Params!$B$47),Params!$B$45*(1-Params!$B$45)^(J$1-1),0) | ... BV56: =IF(AND(BV$1>=1,BV$1<=Params!$B$47),Params!$B$45*(1-Params!$B$45)^(BV$1-1),0)
A57: S_MONTHLY_Y1@2 | C57: =IF(C$1<12,C50,0) | D57: =IF(D$1<12,D50,0) | E57: =IF(E$1<12,E50,0) | F57: =IF(F$1<12,F50,0) | G57: =IF(G$1<12,G50,0) | H57: =IF(H$1<12,H50,0) | I57: =IF(I$1<12,I50,0) | J57: =IF(J$1<12,J50,0) | ... BV57: =IF(BV$1<12,BV50,0)
A58: S_ANNUAL_Y1@2 | C58: =IF(C$1<12,C51,0) | D58: =IF(D$1<12,D51,0) | E58: =IF(E$1<12,E51,0) | F58: =IF(F$1<12,F51,0) | G58: =IF(G$1<12,G51,0) | H58: =IF(H$1<12,H51,0) | I58: =IF(I$1<12,I51,0) | J58: =IF(J$1<12,J51,0) | ... BV58: =IF(BV$1<12,BV51,0)
A59: S_REACT_Y1@2 | C59: =IF(C$1<12,C54,0) | D59: =IF(D$1<12,D54,0) | E59: =IF(E$1<12,E54,0) | F59: =IF(F$1<12,F54,0) | G59: =IF(G$1<12,G54,0) | H59: =IF(H$1<12,H54,0) | I59: =IF(I$1<12,I54,0) | J59: =IF(J$1<12,J54,0) | ... BV59: =IF(BV$1<12,BV54,0)
A61: S_MONTHLY@2 reversed | C61: =INDEX($C$50:$BV$50,72) | D61: =INDEX($C$50:$BV$50,71) | E61: =INDEX($C$50:$BV$50,70) | F61: =INDEX($C$50:$BV$50,69) | G61: =INDEX($C$50:$BV$50,68) | H61: =INDEX($C$50:$BV$50,67) | I61: =INDEX($C$50:$BV$50,66) | J61: =INDEX($C$50:$BV$50,65) | K61: =INDEX($C$50:$BV$50,64) | L61: =INDEX($C$50:$BV$50,63) | M61: =INDEX($C$50:$BV$50,62) | N61: =INDEX($C$50:$BV$50,61) | O61: =INDEX($C$50:$BV$50,60) | P61: =INDEX($C$50:$BV$50,59) | Q61: =INDEX($C$50:$BV$50,58) | R61: =INDEX($C$50:$BV$50,57) | S61: =INDEX($C$50:$BV$50,56) | T61: =INDEX($C$50:$BV$50,55) | U61: =INDEX($C$50:$BV$50,54) | V61: =INDEX($C$50:$BV$50,53) | W61: =INDEX($C$50:$BV$50,52) | X61: =INDEX($C$50:$BV$50,51) | Y61: =INDEX($C$50:$BV$50,50) | Z61: =INDEX($C$50:$BV$50,49) | AA61: =INDEX($C$50:$BV$50,48) | AB61: =INDEX($C$50:$BV$50,47) | AC61: =INDEX($C$50:$BV$50,46) | AD61: =INDEX($C$50:$BV$50,45) | AE61: =INDEX($C$50:$BV$50,44) | AF61: =INDEX($C$50:$BV$50,43) | AG61: =INDEX($C$50:$BV$50,42) | AH61: =INDEX($C$50:$BV$50,41) | AI61: =INDEX($C$50:$BV$50,40) | AJ61: =INDEX($C$50:$BV$50,39) | AK61: =INDEX($C$50:$BV$50,38) | AL61: =INDEX($C$50:$BV$50,37) | AM61: =INDEX($C$50:$BV$50,36) | AN61: =INDEX($C$50:$BV$50,35) | AO61: =INDEX($C$50:$BV$50,34) | AP61: =INDEX($C$50:$BV$50,33) | AQ61: =INDEX($C$50:$BV$50,32) | AR61: =INDEX($C$50:$BV$50,31) | AS61: =INDEX($C$50:$BV$50,30) | AT61: =INDEX($C$50:$BV$50,29) | AU61: =INDEX($C$50:$BV$50,28) | AV61: =INDEX($C$50:$BV$50,27) | AW61: =INDEX($C$50:$BV$50,26) | AX61: =INDEX($C$50:$BV$50,25) | AY61: =INDEX($C$50:$BV$50,24) | AZ61: =INDEX($C$50:$BV$50,23) | BA61: =INDEX($C$50:$BV$50,22) | BB61: =INDEX($C$50:$BV$50,21) | BC61: =INDEX($C$50:$BV$50,20) | BD61: =INDEX($C$50:$BV$50,19) | BE61: =INDEX($C$50:$BV$50,18) | BF61: =INDEX($C$50:$BV$50,17) | BG61: =INDEX($C$50:$BV$50,16) | BH61: =INDEX($C$50:$BV$50,15) | BI61: =INDEX($C$50:$BV$50,14) | BJ61: =INDEX($C$50:$BV$50,13) | BK61: =INDEX($C$50:$BV$50,12) | BL61: =INDEX($C$50:$BV$50,11) | BM61: =INDEX($C$50:$BV$50,10) | BN61: =INDEX($C$50:$BV$50,9) | BO61: =INDEX($C$50:$BV$50,8) | BP61: =INDEX($C$50:$BV$50,7) | BQ61: =INDEX($C$50:$BV$50,6) | BR61: =INDEX($C$50:$BV$50,5) | BS61: =INDEX($C$50:$BV$50,4) | BT61: =INDEX($C$50:$BV$50,3) | BU61: =INDEX($C$50:$BV$50,2) | BV61: =INDEX($C$50:$BV$50,1)
A62: S_ANNUAL@2 reversed | C62: =INDEX($C$51:$BV$51,72) | D62: =INDEX($C$51:$BV$51,71) | E62: =INDEX($C$51:$BV$51,70) | F62: =INDEX($C$51:$BV$51,69) | G62: =INDEX($C$51:$BV$51,68) | H62: =INDEX($C$51:$BV$51,67) | I62: =INDEX($C$51:$BV$51,66) | J62: =INDEX($C$51:$BV$51,65) | K62: =INDEX($C$51:$BV$51,64) | L62: =INDEX($C$51:$BV$51,63) | M62: =INDEX($C$51:$BV$51,62) | N62: =INDEX($C$51:$BV$51,61) | O62: =INDEX($C$51:$BV$51,60) | P62: =INDEX($C$51:$BV$51,59) | Q62: =INDEX($C$51:$BV$51,58) | R62: =INDEX($C$51:$BV$51,57) | S62: =INDEX($C$51:$BV$51,56) | T62: =INDEX($C$51:$BV$51,55) | U62: =INDEX($C$51:$BV$51,54) | V62: =INDEX($C$51:$BV$51,53) | W62: =INDEX($C$51:$BV$51,52) | X62: =INDEX($C$51:$BV$51,51) | Y62: =INDEX($C$51:$BV$51,50) | Z62: =INDEX($C$51:$BV$51,49) | AA62: =INDEX($C$51:$BV$51,48) | AB62: =INDEX($C$51:$BV$51,47) | AC62: =INDEX($C$51:$BV$51,46) | AD62: =INDEX($C$51:$BV$51,45) | AE62: =INDEX($C$51:$BV$51,44) | AF62: =INDEX($C$51:$BV$51,43) | AG62: =INDEX($C$51:$BV$51,42) | AH62: =INDEX($C$51:$BV$51,41) | AI62: =INDEX($C$51:$BV$51,40) | AJ62: =INDEX($C$51:$BV$51,39) | AK62: =INDEX($C$51:$BV$51,38) | AL62: =INDEX($C$51:$BV$51,37) | AM62: =INDEX($C$51:$BV$51,36) | AN62: =INDEX($C$51:$BV$51,35) | AO62: =INDEX($C$51:$BV$51,34) | AP62: =INDEX($C$51:$BV$51,33) | AQ62: =INDEX($C$51:$BV$51,32) | AR62: =INDEX($C$51:$BV$51,31) | AS62: =INDEX($C$51:$BV$51,30) | AT62: =INDEX($C$51:$BV$51,29) | AU62: =INDEX($C$51:$BV$51,28) | AV62: =INDEX($C$51:$BV$51,27) | AW62: =INDEX($C$51:$BV$51,26) | AX62: =INDEX($C$51:$BV$51,25) | AY62: =INDEX($C$51:$BV$51,24) | AZ62: =INDEX($C$51:$BV$51,23) | BA62: =INDEX($C$51:$BV$51,22) | BB62: =INDEX($C$51:$BV$51,21) | BC62: =INDEX($C$51:$BV$51,20) | BD62: =INDEX($C$51:$BV$51,19) | BE62: =INDEX($C$51:$BV$51,18) | BF62: =INDEX($C$51:$BV$51,17) | BG62: =INDEX($C$51:$BV$51,16) | BH62: =INDEX($C$51:$BV$51,15) | BI62: =INDEX($C$51:$BV$51,14) | BJ62: =INDEX($C$51:$BV$51,13) | BK62: =INDEX($C$51:$BV$51,12) | BL62: =INDEX($C$51:$BV$51,11) | BM62: =INDEX($C$51:$BV$51,10) | BN62: =INDEX($C$51:$BV$51,9) | BO62: =INDEX($C$51:$BV$51,8) | BP62: =INDEX($C$51:$BV$51,7) | BQ62: =INDEX($C$51:$BV$51,6) | BR62: =INDEX($C$51:$BV$51,5) | BS62: =INDEX($C$51:$BV$51,4) | BT62: =INDEX($C$51:$BV$51,3) | BU62: =INDEX($C$51:$BV$51,2) | BV62: =INDEX($C$51:$BV$51,1)
A63: D_MONTHLY@2 reversed | C63: =INDEX($C$52:$BV$52,72) | D63: =INDEX($C$52:$BV$52,71) | E63: =INDEX($C$52:$BV$52,70) | F63: =INDEX($C$52:$BV$52,69) | G63: =INDEX($C$52:$BV$52,68) | H63: =INDEX($C$52:$BV$52,67) | I63: =INDEX($C$52:$BV$52,66) | J63: =INDEX($C$52:$BV$52,65) | K63: =INDEX($C$52:$BV$52,64) | L63: =INDEX($C$52:$BV$52,63) | M63: =INDEX($C$52:$BV$52,62) | N63: =INDEX($C$52:$BV$52,61) | O63: =INDEX($C$52:$BV$52,60) | P63: =INDEX($C$52:$BV$52,59) | Q63: =INDEX($C$52:$BV$52,58) | R63: =INDEX($C$52:$BV$52,57) | S63: =INDEX($C$52:$BV$52,56) | T63: =INDEX($C$52:$BV$52,55) | U63: =INDEX($C$52:$BV$52,54) | V63: =INDEX($C$52:$BV$52,53) | W63: =INDEX($C$52:$BV$52,52) | X63: =INDEX($C$52:$BV$52,51) | Y63: =INDEX($C$52:$BV$52,50) | Z63: =INDEX($C$52:$BV$52,49) | AA63: =INDEX($C$52:$BV$52,48) | AB63: =INDEX($C$52:$BV$52,47) | AC63: =INDEX($C$52:$BV$52,46) | AD63: =INDEX($C$52:$BV$52,45) | AE63: =INDEX($C$52:$BV$52,44) | AF63: =INDEX($C$52:$BV$52,43) | AG63: =INDEX($C$52:$BV$52,42) | AH63: =INDEX($C$52:$BV$52,41) | AI63: =INDEX($C$52:$BV$52,40) | AJ63: =INDEX($C$52:$BV$52,39) | AK63: =INDEX($C$52:$BV$52,38) | AL63: =INDEX($C$52:$BV$52,37) | AM63: =INDEX($C$52:$BV$52,36) | AN63: =INDEX($C$52:$BV$52,35) | AO63: =INDEX($C$52:$BV$52,34) | AP63: =INDEX($C$52:$BV$52,33) | AQ63: =INDEX($C$52:$BV$52,32) | AR63: =INDEX($C$52:$BV$52,31) | AS63: =INDEX($C$52:$BV$52,30) | AT63: =INDEX($C$52:$BV$52,29) | AU63: =INDEX($C$52:$BV$52,28) | AV63: =INDEX($C$52:$BV$52,27) | AW63: =INDEX($C$52:$BV$52,26) | AX63: =INDEX($C$52:$BV$52,25) | AY63: =INDEX($C$52:$BV$52,24) | AZ63: =INDEX($C$52:$BV$52,23) | BA63: =INDEX($C$52:$BV$52,22) | BB63: =INDEX($C$52:$BV$52,21) | BC63: =INDEX($C$52:$BV$52,20) | BD63: =INDEX($C$52:$BV$52,19) | BE63: =INDEX($C$52:$BV$52,18) | BF63: =INDEX($C$52:$BV$52,17) | BG63: =INDEX($C$52:$BV$52,16) | BH63: =INDEX($C$52:$BV$52,15) | BI63: =INDEX($C$52:$BV$52,14) | BJ63: =INDEX($C$52:$BV$52,13) | BK63: =INDEX($C$52:$BV$52,12) | BL63: =INDEX($C$52:$BV$52,11) | BM63: =INDEX($C$52:$BV$52,10) | BN63: =INDEX($C$52:$BV$52,9) | BO63: =INDEX($C$52:$BV$52,8) | BP63: =INDEX($C$52:$BV$52,7) | BQ63: =INDEX($C$52:$BV$52,6) | BR63: =INDEX($C$52:$BV$52,5) | BS63: =INDEX($C$52:$BV$52,4) | BT63: =INDEX($C$52:$BV$52,3) | BU63: =INDEX($C$52:$BV$52,2) | BV63: =INDEX($C$52:$BV$52,1)
A64: D_ANNUAL@2 reversed | C64: =INDEX($C$53:$BV$53,72) | D64: =INDEX($C$53:$BV$53,71) | E64: =INDEX($C$53:$BV$53,70) | F64: =INDEX($C$53:$BV$53,69) | G64: =INDEX($C$53:$BV$53,68) | H64: =INDEX($C$53:$BV$53,67) | I64: =INDEX($C$53:$BV$53,66) | J64: =INDEX($C$53:$BV$53,65) | K64: =INDEX($C$53:$BV$53,64) | L64: =INDEX($C$53:$BV$53,63) | M64: =INDEX($C$53:$BV$53,62) | N64: =INDEX($C$53:$BV$53,61) | O64: =INDEX($C$53:$BV$53,60) | P64: =INDEX($C$53:$BV$53,59) | Q64: =INDEX($C$53:$BV$53,58) | R64: =INDEX($C$53:$BV$53,57) | S64: =INDEX($C$53:$BV$53,56) | T64: =INDEX($C$53:$BV$53,55) | U64: =INDEX($C$53:$BV$53,54) | V64: =INDEX($C$53:$BV$53,53) | W64: =INDEX($C$53:$BV$53,52) | X64: =INDEX($C$53:$BV$53,51) | Y64: =INDEX($C$53:$BV$53,50) | Z64: =INDEX($C$53:$BV$53,49) | AA64: =INDEX($C$53:$BV$53,48) | AB64: =INDEX($C$53:$BV$53,47) | AC64: =INDEX($C$53:$BV$53,46) | AD64: =INDEX($C$53:$BV$53,45) | AE64: =INDEX($C$53:$BV$53,44) | AF64: =INDEX($C$53:$BV$53,43) | AG64: =INDEX($C$53:$BV$53,42) | AH64: =INDEX($C$53:$BV$53,41) | AI64: =INDEX($C$53:$BV$53,40) | AJ64: =INDEX($C$53:$BV$53,39) | AK64: =INDEX($C$53:$BV$53,38) | AL64: =INDEX($C$53:$BV$53,37) | AM64: =INDEX($C$53:$BV$53,36) | AN64: =INDEX($C$53:$BV$53,35) | AO64: =INDEX($C$53:$BV$53,34) | AP64: =INDEX($C$53:$BV$53,33) | AQ64: =INDEX($C$53:$BV$53,32) | AR64: =INDEX($C$53:$BV$53,31) | AS64: =INDEX($C$53:$BV$53,30) | AT64: =INDEX($C$53:$BV$53,29) | AU64: =INDEX($C$53:$BV$53,28) | AV64: =INDEX($C$53:$BV$53,27) | AW64: =INDEX($C$53:$BV$53,26) | AX64: =INDEX($C$53:$BV$53,25) | AY64: =INDEX($C$53:$BV$53,24) | AZ64: =INDEX($C$53:$BV$53,23) | BA64: =INDEX($C$53:$BV$53,22) | BB64: =INDEX($C$53:$BV$53,21) | BC64: =INDEX($C$53:$BV$53,20) | BD64: =INDEX($C$53:$BV$53,19) | BE64: =INDEX($C$53:$BV$53,18) | BF64: =INDEX($C$53:$BV$53,17) | BG64: =INDEX($C$53:$BV$53,16) | BH64: =INDEX($C$53:$BV$53,15) | BI64: =INDEX($C$53:$BV$53,14) | BJ64: =INDEX($C$53:$BV$53,13) | BK64: =INDEX($C$53:$BV$53,12) | BL64: =INDEX($C$53:$BV$53,11) | BM64: =INDEX($C$53:$BV$53,10) | BN64: =INDEX($C$53:$BV$53,9) | BO64: =INDEX($C$53:$BV$53,8) | BP64: =INDEX($C$53:$BV$53,7) | BQ64: =INDEX($C$53:$BV$53,6) | BR64: =INDEX($C$53:$BV$53,5) | BS64: =INDEX($C$53:$BV$53,4) | BT64: =INDEX($C$53:$BV$53,3) | BU64: =INDEX($C$53:$BV$53,2) | BV64: =INDEX($C$53:$BV$53,1)
A65: S_REACT@2 reversed | C65: =INDEX($C$54:$BV$54,72) | D65: =INDEX($C$54:$BV$54,71) | E65: =INDEX($C$54:$BV$54,70) | F65: =INDEX($C$54:$BV$54,69) | G65: =INDEX($C$54:$BV$54,68) | H65: =INDEX($C$54:$BV$54,67) | I65: =INDEX($C$54:$BV$54,66) | J65: =INDEX($C$54:$BV$54,65) | K65: =INDEX($C$54:$BV$54,64) | L65: =INDEX($C$54:$BV$54,63) | M65: =INDEX($C$54:$BV$54,62) | N65: =INDEX($C$54:$BV$54,61) | O65: =INDEX($C$54:$BV$54,60) | P65: =INDEX($C$54:$BV$54,59) | Q65: =INDEX($C$54:$BV$54,58) | R65: =INDEX($C$54:$BV$54,57) | S65: =INDEX($C$54:$BV$54,56) | T65: =INDEX($C$54:$BV$54,55) | U65: =INDEX($C$54:$BV$54,54) | V65: =INDEX($C$54:$BV$54,53) | W65: =INDEX($C$54:$BV$54,52) | X65: =INDEX($C$54:$BV$54,51) | Y65: =INDEX($C$54:$BV$54,50) | Z65: =INDEX($C$54:$BV$54,49) | AA65: =INDEX($C$54:$BV$54,48) | AB65: =INDEX($C$54:$BV$54,47) | AC65: =INDEX($C$54:$BV$54,46) | AD65: =INDEX($C$54:$BV$54,45) | AE65: =INDEX($C$54:$BV$54,44) | AF65: =INDEX($C$54:$BV$54,43) | AG65: =INDEX($C$54:$BV$54,42) | AH65: =INDEX($C$54:$BV$54,41) | AI65: =INDEX($C$54:$BV$54,40) | AJ65: =INDEX($C$54:$BV$54,39) | AK65: =INDEX($C$54:$BV$54,38) | AL65: =INDEX($C$54:$BV$54,37) | AM65: =INDEX($C$54:$BV$54,36) | AN65: =INDEX($C$54:$BV$54,35) | AO65: =INDEX($C$54:$BV$54,34) | AP65: =INDEX($C$54:$BV$54,33) | AQ65: =INDEX($C$54:$BV$54,32) | AR65: =INDEX($C$54:$BV$54,31) | AS65: =INDEX($C$54:$BV$54,30) | AT65: =INDEX($C$54:$BV$54,29) | AU65: =INDEX($C$54:$BV$54,28) | AV65: =INDEX($C$54:$BV$54,27) | AW65: =INDEX($C$54:$BV$54,26) | AX65: =INDEX($C$54:$BV$54,25) | AY65: =INDEX($C$54:$BV$54,24) | AZ65: =INDEX($C$54:$BV$54,23) | BA65: =INDEX($C$54:$BV$54,22) | BB65: =INDEX($C$54:$BV$54,21) | BC65: =INDEX($C$54:$BV$54,20) | BD65: =INDEX($C$54:$BV$54,19) | BE65: =INDEX($C$54:$BV$54,18) | BF65: =INDEX($C$54:$BV$54,17) | BG65: =INDEX($C$54:$BV$54,16) | BH65: =INDEX($C$54:$BV$54,15) | BI65: =INDEX($C$54:$BV$54,14) | BJ65: =INDEX($C$54:$BV$54,13) | BK65: =INDEX($C$54:$BV$54,12) | BL65: =INDEX($C$54:$BV$54,11) | BM65: =INDEX($C$54:$BV$54,10) | BN65: =INDEX($C$54:$BV$54,9) | BO65: =INDEX($C$54:$BV$54,8) | BP65: =INDEX($C$54:$BV$54,7) | BQ65: =INDEX($C$54:$BV$54,6) | BR65: =INDEX($C$54:$BV$54,5) | BS65: =INDEX($C$54:$BV$54,4) | BT65: =INDEX($C$54:$BV$54,3) | BU65: =INDEX($C$54:$BV$54,2) | BV65: =INDEX($C$54:$BV$54,1)
A66: D_REACT@2 reversed | C66: =INDEX($C$55:$BV$55,72) | D66: =INDEX($C$55:$BV$55,71) | E66: =INDEX($C$55:$BV$55,70) | F66: =INDEX($C$55:$BV$55,69) | G66: =INDEX($C$55:$BV$55,68) | H66: =INDEX($C$55:$BV$55,67) | I66: =INDEX($C$55:$BV$55,66) | J66: =INDEX($C$55:$BV$55,65) | K66: =INDEX($C$55:$BV$55,64) | L66: =INDEX($C$55:$BV$55,63) | M66: =INDEX($C$55:$BV$55,62) | N66: =INDEX($C$55:$BV$55,61) | O66: =INDEX($C$55:$BV$55,60) | P66: =INDEX($C$55:$BV$55,59) | Q66: =INDEX($C$55:$BV$55,58) | R66: =INDEX($C$55:$BV$55,57) | S66: =INDEX($C$55:$BV$55,56) | T66: =INDEX($C$55:$BV$55,55) | U66: =INDEX($C$55:$BV$55,54) | V66: =INDEX($C$55:$BV$55,53) | W66: =INDEX($C$55:$BV$55,52) | X66: =INDEX($C$55:$BV$55,51) | Y66: =INDEX($C$55:$BV$55,50) | Z66: =INDEX($C$55:$BV$55,49) | AA66: =INDEX($C$55:$BV$55,48) | AB66: =INDEX($C$55:$BV$55,47) | AC66: =INDEX($C$55:$BV$55,46) | AD66: =INDEX($C$55:$BV$55,45) | AE66: =INDEX($C$55:$BV$55,44) | AF66: =INDEX($C$55:$BV$55,43) | AG66: =INDEX($C$55:$BV$55,42) | AH66: =INDEX($C$55:$BV$55,41) | AI66: =INDEX($C$55:$BV$55,40) | AJ66: =INDEX($C$55:$BV$55,39) | AK66: =INDEX($C$55:$BV$55,38) | AL66: =INDEX($C$55:$BV$55,37) | AM66: =INDEX($C$55:$BV$55,36) | AN66: =INDEX($C$55:$BV$55,35) | AO66: =INDEX($C$55:$BV$55,34) | AP66: =INDEX($C$55:$BV$55,33) | AQ66: =INDEX($C$55:$BV$55,32) | AR66: =INDEX($C$55:$BV$55,31) | AS66: =INDEX($C$55:$BV$55,30) | AT66: =INDEX($C$55:$BV$55,29) | AU66: =INDEX($C$55:$BV$55,28) | AV66: =INDEX($C$55:$BV$55,27) | AW66: =INDEX($C$55:$BV$55,26) | AX66: =INDEX($C$55:$BV$55,25) | AY66: =INDEX($C$55:$BV$55,24) | AZ66: =INDEX($C$55:$BV$55,23) | BA66: =INDEX($C$55:$BV$55,22) | BB66: =INDEX($C$55:$BV$55,21) | BC66: =INDEX($C$55:$BV$55,20) | BD66: =INDEX($C$55:$BV$55,19) | BE66: =INDEX($C$55:$BV$55,18) | BF66: =INDEX($C$55:$BV$55,17) | BG66: =INDEX($C$55:$BV$55,16) | BH66: =INDEX($C$55:$BV$55,15) | BI66: =INDEX($C$55:$BV$55,14) | BJ66: =INDEX($C$55:$BV$55,13) | BK66: =INDEX($C$55:$BV$55,12) | BL66: =INDEX($C$55:$BV$55,11) | BM66: =INDEX($C$55:$BV$55,10) | BN66: =INDEX($C$55:$BV$55,9) | BO66: =INDEX($C$55:$BV$55,8) | BP66: =INDEX($C$55:$BV$55,7) | BQ66: =INDEX($C$55:$BV$55,6) | BR66: =INDEX($C$55:$BV$55,5) | BS66: =INDEX($C$55:$BV$55,4) | BT66: =INDEX($C$55:$BV$55,3) | BU66: =INDEX($C$55:$BV$55,2) | BV66: =INDEX($C$55:$BV$55,1)
A67: K_REACT@2 reversed | C67: =INDEX($C$56:$BV$56,72) | D67: =INDEX($C$56:$BV$56,71) | E67: =INDEX($C$56:$BV$56,70) | F67: =INDEX($C$56:$BV$56,69) | G67: =INDEX($C$56:$BV$56,68) | H67: =INDEX($C$56:$BV$56,67) | I67: =INDEX($C$56:$BV$56,66) | J67: =INDEX($C$56:$BV$56,65) | K67: =INDEX($C$56:$BV$56,64) | L67: =INDEX($C$56:$BV$56,63) | M67: =INDEX($C$56:$BV$56,62) | N67: =INDEX($C$56:$BV$56,61) | O67: =INDEX($C$56:$BV$56,60) | P67: =INDEX($C$56:$BV$56,59) | Q67: =INDEX($C$56:$BV$56,58) | R67: =INDEX($C$56:$BV$56,57) | S67: =INDEX($C$56:$BV$56,56) | T67: =INDEX($C$56:$BV$56,55) | U67: =INDEX($C$56:$BV$56,54) | V67: =INDEX($C$56:$BV$56,53) | W67: =INDEX($C$56:$BV$56,52) | X67: =INDEX($C$56:$BV$56,51) | Y67: =INDEX($C$56:$BV$56,50) | Z67: =INDEX($C$56:$BV$56,49) | AA67: =INDEX($C$56:$BV$56,48) | AB67: =INDEX($C$56:$BV$56,47) | AC67: =INDEX($C$56:$BV$56,46) | AD67: =INDEX($C$56:$BV$56,45) | AE67: =INDEX($C$56:$BV$56,44) | AF67: =INDEX($C$56:$BV$56,43) | AG67: =INDEX($C$56:$BV$56,42) | AH67: =INDEX($C$56:$BV$56,41) | AI67: =INDEX($C$56:$BV$56,40) | AJ67: =INDEX($C$56:$BV$56,39) | AK67: =INDEX($C$56:$BV$56,38) | AL67: =INDEX($C$56:$BV$56,37) | AM67: =INDEX($C$56:$BV$56,36) | AN67: =INDEX($C$56:$BV$56,35) | AO67: =INDEX($C$56:$BV$56,34) | AP67: =INDEX($C$56:$BV$56,33) | AQ67: =INDEX($C$56:$BV$56,32) | AR67: =INDEX($C$56:$BV$56,31) | AS67: =INDEX($C$56:$BV$56,30) | AT67: =INDEX($C$56:$BV$56,29) | AU67: =INDEX($C$56:$BV$56,28) | AV67: =INDEX($C$56:$BV$56,27) | AW67: =INDEX($C$56:$BV$56,26) | AX67: =INDEX($C$56:$BV$56,25) | AY67: =INDEX($C$56:$BV$56,24) | AZ67: =INDEX($C$56:$BV$56,23) | BA67: =INDEX($C$56:$BV$56,22) | BB67: =INDEX($C$56:$BV$56,21) | BC67: =INDEX($C$56:$BV$56,20) | BD67: =INDEX($C$56:$BV$56,19) | BE67: =INDEX($C$56:$BV$56,18) | BF67: =INDEX($C$56:$BV$56,17) | BG67: =INDEX($C$56:$BV$56,16) | BH67: =INDEX($C$56:$BV$56,15) | BI67: =INDEX($C$56:$BV$56,14) | BJ67: =INDEX($C$56:$BV$56,13) | BK67: =INDEX($C$56:$BV$56,12) | BL67: =INDEX($C$56:$BV$56,11) | BM67: =INDEX($C$56:$BV$56,10) | BN67: =INDEX($C$56:$BV$56,9) | BO67: =INDEX($C$56:$BV$56,8) | BP67: =INDEX($C$56:$BV$56,7) | BQ67: =INDEX($C$56:$BV$56,6) | BR67: =INDEX($C$56:$BV$56,5) | BS67: =INDEX($C$56:$BV$56,4) | BT67: =INDEX($C$56:$BV$56,3) | BU67: =INDEX($C$56:$BV$56,2) | BV67: =INDEX($C$56:$BV$56,1)
A68: S_MONTHLY_Y1@2 reversed | C68: =INDEX($C$57:$BV$57,72) | D68: =INDEX($C$57:$BV$57,71) | E68: =INDEX($C$57:$BV$57,70) | F68: =INDEX($C$57:$BV$57,69) | G68: =INDEX($C$57:$BV$57,68) | H68: =INDEX($C$57:$BV$57,67) | I68: =INDEX($C$57:$BV$57,66) | J68: =INDEX($C$57:$BV$57,65) | K68: =INDEX($C$57:$BV$57,64) | L68: =INDEX($C$57:$BV$57,63) | M68: =INDEX($C$57:$BV$57,62) | N68: =INDEX($C$57:$BV$57,61) | O68: =INDEX($C$57:$BV$57,60) | P68: =INDEX($C$57:$BV$57,59) | Q68: =INDEX($C$57:$BV$57,58) | R68: =INDEX($C$57:$BV$57,57) | S68: =INDEX($C$57:$BV$57,56) | T68: =INDEX($C$57:$BV$57,55) | U68: =INDEX($C$57:$BV$57,54) | V68: =INDEX($C$57:$BV$57,53) | W68: =INDEX($C$57:$BV$57,52) | X68: =INDEX($C$57:$BV$57,51) | Y68: =INDEX($C$57:$BV$57,50) | Z68: =INDEX($C$57:$BV$57,49) | AA68: =INDEX($C$57:$BV$57,48) | AB68: =INDEX($C$57:$BV$57,47) | AC68: =INDEX($C$57:$BV$57,46) | AD68: =INDEX($C$57:$BV$57,45) | AE68: =INDEX($C$57:$BV$57,44) | AF68: =INDEX($C$57:$BV$57,43) | AG68: =INDEX($C$57:$BV$57,42) | AH68: =INDEX($C$57:$BV$57,41) | AI68: =INDEX($C$57:$BV$57,40) | AJ68: =INDEX($C$57:$BV$57,39) | AK68: =INDEX($C$57:$BV$57,38) | AL68: =INDEX($C$57:$BV$57,37) | AM68: =INDEX($C$57:$BV$57,36) | AN68: =INDEX($C$57:$BV$57,35) | AO68: =INDEX($C$57:$BV$57,34) | AP68: =INDEX($C$57:$BV$57,33) | AQ68: =INDEX($C$57:$BV$57,32) | AR68: =INDEX($C$57:$BV$57,31) | AS68: =INDEX($C$57:$BV$57,30) | AT68: =INDEX($C$57:$BV$57,29) | AU68: =INDEX($C$57:$BV$57,28) | AV68: =INDEX($C$57:$BV$57,27) | AW68: =INDEX($C$57:$BV$57,26) | AX68: =INDEX($C$57:$BV$57,25) | AY68: =INDEX($C$57:$BV$57,24) | AZ68: =INDEX($C$57:$BV$57,23) | BA68: =INDEX($C$57:$BV$57,22) | BB68: =INDEX($C$57:$BV$57,21) | BC68: =INDEX($C$57:$BV$57,20) | BD68: =INDEX($C$57:$BV$57,19) | BE68: =INDEX($C$57:$BV$57,18) | BF68: =INDEX($C$57:$BV$57,17) | BG68: =INDEX($C$57:$BV$57,16) | BH68: =INDEX($C$57:$BV$57,15) | BI68: =INDEX($C$57:$BV$57,14) | BJ68: =INDEX($C$57:$BV$57,13) | BK68: =INDEX($C$57:$BV$57,12) | BL68: =INDEX($C$57:$BV$57,11) | BM68: =INDEX($C$57:$BV$57,10) | BN68: =INDEX($C$57:$BV$57,9) | BO68: =INDEX($C$57:$BV$57,8) | BP68: =INDEX($C$57:$BV$57,7) | BQ68: =INDEX($C$57:$BV$57,6) | BR68: =INDEX($C$57:$BV$57,5) | BS68: =INDEX($C$57:$BV$57,4) | BT68: =INDEX($C$57:$BV$57,3) | BU68: =INDEX($C$57:$BV$57,2) | BV68: =INDEX($C$57:$BV$57,1)
A69: S_ANNUAL_Y1@2 reversed | C69: =INDEX($C$58:$BV$58,72) | D69: =INDEX($C$58:$BV$58,71) | E69: =INDEX($C$58:$BV$58,70) | F69: =INDEX($C$58:$BV$58,69) | G69: =INDEX($C$58:$BV$58,68) | H69: =INDEX($C$58:$BV$58,67) | I69: =INDEX($C$58:$BV$58,66) | J69: =INDEX($C$58:$BV$58,65) | K69: =INDEX($C$58:$BV$58,64) | L69: =INDEX($C$58:$BV$58,63) | M69: =INDEX($C$58:$BV$58,62) | N69: =INDEX($C$58:$BV$58,61) | O69: =INDEX($C$58:$BV$58,60) | P69: =INDEX($C$58:$BV$58,59) | Q69: =INDEX($C$58:$BV$58,58) | R69: =INDEX($C$58:$BV$58,57) | S69: =INDEX($C$58:$BV$58,56) | T69: =INDEX($C$58:$BV$58,55) | U69: =INDEX($C$58:$BV$58,54) | V69: =INDEX($C$58:$BV$58,53) | W69: =INDEX($C$58:$BV$58,52) | X69: =INDEX($C$58:$BV$58,51) | Y69: =INDEX($C$58:$BV$58,50) | Z69: =INDEX($C$58:$BV$58,49) | AA69: =INDEX($C$58:$BV$58,48) | AB69: =INDEX($C$58:$BV$58,47) | AC69: =INDEX($C$58:$BV$58,46) | AD69: =INDEX($C$58:$BV$58,45) | AE69: =INDEX($C$58:$BV$58,44) | AF69: =INDEX($C$58:$BV$58,43) | AG69: =INDEX($C$58:$BV$58,42) | AH69: =INDEX($C$58:$BV$58,41) | AI69: =INDEX($C$58:$BV$58,40) | AJ69: =INDEX($C$58:$BV$58,39) | AK69: =INDEX($C$58:$BV$58,38) | AL69: =INDEX($C$58:$BV$58,37) | AM69: =INDEX($C$58:$BV$58,36) | AN69: =INDEX($C$58:$BV$58,35) | AO69: =INDEX($C$58:$BV$58,34) | AP69: =INDEX($C$58:$BV$58,33) | AQ69: =INDEX($C$58:$BV$58,32) | AR69: =INDEX($C$58:$BV$58,31) | AS69: =INDEX($C$58:$BV$58,30) | AT69: =INDEX($C$58:$BV$58,29) | AU69: =INDEX($C$58:$BV$58,28) | AV69: =INDEX($C$58:$BV$58,27) | AW69: =INDEX($C$58:$BV$58,26) | AX69: =INDEX($C$58:$BV$58,25) | AY69: =INDEX($C$58:$BV$58,24) | AZ69: =INDEX($C$58:$BV$58,23) | BA69: =INDEX($C$58:$BV$58,22) | BB69: =INDEX($C$58:$BV$58,21) | BC69: =INDEX($C$58:$BV$58,20) | BD69: =INDEX($C$58:$BV$58,19) | BE69: =INDEX($C$58:$BV$58,18) | BF69: =INDEX($C$58:$BV$58,17) | BG69: =INDEX($C$58:$BV$58,16) | BH69: =INDEX($C$58:$BV$58,15) | BI69: =INDEX($C$58:$BV$58,14) | BJ69: =INDEX($C$58:$BV$58,13) | BK69: =INDEX($C$58:$BV$58,12) | BL69: =INDEX($C$58:$BV$58,11) | BM69: =INDEX($C$58:$BV$58,10) | BN69: =INDEX($C$58:$BV$58,9) | BO69: =INDEX($C$58:$BV$58,8) | BP69: =INDEX($C$58:$BV$58,7) | BQ69: =INDEX($C$58:$BV$58,6) | BR69: =INDEX($C$58:$BV$58,5) | BS69: =INDEX($C$58:$BV$58,4) | BT69: =INDEX($C$58:$BV$58,3) | BU69: =INDEX($C$58:$BV$58,2) | BV69: =INDEX($C$58:$BV$58,1)
A70: S_REACT_Y1@2 reversed | C70: =INDEX($C$59:$BV$59,72) | D70: =INDEX($C$59:$BV$59,71) | E70: =INDEX($C$59:$BV$59,70) | F70: =INDEX($C$59:$BV$59,69) | G70: =INDEX($C$59:$BV$59,68) | H70: =INDEX($C$59:$BV$59,67) | I70: =INDEX($C$59:$BV$59,66) | J70: =INDEX($C$59:$BV$59,65) | K70: =INDEX($C$59:$BV$59,64) | L70: =INDEX($C$59:$BV$59,63) | M70: =INDEX($C$59:$BV$59,62) | N70: =INDEX($C$59:$BV$59,61) | O70: =INDEX($C$59:$BV$59,60) | P70: =INDEX($C$59:$BV$59,59) | Q70: =INDEX($C$59:$BV$59,58) | R70: =INDEX($C$59:$BV$59,57) | S70: =INDEX($C$59:$BV$59,56) | T70: =INDEX($C$59:$BV$59,55) | U70: =INDEX($C$59:$BV$59,54) | V70: =INDEX($C$59:$BV$59,53) | W70: =INDEX($C$59:$BV$59,52) | X70: =INDEX($C$59:$BV$59,51) | Y70: =INDEX($C$59:$BV$59,50) | Z70: =INDEX($C$59:$BV$59,49) | AA70: =INDEX($C$59:$BV$59,48) | AB70: =INDEX($C$59:$BV$59,47) | AC70: =INDEX($C$59:$BV$59,46) | AD70: =INDEX($C$59:$BV$59,45) | AE70: =INDEX($C$59:$BV$59,44) | AF70: =INDEX($C$59:$BV$59,43) | AG70: =INDEX($C$59:$BV$59,42) | AH70: =INDEX($C$59:$BV$59,41) | AI70: =INDEX($C$59:$BV$59,40) | AJ70: =INDEX($C$59:$BV$59,39) | AK70: =INDEX($C$59:$BV$59,38) | AL70: =INDEX($C$59:$BV$59,37) | AM70: =INDEX($C$59:$BV$59,36) | AN70: =INDEX($C$59:$BV$59,35) | AO70: =INDEX($C$59:$BV$59,34) | AP70: =INDEX($C$59:$BV$59,33) | AQ70: =INDEX($C$59:$BV$59,32) | AR70: =INDEX($C$59:$BV$59,31) | AS70: =INDEX($C$59:$BV$59,30) | AT70: =INDEX($C$59:$BV$59,29) | AU70: =INDEX($C$59:$BV$59,28) | AV70: =INDEX($C$59:$BV$59,27) | AW70: =INDEX($C$59:$BV$59,26) | AX70: =INDEX($C$59:$BV$59,25) | AY70: =INDEX($C$59:$BV$59,24) | AZ70: =INDEX($C$59:$BV$59,23) | BA70: =INDEX($C$59:$BV$59,22) | BB70: =INDEX($C$59:$BV$59,21) | BC70: =INDEX($C$59:$BV$59,20) | BD70: =INDEX($C$59:$BV$59,19) | BE70: =INDEX($C$59:$BV$59,18) | BF70: =INDEX($C$59:$BV$59,17) | BG70: =INDEX($C$59:$BV$59,16) | BH70: =INDEX($C$59:$BV$59,15) | BI70: =INDEX($C$59:$BV$59,14) | BJ70: =INDEX($C$59:$BV$59,13) | BK70: =INDEX($C$59:$BV$59,12) | BL70: =INDEX($C$59:$BV$59,11) | BM70: =INDEX($C$59:$BV$59,10) | BN70: =INDEX($C$59:$BV$59,9) | BO70: =INDEX($C$59:$BV$59,8) | BP70: =INDEX($C$59:$BV$59,7) | BQ70: =INDEX($C$59:$BV$59,6) | BR70: =INDEX($C$59:$BV$59,5) | BS70: =INDEX($C$59:$BV$59,4) | BT70: =INDEX($C$59:$BV$59,3) | BU70: =INDEX($C$59:$BV$59,2) | BV70: =INDEX($C$59:$BV$59,1)

Sheet Eras
A1: line | B1: segment | C1: 2025-01 | D1: 2025-02 | E1: 2025-03 | F1: 2025-04 | G1: 2025-05 | H1: 2025-06 | I1: 2025-07 | J1: 2025-08 | K1: 2025-09 | L1: 2025-10 | M1: 2025-11 | N1: 2025-12 | O1: 2026-01 | P1: 2026-02 | Q1: 2026-03 | R1: 2026-04 | S1: 2026-05 | T1: 2026-06 | U1: 2026-07 | V1: 2026-08 | W1: 2026-09 | X1: 2026-10 | Y1: 2026-11 | Z1: 2026-12 | AA1: 2027-01 | AB1: 2027-02 | AC1: 2027-03 | AD1: 2027-04 | AE1: 2027-05 | AF1: 2027-06 | AG1: 2027-07 | AH1: 2027-08 | AI1: 2027-09 | AJ1: 2027-10 | AK1: 2027-11 | AL1: 2027-12 | AM1: 2028-01 | AN1: 2028-02 | AO1: 2028-03 | AP1: 2028-04 | AQ1: 2028-05 | AR1: 2028-06 | AS1: 2028-07 | AT1: 2028-08 | AU1: 2028-09 | AV1: 2028-10 | AW1: 2028-11 | AX1: 2028-12 | AY1: 2029-01 | AZ1: 2029-02 | BA1: 2029-03 | BB1: 2029-04 | BC1: 2029-05 | BD1: 2029-06 | BE1: 2029-07 | BF1: 2029-08 | BG1: 2029-09 | BH1: 2029-10 | BI1: 2029-11 | BJ1: 2029-12 | BK1: 2030-01 | BL1: 2030-02 | BM1: 2030-03 | BN1: 2030-04 | BO1: 2030-05 | BP1: 2030-06 | BQ1: 2030-07 | BR1: 2030-08 | BS1: 2030-09 | BT1: 2030-10 | BU1: 2030-11 | BV1: 2030-12
A2: month index (0 = Jan 2025) | C2: 0 | D2: 1 | E2: 2 | F2: 3 | G2: 4 | H2: 5 | I2: 6 | J2: 7 | K2: 8 | L2: 9 | M2: 10 | N2: 11 | O2: 12 | P2: 13 | Q2: 14 | R2: 15 | S2: 16 | T2: 17 | U2: 18 | V2: 19 | W2: 20 | X2: 21 | Y2: 22 | Z2: 23 | AA2: 24 | AB2: 25 | AC2: 26 | AD2: 27 | AE2: 28 | AF2: 29 | AG2: 30 | AH2: 31 | AI2: 32 | AJ2: 33 | AK2: 34 | AL2: 35 | AM2: 36 | AN2: 37 | AO2: 38 | AP2: 39 | AQ2: 40 | AR2: 41 | AS2: 42 | AT2: 43 | AU2: 44 | AV2: 45 | AW2: 46 | AX2: 47 | AY2: 48 | AZ2: 49 | BA2: 50 | BB2: 51 | BC2: 52 | BD2: 53 | BE2: 54 | BF2: 55 | BG2: 56 | BH2: 57 | BI2: 58 | BJ2: 59 | BK2: 60 | BL2: 61 | BM2: 62 | BN2: 63 | BO2: 64 | BP2: 65 | BQ2: 66 | BR2: 67 | BS2: 68 | BT2: 69 | BU2: 70 | BV2: 71
A3: era @0 history | B3: mask | C3: =IF(C$2<(Params!$B$8-1),1,0) | D3: =IF(D$2<(Params!$B$8-1),1,0) | E3: =IF(E$2<(Params!$B$8-1),1,0) | F3: =IF(F$2<(Params!$B$8-1),1,0) | G3: =IF(G$2<(Params!$B$8-1),1,0) | H3: =IF(H$2<(Params!$B$8-1),1,0) | I3: =IF(I$2<(Params!$B$8-1),1,0) | J3: =IF(J$2<(Params!$B$8-1),1,0) | ... BV3: =IF(BV$2<(Params!$B$8-1),1,0)
A4: era @1 forecast | B4: mask | C4: =1-C3-C5 | D4: =1-D3-D5 | E4: =1-E3-E5 | F4: =1-F3-F5 | G4: =1-G3-G5 | H4: =1-H3-H5 | I4: =1-I3-I5 | J4: =1-J3-J5 | ... BV4: =1-BV3-BV5
A5: era @2 experiment | B5: mask | C5: =IF(AND(C$2>=(Params!$B$8-1),Params!$B$9=1,C$2>=(Params!$B$10-1)),1,0) | D5: =IF(AND(D$2>=(Params!$B$8-1),Params!$B$9=1,D$2>=(Params!$B$10-1)),1,0) | E5: =IF(AND(E$2>=(Params!$B$8-1),Params!$B$9=1,E$2>=(Params!$B$10-1)),1,0) | F5: =IF(AND(F$2>=(Params!$B$8-1),Params!$B$9=1,F$2>=(Params!$B$10-1)),1,0) | G5: =IF(AND(G$2>=(Params!$B$8-1),Params!$B$9=1,G$2>=(Params!$B$10-1)),1,0) | H5: =IF(AND(H$2>=(Params!$B$8-1),Params!$B$9=1,H$2>=(Params!$B$10-1)),1,0) | I5: =IF(AND(I$2>=(Params!$B$8-1),Params!$B$9=1,I$2>=(Params!$B$10-1)),1,0) | J5: =IF(AND(J$2>=(Params!$B$8-1),Params!$B$9=1,J$2>=(Params!$B$10-1)),1,0) | ... BV5: =IF(AND(BV$2>=(Params!$B$8-1),Params!$B$9=1,BV$2>=(Params!$B$10-1)),1,0)
A7: conversion multiplier | B7: by month | C7: =(C3*Params!$B$26+(C4+C5)*Params!$B$27)*(1+Params!$B$11*C5) | D7: =(D3*Params!$B$26+(D4+D5)*Params!$B$27)*(1+Params!$B$11*D5) | E7: =(E3*Params!$B$26+(E4+E5)*Params!$B$27)*(1+Params!$B$11*E5) | F7: =(F3*Params!$B$26+(F4+F5)*Params!$B$27)*(1+Params!$B$11*F5) | G7: =(G3*Params!$B$26+(G4+G5)*Params!$B$27)*(1+Params!$B$11*G5) | H7: =(H3*Params!$B$26+(H4+H5)*Params!$B$27)*(1+Params!$B$11*H5) | I7: =(I3*Params!$B$26+(I4+I5)*Params!$B$27)*(1+Params!$B$11*I5) | J7: =(J3*Params!$B$26+(J4+J5)*Params!$B$27)*(1+Params!$B$11*J5) | ... BV7: =(BV3*Params!$B$26+(BV4+BV5)*Params!$B$27)*(1+Params!$B$11*BV5)
A8: trial share of sign-ups | B8: by month | C8: =(C3*Params!$B$28+(C4+C5)*Params!$B$29) | D8: =(D3*Params!$B$28+(D4+D5)*Params!$B$29) | E8: =(E3*Params!$B$28+(E4+E5)*Params!$B$29) | F8: =(F3*Params!$B$28+(F4+F5)*Params!$B$29) | G8: =(G3*Params!$B$28+(G4+G5)*Params!$B$29) | H8: =(H3*Params!$B$28+(H4+H5)*Params!$B$29) | I8: =(I3*Params!$B$28+(I4+I5)*Params!$B$29) | J8: =(J3*Params!$B$28+(J4+J5)*Params!$B$29) | ... BV8: =(BV3*Params!$B$28+(BV4+BV5)*Params!$B$29)
A9: trial-to-paid (by trial start) | B9: by month | C9: =(C3*Params!$B$30+(C4+C5)*Params!$B$31) | D9: =(D3*Params!$B$30+(D4+D5)*Params!$B$31) | E9: =(E3*Params!$B$30+(E4+E5)*Params!$B$31) | F9: =(F3*Params!$B$30+(F4+F5)*Params!$B$31) | G9: =(G3*Params!$B$30+(G4+G5)*Params!$B$31) | H9: =(H3*Params!$B$30+(H4+H5)*Params!$B$31) | I9: =(I3*Params!$B$30+(I4+I5)*Params!$B$31) | J9: =(J3*Params!$B$30+(J4+J5)*Params!$B$31) | ... BV9: =(BV3*Params!$B$30+(BV4+BV5)*Params!$B$31)
A10: price factor | B10: by month | C10: =1+Params!$B$13*C5 | D10: =1+Params!$B$13*D5 | E10: =1+Params!$B$13*E5 | F10: =1+Params!$B$13*F5 | G10: =1+Params!$B$13*G5 | H10: =1+Params!$B$13*H5 | I10: =1+Params!$B$13*I5 | J10: =1+Params!$B$13*J5 | ... BV10: =1+Params!$B$13*BV5

Sheet MAU
A1: line | B1: segment | C1: 2025-01 | D1: 2025-02 | E1: 2025-03 | F1: 2025-04 | G1: 2025-05 | H1: 2025-06 | I1: 2025-07 | J1: 2025-08 | K1: 2025-09 | L1: 2025-10 | M1: 2025-11 | N1: 2025-12 | O1: 2026-01 | P1: 2026-02 | Q1: 2026-03 | R1: 2026-04 | S1: 2026-05 | T1: 2026-06 | U1: 2026-07 | V1: 2026-08 | W1: 2026-09 | X1: 2026-10 | Y1: 2026-11 | Z1: 2026-12 | AA1: 2027-01 | AB1: 2027-02 | AC1: 2027-03 | AD1: 2027-04 | AE1: 2027-05 | AF1: 2027-06 | AG1: 2027-07 | AH1: 2027-08 | AI1: 2027-09 | AJ1: 2027-10 | AK1: 2027-11 | AL1: 2027-12 | AM1: 2028-01 | AN1: 2028-02 | AO1: 2028-03 | AP1: 2028-04 | AQ1: 2028-05 | AR1: 2028-06 | AS1: 2028-07 | AT1: 2028-08 | AU1: 2028-09 | AV1: 2028-10 | AW1: 2028-11 | AX1: 2028-12 | AY1: 2029-01 | AZ1: 2029-02 | BA1: 2029-03 | BB1: 2029-04 | BC1: 2029-05 | BD1: 2029-06 | BE1: 2029-07 | BF1: 2029-08 | BG1: 2029-09 | BH1: 2029-10 | BI1: 2029-11 | BJ1: 2029-12 | BK1: 2030-01 | BL1: 2030-02 | BM1: 2030-03 | BN1: 2030-04 | BO1: 2030-05 | BP1: 2030-06 | BQ1: 2030-07 | BR1: 2030-08 | BS1: 2030-09 | BT1: 2030-10 | BU1: 2030-11 | BV1: 2030-12
A2: month index (0 = Jan 2025) | C2: 0 | D2: 1 | E2: 2 | F2: 3 | G2: 4 | H2: 5 | I2: 6 | J2: 7 | K2: 8 | L2: 9 | M2: 10 | N2: 11 | O2: 12 | P2: 13 | Q2: 14 | R2: 15 | S2: 16 | T2: 17 | U2: 18 | V2: 19 | W2: 20 | X2: 21 | Y2: 22 | Z2: 23 | AA2: 24 | AB2: 25 | AC2: 26 | AD2: 27 | AE2: 28 | AF2: 29 | AG2: 30 | AH2: 31 | AI2: 32 | AJ2: 33 | AK2: 34 | AL2: 35 | AM2: 36 | AN2: 37 | AO2: 38 | AP2: 39 | AQ2: 40 | AR2: 41 | AS2: 42 | AT2: 43 | AU2: 44 | AV2: 45 | AW2: 46 | AX2: 47 | AY2: 48 | AZ2: 49 | BA2: 50 | BB2: 51 | BC2: 52 | BD2: 53 | BE2: 54 | BF2: 55 | BG2: 56 | BH2: 57 | BI2: 58 | BJ2: 59 | BK2: 60 | BL2: 61 | BM2: 62 | BN2: 63 | BO2: 64 | BP2: 65 | BQ2: 66 | BR2: 67 | BS2: 68 | BT2: 69 | BU2: 70 | BV2: 71
A3: MAU total | B3: all | C3: =Params!$B$2 | D3: =C3*(1+IF(INT(D$2/12)=0,Params!$B$3,Params!$B$4+(Params!$B$5-Params!$B$4)*(INT(D$2/12)-1)/4))^(1/12) | E3: =D3*(1+IF(INT(E$2/12)=0,Params!$B$3,Params!$B$4+(Params!$B$5-Params!$B$4)*(INT(E$2/12)-1)/4))^(1/12) | F3: =E3*(1+IF(INT(F$2/12)=0,Params!$B$3,Params!$B$4+(Params!$B$5-Params!$B$4)*(INT(F$2/12)-1)/4))^(1/12) | G3: =F3*(1+IF(INT(G$2/12)=0,Params!$B$3,Params!$B$4+(Params!$B$5-Params!$B$4)*(INT(G$2/12)-1)/4))^(1/12) | H3: =G3*(1+IF(INT(H$2/12)=0,Params!$B$3,Params!$B$4+(Params!$B$5-Params!$B$4)*(INT(H$2/12)-1)/4))^(1/12) | I3: =H3*(1+IF(INT(I$2/12)=0,Params!$B$3,Params!$B$4+(Params!$B$5-Params!$B$4)*(INT(I$2/12)-1)/4))^(1/12) | J3: =I3*(1+IF(INT(J$2/12)=0,Params!$B$3,Params!$B$4+(Params!$B$5-Params!$B$4)*(INT(J$2/12)-1)/4))^(1/12) | K3: =J3*(1+IF(INT(K$2/12)=0,Params!$B$3,Params!$B$4+(Params!$B$5-Params!$B$4)*(INT(K$2/12)-1)/4))^(1/12) | ... BV3: =BU3*(1+IF(INT(BV$2/12)=0,Params!$B$3,Params!$B$4+(Params!$B$5-Params!$B$4)*(INT(BV$2/12)-1)/4))^(1/12)
A4: MAU | B4: US_CA | C4: =C$3*Params!$B$52 | D4: =D$3*Params!$B$52 | E4: =E$3*Params!$B$52 | F4: =F$3*Params!$B$52 | G4: =G$3*Params!$B$52 | H4: =H$3*Params!$B$52 | I4: =I$3*Params!$B$52 | J4: =J$3*Params!$B$52 | ... BV4: =BV$3*Params!$B$52
A5: MAU | B5: EUROPE | C5: =C$3*Params!$B$53 | D5: =D$3*Params!$B$53 | E5: =E$3*Params!$B$53 | F5: =F$3*Params!$B$53 | G5: =G$3*Params!$B$53 | H5: =H$3*Params!$B$53 | I5: =I$3*Params!$B$53 | J5: =J$3*Params!$B$53 | ... BV5: =BV$3*Params!$B$53
A6: MAU | B6: LATAM | C6: =C$3*Params!$B$54 | D6: =D$3*Params!$B$54 | E6: =E$3*Params!$B$54 | F6: =F$3*Params!$B$54 | G6: =G$3*Params!$B$54 | H6: =H$3*Params!$B$54 | I6: =I$3*Params!$B$54 | J6: =J$3*Params!$B$54 | ... BV6: =BV$3*Params!$B$54
A7: MAU | B7: APAC | C7: =C$3*Params!$B$55 | D7: =D$3*Params!$B$55 | E7: =E$3*Params!$B$55 | F7: =F$3*Params!$B$55 | G7: =G$3*Params!$B$55 | H7: =H$3*Params!$B$55 | I7: =I$3*Params!$B$55 | J7: =J$3*Params!$B$55 | ... BV7: =BV$3*Params!$B$55
A8: MAU | B8: ROW | C8: =C$3*Params!$B$56 | D8: =D$3*Params!$B$56 | E8: =E$3*Params!$B$56 | F8: =F$3*Params!$B$56 | G8: =G$3*Params!$B$56 | H8: =H$3*Params!$B$56 | I8: =I$3*Params!$B$56 | J8: =J$3*Params!$B$56 | ... BV8: =BV$3*Params!$B$56

Sheet Prices
A1: region | B1: plan | C1: list $/mo | D1: x regional index | E1: after discount & VAT | F1: keep after fees (yr 1) | G1: keep after fees (later) | H1: net $/mo (yr 1) | I1: net $/mo (later)
A2: US_CA | B2: NITRO_M | C2: =Params!$B$100/Params!$B$104 | D2: =C2*Params!$B$62 | E2: =D2*(1-Params!$B$17)*(1-Params!$B$67) | F2: =Params!$B$77*(1-Params!$B$18)+Params!$B$78*(1-Params!$B$19)+Params!$B$79*(1-Params!$B$21) | G2: =Params!$B$77*(1-Params!$B$18)+Params!$B$78*(1-Params!$B$20)+Params!$B$79*(1-Params!$B$21) | H2: =E2*F2 | I2: =E2*G2
A3: US_CA | B3: NITRO_A | C3: =Params!$B$101/Params!$B$105 | D3: =C3*Params!$B$62 | E3: =D3*(1-Params!$B$17)*(1-Params!$B$67) | F3: =Params!$B$77*(1-Params!$B$18)+Params!$B$78*(1-Params!$B$19)+Params!$B$79*(1-Params!$B$21) | G3: =Params!$B$77*(1-Params!$B$18)+Params!$B$78*(1-Params!$B$20)+Params!$B$79*(1-Params!$B$21) | H3: =E3*F3 | I3: =E3*G3
A4: US_CA | B4: BASIC_M | C4: =Params!$B$102/Params!$B$106 | D4: =C4*Params!$B$62 | E4: =D4*(1-Params!$B$17)*(1-Params!$B$67) | F4: =Params!$B$77*(1-Params!$B$18)+Params!$B$78*(1-Params!$B$19)+Params!$B$79*(1-Params!$B$21) | G4: =Params!$B$77*(1-Params!$B$18)+Params!$B$78*(1-Params!$B$20)+Params!$B$79*(1-Params!$B$21) | H4: =E4*F4 | I4: =E4*G4
A5: US_CA | B5: BASIC_A | C5: =Params!$B$103/Params!$B$107 | D5: =C5*Params!$B$62 | E5: =D5*(1-Params!$B$17)*(1-Params!$B$67) | F5: =Params!$B$77*(1-Params!$B$18)+Params!$B$78*(1-Params!$B$19)+Params!$B$79*(1-Params!$B$21) | G5: =Params!$B$77*(1-Params!$B$18)+Params!$B$78*(1-Params!$B$20)+Params!$B$79*(1-Params!$B$21) | H5: =E5*F5 | I5: =E5*G5
A6: EUROPE | B6: NITRO_M | C6: =Params!$B$100/Params!$B$104 | D6: =C6*Params!$B$63 | E6: =D6*(1-Params!$B$17)*(1-Params!$B$68) | F6: =Params!$B$80*(1-Params!$B$18)+Params!$B$81*(1-Params!$B$19)+Params!$B$82*(1-Params!$B$21) | G6: =Params!$B$80*(1-Params!$B$18)+Params!$B$81*(1-Params!$B$20)+Params!$B$82*(1-Params!$B$21) | H6: =E6*F6 | I6: =E6*G6
A7: EUROPE | B7: NITRO_A | C7: =Params!$B$101/Params!$B$105 | D7: =C7*Params!$B$63 | E7: =D7*(1-Params!$B$17)*(1-Params!$B$68) | F7: =Params!$B$80*(1-Params!$B$18)+Params!$B$81*(1-Params!$B$19)+Params!$B$82*(1-Params!$B$21) | G7: =Params!$B$80*(1-Params!$B$18)+Params!$B$81*(1-Params!$B$20)+Params!$B$82*(1-Params!$B$21) | H7: =E7*F7 | I7: =E7*G7
A8: EUROPE | B8: BASIC_M | C8: =Params!$B$102/Params!$B$106 | D8: =C8*Params!$B$63 | E8: =D8*(1-Params!$B$17)*(1-Params!$B$68) | F8: =Params!$B$80*(1-Params!$B$18)+Params!$B$81*(1-Params!$B$19)+Params!$B$82*(1-Params!$B$21) | G8: =Params!$B$80*(1-Params!$B$18)+Params!$B$81*(1-Params!$B$20)+Params!$B$82*(1-Params!$B$21) | H8: =E8*F8 | I8: =E8*G8
A9: EUROPE | B9: BASIC_A | C9: =Params!$B$103/Params!$B$107 | D9: =C9*Params!$B$63 | E9: =D9*(1-Params!$B$17)*(1-Params!$B$68) | F9: =Params!$B$80*(1-Params!$B$18)+Params!$B$81*(1-Params!$B$19)+Params!$B$82*(1-Params!$B$21) | G9: =Params!$B$80*(1-Params!$B$18)+Params!$B$81*(1-Params!$B$20)+Params!$B$82*(1-Params!$B$21) | H9: =E9*F9 | I9: =E9*G9
A10: LATAM | B10: NITRO_M | C10: =Params!$B$100/Params!$B$104 | D10: =C10*Params!$B$64 | E10: =D10*(1-Params!$B$17)*(1-Params!$B$69) | F10: =Params!$B$83*(1-Params!$B$18)+Params!$B$84*(1-Params!$B$19)+Params!$B$85*(1-Params!$B$21) | G10: =Params!$B$83*(1-Params!$B$18)+Params!$B$84*(1-Params!$B$20)+Params!$B$85*(1-Params!$B$21) | H10: =E10*F10 | I10: =E10*G10
A11: LATAM | B11: NITRO_A | C11: =Params!$B$101/Params!$B$105 | D11: =C11*Params!$B$64 | E11: =D11*(1-Params!$B$17)*(1-Params!$B$69) | F11: =Params!$B$83*(1-Params!$B$18)+Params!$B$84*(1-Params!$B$19)+Params!$B$85*(1-Params!$B$21) | G11: =Params!$B$83*(1-Params!$B$18)+Params!$B$84*(1-Params!$B$20)+Params!$B$85*(1-Params!$B$21) | H11: =E11*F11 | I11: =E11*G11
A12: LATAM | B12: BASIC_M | C12: =Params!$B$102/Params!$B$106 | D12: =C12*Params!$B$64 | E12: =D12*(1-Params!$B$17)*(1-Params!$B$69) | F12: =Params!$B$83*(1-Params!$B$18)+Params!$B$84*(1-Params!$B$19)+Params!$B$85*(1-Params!$B$21) | G12: =Params!$B$83*(1-Params!$B$18)+Params!$B$84*(1-Params!$B$20)+Params!$B$85*(1-Params!$B$21) | H12: =E12*F12 | I12: =E12*G12
A13: LATAM | B13: BASIC_A | C13: =Params!$B$103/Params!$B$107 | D13: =C13*Params!$B$64 | E13: =D13*(1-Params!$B$17)*(1-Params!$B$69) | F13: =Params!$B$83*(1-Params!$B$18)+Params!$B$84*(1-Params!$B$19)+Params!$B$85*(1-Params!$B$21) | G13: =Params!$B$83*(1-Params!$B$18)+Params!$B$84*(1-Params!$B$20)+Params!$B$85*(1-Params!$B$21) | H13: =E13*F13 | I13: =E13*G13
A14: APAC | B14: NITRO_M | C14: =Params!$B$100/Params!$B$104 | D14: =C14*Params!$B$65 | E14: =D14*(1-Params!$B$17)*(1-Params!$B$70) | F14: =Params!$B$86*(1-Params!$B$18)+Params!$B$87*(1-Params!$B$19)+Params!$B$88*(1-Params!$B$21) | G14: =Params!$B$86*(1-Params!$B$18)+Params!$B$87*(1-Params!$B$20)+Params!$B$88*(1-Params!$B$21) | H14: =E14*F14 | I14: =E14*G14
A15: APAC | B15: NITRO_A | C15: =Params!$B$101/Params!$B$105 | D15: =C15*Params!$B$65 | E15: =D15*(1-Params!$B$17)*(1-Params!$B$70) | F15: =Params!$B$86*(1-Params!$B$18)+Params!$B$87*(1-Params!$B$19)+Params!$B$88*(1-Params!$B$21) | G15: =Params!$B$86*(1-Params!$B$18)+Params!$B$87*(1-Params!$B$20)+Params!$B$88*(1-Params!$B$21) | H15: =E15*F15 | I15: =E15*G15
A16: APAC | B16: BASIC_M | C16: =Params!$B$102/Params!$B$106 | D16: =C16*Params!$B$65 | E16: =D16*(1-Params!$B$17)*(1-Params!$B$70) | F16: =Params!$B$86*(1-Params!$B$18)+Params!$B$87*(1-Params!$B$19)+Params!$B$88*(1-Params!$B$21) | G16: =Params!$B$86*(1-Params!$B$18)+Params!$B$87*(1-Params!$B$20)+Params!$B$88*(1-Params!$B$21) | H16: =E16*F16 | I16: =E16*G16
A17: APAC | B17: BASIC_A | C17: =Params!$B$103/Params!$B$107 | D17: =C17*Params!$B$65 | E17: =D17*(1-Params!$B$17)*(1-Params!$B$70) | F17: =Params!$B$86*(1-Params!$B$18)+Params!$B$87*(1-Params!$B$19)+Params!$B$88*(1-Params!$B$21) | G17: =Params!$B$86*(1-Params!$B$18)+Params!$B$87*(1-Params!$B$20)+Params!$B$88*(1-Params!$B$21) | H17: =E17*F17 | I17: =E17*G17
A18: ROW | B18: NITRO_M | C18: =Params!$B$100/Params!$B$104 | D18: =C18*Params!$B$66 | E18: =D18*(1-Params!$B$17)*(1-Params!$B$71) | F18: =Params!$B$89*(1-Params!$B$18)+Params!$B$90*(1-Params!$B$19)+Params!$B$91*(1-Params!$B$21) | G18: =Params!$B$89*(1-Params!$B$18)+Params!$B$90*(1-Params!$B$20)+Params!$B$91*(1-Params!$B$21) | H18: =E18*F18 | I18: =E18*G18
A19: ROW | B19: NITRO_A | C19: =Params!$B$101/Params!$B$105 | D19: =C19*Params!$B$66 | E19: =D19*(1-Params!$B$17)*(1-Params!$B$71) | F19: =Params!$B$89*(1-Params!$B$18)+Params!$B$90*(1-Params!$B$19)+Params!$B$91*(1-Params!$B$21) | G19: =Params!$B$89*(1-Params!$B$18)+Params!$B$90*(1-Params!$B$20)+Params!$B$91*(1-Params!$B$21) | H19: =E19*F19 | I19: =E19*G19
A20: ROW | B20: BASIC_M | C20: =Params!$B$102/Params!$B$106 | D20: =C20*Params!$B$66 | E20: =D20*(1-Params!$B$17)*(1-Params!$B$71) | F20: =Params!$B$89*(1-Params!$B$18)+Params!$B$90*(1-Params!$B$19)+Params!$B$91*(1-Params!$B$21) | G20: =Params!$B$89*(1-Params!$B$18)+Params!$B$90*(1-Params!$B$20)+Params!$B$91*(1-Params!$B$21) | H20: =E20*F20 | I20: =E20*G20
A21: ROW | B21: BASIC_A | C21: =Params!$B$103/Params!$B$107 | D21: =C21*Params!$B$66 | E21: =D21*(1-Params!$B$17)*(1-Params!$B$71) | F21: =Params!$B$89*(1-Params!$B$18)+Params!$B$90*(1-Params!$B$19)+Params!$B$91*(1-Params!$B$21) | G21: =Params!$B$89*(1-Params!$B$18)+Params!$B$90*(1-Params!$B$20)+Params!$B$91*(1-Params!$B$21) | H21: =E21*F21 | I21: =E21*G21

Sheet FX
A1: line | B1: segment | C1: 2025-01 | D1: 2025-02 | E1: 2025-03 | F1: 2025-04 | G1: 2025-05 | H1: 2025-06 | I1: 2025-07 | J1: 2025-08 | K1: 2025-09 | L1: 2025-10 | M1: 2025-11 | N1: 2025-12 | O1: 2026-01 | P1: 2026-02 | Q1: 2026-03 | R1: 2026-04 | S1: 2026-05 | T1: 2026-06 | U1: 2026-07 | V1: 2026-08 | W1: 2026-09 | X1: 2026-10 | Y1: 2026-11 | Z1: 2026-12 | AA1: 2027-01 | AB1: 2027-02 | AC1: 2027-03 | AD1: 2027-04 | AE1: 2027-05 | AF1: 2027-06 | AG1: 2027-07 | AH1: 2027-08 | AI1: 2027-09 | AJ1: 2027-10 | AK1: 2027-11 | AL1: 2027-12 | AM1: 2028-01 | AN1: 2028-02 | AO1: 2028-03 | AP1: 2028-04 | AQ1: 2028-05 | AR1: 2028-06 | AS1: 2028-07 | AT1: 2028-08 | AU1: 2028-09 | AV1: 2028-10 | AW1: 2028-11 | AX1: 2028-12 | AY1: 2029-01 | AZ1: 2029-02 | BA1: 2029-03 | BB1: 2029-04 | BC1: 2029-05 | BD1: 2029-06 | BE1: 2029-07 | BF1: 2029-08 | BG1: 2029-09 | BH1: 2029-10 | BI1: 2029-11 | BJ1: 2029-12 | BK1: 2030-01 | BL1: 2030-02 | BM1: 2030-03 | BN1: 2030-04 | BO1: 2030-05 | BP1: 2030-06 | BQ1: 2030-07 | BR1: 2030-08 | BS1: 2030-09 | BT1: 2030-10 | BU1: 2030-11 | BV1: 2030-12
A2: month index (0 = Jan 2025) | C2: 0 | D2: 1 | E2: 2 | F2: 3 | G2: 4 | H2: 5 | I2: 6 | J2: 7 | K2: 8 | L2: 9 | M2: 10 | N2: 11 | O2: 12 | P2: 13 | Q2: 14 | R2: 15 | S2: 16 | T2: 17 | U2: 18 | V2: 19 | W2: 20 | X2: 21 | Y2: 22 | Z2: 23 | AA2: 24 | AB2: 25 | AC2: 26 | AD2: 27 | AE2: 28 | AF2: 29 | AG2: 30 | AH2: 31 | AI2: 32 | AJ2: 33 | AK2: 34 | AL2: 35 | AM2: 36 | AN2: 37 | AO2: 38 | AP2: 39 | AQ2: 40 | AR2: 41 | AS2: 42 | AT2: 43 | AU2: 44 | AV2: 45 | AW2: 46 | AX2: 47 | AY2: 48 | AZ2: 49 | BA2: 50 | BB2: 51 | BC2: 52 | BD2: 53 | BE2: 54 | BF2: 55 | BG2: 56 | BH2: 57 | BI2: 58 | BJ2: 59 | BK2: 60 | BL2: 61 | BM2: 62 | BN2: 63 | BO2: 64 | BP2: 65 | BQ2: 66 | BR2: 67 | BS2: 68 | BT2: 69 | BU2: 70 | BV2: 71
A3: Rates: local currency per USD. FY2025 average to Dec 2025, linear to spot, then covered-interest-parity forwards.
A5: rate (local per USD) | B5: USD | C5: =IF(C$2<=11,Params!$B$108,IF(C$2<=(Params!$B$25-1),Params!$B$108+(Params!$B$113-Params!$B$108)*(C$2-11)/((Params!$B$25-1)-11),Params!$B$113*((1+Params!$B$118)/(1+Params!$B$118))^((C$2-(Params!$B$25-1))/12))) | D5: =IF(D$2<=11,Params!$B$108,IF(D$2<=(Params!$B$25-1),Params!$B$108+(Params!$B$113-Params!$B$108)*(D$2-11)/((Params!$B$25-1)-11),Params!$B$113*((1+Params!$B$118)/(1+Params!$B$118))^((D$2-(Params!$B$25-1))/12))) | E5: =IF(E$2<=11,Params!$B$108,IF(E$2<=(Params!$B$25-1),Params!$B$108+(Params!$B$113-Params!$B$108)*(E$2-11)/((Params!$B$25-1)-11),Params!$B$113*((1+Params!$B$118)/(1+Params!$B$118))^((E$2-(Params!$B$25-1))/12))) | F5: =IF(F$2<=11,Params!$B$108,IF(F$2<=(Params!$B$25-1),Params!$B$108+(Params!$B$113-Params!$B$108)*(F$2-11)/((Params!$B$25-1)-11),Params!$B$113*((1+Params!$B$118)/(1+Params!$B$118))^((F$2-(Params!$B$25-1))/12))) | G5: =IF(G$2<=11,Params!$B$108,IF(G$2<=(Params!$B$25-1),Params!$B$108+(Params!$B$113-Params!$B$108)*(G$2-11)/((Params!$B$25-1)-11),Params!$B$113*((1+Params!$B$118)/(1+Params!$B$118))^((G$2-(Params!$B$25-1))/12))) | H5: =IF(H$2<=11,Params!$B$108,IF(H$2<=(Params!$B$25-1),Params!$B$108+(Params!$B$113-Params!$B$108)*(H$2-11)/((Params!$B$25-1)-11),Params!$B$113*((1+Params!$B$118)/(1+Params!$B$118))^((H$2-(Params!$B$25-1))/12))) | I5: =IF(I$2<=11,Params!$B$108,IF(I$2<=(Params!$B$25-1),Params!$B$108+(Params!$B$113-Params!$B$108)*(I$2-11)/((Params!$B$25-1)-11),Params!$B$113*((1+Params!$B$118)/(1+Params!$B$118))^((I$2-(Params!$B$25-1))/12))) | J5: =IF(J$2<=11,Params!$B$108,IF(J$2<=(Params!$B$25-1),Params!$B$108+(Params!$B$113-Params!$B$108)*(J$2-11)/((Params!$B$25-1)-11),Params!$B$113*((1+Params!$B$118)/(1+Params!$B$118))^((J$2-(Params!$B$25-1))/12))) | ... BV5: =IF(BV$2<=11,Params!$B$108,IF(BV$2<=(Params!$B$25-1),Params!$B$108+(Params!$B$113-Params!$B$108)*(BV$2-11)/((Params!$B$25-1)-11),Params!$B$113*((1+Params!$B$118)/(1+Params!$B$118))^((BV$2-(Params!$B$25-1))/12)))
A6: rate (local per USD) | B6: EUR | C6: =IF(C$2<=11,Params!$B$109,IF(C$2<=(Params!$B$25-1),Params!$B$109+(Params!$B$114-Params!$B$109)*(C$2-11)/((Params!$B$25-1)-11),Params!$B$114*((1+Params!$B$119)/(1+Params!$B$118))^((C$2-(Params!$B$25-1))/12)))*IF(C$2>(Params!$B$25-1),1+Params!$B$129*Params!$B$24,1) | D6: =IF(D$2<=11,Params!$B$109,IF(D$2<=(Params!$B$25-1),Params!$B$109+(Params!$B$114-Params!$B$109)*(D$2-11)/((Params!$B$25-1)-11),Params!$B$114*((1+Params!$B$119)/(1+Params!$B$118))^((D$2-(Params!$B$25-1))/12)))*IF(D$2>(Params!$B$25-1),1+Params!$B$129*Params!$B$24,1) | E6: =IF(E$2<=11,Params!$B$109,IF(E$2<=(Params!$B$25-1),Params!$B$109+(Params!$B$114-Params!$B$109)*(E$2-11)/((Params!$B$25-1)-11),Params!$B$114*((1+Params!$B$119)/(1+Params!$B$118))^((E$2-(Params!$B$25-1))/12)))*IF(E$2>(Params!$B$25-1),1+Params!$B$129*Params!$B$24,1) | F6: =IF(F$2<=11,Params!$B$109,IF(F$2<=(Params!$B$25-1),Params!$B$109+(Params!$B$114-Params!$B$109)*(F$2-11)/((Params!$B$25-1)-11),Params!$B$114*((1+Params!$B$119)/(1+Params!$B$118))^((F$2-(Params!$B$25-1))/12)))*IF(F$2>(Params!$B$25-1),1+Params!$B$129*Params!$B$24,1) | G6: =IF(G$2<=11,Params!$B$109,IF(G$2<=(Params!$B$25-1),Params!$B$109+(Params!$B$114-Params!$B$109)*(G$2-11)/((Params!$B$25-1)-11),Params!$B$114*((1+Params!$B$119)/(1+Params!$B$118))^((G$2-(Params!$B$25-1))/12)))*IF(G$2>(Params!$B$25-1),1+Params!$B$129*Params!$B$24,1) | H6: =IF(H$2<=11,Params!$B$109,IF(H$2<=(Params!$B$25-1),Params!$B$109+(Params!$B$114-Params!$B$109)*(H$2-11)/((Params!$B$25-1)-11),Params!$B$114*((1+Params!$B$119)/(1+Params!$B$118))^((H$2-(Params!$B$25-1))/12)))*IF(H$2>(Params!$B$25-1),1+Params!$B$129*Params!$B$24,1) | I6: =IF(I$2<=11,Params!$B$109,IF(I$2<=(Params!$B$25-1),Params!$B$109+(Params!$B$114-Params!$B$109)*(I$2-11)/((Params!$B$25-1)-11),Params!$B$114*((1+Params!$B$119)/(1+Params!$B$118))^((I$2-(Params!$B$25-1))/12)))*IF(I$2>(Params!$B$25-1),1+Params!$B$129*Params!$B$24,1) | J6: =IF(J$2<=11,Params!$B$109,IF(J$2<=(Params!$B$25-1),Params!$B$109+(Params!$B$114-Params!$B$109)*(J$2-11)/((Params!$B$25-1)-11),Params!$B$114*((1+Params!$B$119)/(1+Params!$B$118))^((J$2-(Params!$B$25-1))/12)))*IF(J$2>(Params!$B$25-1),1+Params!$B$129*Params!$B$24,1) | ... BV6: =IF(BV$2<=11,Params!$B$109,IF(BV$2<=(Params!$B$25-1),Params!$B$109+(Params!$B$114-Params!$B$109)*(BV$2-11)/((Params!$B$25-1)-11),Params!$B$114*((1+Params!$B$119)/(1+Params!$B$118))^((BV$2-(Params!$B$25-1))/12)))*IF(BV$2>(Params!$B$25-1),1+Params!$B$129*Params!$B$24,1)
A7: rate (local per USD) | B7: BRL | C7: =IF(C$2<=11,Params!$B$110,IF(C$2<=(Params!$B$25-1),Params!$B$110+(Params!$B$115-Params!$B$110)*(C$2-11)/((Params!$B$25-1)-11),Params!$B$115*((1+Params!$B$120)/(1+Params!$B$118))^((C$2-(Params!$B$25-1))/12)))*IF(C$2>(Params!$B$25-1),1+Params!$B$129*Params!$B$24,1) | D7: =IF(D$2<=11,Params!$B$110,IF(D$2<=(Params!$B$25-1),Params!$B$110+(Params!$B$115-Params!$B$110)*(D$2-11)/((Params!$B$25-1)-11),Params!$B$115*((1+Params!$B$120)/(1+Params!$B$118))^((D$2-(Params!$B$25-1))/12)))*IF(D$2>(Params!$B$25-1),1+Params!$B$129*Params!$B$24,1) | E7: =IF(E$2<=11,Params!$B$110,IF(E$2<=(Params!$B$25-1),Params!$B$110+(Params!$B$115-Params!$B$110)*(E$2-11)/((Params!$B$25-1)-11),Params!$B$115*((1+Params!$B$120)/(1+Params!$B$118))^((E$2-(Params!$B$25-1))/12)))*IF(E$2>(Params!$B$25-1),1+Params!$B$129*Params!$B$24,1) | F7: =IF(F$2<=11,Params!$B$110,IF(F$2<=(Params!$B$25-1),Params!$B$110+(Params!$B$115-Params!$B$110)*(F$2-11)/((Params!$B$25-1)-11),Params!$B$115*((1+Params!$B$120)/(1+Params!$B$118))^((F$2-(Params!$B$25-1))/12)))*IF(F$2>(Params!$B$25-1),1+Params!$B$129*Params!$B$24,1) | G7: =IF(G$2<=11,Params!$B$110,IF(G$2<=(Params!$B$25-1),Params!$B$110+(Params!$B$115-Params!$B$110)*(G$2-11)/((Params!$B$25-1)-11),Params!$B$115*((1+Params!$B$120)/(1+Params!$B$118))^((G$2-(Params!$B$25-1))/12)))*IF(G$2>(Params!$B$25-1),1+Params!$B$129*Params!$B$24,1) | H7: =IF(H$2<=11,Params!$B$110,IF(H$2<=(Params!$B$25-1),Params!$B$110+(Params!$B$115-Params!$B$110)*(H$2-11)/((Params!$B$25-1)-11),Params!$B$115*((1+Params!$B$120)/(1+Params!$B$118))^((H$2-(Params!$B$25-1))/12)))*IF(H$2>(Params!$B$25-1),1+Params!$B$129*Params!$B$24,1) | I7: =IF(I$2<=11,Params!$B$110,IF(I$2<=(Params!$B$25-1),Params!$B$110+(Params!$B$115-Params!$B$110)*(I$2-11)/((Params!$B$25-1)-11),Params!$B$115*((1+Params!$B$120)/(1+Params!$B$118))^((I$2-(Params!$B$25-1))/12)))*IF(I$2>(Params!$B$25-1),1+Params!$B$129*Params!$B$24,1) | J7: =IF(J$2<=11,Params!$B$110,IF(J$2<=(Params!$B$25-1),Params!$B$110+(Params!$B$115-Params!$B$110)*(J$2-11)/((Params!$B$25-1)-11),Params!$B$115*((1+Params!$B$120)/(1+Params!$B$118))^((J$2-(Params!$B$25-1))/12)))*IF(J$2>(Params!$B$25-1),1+Params!$B$129*Params!$B$24,1) | ... BV7: =IF(BV$2<=11,Params!$B$110,IF(BV$2<=(Params!$B$25-1),Params!$B$110+(Params!$B$115-Params!$B$110)*(BV$2-11)/((Params!$B$25-1)-11),Params!$B$115*((1+Params!$B$120)/(1+Params!$B$118))^((BV$2-(Params!$B$25-1))/12)))*IF(BV$2>(Params!$B$25-1),1+Params!$B$129*Params!$B$24,1)
A8: rate (local per USD) | B8: JPY | C8: =IF(C$2<=11,Params!$B$111,IF(C$2<=(Params!$B$25-1),Params!$B$111+(Params!$B$116-Params!$B$111)*(C$2-11)/((Params!$B$25-1)-11),Params!$B$116*((1+Params!$B$121)/(1+Params!$B$118))^((C$2-(Params!$B$25-1))/12)))*IF(C$2>(Params!$B$25-1),1+Params!$B$129*Params!$B$24,1) | D8: =IF(D$2<=11,Params!$B$111,IF(D$2<=(Params!$B$25-1),Params!$B$111+(Params!$B$116-Params!$B$111)*(D$2-11)/((Params!$B$25-1)-11),Params!$B$116*((1+Params!$B$121)/(1+Params!$B$118))^((D$2-(Params!$B$25-1))/12)))*IF(D$2>(Params!$B$25-1),1+Params!$B$129*Params!$B$24,1) | E8: =IF(E$2<=11,Params!$B$111,IF(E$2<=(Params!$B$25-1),Params!$B$111+(Params!$B$116-Params!$B$111)*(E$2-11)/((Params!$B$25-1)-11),Params!$B$116*((1+Params!$B$121)/(1+Params!$B$118))^((E$2-(Params!$B$25-1))/12)))*IF(E$2>(Params!$B$25-1),1+Params!$B$129*Params!$B$24,1) | F8: =IF(F$2<=11,Params!$B$111,IF(F$2<=(Params!$B$25-1),Params!$B$111+(Params!$B$116-Params!$B$111)*(F$2-11)/((Params!$B$25-1)-11),Params!$B$116*((1+Params!$B$121)/(1+Params!$B$118))^((F$2-(Params!$B$25-1))/12)))*IF(F$2>(Params!$B$25-1),1+Params!$B$129*Params!$B$24,1) | G8: =IF(G$2<=11,Params!$B$111,IF(G$2<=(Params!$B$25-1),Params!$B$111+(Params!$B$116-Params!$B$111)*(G$2-11)/((Params!$B$25-1)-11),Params!$B$116*((1+Params!$B$121)/(1+Params!$B$118))^((G$2-(Params!$B$25-1))/12)))*IF(G$2>(Params!$B$25-1),1+Params!$B$129*Params!$B$24,1) | H8: =IF(H$2<=11,Params!$B$111,IF(H$2<=(Params!$B$25-1),Params!$B$111+(Params!$B$116-Params!$B$111)*(H$2-11)/((Params!$B$25-1)-11),Params!$B$116*((1+Params!$B$121)/(1+Params!$B$118))^((H$2-(Params!$B$25-1))/12)))*IF(H$2>(Params!$B$25-1),1+Params!$B$129*Params!$B$24,1) | I8: =IF(I$2<=11,Params!$B$111,IF(I$2<=(Params!$B$25-1),Params!$B$111+(Params!$B$116-Params!$B$111)*(I$2-11)/((Params!$B$25-1)-11),Params!$B$116*((1+Params!$B$121)/(1+Params!$B$118))^((I$2-(Params!$B$25-1))/12)))*IF(I$2>(Params!$B$25-1),1+Params!$B$129*Params!$B$24,1) | J8: =IF(J$2<=11,Params!$B$111,IF(J$2<=(Params!$B$25-1),Params!$B$111+(Params!$B$116-Params!$B$111)*(J$2-11)/((Params!$B$25-1)-11),Params!$B$116*((1+Params!$B$121)/(1+Params!$B$118))^((J$2-(Params!$B$25-1))/12)))*IF(J$2>(Params!$B$25-1),1+Params!$B$129*Params!$B$24,1) | ... BV8: =IF(BV$2<=11,Params!$B$111,IF(BV$2<=(Params!$B$25-1),Params!$B$111+(Params!$B$116-Params!$B$111)*(BV$2-11)/((Params!$B$25-1)-11),Params!$B$116*((1+Params!$B$121)/(1+Params!$B$118))^((BV$2-(Params!$B$25-1))/12)))*IF(BV$2>(Params!$B$25-1),1+Params!$B$129*Params!$B$24,1)
A9: rate (local per USD) | B9: INR | C9: =IF(C$2<=11,Params!$B$112,IF(C$2<=(Params!$B$25-1),Params!$B$112+(Params!$B$117-Params!$B$112)*(C$2-11)/((Params!$B$25-1)-11),Params!$B$117*((1+Params!$B$122)/(1+Params!$B$118))^((C$2-(Params!$B$25-1))/12)))*IF(C$2>(Params!$B$25-1),1+Params!$B$129*Params!$B$24,1) | D9: =IF(D$2<=11,Params!$B$112,IF(D$2<=(Params!$B$25-1),Params!$B$112+(Params!$B$117-Params!$B$112)*(D$2-11)/((Params!$B$25-1)-11),Params!$B$117*((1+Params!$B$122)/(1+Params!$B$118))^((D$2-(Params!$B$25-1))/12)))*IF(D$2>(Params!$B$25-1),1+Params!$B$129*Params!$B$24,1) | E9: =IF(E$2<=11,Params!$B$112,IF(E$2<=(Params!$B$25-1),Params!$B$112+(Params!$B$117-Params!$B$112)*(E$2-11)/((Params!$B$25-1)-11),Params!$B$117*((1+Params!$B$122)/(1+Params!$B$118))^((E$2-(Params!$B$25-1))/12)))*IF(E$2>(Params!$B$25-1),1+Params!$B$129*Params!$B$24,1) | F9: =IF(F$2<=11,Params!$B$112,IF(F$2<=(Params!$B$25-1),Params!$B$112+(Params!$B$117-Params!$B$112)*(F$2-11)/((Params!$B$25-1)-11),Params!$B$117*((1+Params!$B$122)/(1+Params!$B$118))^((F$2-(Params!$B$25-1))/12)))*IF(F$2>(Params!$B$25-1),1+Params!$B$129*Params!$B$24,1) | G9: =IF(G$2<=11,Params!$B$112,IF(G$2<=(Params!$B$25-1),Params!$B$112+(Params!$B$117-Params!$B$112)*(G$2-11)/((Params!$B$25-1)-11),Params!$B$117*((1+Params!$B$122)/(1+Params!$B$118))^((G$2-(Params!$B$25-1))/12)))*IF(G$2>(Params!$B$25-1),1+Params!$B$129*Params!$B$24,1) | H9: =IF(H$2<=11,Params!$B$112,IF(H$2<=(Params!$B$25-1),Params!$B$112+(Params!$B$117-Params!$B$112)*(H$2-11)/((Params!$B$25-1)-11),Params!$B$117*((1+Params!$B$122)/(1+Params!$B$118))^((H$2-(Params!$B$25-1))/12)))*IF(H$2>(Params!$B$25-1),1+Params!$B$129*Params!$B$24,1) | I9: =IF(I$2<=11,Params!$B$112,IF(I$2<=(Params!$B$25-1),Params!$B$112+(Params!$B$117-Params!$B$112)*(I$2-11)/((Params!$B$25-1)-11),Params!$B$117*((1+Params!$B$122)/(1+Params!$B$118))^((I$2-(Params!$B$25-1))/12)))*IF(I$2>(Params!$B$25-1),1+Params!$B$129*Params!$B$24,1) | J9: =IF(J$2<=11,Params!$B$112,IF(J$2<=(Params!$B$25-1),Params!$B$112+(Params!$B$117-Params!$B$112)*(J$2-11)/((Params!$B$25-1)-11),Params!$B$117*((1+Params!$B$122)/(1+Params!$B$118))^((J$2-(Params!$B$25-1))/12)))*IF(J$2>(Params!$B$25-1),1+Params!$B$129*Params!$B$24,1) | ... BV9: =IF(BV$2<=11,Params!$B$112,IF(BV$2<=(Params!$B$25-1),Params!$B$112+(Params!$B$117-Params!$B$112)*(BV$2-11)/((Params!$B$25-1)-11),Params!$B$117*((1+Params!$B$122)/(1+Params!$B$118))^((BV$2-(Params!$B$25-1))/12)))*IF(BV$2>(Params!$B$25-1),1+Params!$B$129*Params!$B$24,1)
A11: FX index: USD value of local-currency prices vs FY2025 average (1.0 in FY2025).
A12: FX index | B12: US_CA | C12: =Params!$B$123*Params!$B$108/C5 | D12: =Params!$B$123*Params!$B$108/D5 | E12: =Params!$B$123*Params!$B$108/E5 | F12: =Params!$B$123*Params!$B$108/F5 | G12: =Params!$B$123*Params!$B$108/G5 | H12: =Params!$B$123*Params!$B$108/H5 | I12: =Params!$B$123*Params!$B$108/I5 | J12: =Params!$B$123*Params!$B$108/J5 | ... BV12: =Params!$B$123*Params!$B$108/BV5
A13: FX index | B13: EUROPE | C13: =Params!$B$124*Params!$B$109/C6 | D13: =Params!$B$124*Params!$B$109/D6 | E13: =Params!$B$124*Params!$B$109/E6 | F13: =Params!$B$124*Params!$B$109/F6 | G13: =Params!$B$124*Params!$B$109/G6 | H13: =Params!$B$124*Params!$B$109/H6 | I13: =Params!$B$124*Params!$B$109/I6 | J13: =Params!$B$124*Params!$B$109/J6 | ... BV13: =Params!$B$124*Params!$B$109/BV6
A14: FX index | B14: LATAM | C14: =Params!$B$125*Params!$B$110/C7 | D14: =Params!$B$125*Params!$B$110/D7 | E14: =Params!$B$125*Params!$B$110/E7 | F14: =Params!$B$125*Params!$B$110/F7 | G14: =Params!$B$125*Params!$B$110/G7 | H14: =Params!$B$125*Params!$B$110/H7 | I14: =Params!$B$125*Params!$B$110/I7 | J14: =Params!$B$125*Params!$B$110/J7 | ... BV14: =Params!$B$125*Params!$B$110/BV7
A15: FX index | B15: APAC | C15: =Params!$B$126*Params!$B$111/C8+Params!$B$127*Params!$B$112/C9 | D15: =Params!$B$126*Params!$B$111/D8+Params!$B$127*Params!$B$112/D9 | E15: =Params!$B$126*Params!$B$111/E8+Params!$B$127*Params!$B$112/E9 | F15: =Params!$B$126*Params!$B$111/F8+Params!$B$127*Params!$B$112/F9 | G15: =Params!$B$126*Params!$B$111/G8+Params!$B$127*Params!$B$112/G9 | H15: =Params!$B$126*Params!$B$111/H8+Params!$B$127*Params!$B$112/H9 | I15: =Params!$B$126*Params!$B$111/I8+Params!$B$127*Params!$B$112/I9 | J15: =Params!$B$126*Params!$B$111/J8+Params!$B$127*Params!$B$112/J9 | ... BV15: =Params!$B$126*Params!$B$111/BV8+Params!$B$127*Params!$B$112/BV9
A16: FX index | B16: ROW | C16: =Params!$B$128*Params!$B$108/C5 | D16: =Params!$B$128*Params!$B$108/D5 | E16: =Params!$B$128*Params!$B$108/E5 | F16: =Params!$B$128*Params!$B$108/F5 | G16: =Params!$B$128*Params!$B$108/G5 | H16: =Params!$B$128*Params!$B$108/H5 | I16: =Params!$B$128*Params!$B$108/I5 | J16: =Params!$B$128*Params!$B$108/J5 | ... BV16: =Params!$B$128*Params!$B$108/BV5

Sheet Adds
A1: line | B1: segment | C1: 2025-01 | D1: 2025-02 | E1: 2025-03 | F1: 2025-04 | G1: 2025-05 | H1: 2025-06 | I1: 2025-07 | J1: 2025-08 | K1: 2025-09 | L1: 2025-10 | M1: 2025-11 | N1: 2025-12 | O1: 2026-01 | P1: 2026-02 | Q1: 2026-03 | R1: 2026-04 | S1: 2026-05 | T1: 2026-06 | U1: 2026-07 | V1: 2026-08 | W1: 2026-09 | X1: 2026-10 | Y1: 2026-11 | Z1: 2026-12 | AA1: 2027-01 | AB1: 2027-02 | AC1: 2027-03 | AD1: 2027-04 | AE1: 2027-05 | AF1: 2027-06 | AG1: 2027-07 | AH1: 2027-08 | AI1: 2027-09 | AJ1: 2027-10 | AK1: 2027-11 | AL1: 2027-12 | AM1: 2028-01 | AN1: 2028-02 | AO1: 2028-03 | AP1: 2028-04 | AQ1: 2028-05 | AR1: 2028-06 | AS1: 2028-07 | AT1: 2028-08 | AU1: 2028-09 | AV1: 2028-10 | AW1: 2028-11 | AX1: 2028-12 | AY1: 2029-01 | AZ1: 2029-02 | BA1: 2029-03 | BB1: 2029-04 | BC1: 2029-05 | BD1: 2029-06 | BE1: 2029-07 | BF1: 2029-08 | BG1: 2029-09 | BH1: 2029-10 | BI1: 2029-11 | BJ1: 2029-12 | BK1: 2030-01 | BL1: 2030-02 | BM1: 2030-03 | BN1: 2030-04 | BO1: 2030-05 | BP1: 2030-06 | BQ1: 2030-07 | BR1: 2030-08 | BS1: 2030-09 | BT1: 2030-10 | BU1: 2030-11 | BV1: 2030-12
A2: month index (0 = Jan 2025) | C2: 0 | D2: 1 | E2: 2 | F2: 3 | G2: 4 | H2: 5 | I2: 6 | J2: 7 | K2: 8 | L2: 9 | M2: 10 | N2: 11 | O2: 12 | P2: 13 | Q2: 14 | R2: 15 | S2: 16 | T2: 17 | U2: 18 | V2: 19 | W2: 20 | X2: 21 | Y2: 22 | Z2: 23 | AA2: 24 | AB2: 25 | AC2: 26 | AD2: 27 | AE2: 28 | AF2: 29 | AG2: 30 | AH2: 31 | AI2: 32 | AJ2: 33 | AK2: 34 | AL2: 35 | AM2: 36 | AN2: 37 | AO2: 38 | AP2: 39 | AQ2: 40 | AR2: 41 | AS2: 42 | AT2: 43 | AU2: 44 | AV2: 45 | AW2: 46 | AX2: 47 | AY2: 48 | AZ2: 49 | BA2: 50 | BB2: 51 | BC2: 52 | BD2: 53 | BE2: 54 | BF2: 55 | BG2: 56 | BH2: 57 | BI2: 58 | BJ2: 59 | BK2: 60 | BL2: 61 | BM2: 62 | BN2: 63 | BO2: 64 | BP2: 65 | BQ2: 66 | BR2: 67 | BS2: 68 | BT2: 69 | BU2: 70 | BV2: 71
A3: gross adds | B3: US_CA|NITRO_M | C3: =MAU!C4*Params!$B$57*Eras!C$7*Params!$B$130*Params!$B$92 | D3: =MAU!D4*Params!$B$57*Eras!D$7*Params!$B$130*Params!$B$92 | E3: =MAU!E4*Params!$B$57*Eras!E$7*Params!$B$130*Params!$B$92 | F3: =MAU!F4*Params!$B$57*Eras!F$7*Params!$B$130*Params!$B$92 | G3: =MAU!G4*Params!$B$57*Eras!G$7*Params!$B$130*Params!$B$92 | H3: =MAU!H4*Params!$B$57*Eras!H$7*Params!$B$130*Params!$B$92 | I3: =MAU!I4*Params!$B$57*Eras!I$7*Params!$B$130*Params!$B$92 | J3: =MAU!J4*Params!$B$57*Eras!J$7*Params!$B$130*Params!$B$92 | ... BV3: =MAU!BV4*Params!$B$57*Eras!BV$7*Params!$B$130*Params!$B$92
A4: trial starts | B4: US_CA|NITRO_M | C4: =C3*Eras!C$8 | D4: =D3*Eras!D$8 | E4: =E3*Eras!E$8 | F4: =F3*Eras!F$8 | G4: =G3*Eras!G$8 | H4: =H3*Eras!H$8 | I4: =I3*Eras!I$8 | J4: =J3*Eras!J$8 | ... BV4: =BV3*Eras!BV$8
A5: direct paid starts | B5: US_CA|NITRO_M | C5: =C3-C4 | D5: =D3-D4 | E5: =E3-E4 | F5: =F3-F4 | G5: =G3-G4 | H5: =H3-H4 | I5: =I3-I4 | J5: =J3-J4 | ... BV5: =BV3-BV4
A6: trials ending | B6: US_CA|NITRO_M | C6: =IF(C$2>=Params!$B$6,INDEX($C$4:$BV$4,C$2-Params!$B$6+1),0) | D6: =IF(D$2>=Params!$B$6,INDEX($C$4:$BV$4,D$2-Params!$B$6+1),0) | E6: =IF(E$2>=Params!$B$6,INDEX($C$4:$BV$4,E$2-Params!$B$6+1),0) | F6: =IF(F$2>=Params!$B$6,INDEX($C$4:$BV$4,F$2-Params!$B$6+1),0) | G6: =IF(G$2>=Params!$B$6,INDEX($C$4:$BV$4,G$2-Params!$B$6+1),0) | H6: =IF(H$2>=Params!$B$6,INDEX($C$4:$BV$4,H$2-Params!$B$6+1),0) | I6: =IF(I$2>=Params!$B$6,INDEX($C$4:$BV$4,I$2-Params!$B$6+1),0) | J6: =IF(J$2>=Params!$B$6,INDEX($C$4:$BV$4,J$2-Params!$B$6+1),0) | ... BV6: =IF(BV$2>=Params!$B$6,INDEX($C$4:$BV$4,BV$2-Params!$B$6+1),0)
A7: trial starts x conversion | B7: US_CA|NITRO_M | C7: =C4*Eras!C$9 | D7: =D4*Eras!D$9 | E7: =E4*Eras!E$9 | F7: =F4*Eras!F$9 | G7: =G4*Eras!G$9 | H7: =H4*Eras!H$9 | I7: =I4*Eras!I$9 | J7: =J4*Eras!J$9 | ... BV7: =BV4*Eras!BV$9
A8: trials converted | B8: US_CA|NITRO_M | C8: =IF(C$2>=Params!$B$6,INDEX($C$7:$BV$7,C$2-Params!$B$6+1),0) | D8: =IF(D$2>=Params!$B$6,INDEX($C$7:$BV$7,D$2-Params!$B$6+1),0) | E8: =IF(E$2>=Params!$B$6,INDEX($C$7:$BV$7,E$2-Params!$B$6+1),0) | F8: =IF(F$2>=Params!$B$6,INDEX($C$7:$BV$7,F$2-Params!$B$6+1),0) | G8: =IF(G$2>=Params!$B$6,INDEX($C$7:$BV$7,G$2-Params!$B$6+1),0) | H8: =IF(H$2>=Params!$B$6,INDEX($C$7:$BV$7,H$2-Params!$B$6+1),0) | I8: =IF(I$2>=Params!$B$6,INDEX($C$7:$BV$7,I$2-Params!$B$6+1),0) | J8: =IF(J$2>=Params!$B$6,INDEX($C$7:$BV$7,J$2-Params!$B$6+1),0) | ... BV8: =IF(BV$2>=Params!$B$6,INDEX($C$7:$BV$7,BV$2-Params!$B$6+1),0)
A9: trials lost | B9: US_CA|NITRO_M | C9: =C6-C8 | D9: =D6-D8 | E9: =E6-E8 | F9: =F6-F8 | G9: =G6-G8 | H9: =H6-H8 | I9: =I6-I8 | J9: =J6-J8 | ... BV9: =BV6-BV8
A10: cum trial starts | B10: US_CA|NITRO_M | C10: =SUM($C4:C4) | D10: =SUM($C4:D4) | E10: =SUM($C4:E4) | F10: =SUM($C4:F4) | G10: =SUM($C4:G4) | H10: =SUM($C4:H4) | I10: =SUM($C4:I4) | J10: =SUM($C4:J4) | ... BV10: =SUM($C4:BV4)
A11: cum trials ending | B11: US_CA|NITRO_M | C11: =SUM($C6:C6) | D11: =SUM($C6:D6) | E11: =SUM($C6:E6) | F11: =SUM($C6:F6) | G11: =SUM($C6:G6) | H11: =SUM($C6:H6) | I11: =SUM($C6:I6) | J11: =SUM($C6:J6) | ... BV11: =SUM($C6:BV6)
A12: trials active | B12: US_CA|NITRO_M | C12: =C10-C11 | D12: =D10-D11 | E12: =E10-E11 | F12: =F10-F11 | G12: =G10-G11 | H12: =H10-H11 | I12: =I10-I11 | J12: =J10-J11 | ... BV12: =BV10-BV11
A13: paid starts | B13: US_CA|NITRO_M | C13: =C5+C8 | D13: =D5+D8 | E13: =E5+E8 | F13: =F5+F8 | G13: =G5+G8 | H13: =H5+H8 | I13: =I5+I8 | J13: =J5+J8 | ... BV13: =BV5+BV8
A14: paid starts @0 | B14: US_CA|NITRO_M | C14: =C13*Eras!C$3 | D14: =D13*Eras!D$3 | E14: =E13*Eras!E$3 | F14: =F13*Eras!F$3 | G14: =G13*Eras!G$3 | H14: =H13*Eras!H$3 | I14: =I13*Eras!I$3 | J14: =J13*Eras!J$3 | ... BV14: =BV13*Eras!BV$3
A15: paid starts @1 | B15: US_CA|NITRO_M | C15: =C13*Eras!C$4 | D15: =D13*Eras!D$4 | E15: =E13*Eras!E$4 | F15: =F13*Eras!F$4 | G15: =G13*Eras!G$4 | H15: =H13*Eras!H$4 | I15: =I13*Eras!I$4 | J15: =J13*Eras!J$4 | ... BV15: =BV13*Eras!BV$4
A16: paid starts @2 | B16: US_CA|NITRO_M | C16: =C13*Eras!C$5 | D16: =D13*Eras!D$5 | E16: =E13*Eras!E$5 | F16: =F13*Eras!F$5 | G16: =G13*Eras!G$5 | H16: =H13*Eras!H$5 | I16: =I13*Eras!I$5 | J16: =J13*Eras!J$5 | ... BV16: =BV13*Eras!BV$5
A18: gross adds | B18: US_CA|NITRO_A | C18: =MAU!C4*Params!$B$57*Eras!C$7*Params!$B$130*Params!$B$93 | D18: =MAU!D4*Params!$B$57*Eras!D$7*Params!$B$130*Params!$B$93 | E18: =MAU!E4*Params!$B$57*Eras!E$7*Params!$B$130*Params!$B$93 | F18: =MAU!F4*Params!$B$57*Eras!F$7*Params!$B$130*Params!$B$93 | G18: =MAU!G4*Params!$B$57*Eras!G$7*Params!$B$130*Params!$B$93 | H18: =MAU!H4*Params!$B$57*Eras!H$7*Params!$B$130*Params!$B$93 | I18: =MAU!I4*Params!$B$57*Eras!I$7*Params!$B$130*Params!$B$93 | J18: =MAU!J4*Params!$B$57*Eras!J$7*Params!$B$130*Params!$B$93 | ... BV18: =MAU!BV4*Params!$B$57*Eras!BV$7*Params!$B$130*Params!$B$93
A19: trial starts | B19: US_CA|NITRO_A | C19: =C18*Eras!C$8 | D19: =D18*Eras!D$8 | E19: =E18*Eras!E$8 | F19: =F18*Eras!F$8 | G19: =G18*Eras!G$8 | H19: =H18*Eras!H$8 | I19: =I18*Eras!I$8 | J19: =J18*Eras!J$8 | ... BV19: =BV18*Eras!BV$8
A20: direct paid starts | B20: US_CA|NITRO_A | C20: =C18-C19 | D20: =D18-D19 | E20: =E18-E19 | F20: =F18-F19 | G20: =G18-G19 | H20: =H18-H19 | I20: =I18-I19 | J20: =J18-J19 | ... BV20: =BV18-BV19
A21: trials ending | B21: US_CA|NITRO_A | C21: =IF(C$2>=Params!$B$6,INDEX($C$19:$BV$19,C$2-Params!$B$6+1),0) | D21: =IF(D$2>=Params!$B$6,INDEX($C$19:$BV$19,D$2-Params!$B$6+1),0) | E21: =IF(E$2>=Params!$B$6,INDEX($C$19:$BV$19,E$2-Params!$B$6+1),0) | F21: =IF(F$2>=Params!$B$6,INDEX($C$19:$BV$19,F$2-Params!$B$6+1),0) | G21: =IF(G$2>=Params!$B$6,INDEX($C$19:$BV$19,G$2-Params!$B$6+1),0) | H21: =IF(H$2>=Params!$B$6,INDEX($C$19:$BV$19,H$2-Params!$B$6+1),0) | I21: =IF(I$2>=Params!$B$6,INDEX($C$19:$BV$19,I$2-Params!$B$6+1),0) | J21: =IF(J$2>=Params!$B$6,INDEX($C$19:$BV$19,J$2-Params!$B$6+1),0) | ... BV21: =IF(BV$2>=Params!$B$6,INDEX($C$19:$BV$19,BV$2-Params!$B$6+1),0)
A22: trial starts x conversion | B22: US_CA|NITRO_A | C22: =C19*Eras!C$9 | D22: =D19*Eras!D$9 | E22: =E19*Eras!E$9 | F22: =F19*Eras!F$9 | G22: =G19*Eras!G$9 | H22: =H19*Eras!H$9 | I22: =I19*Eras!I$9 | J22: =J19*Eras!J$9 | ... BV22: =BV19*Eras!BV$9
A23: trials converted | B23: US_CA|NITRO_A | C23: =IF(C$2>=Params!$B$6,INDEX($C$22:$BV$22,C$2-Params!$B$6+1),0) | D23: =IF(D$2>=Params!$B$6,INDEX($C$22:$BV$22,D$2-Params!$B$6+1),0) | E23: =IF(E$2>=Params!$B$6,INDEX($C$22:$BV$22,E$2-Params!$B$6+1),0) | F23: =IF(F$2>=Params!$B$6,INDEX($C$22:$BV$22,F$2-Params!$B$6+1),0) | G23: =IF(G$2>=Params!$B$6,INDEX($C$22:$BV$22,G$2-Params!$B$6+1),0) | H23: =IF(H$2>=Params!$B$6,INDEX($C$22:$BV$22,H$2-Params!$B$6+1),0) | I23: =IF(I$2>=Params!$B$6,INDEX($C$22:$BV$22,I$2-Params!$B$6+1),0) | J23: =IF(J$2>=Params!$B$6,INDEX($C$22:$BV$22,J$2-Params!$B$6+1),0) | ... BV23: =IF(BV$2>=Params!$B$6,INDEX($C$22:$BV$22,BV$2-Params!$B$6+1),0)
A24: trials lost | B24: US_CA|NITRO_A | C24: =C21-C23 | D24: =D21-D23 | E24: =E21-E23 | F24: =F21-F23 | G24: =G21-G23 | H24: =H21-H23 | I24: =I21-I23 | J24: =J21-J23 | ... BV24: =BV21-BV23
A25: cum trial starts | B25: US_CA|NITRO_A | C25: =SUM($C19:C19) | D25: =SUM($C19:D19) | E25: =SUM($C19:E19) | F25: =SUM($C19:F19) | G25: =SUM($C19:G19) | H25: =SUM($C19:H19) | I25: =SUM($C19:I19) | J25: =SUM($C19:J19) | ... BV25: =SUM($C19:BV19)
A26: cum trials ending | B26: US_CA|NITRO_A | C26: =SUM($C21:C21) | D26: =SUM($C21:D21) | E26: =SUM($C21:E21) | F26: =SUM($C21:F21) | G26: =SUM($C21:G21) | H26: =SUM($C21:H21) | I26: =SUM($C21:I21) | J26: =SUM($C21:J21) | ... BV26: =SUM($C21:BV21)
A27: trials active | B27: US_CA|NITRO_A | C27: =C25-C26 | D27: =D25-D26 | E27: =E25-E26 | F27: =F25-F26 | G27: =G25-G26 | H27: =H25-H26 | I27: =I25-I26 | J27: =J25-J26 | ... BV27: =BV25-BV26
A28: paid starts | B28: US_CA|NITRO_A | C28: =C20+C23 | D28: =D20+D23 | E28: =E20+E23 | F28: =F20+F23 | G28: =G20+G23 | H28: =H20+H23 | I28: =I20+I23 | J28: =J20+J23 | ... BV28: =BV20+BV23
A29: paid starts @0 | B29: US_CA|NITRO_A | C29: =C28*Eras!C$3 | D29: =D28*Eras!D$3 | E29: =E28*Eras!E$3 | F29: =F28*Eras!F$3 | G29: =G28*Eras!G$3 | H29: =H28*Eras!H$3 | I29: =I28*Eras!I$3 | J29: =J28*Eras!J$3 | ... BV29: =BV28*Eras!BV$3
A30: paid starts @1 | B30: US_CA|NITRO_A | C30: =C28*Eras!C$4 | D30: =D28*Eras!D$4 | E30: =E28*Eras!E$4 | F30: =F28*Eras!F$4 | G30: =G28*Eras!G$4 | H30: =H28*Eras!H$4 | I30: =I28*Eras!I$4 | J30: =J28*Eras!J$4 | ... BV30: =BV28*Eras!BV$4
A31: paid starts @2 | B31: US_CA|NITRO_A | C31: =C28*Eras!C$5 | D31: =D28*Eras!D$5 | E31: =E28*Eras!E$5 | F31: =F28*Eras!F$5 | G31: =G28*Eras!G$5 | H31: =H28*Eras!H$5 | I31: =I28*Eras!I$5 | J31: =J28*Eras!J$5 | ... BV31: =BV28*Eras!BV$5
A33: gross adds | B33: US_CA|BASIC_M | C33: =MAU!C4*Params!$B$57*Eras!C$7*Params!$B$130*Params!$B$94 | D33: =MAU!D4*Params!$B$57*Eras!D$7*Params!$B$130*Params!$B$94 | E33: =MAU!E4*Params!$B$57*Eras!E$7*Params!$B$130*Params!$B$94 | F33: =MAU!F4*Params!$B$57*Eras!F$7*Params!$B$130*Params!$B$94 | G33: =MAU!G4*Params!$B$57*Eras!G$7*Params!$B$130*Params!$B$94 | H33: =MAU!H4*Params!$B$57*Eras!H$7*Params!$B$130*Params!$B$94 | I33: =MAU!I4*Params!$B$57*Eras!I$7*Params!$B$130*Params!$B$94 | J33: =MAU!J4*Params!$B$57*Eras!J$7*Params!$B$130*Params!$B$94 | ... BV33: =MAU!BV4*Params!$B$57*Eras!BV$7*Params!$B$130*Params!$B$94
A34: trial starts | B34: US_CA|BASIC_M | C34: =C33*Eras!C$8 | D34: =D33*Eras!D$8 | E34: =E33*Eras!E$8 | F34: =F33*Eras!F$8 | G34: =G33*Eras!G$8 | H34: =H33*Eras!H$8 | I34: =I33*Eras!I$8 | J34: =J33*Eras!J$8 | ... BV34: =BV33*Eras!BV$8
A35: direct paid starts | B35: US_CA|BASIC_M | C35: =C33-C34 | D35: =D33-D34 | E35: =E33-E34 | F35: =F33-F34 | G35: =G33-G34 | H35: =H33-H34 | I35: =I33-I34 | J35: =J33-J34 | ... BV35: =BV33-BV34
A36: trials ending | B36: US_CA|BASIC_M | C36: =IF(C$2>=Params!$B$6,INDEX($C$34:$BV$34,C$2-Params!$B$6+1),0) | D36: =IF(D$2>=Params!$B$6,INDEX($C$34:$BV$34,D$2-Params!$B$6+1),0) | E36: =IF(E$2>=Params!$B$6,INDEX($C$34:$BV$34,E$2-Params!$B$6+1),0) | F36: =IF(F$2>=Params!$B$6,INDEX($C$34:$BV$34,F$2-Params!$B$6+1),0) | G36: =IF(G$2>=Params!$B$6,INDEX($C$34:$BV$34,G$2-Params!$B$6+1),0) | H36: =IF(H$2>=Params!$B$6,INDEX($C$34:$BV$34,H$2-Params!$B$6+1),0) | I36: =IF(I$2>=Params!$B$6,INDEX($C$34:$BV$34,I$2-Params!$B$6+1),0) | J36: =IF(J$2>=Params!$B$6,INDEX($C$34:$BV$34,J$2-Params!$B$6+1),0) | ... BV36: =IF(BV$2>=Params!$B$6,INDEX($C$34:$BV$34,BV$2-Params!$B$6+1),0)
A37: trial starts x conversion | B37: US_CA|BASIC_M | C37: =C34*Eras!C$9 | D37: =D34*Eras!D$9 | E37: =E34*Eras!E$9 | F37: =F34*Eras!F$9 | G37: =G34*Eras!G$9 | H37: =H34*Eras!H$9 | I37: =I34*Eras!I$9 | J37: =J34*Eras!J$9 | ... BV37: =BV34*Eras!BV$9
A38: trials converted | B38: US_CA|BASIC_M | C38: =IF(C$2>=Params!$B$6,INDEX($C$37:$BV$37,C$2-Params!$B$6+1),0) | D38: =IF(D$2>=Params!$B$6,INDEX($C$37:$BV$37,D$2-Params!$B$6+1),0) | E38: =IF(E$2>=Params!$B$6,INDEX($C$37:$BV$37,E$2-Params!$B$6+1),0) | F38: =IF(F$2>=Params!$B$6,INDEX($C$37:$BV$37,F$2-Params!$B$6+1),0) | G38: =IF(G$2>=Params!$B$6,INDEX($C$37:$BV$37,G$2-Params!$B$6+1),0) | H38: =IF(H$2>=Params!$B$6,INDEX($C$37:$BV$37,H$2-Params!$B$6+1),0) | I38: =IF(I$2>=Params!$B$6,INDEX($C$37:$BV$37,I$2-Params!$B$6+1),0) | J38: =IF(J$2>=Params!$B$6,INDEX($C$37:$BV$37,J$2-Params!$B$6+1),0) | ... BV38: =IF(BV$2>=Params!$B$6,INDEX($C$37:$BV$37,BV$2-Params!$B$6+1),0)
A39: trials lost | B39: US_CA|BASIC_M | C39: =C36-C38 | D39: =D36-D38 | E39: =E36-E38 | F39: =F36-F38 | G39: =G36-G38 | H39: =H36-H38 | I39: =I36-I38 | J39: =J36-J38 | ... BV39: =BV36-BV38
A40: cum trial starts | B40: US_CA|BASIC_M | C40: =SUM($C34:C34) | D40: =SUM($C34:D34) | E40: =SUM($C34:E34) | F40: =SUM($C34:F34) | G40: =SUM($C34:G34) | H40: =SUM($C34:H34) | I40: =SUM($C34:I34) | J40: =SUM($C34:J34) | ... BV40: =SUM($C34:BV34)
A41: cum trials ending | B41: US_CA|BASIC_M | C41: =SUM($C36:C36) | D41: =SUM($C36:D36) | E41: =SUM($C36:E36) | F41: =SUM($C36:F36) | G41: =SUM($C36:G36) | H41: =SUM($C36:H36) | I41: =SUM($C36:I36) | J41: =SUM($C36:J36) | ... BV41: =SUM($C36:BV36)
A42: trials active | B42: US_CA|BASIC_M | C42: =C40-C41 | D42: =D40-D41 | E42: =E40-E41 | F42: =F40-F41 | G42: =G40-G41 | H42: =H40-H41 | I42: =I40-I41 | J42: =J40-J41 | ... BV42: =BV40-BV41
A43: paid starts | B43: US_CA|BASIC_M | C43: =C35+C38 | D43: =D35+D38 | E43: =E35+E38 | F43: =F35+F38 | G43: =G35+G38 | H43: =H35+H38 | I43: =I35+I38 | J43: =J35+J38 | ... BV43: =BV35+BV38
A44: paid starts @0 | B44: US_CA|BASIC_M | C44: =C43*Eras!C$3 | D44: =D43*Eras!D$3 | E44: =E43*Eras!E$3 | F44: =F43*Eras!F$3 | G44: =G43*Eras!G$3 | H44: =H43*Eras!H$3 | I44: =I43*Eras!I$3 | J44: =J43*Eras!J$3 | ... BV44: =BV43*Eras!BV$3
A45: paid starts @1 | B45: US_CA|BASIC_M | C45: =C43*Eras!C$4 | D45: =D43*Eras!D$4 | E45: =E43*Eras!E$4 | F45: =F43*Eras!F$4 | G45: =G43*Eras!G$4 | H45: =H43*Eras!H$4 | I45: =I43*Eras!I$4 | J45: =J43*Eras!J$4 | ... BV45: =BV43*Eras!BV$4
A46: paid starts @2 | B46: US_CA|BASIC_M | C46: =C43*Eras!C$5 | D46: =D43*Eras!D$5 | E46: =E43*Eras!E$5 | F46: =F43*Eras!F$5 | G46: =G43*Eras!G$5 | H46: =H43*Eras!H$5 | I46: =I43*Eras!I$5 | J46: =J43*Eras!J$5 | ... BV46: =BV43*Eras!BV$5
A48: gross adds | B48: US_CA|BASIC_A | C48: =MAU!C4*Params!$B$57*Eras!C$7*Params!$B$130*Params!$B$95 | D48: =MAU!D4*Params!$B$57*Eras!D$7*Params!$B$130*Params!$B$95 | E48: =MAU!E4*Params!$B$57*Eras!E$7*Params!$B$130*Params!$B$95 | F48: =MAU!F4*Params!$B$57*Eras!F$7*Params!$B$130*Params!$B$95 | G48: =MAU!G4*Params!$B$57*Eras!G$7*Params!$B$130*Params!$B$95 | H48: =MAU!H4*Params!$B$57*Eras!H$7*Params!$B$130*Params!$B$95 | I48: =MAU!I4*Params!$B$57*Eras!I$7*Params!$B$130*Params!$B$95 | J48: =MAU!J4*Params!$B$57*Eras!J$7*Params!$B$130*Params!$B$95 | ... BV48: =MAU!BV4*Params!$B$57*Eras!BV$7*Params!$B$130*Params!$B$95
A49: trial starts | B49: US_CA|BASIC_A | C49: =C48*Eras!C$8 | D49: =D48*Eras!D$8 | E49: =E48*Eras!E$8 | F49: =F48*Eras!F$8 | G49: =G48*Eras!G$8 | H49: =H48*Eras!H$8 | I49: =I48*Eras!I$8 | J49: =J48*Eras!J$8 | ... BV49: =BV48*Eras!BV$8
A50: direct paid starts | B50: US_CA|BASIC_A | C50: =C48-C49 | D50: =D48-D49 | E50: =E48-E49 | F50: =F48-F49 | G50: =G48-G49 | H50: =H48-H49 | I50: =I48-I49 | J50: =J48-J49 | ... BV50: =BV48-BV49
A51: trials ending | B51: US_CA|BASIC_A | C51: =IF(C$2>=Params!$B$6,INDEX($C$49:$BV$49,C$2-Params!$B$6+1),0) | D51: =IF(D$2>=Params!$B$6,INDEX($C$49:$BV$49,D$2-Params!$B$6+1),0) | E51: =IF(E$2>=Params!$B$6,INDEX($C$49:$BV$49,E$2-Params!$B$6+1),0) | F51: =IF(F$2>=Params!$B$6,INDEX($C$49:$BV$49,F$2-Params!$B$6+1),0) | G51: =IF(G$2>=Params!$B$6,INDEX($C$49:$BV$49,G$2-Params!$B$6+1),0) | H51: =IF(H$2>=Params!$B$6,INDEX($C$49:$BV$49,H$2-Params!$B$6+1),0) | I51: =IF(I$2>=Params!$B$6,INDEX($C$49:$BV$49,I$2-Params!$B$6+1),0) | J51: =IF(J$2>=Params!$B$6,INDEX($C$49:$BV$49,J$2-Params!$B$6+1),0) | ... BV51: =IF(BV$2>=Params!$B$6,INDEX($C$49:$BV$49,BV$2-Params!$B$6+1),0)
A52: trial starts x conversion | B52: US_CA|BASIC_A | C52: =C49*Eras!C$9 | D52: =D49*Eras!D$9 | E52: =E49*Eras!E$9 | F52: =F49*Eras!F$9 | G52: =G49*Eras!G$9 | H52: =H49*Eras!H$9 | I52: =I49*Eras!I$9 | J52: =J49*Eras!J$9 | ... BV52: =BV49*Eras!BV$9
A53: trials converted | B53: US_CA|BASIC_A | C53: =IF(C$2>=Params!$B$6,INDEX($C$52:$BV$52,C$2-Params!$B$6+1),0) | D53: =IF(D$2>=Params!$B$6,INDEX($C$52:$BV$52,D$2-Params!$B$6+1),0) | E53: =IF(E$2>=Params!$B$6,INDEX($C$52:$BV$52,E$2-Params!$B$6+1),0) | F53: =IF(F$2>=Params!$B$6,INDEX($C$52:$BV$52,F$2-Params!$B$6+1),0) | G53: =IF(G$2>=Params!$B$6,INDEX($C$52:$BV$52,G$2-Params!$B$6+1),0) | H53: =IF(H$2>=Params!$B$6,INDEX($C$52:$BV$52,H$2-Params!$B$6+1),0) | I53: =IF(I$2>=Params!$B$6,INDEX($C$52:$BV$52,I$2-Params!$B$6+1),0) | J53: =IF(J$2>=Params!$B$6,INDEX($C$52:$BV$52,J$2-Params!$B$6+1),0) | ... BV53: =IF(BV$2>=Params!$B$6,INDEX($C$52:$BV$52,BV$2-Params!$B$6+1),0)
A54: trials lost | B54: US_CA|BASIC_A | C54: =C51-C53 | D54: =D51-D53 | E54: =E51-E53 | F54: =F51-F53 | G54: =G51-G53 | H54: =H51-H53 | I54: =I51-I53 | J54: =J51-J53 | ... BV54: =BV51-BV53
A55: cum trial starts | B55: US_CA|BASIC_A | C55: =SUM($C49:C49) | D55: =SUM($C49:D49) | E55: =SUM($C49:E49) | F55: =SUM($C49:F49) | G55: =SUM($C49:G49) | H55: =SUM($C49:H49) | I55: =SUM($C49:I49) | J55: =SUM($C49:J49) | ... BV55: =SUM($C49:BV49)
A56: cum trials ending | B56: US_CA|BASIC_A | C56: =SUM($C51:C51) | D56: =SUM($C51:D51) | E56: =SUM($C51:E51) | F56: =SUM($C51:F51) | G56: =SUM($C51:G51) | H56: =SUM($C51:H51) | I56: =SUM($C51:I51) | J56: =SUM($C51:J51) | ... BV56: =SUM($C51:BV51)
A57: trials active | B57: US_CA|BASIC_A | C57: =C55-C56 | D57: =D55-D56 | E57: =E55-E56 | F57: =F55-F56 | G57: =G55-G56 | H57: =H55-H56 | I57: =I55-I56 | J57: =J55-J56 | ... BV57: =BV55-BV56
A58: paid starts | B58: US_CA|BASIC_A | C58: =C50+C53 | D58: =D50+D53 | E58: =E50+E53 | F58: =F50+F53 | G58: =G50+G53 | H58: =H50+H53 | I58: =I50+I53 | J58: =J50+J53 | ... BV58: =BV50+BV53
A59: paid starts @0 | B59: US_CA|BASIC_A | C59: =C58*Eras!C$3 | D59: =D58*Eras!D$3 | E59: =E58*Eras!E$3 | F59: =F58*Eras!F$3 | G59: =G58*Eras!G$3 | H59: =H58*Eras!H$3 | I59: =I58*Eras!I$3 | J59: =J58*Eras!J$3 | ... BV59: =BV58*Eras!BV$3
A60: paid starts @1 | B60: US_CA|BASIC_A | C60: =C58*Eras!C$4 | D60: =D58*Eras!D$4 | E60: =E58*Eras!E$4 | F60: =F58*Eras!F$4 | G60: =G58*Eras!G$4 | H60: =H58*Eras!H$4 | I60: =I58*Eras!I$4 | J60: =J58*Eras!J$4 | ... BV60: =BV58*Eras!BV$4
A61: paid starts @2 | B61: US_CA|BASIC_A | C61: =C58*Eras!C$5 | D61: =D58*Eras!D$5 | E61: =E58*Eras!E$5 | F61: =F58*Eras!F$5 | G61: =G58*Eras!G$5 | H61: =H58*Eras!H$5 | I61: =I58*Eras!I$5 | J61: =J58*Eras!J$5 | ... BV61: =BV58*Eras!BV$5
A63: gross adds | B63: EUROPE|NITRO_M | C63: =MAU!C5*Params!$B$58*Eras!C$7*Params!$B$130*Params!$B$92 | D63: =MAU!D5*Params!$B$58*Eras!D$7*Params!$B$130*Params!$B$92 | E63: =MAU!E5*Params!$B$58*Eras!E$7*Params!$B$130*Params!$B$92 | F63: =MAU!F5*Params!$B$58*Eras!F$7*Params!$B$130*Params!$B$92 | G63: =MAU!G5*Params!$B$58*Eras!G$7*Params!$B$130*Params!$B$92 | H63: =MAU!H5*Params!$B$58*Eras!H$7*Params!$B$130*Params!$B$92 | I63: =MAU!I5*Params!$B$58*Eras!I$7*Params!$B$130*Params!$B$92 | J63: =MAU!J5*Params!$B$58*Eras!J$7*Params!$B$130*Params!$B$92 | ... BV63: =MAU!BV5*Params!$B$58*Eras!BV$7*Params!$B$130*Params!$B$92
A64: trial starts | B64: EUROPE|NITRO_M | C64: =C63*Eras!C$8 | D64: =D63*Eras!D$8 | E64: =E63*Eras!E$8 | F64: =F63*Eras!F$8 | G64: =G63*Eras!G$8 | H64: =H63*Eras!H$8 | I64: =I63*Eras!I$8 | J64: =J63*Eras!J$8 | ... BV64: =BV63*Eras!BV$8
A65: direct paid starts | B65: EUROPE|NITRO_M | C65: =C63-C64 | D65: =D63-D64 | E65: =E63-E64 | F65: =F63-F64 | G65: =G63-G64 | H65: =H63-H64 | I65: =I63-I64 | J65: =J63-J64 | ... BV65: =BV63-BV64
A66: trials ending | B66: EUROPE|NITRO_M | C66: =IF(C$2>=Params!$B$6,INDEX($C$64:$BV$64,C$2-Params!$B$6+1),0) | D66: =IF(D$2>=Params!$B$6,INDEX($C$64:$BV$64,D$2-Params!$B$6+1),0) | E66: =IF(E$2>=Params!$B$6,INDEX($C$64:$BV$64,E$2-Params!$B$6+1),0) | F66: =IF(F$2>=Params!$B$6,INDEX($C$64:$BV$64,F$2-Params!$B$6+1),0) | G66: =IF(G$2>=Params!$B$6,INDEX($C$64:$BV$64,G$2-Params!$B$6+1),0) | H66: =IF(H$2>=Params!$B$6,INDEX($C$64:$BV$64,H$2-Params!$B$6+1),0) | I66: =IF(I$2>=Params!$B$6,INDEX($C$64:$BV$64,I$2-Params!$B$6+1),0) | J66: =IF(J$2>=Params!$B$6,INDEX($C$64:$BV$64,J$2-Params!$B$6+1),0) | ... BV66: =IF(BV$2>=Params!$B$6,INDEX($C$64:$BV$64,BV$2-Params!$B$6+1),0)
A67: trial starts x conversion | B67: EUROPE|NITRO_M | C67: =C64*Eras!C$9 | D67: =D64*Eras!D$9 | E67: =E64*Eras!E$9 | F67: =F64*Eras!F$9 | G67: =G64*Eras!G$9 | H67: =H64*Eras!H$9 | I67: =I64*Eras!I$9 | J67: =J64*Eras!J$9 | ... BV67: =BV64*Eras!BV$9
A68: trials converted | B68: EUROPE|NITRO_M | C68: =IF(C$2>=Params!$B$6,INDEX($C$67:$BV$67,C$2-Params!$B$6+1),0) | D68: =IF(D$2>=Params!$B$6,INDEX($C$67:$BV$67,D$2-Params!$B$6+1),0) | E68: =IF(E$2>=Params!$B$6,INDEX($C$67:$BV$67,E$2-Params!$B$6+1),0) | F68: =IF(F$2>=Params!$B$6,INDEX($C$67:$BV$67,F$2-Params!$B$6+1),0) | G68: =IF(G$2>=Params!$B$6,INDEX($C$67:$BV$67,G$2-Params!$B$6+1),0) | H68: =IF(H$2>=Params!$B$6,INDEX($C$67:$BV$67,H$2-Params!$B$6+1),0) | I68: =IF(I$2>=Params!$B$6,INDEX($C$67:$BV$67,I$2-Params!$B$6+1),0) | J68: =IF(J$2>=Params!$B$6,INDEX($C$67:$BV$67,J$2-Params!$B$6+1),0) | ... BV68: =IF(BV$2>=Params!$B$6,INDEX($C$67:$BV$67,BV$2-Params!$B$6+1),0)
A69: trials lost | B69: EUROPE|NITRO_M | C69: =C66-C68 | D69: =D66-D68 | E69: =E66-E68 | F69: =F66-F68 | G69: =G66-G68 | H69: =H66-H68 | I69: =I66-I68 | J69: =J66-J68 | ... BV69: =BV66-BV68
A70: cum trial starts | B70: EUROPE|NITRO_M | C70: =SUM($C64:C64) | D70: =SUM($C64:D64) | E70: =SUM($C64:E64) | F70: =SUM($C64:F64) | G70: =SUM($C64:G64) | H70: =SUM($C64:H64) | I70: =SUM($C64:I64) | J70: =SUM($C64:J64) | ... BV70: =SUM($C64:BV64)
A71: cum trials ending | B71: EUROPE|NITRO_M | C71: =SUM($C66:C66) | D71: =SUM($C66:D66) | E71: =SUM($C66:E66) | F71: =SUM($C66:F66) | G71: =SUM($C66:G66) | H71: =SUM($C66:H66) | I71: =SUM($C66:I66) | J71: =SUM($C66:J66) | ... BV71: =SUM($C66:BV66)
A72: trials active | B72: EUROPE|NITRO_M | C72: =C70-C71 | D72: =D70-D71 | E72: =E70-E71 | F72: =F70-F71 | G72: =G70-G71 | H72: =H70-H71 | I72: =I70-I71 | J72: =J70-J71 | ... BV72: =BV70-BV71
A73: paid starts | B73: EUROPE|NITRO_M | C73: =C65+C68 | D73: =D65+D68 | E73: =E65+E68 | F73: =F65+F68 | G73: =G65+G68 | H73: =H65+H68 | I73: =I65+I68 | J73: =J65+J68 | ... BV73: =BV65+BV68
A74: paid starts @0 | B74: EUROPE|NITRO_M | C74: =C73*Eras!C$3 | D74: =D73*Eras!D$3 | E74: =E73*Eras!E$3 | F74: =F73*Eras!F$3 | G74: =G73*Eras!G$3 | H74: =H73*Eras!H$3 | I74: =I73*Eras!I$3 | J74: =J73*Eras!J$3 | ... BV74: =BV73*Eras!BV$3
A75: paid starts @1 | B75: EUROPE|NITRO_M | C75: =C73*Eras!C$4 | D75: =D73*Eras!D$4 | E75: =E73*Eras!E$4 | F75: =F73*Eras!F$4 | G75: =G73*Eras!G$4 | H75: =H73*Eras!H$4 | I75: =I73*Eras!I$4 | J75: =J73*Eras!J$4 | ... BV75: =BV73*Eras!BV$4
A76: paid starts @2 | B76: EUROPE|NITRO_M | C76: =C73*Eras!C$5 | D76: =D73*Eras!D$5 | E76: =E73*Eras!E$5 | F76: =F73*Eras!F$5 | G76: =G73*Eras!G$5 | H76: =H73*Eras!H$5 | I76: =I73*Eras!I$5 | J76: =J73*Eras!J$5 | ... BV76: =BV73*Eras!BV$5
A78: gross adds | B78: EUROPE|NITRO_A | C78: =MAU!C5*Params!$B$58*Eras!C$7*Params!$B$130*Params!$B$93 | D78: =MAU!D5*Params!$B$58*Eras!D$7*Params!$B$130*Params!$B$93 | E78: =MAU!E5*Params!$B$58*Eras!E$7*Params!$B$130*Params!$B$93 | F78: =MAU!F5*Params!$B$58*Eras!F$7*Params!$B$130*Params!$B$93 | G78: =MAU!G5*Params!$B$58*Eras!G$7*Params!$B$130*Params!$B$93 | H78: =MAU!H5*Params!$B$58*Eras!H$7*Params!$B$130*Params!$B$93 | I78: =MAU!I5*Params!$B$58*Eras!I$7*Params!$B$130*Params!$B$93 | J78: =MAU!J5*Params!$B$58*Eras!J$7*Params!$B$130*Params!$B$93 | ... BV78: =MAU!BV5*Params!$B$58*Eras!BV$7*Params!$B$130*Params!$B$93
A79: trial starts | B79: EUROPE|NITRO_A | C79: =C78*Eras!C$8 | D79: =D78*Eras!D$8 | E79: =E78*Eras!E$8 | F79: =F78*Eras!F$8 | G79: =G78*Eras!G$8 | H79: =H78*Eras!H$8 | I79: =I78*Eras!I$8 | J79: =J78*Eras!J$8 | ... BV79: =BV78*Eras!BV$8
A80: direct paid starts | B80: EUROPE|NITRO_A | C80: =C78-C79 | D80: =D78-D79 | E80: =E78-E79 | F80: =F78-F79 | G80: =G78-G79 | H80: =H78-H79 | I80: =I78-I79 | J80: =J78-J79 | ... BV80: =BV78-BV79
A81: trials ending | B81: EUROPE|NITRO_A | C81: =IF(C$2>=Params!$B$6,INDEX($C$79:$BV$79,C$2-Params!$B$6+1),0) | D81: =IF(D$2>=Params!$B$6,INDEX($C$79:$BV$79,D$2-Params!$B$6+1),0) | E81: =IF(E$2>=Params!$B$6,INDEX($C$79:$BV$79,E$2-Params!$B$6+1),0) | F81: =IF(F$2>=Params!$B$6,INDEX($C$79:$BV$79,F$2-Params!$B$6+1),0) | G81: =IF(G$2>=Params!$B$6,INDEX($C$79:$BV$79,G$2-Params!$B$6+1),0) | H81: =IF(H$2>=Params!$B$6,INDEX($C$79:$BV$79,H$2-Params!$B$6+1),0) | I81: =IF(I$2>=Params!$B$6,INDEX($C$79:$BV$79,I$2-Params!$B$6+1),0) | J81: =IF(J$2>=Params!$B$6,INDEX($C$79:$BV$79,J$2-Params!$B$6+1),0) | ... BV81: =IF(BV$2>=Params!$B$6,INDEX($C$79:$BV$79,BV$2-Params!$B$6+1),0)
A82: trial starts x conversion | B82: EUROPE|NITRO_A | C82: =C79*Eras!C$9 | D82: =D79*Eras!D$9 | E82: =E79*Eras!E$9 | F82: =F79*Eras!F$9 | G82: =G79*Eras!G$9 | H82: =H79*Eras!H$9 | I82: =I79*Eras!I$9 | J82: =J79*Eras!J$9 | ... BV82: =BV79*Eras!BV$9
A83: trials converted | B83: EUROPE|NITRO_A | C83: =IF(C$2>=Params!$B$6,INDEX($C$82:$BV$82,C$2-Params!$B$6+1),0) | D83: =IF(D$2>=Params!$B$6,INDEX($C$82:$BV$82,D$2-Params!$B$6+1),0) | E83: =IF(E$2>=Params!$B$6,INDEX($C$82:$BV$82,E$2-Params!$B$6+1),0) | F83: =IF(F$2>=Params!$B$6,INDEX($C$82:$BV$82,F$2-Params!$B$6+1),0) | G83: =IF(G$2>=Params!$B$6,INDEX($C$82:$BV$82,G$2-Params!$B$6+1),0) | H83: =IF(H$2>=Params!$B$6,INDEX($C$82:$BV$82,H$2-Params!$B$6+1),0) | I83: =IF(I$2>=Params!$B$6,INDEX($C$82:$BV$82,I$2-Params!$B$6+1),0) | J83: =IF(J$2>=Params!$B$6,INDEX($C$82:$BV$82,J$2-Params!$B$6+1),0) | ... BV83: =IF(BV$2>=Params!$B$6,INDEX($C$82:$BV$82,BV$2-Params!$B$6+1),0)
A84: trials lost | B84: EUROPE|NITRO_A | C84: =C81-C83 | D84: =D81-D83 | E84: =E81-E83 | F84: =F81-F83 | G84: =G81-G83 | H84: =H81-H83 | I84: =I81-I83 | J84: =J81-J83 | ... BV84: =BV81-BV83
A85: cum trial starts | B85: EUROPE|NITRO_A | C85: =SUM($C79:C79) | D85: =SUM($C79:D79) | E85: =SUM($C79:E79) | F85: =SUM($C79:F79) | G85: =SUM($C79:G79) | H85: =SUM($C79:H79) | I85: =SUM($C79:I79) | J85: =SUM($C79:J79) | ... BV85: =SUM($C79:BV79)
A86: cum trials ending | B86: EUROPE|NITRO_A | C86: =SUM($C81:C81) | D86: =SUM($C81:D81) | E86: =SUM($C81:E81) | F86: =SUM($C81:F81) | G86: =SUM($C81:G81) | H86: =SUM($C81:H81) | I86: =SUM($C81:I81) | J86: =SUM($C81:J81) | ... BV86: =SUM($C81:BV81)
A87: trials active | B87: EUROPE|NITRO_A | C87: =C85-C86 | D87: =D85-D86 | E87: =E85-E86 | F87: =F85-F86 | G87: =G85-G86 | H87: =H85-H86 | I87: =I85-I86 | J87: =J85-J86 | ... BV87: =BV85-BV86
A88: paid starts | B88: EUROPE|NITRO_A | C88: =C80+C83 | D88: =D80+D83 | E88: =E80+E83 | F88: =F80+F83 | G88: =G80+G83 | H88: =H80+H83 | I88: =I80+I83 | J88: =J80+J83 | ... BV88: =BV80+BV83
A89: paid starts @0 | B89: EUROPE|NITRO_A | C89: =C88*Eras!C$3 | D89: =D88*Eras!D$3 | E89: =E88*Eras!E$3 | F89: =F88*Eras!F$3 | G89: =G88*Eras!G$3 | H89: =H88*Eras!H$3 | I89: =I88*Eras!I$3 | J89: =J88*Eras!J$3 | ... BV89: =BV88*Eras!BV$3
A90: paid starts @1 | B90: EUROPE|NITRO_A | C90: =C88*Eras!C$4 | D90: =D88*Eras!D$4 | E90: =E88*Eras!E$4 | F90: =F88*Eras!F$4 | G90: =G88*Eras!G$4 | H90: =H88*Eras!H$4 | I90: =I88*Eras!I$4 | J90: =J88*Eras!J$4 | ... BV90: =BV88*Eras!BV$4
A91: paid starts @2 | B91: EUROPE|NITRO_A | C91: =C88*Eras!C$5 | D91: =D88*Eras!D$5 | E91: =E88*Eras!E$5 | F91: =F88*Eras!F$5 | G91: =G88*Eras!G$5 | H91: =H88*Eras!H$5 | I91: =I88*Eras!I$5 | J91: =J88*Eras!J$5 | ... BV91: =BV88*Eras!BV$5
A93: gross adds | B93: EUROPE|BASIC_M | C93: =MAU!C5*Params!$B$58*Eras!C$7*Params!$B$130*Params!$B$94 | D93: =MAU!D5*Params!$B$58*Eras!D$7*Params!$B$130*Params!$B$94 | E93: =MAU!E5*Params!$B$58*Eras!E$7*Params!$B$130*Params!$B$94 | F93: =MAU!F5*Params!$B$58*Eras!F$7*Params!$B$130*Params!$B$94 | G93: =MAU!G5*Params!$B$58*Eras!G$7*Params!$B$130*Params!$B$94 | H93: =MAU!H5*Params!$B$58*Eras!H$7*Params!$B$130*Params!$B$94 | I93: =MAU!I5*Params!$B$58*Eras!I$7*Params!$B$130*Params!$B$94 | J93: =MAU!J5*Params!$B$58*Eras!J$7*Params!$B$130*Params!$B$94 | ... BV93: =MAU!BV5*Params!$B$58*Eras!BV$7*Params!$B$130*Params!$B$94
A94: trial starts | B94: EUROPE|BASIC_M | C94: =C93*Eras!C$8 | D94: =D93*Eras!D$8 | E94: =E93*Eras!E$8 | F94: =F93*Eras!F$8 | G94: =G93*Eras!G$8 | H94: =H93*Eras!H$8 | I94: =I93*Eras!I$8 | J94: =J93*Eras!J$8 | ... BV94: =BV93*Eras!BV$8
A95: direct paid starts | B95: EUROPE|BASIC_M | C95: =C93-C94 | D95: =D93-D94 | E95: =E93-E94 | F95: =F93-F94 | G95: =G93-G94 | H95: =H93-H94 | I95: =I93-I94 | J95: =J93-J94 | ... BV95: =BV93-BV94
A96: trials ending | B96: EUROPE|BASIC_M | C96: =IF(C$2>=Params!$B$6,INDEX($C$94:$BV$94,C$2-Params!$B$6+1),0) | D96: =IF(D$2>=Params!$B$6,INDEX($C$94:$BV$94,D$2-Params!$B$6+1),0) | E96: =IF(E$2>=Params!$B$6,INDEX($C$94:$BV$94,E$2-Params!$B$6+1),0) | F96: =IF(F$2>=Params!$B$6,INDEX($C$94:$BV$94,F$2-Params!$B$6+1),0) | G96: =IF(G$2>=Params!$B$6,INDEX($C$94:$BV$94,G$2-Params!$B$6+1),0) | H96: =IF(H$2>=Params!$B$6,INDEX($C$94:$BV$94,H$2-Params!$B$6+1),0) | I96: =IF(I$2>=Params!$B$6,INDEX($C$94:$BV$94,I$2-Params!$B$6+1),0) | J96: =IF(J$2>=Params!$B$6,INDEX($C$94:$BV$94,J$2-Params!$B$6+1),0) | ... BV96: =IF(BV$2>=Params!$B$6,INDEX($C$94:$BV$94,BV$2-Params!$B$6+1),0)
A97: trial starts x conversion | B97: EUROPE|BASIC_M | C97: =C94*Eras!C$9 | D97: =D94*Eras!D$9 | E97: =E94*Eras!E$9 | F97: =F94*Eras!F$9 | G97: =G94*Eras!G$9 | H97: =H94*Eras!H$9 | I97: =I94*Eras!I$9 | J97: =J94*Eras!J$9 | ... BV97: =BV94*Eras!BV$9
A98: trials converted | B98: EUROPE|BASIC_M | C98: =IF(C$2>=Params!$B$6,INDEX($C$97:$BV$97,C$2-Params!$B$6+1),0) | D98: =IF(D$2>=Params!$B$6,INDEX($C$97:$BV$97,D$2-Params!$B$6+1),0) | E98: =IF(E$2>=Params!$B$6,INDEX($C$97:$BV$97,E$2-Params!$B$6+1),0) | F98: =IF(F$2>=Params!$B$6,INDEX($C$97:$BV$97,F$2-Params!$B$6+1),0) | G98: =IF(G$2>=Params!$B$6,INDEX($C$97:$BV$97,G$2-Params!$B$6+1),0) | H98: =IF(H$2>=Params!$B$6,INDEX($C$97:$BV$97,H$2-Params!$B$6+1),0) | I98: =IF(I$2>=Params!$B$6,INDEX($C$97:$BV$97,I$2-Params!$B$6+1),0) | J98: =IF(J$2>=Params!$B$6,INDEX($C$97:$BV$97,J$2-Params!$B$6+1),0) | ... BV98: =IF(BV$2>=Params!$B$6,INDEX($C$97:$BV$97,BV$2-Params!$B$6+1),0)
A99: trials lost | B99: EUROPE|BASIC_M | C99: =C96-C98 | D99: =D96-D98 | E99: =E96-E98 | F99: =F96-F98 | G99: =G96-G98 | H99: =H96-H98 | I99: =I96-I98 | J99: =J96-J98 | ... BV99: =BV96-BV98
A100: cum trial starts | B100: EUROPE|BASIC_M | C100: =SUM($C94:C94) | D100: =SUM($C94:D94) | E100: =SUM($C94:E94) | F100: =SUM($C94:F94) | G100: =SUM($C94:G94) | H100: =SUM($C94:H94) | I100: =SUM($C94:I94) | J100: =SUM($C94:J94) | ... BV100: =SUM($C94:BV94)
A101: cum trials ending | B101: EUROPE|BASIC_M | C101: =SUM($C96:C96) | D101: =SUM($C96:D96) | E101: =SUM($C96:E96) | F101: =SUM($C96:F96) | G101: =SUM($C96:G96) | H101: =SUM($C96:H96) | I101: =SUM($C96:I96) | J101: =SUM($C96:J96) | ... BV101: =SUM($C96:BV96)
A102: trials active | B102: EUROPE|BASIC_M | C102: =C100-C101 | D102: =D100-D101 | E102: =E100-E101 | F102: =F100-F101 | G102: =G100-G101 | H102: =H100-H101 | I102: =I100-I101 | J102: =J100-J101 | ... BV102: =BV100-BV101
A103: paid starts | B103: EUROPE|BASIC_M | C103: =C95+C98 | D103: =D95+D98 | E103: =E95+E98 | F103: =F95+F98 | G103: =G95+G98 | H103: =H95+H98 | I103: =I95+I98 | J103: =J95+J98 | ... BV103: =BV95+BV98
A104: paid starts @0 | B104: EUROPE|BASIC_M | C104: =C103*Eras!C$3 | D104: =D103*Eras!D$3 | E104: =E103*Eras!E$3 | F104: =F103*Eras!F$3 | G104: =G103*Eras!G$3 | H104: =H103*Eras!H$3 | I104: =I103*Eras!I$3 | J104: =J103*Eras!J$3 | ... BV104: =BV103*Eras!BV$3
A105: paid starts @1 | B105: EUROPE|BASIC_M | C105: =C103*Eras!C$4 | D105: =D103*Eras!D$4 | E105: =E103*Eras!E$4 | F105: =F103*Eras!F$4 | G105: =G103*Eras!G$4 | H105: =H103*Eras!H$4 | I105: =I103*Eras!I$4 | J105: =J103*Eras!J$4 | ... BV105: =BV103*Eras!BV$4
A106: paid starts @2 | B106: EUROPE|BASIC_M | C106: =C103*Eras!C$5 | D106: =D103*Eras!D$5 | E106: =E103*Eras!E$5 | F106: =F103*Eras!F$5 | G106: =G103*Eras!G$5 | H106: =H103*Eras!H$5 | I106: =I103*Eras!I$5 | J106: =J103*Eras!J$5 | ... BV106: =BV103*Eras!BV$5
...

Sheet Paid
A1: line | B1: segment | C1: 2025-01 | D1: 2025-02 | E1: 2025-03 | F1: 2025-04 | G1: 2025-05 | H1: 2025-06 | I1: 2025-07 | J1: 2025-08 | K1: 2025-09 | L1: 2025-10 | M1: 2025-11 | N1: 2025-12 | O1: 2026-01 | P1: 2026-02 | Q1: 2026-03 | R1: 2026-04 | S1: 2026-05 | T1: 2026-06 | U1: 2026-07 | V1: 2026-08 | W1: 2026-09 | X1: 2026-10 | Y1: 2026-11 | Z1: 2026-12 | AA1: 2027-01 | AB1: 2027-02 | AC1: 2027-03 | AD1: 2027-04 | AE1: 2027-05 | AF1: 2027-06 | AG1: 2027-07 | AH1: 2027-08 | AI1: 2027-09 | AJ1: 2027-10 | AK1: 2027-11 | AL1: 2027-12 | AM1: 2028-01 | AN1: 2028-02 | AO1: 2028-03 | AP1: 2028-04 | AQ1: 2028-05 | AR1: 2028-06 | AS1: 2028-07 | AT1: 2028-08 | AU1: 2028-09 | AV1: 2028-10 | AW1: 2028-11 | AX1: 2028-12 | AY1: 2029-01 | AZ1: 2029-02 | BA1: 2029-03 | BB1: 2029-04 | BC1: 2029-05 | BD1: 2029-06 | BE1: 2029-07 | BF1: 2029-08 | BG1: 2029-09 | BH1: 2029-10 | BI1: 2029-11 | BJ1: 2029-12 | BK1: 2030-01 | BL1: 2030-02 | BM1: 2030-03 | BN1: 2030-04 | BO1: 2030-05 | BP1: 2030-06 | BQ1: 2030-07 | BR1: 2030-08 | BS1: 2030-09 | BT1: 2030-10 | BU1: 2030-11 | BV1: 2030-12
A2: month index (0 = Jan 2025) | C2: 0 | D2: 1 | E2: 2 | F2: 3 | G2: 4 | H2: 5 | I2: 6 | J2: 7 | K2: 8 | L2: 9 | M2: 10 | N2: 11 | O2: 12 | P2: 13 | Q2: 14 | R2: 15 | S2: 16 | T2: 17 | U2: 18 | V2: 19 | W2: 20 | X2: 21 | Y2: 22 | Z2: 23 | AA2: 24 | AB2: 25 | AC2: 26 | AD2: 27 | AE2: 28 | AF2: 29 | AG2: 30 | AH2: 31 | AI2: 32 | AJ2: 33 | AK2: 34 | AL2: 35 | AM2: 36 | AN2: 37 | AO2: 38 | AP2: 39 | AQ2: 40 | AR2: 41 | AS2: 42 | AT2: 43 | AU2: 44 | AV2: 45 | AW2: 46 | AX2: 47 | AY2: 48 | AZ2: 49 | BA2: 50 | BB2: 51 | BC2: 52 | BD2: 53 | BE2: 54 | BF2: 55 | BG2: 56 | BH2: 57 | BI2: 58 | BJ2: 59 | BK2: 60 | BL2: 61 | BM2: 62 | BN2: 63 | BO2: 64 | BP2: 65 | BQ2: 66 | BR2: 67 | BS2: 68 | BT2: 69 | BU2: 70 | BV2: 71
A3: active | B3: US_CA|NITRO_M | C3: =Adds!$C$14*Curves!$BV$15+Adds!$C$15*Curves!$BV$38+Adds!$C$16*Curves!$BV$61 | D3: =SUMPRODUCT(Adds!$C$14:$D$14,Curves!$BU$15:$BV$15)+SUMPRODUCT(Adds!$C$15:$D$15,Curves!$BU$38:$BV$38)+SUMPRODUCT(Adds!$C$16:$D$16,Curves!$BU$61:$BV$61) | E3: =SUMPRODUCT(Adds!$C$14:$E$14,Curves!$BT$15:$BV$15)+SUMPRODUCT(Adds!$C$15:$E$15,Curves!$BT$38:$BV$38)+SUMPRODUCT(Adds!$C$16:$E$16,Curves!$BT$61:$BV$61) | F3: =SUMPRODUCT(Adds!$C$14:$F$14,Curves!$BS$15:$BV$15)+SUMPRODUCT(Adds!$C$15:$F$15,Curves!$BS$38:$BV$38)+SUMPRODUCT(Adds!$C$16:$F$16,Curves!$BS$61:$BV$61) | G3: =SUMPRODUCT(Adds!$C$14:$G$14,Curves!$BR$15:$BV$15)+SUMPRODUCT(Adds!$C$15:$G$15,Curves!$BR$38:$BV$38)+SUMPRODUCT(Adds!$C$16:$G$16,Curves!$BR$61:$BV$61) | H3: =SUMPRODUCT(Adds!$C$14:$H$14,Curves!$BQ$15:$BV$15)+SUMPRODUCT(Adds!$C$15:$H$15,Curves!$BQ$38:$BV$38)+SUMPRODUCT(Adds!$C$16:$H$16,Curves!$BQ$61:$BV$61) | I3: =SUMPRODUCT(Adds!$C$14:$I$14,Curves!$BP$15:$BV$15)+SUMPRODUCT(Adds!$C$15:$I$15,Curves!$BP$38:$BV$38)+SUMPRODUCT(Adds!$C$16:$I$16,Curves!$BP$61:$BV$61) | J3: =SUMPRODUCT(Adds!$C$14:$J$14,Curves!$BO$15:$BV$15)+SUMPRODUCT(Adds!$C$15:$J$15,Curves!$BO$38:$BV$38)+SUMPRODUCT(Adds!$C$16:$J$16,Curves!$BO$61:$BV$61) | K3: =SUMPRODUCT(Adds!$C$14:$K$14,Curves!$BN$15:$BV$15)+SUMPRODUCT(Adds!$C$15:$K$15,Curves!$BN$38:$BV$38)+SUMPRODUCT(Adds!$C$16:$K$16,Curves!$BN$61:$BV$61) | L3: =SUMPRODUCT(Adds!$C$14:$L$14,Curves!$BM$15:$BV$15)+SUMPRODUCT(Adds!$C$15:$L$15,Curves!$BM$38:$BV$38)+SUMPRODUCT(Adds!$C$16:$L$16,Curves!$BM$61:$BV$61) | M3: =SUMPRODUCT(Adds!$C$14:$M$14,Curves!$BL$15:$BV$15)+SUMPRODUCT(Adds!$C$15:$M$15,Curves!$BL$38:$BV$38)+SUMPRODUCT(Adds!$C$16:$M$16,Curves!$BL$61:$BV$61) | N3: =SUMPRODUCT(Adds!$C$14:$N$14,Curves!$BK$15:$BV$15)+SUMPRODUCT(Adds!$C$15:$N$15,Curves!$BK$38:$BV$38)+SUMPRODUCT(Adds!$C$16:$N$16,Curves!$BK$61:$BV$61) | O3: =SUMPRODUCT(Adds!$C$14:$O$14,Curves!$BJ$15:$BV$15)+SUMPRODUCT(Adds!$C$15:$O$15,Curves!$BJ$38:$BV$38)+SUMPRODUCT(Adds!$C$16:$O$16,Curves!$BJ$61:$BV$61) | P3: =SUMPRODUCT(Adds!$C$14:$P$14,Curves!$BI$15:$BV$15)+SUMPRODUCT(Adds!$C$15:$P$15,Curves!$BI$38:$BV$38)+SUMPRODUCT(Adds!$C$16:$P$16,Curves!$BI$61:$BV$61) | Q3: =SUMPRODUCT(Adds!$C$14:$Q$14,Curves!$BH$15:$BV$15)+SUMPRODUCT(Adds!$C$15:$Q$15,Curves!$BH$38:$BV$38)+SUMPRODUCT(Adds!$C$16:$Q$16,Curves!$BH$61:$BV$61) | R3: =SUMPRODUCT(Adds!$C$14:$R$14,Curves!$BG$15:$BV$15)+SUMPRODUCT(Adds!$C$15:$R$15,Curves!$BG$38:$BV$38)+SUMPRODUCT(Adds!$C$16:$R$16,Curves!$BG$61:$BV$61) | S3: =SUMPRODUCT(Adds!$C$14:$S$14,Curves!$BF$15:$BV$15)+SUMPRODUCT(Adds!$C$15:$S$15,Curves!$BF$38:$BV$38)+SUMPRODUCT(Adds!$C$16:$S$16,Curves!$BF$61:$BV$61) | T3: =SUMPRODUCT(Adds!$C$14:$T$14,Curves!$BE$15:$BV$15)+SUMPRODUCT(Adds!$C$15:$T$15,Curves!$BE$38:$BV$38)+SUMPRODUCT(Adds!$C$16:$T$16,Curves!$BE$61:$BV$61) | U3: =SUMPRODUCT(Adds!$C$14:$U$14,Curves!$BD$15:$BV$15)+SUMPRODUCT(Adds!$C$15:$U$15,Curves!$BD$38:$BV$38)+SUMPRODUCT(Adds!$C$16:$U$16,Curves!$BD$61:$BV$61) | V3: =SUMPRODUCT(Adds!$C$14:$V$14,Curves!$BC$15:$BV$15)+SUMPRODUCT(Adds!$C$15:$V$15,Curves!$BC$38:$BV$38)+SUMPRODUCT(Adds!$C$16:$V$16,Curves!$BC$61:$BV$61) | W3: =SUMPRODUCT(Adds!$C$14:$W$14,Curves!$BB$15:$BV$15)+SUMPRODUCT(Adds!$C$15:$W$15,Curves!$BB$38:$BV$38)+SUMPRODUCT(Adds!$C$16:$W$16,Curves!$BB$61:$BV$61) | X3: =SUMPRODUCT(Adds!$C$14:$X$14,Curves!$BA$15:$BV$15)+SUMPRODUCT(Adds!$C$15:$X$15,Curves!$BA$38:$BV$38)+SUMPRODUCT(Adds!$C$16:$X$16,Curves!$BA$61:$BV$61) | Y3: =SUMPRODUCT(Adds!$C$14:$Y$14,Curves!$AZ$15:$BV$15)+SUMPRODUCT(Adds!$C$15:$Y$15,Curves!$AZ$38:$BV$38)+SUMPRODUCT(Adds!$C$16:$Y$16,Curves!$AZ$61:$BV$61) | Z3: =SUMPRODUCT(Adds!$C$14:$Z$14,Curves!$AY$15:$BV$15)+SUMPRODUCT(Adds!$C$15:$Z$15,Curves!$AY$38:$BV$38)+SUMPRODUCT(Adds!$C$16:$Z$16,Curves!$AY$61:$BV$61) | AA3: =SUMPRODUCT(Adds!$C$14:$AA$14,Curves!$AX$15:$BV$15)+SUMPRODUCT(Adds!$C$15:$AA$15,Curves!$AX$38:$BV$38)+SUMPRODUCT(Adds!$C$16:$AA$16,Curves!$AX$61:$BV$61) | AB3: =SUMPRODUCT(Adds!$C$14:$AB$14,Curves!$AW$15:$BV$15)+SUMPRODUCT(Adds!$C$15:$AB$15,Curves!$AW$38:$BV$38)+SUMPRODUCT(Adds!$C$16:$AB$16,Curves!$AW$61:$BV$61) | AC3: =SUMPRODUCT(Adds!$C$14:$AC$14,Curves!$AV$15:$BV$15)+SUMPRODUCT(Adds!$C$15:$AC$15,Curves!$AV$38:$BV$38)+SUMPRODUCT(Adds!$C$16:$AC$16,Curves!$AV$61:$BV$61) | AD3: =SUMPRODUCT(Adds!$C$14:$AD$14,Curves!$AU$15:$BV$15)+SUMPRODUCT(Adds!$C$15:$AD$15,Curves!$AU$38:$BV$38)+SUMPRODUCT(Adds!$C$16:$AD$16,Curves!$AU$61:$BV$61) | AE3: =SUMPRODUCT(Adds!$C$14:$AE$14,Curves!$AT$15:$BV$15)+SUMPRODUCT(Adds!$C$15:$AE$15,Curves!$AT$38:$BV$38)+SUMPRODUCT(Adds!$C$16:$AE$16,Curves!$AT$61:$BV$61) | AF3: =SUMPRODUCT(Adds!$C$14:$AF$14,Curves!$AS$15:$BV$15)+SUMPRODUCT(Adds!$C$15:$AF$15,Curves!$AS$38:$BV$38)+SUMPRODUCT(Adds!$C$16:$AF$16,Curves!$AS$61:$BV$61) | AG3: =SUMPRODUCT(Adds!$C$14:$AG$14,Curves!$AR$15:$BV$15)+SUMPRODUCT(Adds!$C$15:$AG$15,Curves!$AR$38:$BV$38)+SUMPRODUCT(Adds!$C$16:$AG$16,Curves!$AR$61:$BV$61) | AH3: =SUMPRODUCT(Adds!$C$14:$AH$14,Curves!$AQ$15:$BV$15)+SUMPRODUCT(Adds!$C$15:$AH$15,Curves!$AQ$38:$BV$38)+SUMPRODUCT(Adds!$C$16:$AH$16,Curves!$AQ$61:$BV$61) | AI3: =SUMPRODUCT(Adds!$C$14:$AI$14,Curves!$AP$15:$BV$15)+SUMPRODUCT(Adds!$C$15:$AI$15,Curves!$AP$38:$BV$38)+SUMPRODUCT(Adds!$C$16:$AI$16,Curves!$AP$61:$BV$61) | AJ3: =SUMPRODUCT(Adds!$C$14:$AJ$14,Curves!$AO$15:$BV$15)+SUMPRODUCT(Adds!$C$15:$AJ$15,Curves!$AO$38:$BV$38)+SUMPRODUCT(Adds!$C$16:$AJ$16,Curves!$AO$61:$BV$61) | AK3: =SUMPRODUCT(Adds!$C$14:$AK$14,Curves!$AN$15:$BV$15)+SUMPRODUCT(Adds!$C$15:$AK$15,Curves!$AN$38:$BV$38)+SUMPRODUCT(Adds!$C$16:$AK$16,Curves!$AN$61:$BV$61) | AL3: =SUMPRODUCT(Adds!$C$14:$AL$14,Curves!$AM$15:$BV$15)+SUMPRODUCT(Adds!$C$15:$AL$15,Curves!$AM$38:$BV$38)+SUMPRODUCT(Adds!$C$16:$AL$16,Curves!$AM$61:$BV$61) | AM3: =SUMPRODUCT(Adds!$C$14:$AM$14,Curves!$AL$15:$BV$15)+SUMPRODUCT(Adds!$C$15:$AM$15,Curves!$AL$38:$BV$38)+SUMPRODUCT(Adds!$C$16:$AM$16,Curves!$AL$61:$BV$61) | AN3: =SUMPRODUCT(Adds!$C$14:$AN$14,Curves!$AK$15:$BV$15)+SUMPRODUCT(Adds!$C$15:$AN$15,Curves!$AK$38:$BV$38)+SUMPRODUCT(Adds!$C$16:$AN$16,Curves!$AK$61:$BV$61) | AO3: =SUMPRODUCT(Adds!$C$14:$AO$14,Curves!$AJ$15:$BV$15)+SUMPRODUCT(Adds!$C$15:$AO$15,Curves!$AJ$38:$BV$38)+SUMPRODUCT(Adds!$C$16:$AO$16,Curves!$AJ$61:$BV$61) | AP3: =SUMPRODUCT(Adds!$C$14:$AP$14,Curves!$AI$15:$BV$15)+SUMPRODUCT(Adds!$C$15:$AP$15,Curves!$AI$38:$BV$38)+SUMPRODUCT(Adds!$C$16:$AP$16,Curves!$AI$61:$BV$61) | AQ3: =SUMPRODUCT(Adds!$C$14:$AQ$14,Curves!$AH$15:$BV$15)+SUMPRODUCT(Adds!$C$15:$AQ$15,Curves!$AH$38:$BV$38)+SUMPRODUCT(Adds!$C$16:$AQ$16,Curves!$AH$61:$BV$61) | AR3: =SUMPRODUCT(Adds!$C$14:$AR$14,Curves!$AG$15:$BV$15)+SUMPRODUCT(Adds!$C$15:$AR$15,Curves!$AG$38:$BV$38)+SUMPRODUCT(Adds!$C$16:$AR$16,Curves!$AG$61:$BV$61) | AS3: =SUMPRODUCT(Adds!$C$14:$AS$14,Curves!$AF$15:$BV$15)+SUMPRODUCT(Adds!$C$15:$AS$15,Curves!$AF$38:$BV$38)+SUMPRODUCT(Adds!$C$16:$AS$16,Curves!$AF$61:$BV$61) | AT3: =SUMPRODUCT(Adds!$C$14:$AT$14,Curves!$AE$15:$BV$15)+SUMPRODUCT(Adds!$C$15:$AT$15,Curves!$AE$38:$BV$38)+SUMPRODUCT(Adds!$C$16:$AT$16,Curves!$AE$61:$BV$61) | AU3: =SUMPRODUCT(Adds!$C$14:$AU$14,Curves!$AD$15:$BV$15)+SUMPRODUCT(Adds!$C$15:$AU$15,Curves!$AD$38:$BV$38)+SUMPRODUCT(Adds!$C$16:$AU$16,Curves!$AD$61:$BV$61) | AV3: =SUMPRODUCT(Adds!$C$14:$AV$14,Curves!$AC$15:$BV$15)+SUMPRODUCT(Adds!$C$15:$AV$15,Curves!$AC$38:$BV$38)+SUMPRODUCT(Adds!$C$16:$AV$16,Curves!$AC$61:$BV$61) | AW3: =SUMPRODUCT(Adds!$C$14:$AW$14,Curves!$AB$15:$BV$15)+SUMPRODUCT(Adds!$C$15:$AW$15,Curves!$AB$38:$BV$38)+SUMPRODUCT(Adds!$C$16:$AW$16,Curves!$AB$61:$BV$61) | AX3: =SUMPRODUCT(Adds!$C$14:$AX$14,Curves!$AA$15:$BV$15)+SUMPRODUCT(Adds!$C$15:$AX$15,Curves!$AA$38:$BV$38)+SUMPRODUCT(Adds!$C$16:$AX$16,Curves!$AA$61:$BV$61) | AY3: =SUMPRODUCT(Adds!$C$14:$AY$14,Curves!$Z$15:$BV$15)+SUMPRODUCT(Adds!$C$15:$AY$15,Curves!$Z$38:$BV$38)+SUMPRODUCT(Adds!$C$16:$AY$16,Curves!$Z$61:$BV$61) | AZ3: =SUMPRODUCT(Adds!$C$14:$AZ$14,Curves!$Y$15:$BV$15)+SUMPRODUCT(Adds!$C$15:$AZ$15,Curves!$Y$38:$BV$38)+SUMPRODUCT(Adds!$C$16:$AZ$16,Curves!$Y$61:$BV$61) | BA3: =SUMPRODUCT(Adds!$C$14:$BA$14,Curves!$X$15:$BV$15)+SUMPRODUCT(Adds!$C$15:$BA$15,Curves!$X$38:$BV$38)+SUMPRODUCT(Adds!$C$16:$BA$16,Curves!$X$61:$BV$61) | BB3: =SUMPRODUCT(Adds!$C$14:$BB$14,Curves!$W$15:$BV$15)+SUMPRODUCT(Adds!$C$15:$BB$15,Curves!$W$38:$BV$38)+SUMPRODUCT(Adds!$C$16:$BB$16,Curves!$W$61:$BV$61) | BC3: =SUMPRODUCT(Adds!$C$14:$BC$14,Curves!$V$15:$BV$15)+SUMPRODUCT(Adds!$C$15:$BC$15,Curves!$V$38:$BV$38)+SUMPRODUCT(Adds!$C$16:$BC$16,Curves!$V$61:$BV$61) | BD3: =SUMPRODUCT(Adds!$C$14:$BD$14,Curves!$U$15:$BV$15)+SUMPRODUCT(Adds!$C$15:$BD$15,Curves!$U$38:$BV$38)+SUMPRODUCT(Adds!$C$16:$BD$16,Curves!$U$61:$BV$61) | BE3: =SUMPRODUCT(Adds!$C$14:$BE$14,Curves!$T$15:$BV$15)+SUMPRODUCT(Adds!$C$15:$BE$15,Curves!$T$38:$BV$38)+SUMPRODUCT(Adds!$C$16:$BE$16,Curves!$T$61:$BV$61) | BF3: =SUMPRODUCT(Adds!$C$14:$BF$14,Curves!$S$15:$BV$15)+SUMPRODUCT(Adds!$C$15:$BF$15,Curves!$S$38:$BV$38)+SUMPRODUCT(Adds!$C$16:$BF$16,Curves!$S$61:$BV$61) | BG3: =SUMPRODUCT(Adds!$C$14:$BG$14,Curves!$R$15:$BV$15)+SUMPRODUCT(Adds!$C$15:$BG$15,Curves!$R$38:$BV$38)+SUMPRODUCT(Adds!$C$16:$BG$16,Curves!$R$61:$BV$61) | BH3: =SUMPRODUCT(Adds!$C$14:$BH$14,Curves!$Q$15:$BV$15)+SUMPRODUCT(Adds!$C$15:$BH$15,Curves!$Q$38:$BV$38)+SUMPRODUCT(Adds!$C$16:$BH$16,Curves!$Q$61:$BV$61) | BI3: =SUMPRODUCT(Adds!$C$14:$BI$14,Curves!$P$15:$BV$15)+SUMPRODUCT(Adds!$C$15:$BI$15,Curves!$P$38:$BV$38)+SUMPRODUCT(Adds!$C$16:$BI$16,Curves!$P$61:$BV$61) | BJ3: =SUMPRODUCT(Adds!$C$14:$BJ$14,Curves!$O$15:$BV$15)+SUMPRODUCT(Adds!$C$15:$BJ$15,Curves!$O$38:$BV$38)+SUMPRODUCT(Adds!$C$16:$BJ$16,Curves!$O$61:$BV$61) | BK3: =SUMPRODUCT(Adds!$C$14:$BK$14,Curves!$N$15:$BV$15)+SUMPRODUCT(Adds!$C$15:$BK$15,Curves!$N$38:$BV$38)+SUMPRODUCT(Adds!$C$16:$BK$16,Curves!$N$61:$BV$61) | BL3: =SUMPRODUCT(Adds!$C$14:$BL$14,Curves!$M$15:$BV$15)+SUMPRODUCT(Adds!$C$15:$BL$15,Curves!$M$38:$BV$38)+SUMPRODUCT(Adds!$C$16:$BL$16,Curves!$M$61:$BV$61) | BM3: =SUMPRODUCT(Adds!$C$14:$BM$14,Curves!$L$15:$BV$15)+SUMPRODUCT(Adds!$C$15:$BM$15,Curves!$L$38:$BV$38)+SUMPRODUCT(Adds!$C$16:$BM$16,Curves!$L$61:$BV$61) | BN3: =SUMPRODUCT(Adds!$C$14:$BN$14,Curves!$K$15:$BV$15)+SUMPRODUCT(Adds!$C$15:$BN$15,Curves!$K$38:$BV$38)+SUMPRODUCT(Adds!$C$16:$BN$16,Curves!$K$61:$BV$61) | BO3: =SUMPRODUCT(Adds!$C$14:$BO$14,Curves!$J$15:$BV$15)+SUMPRODUCT(Adds!$C$15:$BO$15,Curves!$J$38:$BV$38)+SUMPRODUCT(Adds!$C$16:$BO$16,Curves!$J$61:$BV$61) | BP3: =SUMPRODUCT(Adds!$C$14:$BP$14,Curves!$I$15:$BV$15)+SUMPRODUCT(Adds!$C$15:$BP$15,Curves!$I$38:$BV$38)+SUMPRODUCT(Adds!$C$16:$BP$16,Curves!$I$61:$BV$61) | BQ3: =SUMPRODUCT(Adds!$C$14:$BQ$14,Curves!$H$15:$BV$15)+SUMPRODUCT(Adds!$C$15:$BQ$15,Curves!$H$38:$BV$38)+SUMPRODUCT(Adds!$C$16:$BQ$16,Curves!$H$61:$BV$61) | BR3: =SUMPRODUCT(Adds!$C$14:$BR$14,Curves!$G$15:$BV$15)+SUMPRODUCT(Adds!$C$15:$BR$15,Curves!$G$38:$BV$38)+SUMPRODUCT(Adds!$C$16:$BR$16,Curves!$G$61:$BV$61) | BS3: =SUMPRODUCT(Adds!$C$14:$BS$14,Curves!$F$15:$BV$15)+SUMPRODUCT(Adds!$C$15:$BS$15,Curves!$F$38:$BV$38)+SUMPRODUCT(Adds!$C$16:$BS$16,Curves!$F$61:$BV$61) | BT3: =SUMPRODUCT(Adds!$C$14:$BT$14,Curves!$E$15:$BV$15)+SUMPRODUCT(Adds!$C$15:$BT$15,Curves!$E$38:$BV$38)+SUMPRODUCT(Adds!$C$16:$BT$16,Curves!$E$61:$BV$61) | BU3: =SUMPRODUCT(Adds!$C$14:$BU$14,Curves!$D$15:$BV$15)+SUMPRODUCT(Adds!$C$15:$BU$15,Curves!$D$38:$BV$38)+SUMPRODUCT(Adds!$C$16:$BU$16,Curves!$D$61:$BV$61) | BV3: =SUMPRODUCT(Adds!$C$14:$BV$14,Curves!$C$15:$BV$15)+SUMPRODUCT(Adds!$C$15:$BV$15,Curves!$C$38:$BV$38)+SUMPRODUCT(Adds!$C$16:$BV$16,Curves!$C$61:$BV$61)
