Workbook

Sheet README
A1: Discord Nitro subscription revenue model (portfolio project). All Discord figures are third-party estimates.
A2: Scenario: base. Generated by nitro_model.excel_export from data/assumptions.csv; mirrors src/nitro_model/cohorts.py.
A3: Flow: Assumptions -> Params -> Curves / MAU / Prices -> Adds -> Paid, Legacy, React -> Subs -> Revenue -> Checks.
A4: Change inputs only on the Assumptions sheet (yellow cells on Params link there). Params!k_cal is solved in Python.
A5: Active subscribers = SUMPRODUCT(sign-ups to date, reversed survival curve). Cohort_US_NitroM shows one segment as a full triangle.
A6: Revenue is at reference (FY2025 average) FX; the FX path arrives in Milestone 3.

Sheet Assumptions
A1: id | B1: group | C1: segment | D1: scenario | E1: value | F1: unit | G1: low | H1: high | I1: status | J1: source_ids | K1: as_of | L1: notes
A2: model_start_year | B2: timeline | C2: all | D2: all | E2: 2025 | F2: year | I2: design | J2: P01 | K2: 2026-10-27 | L2: FY2025 is the calibration year against public estimates
A3: model_start_month | B3: timeline | C3: all | D3: all | E3: 1 | F3: month | I3: design | J3: P01 | K3: 2026-10-27
A4: horizon_months | B4: timeline | C4: all | D4: all | E4: 72 | F4: months | I4: design | J4: P01 | K4: 2026-10-27 | L4: Jan 2025 to Dec 2030: 12 calibration months + 60 forecast months
A5: mau_jan2025 | B5: mau | C5: all | D5: all | E5: 225 | F5: M users | G5: 200 | H5: 260 | I5: proposed | J5: S06;S02;S03;A01 | K5: 2026-10-27 | L5: Discord says 200M+ (May 2025); trackers say 227.7M (2024) to 250-259M (2025). Start below tracker midpoint: trackers likely mix visits and registered users
A6: mau_share | B6: mau | C6: US_CA | D6: all | E6: 0.31 | F6: share | G6: 0.27 | H6: 0.35 | I6: proposed | J6: S07;A01 | K6: 2026-10-27 | L6: Semrush web traffic US 29.1% plus Canada. Caveat: web traffic misses desktop-app and mobile-app use so regional mix may skew; conv_rate by region absorbs part of the error
A7: mau_share | B7: mau | C7: EUROPE | D7: all | E7: 0.28 | F7: share | G7: 0.22 | H7: 0.32 | I7: proposed | J7: S07;A01 | K7: 2026-10-27 | L7: No direct Europe figure found; judgment from country traffic tail (DE/FR/UK/PL)
A8: mau_share | B8: mau | C8: LATAM | D8: all | E8: 0.14 | F8: share | G8: 0.1 | H8: 0.18 | I8: proposed | J8: S07;A01 | K8: 2026-10-27 | L8: Brazil 7.25% of traffic plus rest of LatAm
A9: mau_share | B9: mau | C9: APAC | D9: all | E9: 0.15 | F9: share | G9: 0.1 | H9: 0.2 | I9: proposed | J9: S07;A01 | K9: 2026-10-27 | L9: India 4.9% of traffic plus Japan/SEA/ANZ
A10: mau_share | B10: mau | C10: ROW | D10: all | E10: 0.12 | F10: share | G10: 0.08 | H10: 0.16 | I10: proposed | J10: S07;A01 | K10: 2026-10-27 | L10: Turkey, Russia, MENA, Africa
A11: mau_growth_first | B11: mau | C11: all | D11: base | E11: 0.1 | F11: YoY | G11: 0.06 | H11: 0.14 | I11: proposed | J11: S02;S03;A01 | K11: 2026-10-27 | L11: Tracker YoY 2024-25: 8.7% (Resourcera) to 13.8% (Feedough); applies to 2025
A12: mau_growth_first | B12: mau | C12: all | D12: upside | E12: 0.13 | F12: YoY | G12: 0.1 | H12: 0.16 | I12: proposed | J12: S02;A01 | K12: 2026-10-27 | L12: Near the high tracker growth rate
A13: mau_growth_first | B13: mau | C13: all | D13: downside | E13: 0.06 | F13: YoY | G13: 0.03 | H13: 0.09 | I13: proposed | J13: A01 | K13: 2026-10-27
A14: mau_growth_last | B14: mau | C14: all | D14: base | E14: 0.04 | F14: YoY | G14: 0.02 | H14: 0.06 | I14: proposed | J14: A01 | K14: 2026-10-27 | L14: Applies to 2030; linear fade from first-year growth
A15: mau_growth_last | B15: mau | C15: all | D15: upside | E15: 0.06 | F15: YoY | G15: 0.04 | H15: 0.08 | I15: proposed | J15: A01 | K15: 2026-10-27
A16: mau_growth_last | B16: mau | C16: all | D16: downside | E16: 0 | F16: YoY | G16: -0.03 | H16: 0.02 | I16: proposed | J16: A01 | K16: 2026-10-27 | L16: Flat MAU by 2030
A17: conv_rate | B17: conversion | C17: US_CA | D17: all | E17: 0.0045 | F17: gross adds / MAU / month | G17: 0.003 | H17: 0.006 | I17: proposed | J17: A01 | K17: 2026-10-27 | L17: Back-solved: ~0.65M gross adds/mo holds ~7.3M subs at a ~13-month blended lifetime. Split by willingness to pay. Recalibrated in M3
A18: conv_rate | B18: conversion | C18: EUROPE | D18: all | E18: 0.0032 | F18: gross adds / MAU / month | G18: 0.002 | H18: 0.0045 | I18: proposed | J18: A01 | K18: 2026-10-27
A19: conv_rate | B19: conversion | C19: LATAM | D19: all | E19: 0.0015 | F19: gross adds / MAU / month | G19: 0.0008 | H19: 0.0025 | I19: proposed | J19: A01 | K19: 2026-10-27
A20: conv_rate | B20: conversion | C20: APAC | D20: all | E20: 0.0018 | F20: gross adds / MAU / month | G20: 0.001 | H20: 0.0028 | I20: proposed | J20: A01 | K20: 2026-10-27
A21: conv_rate | B21: conversion | C21: ROW | D21: all | E21: 0.0015 | F21: gross adds / MAU / month | G21: 0.0008 | H21: 0.0025 | I21: proposed | J21: A01 | K21: 2026-10-27
A22: conv_multiplier | B22: conversion | C22: all | D22: base | E22: 1 | F22: x | I22: design | J22: P01 | K22: 2026-10-27
A23: conv_multiplier | B23: conversion | C23: all | D23: upside | E23: 1.1 | F23: x | G23: 1.05 | H23: 1.2 | I23: proposed | J23: A01 | K23: 2026-10-27
A24: conv_multiplier | B24: conversion | C24: all | D24: downside | E24: 0.9 | F24: x | G24: 0.8 | H24: 0.95 | I24: proposed | J24: A01 | K24: 2026-10-27
A25: plan_mix | B25: mix_plan | C25: NITRO_M | D25: all | E25: 0.45 | F25: share of gross adds | G25: 0.35 | H25: 0.55 | I25: proposed | J25: A01 | K25: 2026-10-27 | L25: No public plan mix. Drives most of the ARPU gap vs list price
A26: plan_mix | B26: mix_plan | C26: NITRO_A | D26: all | E26: 0.15 | F26: share of gross adds | G26: 0.08 | H26: 0.25 | I26: proposed | J26: S15;A01 | K26: 2026-10-27 | L26: Duolingo shows annual share can reach 47-71% when pushed hard; Discord does not push annual that hard
A27: plan_mix | B27: mix_plan | C27: BASIC_M | D27: all | E27: 0.32 | F27: share of gross adds | G27: 0.2 | H27: 0.45 | I27: proposed | J27: A01 | K27: 2026-10-27
A28: plan_mix | B28: mix_plan | C28: BASIC_A | D28: all | E28: 0.08 | F28: share of gross adds | G28: 0.03 | H28: 0.15 | I28: proposed | J28: A01 | K28: 2026-10-27
A29: platform_mix | B29: mix_platform | C29: US_CA|WEB | D29: all | E29: 0.55 | F29: share of gross adds | G29: 0.45 | H29: 0.65 | I29: proposed | J29: A01 | K29: 2026-10-27 | L29: Desktop-first product; web/desktop billing avoids app store fees
A30: platform_mix | B30: mix_platform | C30: US_CA|IOS | D30: all | E30: 0.3 | F30: share of gross adds | G30: 0.2 | H30: 0.4 | I30: proposed | J30: A01 | K30: 2026-10-27 | L30: High iPhone share in US
A31: platform_mix | B31: mix_platform | C31: US_CA|ANDROID | D31: all | E31: 0.15 | F31: share of gross adds | G31: 0.1 | H31: 0.2 | I31: proposed | J31: A01 | K31: 2026-10-27
A32: platform_mix | B32: mix_platform | C32: EUROPE|WEB | D32: all | E32: 0.6 | F32: share of gross adds | G32: 0.5 | H32: 0.7 | I32: proposed | J32: A01 | K32: 2026-10-27
A33: platform_mix | B33: mix_platform | C33: EUROPE|IOS | D33: all | E33: 0.22 | F33: share of gross adds | G33: 0.15 | H33: 0.3 | I33: proposed | J33: A01 | K33: 2026-10-27
A34: platform_mix | B34: mix_platform | C34: EUROPE|ANDROID | D34: all | E34: 0.18 | F34: share of gross adds | G34: 0.12 | H34: 0.25 | I34: proposed | J34: A01 | K34: 2026-10-27
A35: platform_mix | B35: mix_platform | C35: LATAM|WEB | D35: all | E35: 0.55 | F35: share of gross adds | G35: 0.45 | H35: 0.65 | I35: proposed | J35: A01 | K35: 2026-10-27
A36: platform_mix | B36: mix_platform | C36: LATAM|IOS | D36: all | E36: 0.1 | F36: share of gross adds | G36: 0.05 | H36: 0.15 | I36: proposed | J36: A01 | K36: 2026-10-27 | L36: Android-dominant region
A37: platform_mix | B37: mix_platform | C37: LATAM|ANDROID | D37: all | E37: 0.35 | F37: share of gross adds | G37: 0.25 | H37: 0.45 | I37: proposed | J37: A01 | K37: 2026-10-27
A38: platform_mix | B38: mix_platform | C38: APAC|WEB | D38: all | E38: 0.55 | F38: share of gross adds | G38: 0.45 | H38: 0.65 | I38: proposed | J38: A01 | K38: 2026-10-27
A39: platform_mix | B39: mix_platform | C39: APAC|IOS | D39: all | E39: 0.2 | F39: share of gross adds | G39: 0.1 | H39: 0.3 | I39: proposed | J39: A01 | K39: 2026-10-27 | L39: Japan iOS-heavy; India Android-heavy
A40: platform_mix | B40: mix_platform | C40: APAC|ANDROID | D40: all | E40: 0.25 | F40: share of gross adds | G40: 0.15 | H40: 0.35 | I40: proposed | J40: A01 | K40: 2026-10-27
A41: platform_mix | B41: mix_platform | C41: ROW|WEB | D41: all | E41: 0.55 | F41: share of gross adds | G41: 0.45 | H41: 0.65 | I41: proposed | J41: A01 | K41: 2026-10-27
A42: platform_mix | B42: mix_platform | C42: ROW|IOS | D42: all | E42: 0.15 | F42: share of gross adds | G42: 0.1 | H42: 0.2 | I42: proposed | J42: A01 | K42: 2026-10-27
A43: platform_mix | B43: mix_platform | C43: ROW|ANDROID | D43: all | E43: 0.3 | F43: share of gross adds | G43: 0.2 | H43: 0.4 | I43: proposed | J43: A01 | K43: 2026-10-27
A44: churn_m1 | B44: churn | C44: MONTHLY | D44: base | E44: 0.3 | F44: share of cohort | G44: 0.25 | H44: 0.35 | I44: benchmark | J44: S13;S16;A01 | K44: 2026-10-27 | L44: Base = Spotify global average plus RevenueCat app benchmarks. Applies to paid starts (direct or converted trialists); trial drop-off is trial_to_paid
A45: churn_m1 | B45: churn | C45: MONTHLY | D45: upside | E45: 0.22 | F45: share of cohort | G45: 0.18 | H45: 0.26 | I45: benchmark | J45: S14;A01 | K45: 2026-10-27 | L45: Upside = Spotify mature markets (US 1-2% tail)
A46: churn_m1 | B46: churn | C46: MONTHLY | D46: downside | E46: 0.4 | F46: share of cohort | G46: 0.35 | H46: 0.5 | I46: benchmark | J46: S15;S16;A01 | K46: 2026-10-27 | L46: Downside = Duolingo monthly (9% renew at 12 mo) / RevenueCat expensive monthly (6.7%)
A47: churn_m2 | B47: churn | C47: MONTHLY | D47: base | E47: 0.14 | F47: share of survivors | G47: 0.1 | H47: 0.18 | I47: benchmark | J47: S13;S16;A01 | K47: 2026-10-27
A48: churn_m2 | B48: churn | C48: MONTHLY | D48: upside | E48: 0.1 | F48: share of survivors | G48: 0.07 | H48: 0.13 | I48: benchmark | J48: S14;A01 | K48: 2026-10-27
A49: churn_m2 | B49: churn | C49: MONTHLY | D49: downside | E49: 0.2 | F49: share of survivors | G49: 0.15 | H49: 0.25 | I49: benchmark | J49: S15;S16;A01 | K49: 2026-10-27
A50: churn_m3 | B50: churn | C50: MONTHLY | D50: base | E50: 0.09 | F50: share of survivors | G50: 0.06 | H50: 0.12 | I50: benchmark | J50: S13;S16;A01 | K50: 2026-10-27
A51: churn_m3 | B51: churn | C51: MONTHLY | D51: upside | E51: 0.06 | F51: share of survivors | G51: 0.04 | H51: 0.08 | I51: benchmark | J51: S14;A01 | K51: 2026-10-27
A52: churn_m3 | B52: churn | C52: MONTHLY | D52: downside | E52: 0.12 | F52: share of survivors | G52: 0.09 | H52: 0.16 | I52: benchmark | J52: S15;S16;A01 | K52: 2026-10-27
A53: churn_tail | B53: churn | C53: MONTHLY | D53: base | E53: 0.05 | F53: share of survivors / month | G53: 0.039 | H53: 0.06 | I53: benchmark | J53: S13;S14 | K53: 2026-10-27 | L53: Spotify Premium 4.8% (Q4'19) and 3.9% (2021 avg); Nitro is more discretionary so slightly higher
A54: churn_tail | B54: churn | C54: MONTHLY | D54: upside | E54: 0.03 | F54: share of survivors / month | G54: 0.02 | H54: 0.039 | I54: benchmark | J54: S14 | K54: 2026-10-27 | L54: Spotify mature markets 1-2%; Nitro set above that
A55: churn_tail | B55: churn | C55: MONTHLY | D55: downside | E55: 0.08 | F55: share of survivors / month | G55: 0.06 | H55: 0.1 | I55: benchmark | J55: S13;S15 | K55: 2026-10-27 | L55: Early Spotify (7.5% Q4'15); Duolingo monthly 4.5-month average lifetime
A56: annual_renewal_first | B56: churn | C56: ANNUAL | D56: base | E56: 0.45 | F56: share renewing | G56: 0.36 | H56: 0.55 | I56: benchmark | J56: S15;S16 | K56: 2026-10-27 | L56: Duolingo ~40% first renewal; RevenueCat cheap annual up to 36%. Nitro set slightly above as a habit product
A57: annual_renewal_first | B57: churn | C57: ANNUAL | D57: upside | E57: 0.55 | F57: share renewing | G57: 0.45 | H57: 0.65 | I57: benchmark | J57: S15;A01 | K57: 2026-10-27
A58: annual_renewal_first | B58: churn | C58: ANNUAL | D58: downside | E58: 0.35 | F58: share renewing | G58: 0.3 | H58: 0.4 | I58: benchmark | J58: S16 | K58: 2026-10-27
A59: annual_renewal_later | B59: churn | C59: ANNUAL | D59: base | E59: 0.65 | F59: share renewing | G59: 0.55 | H59: 0.75 | I59: proposed | J59: A01 | K59: 2026-10-27 | L59: No public second-renewal data found; tenured renewers are stickier
A60: annual_renewal_later | B60: churn | C60: ANNUAL | D60: upside | E60: 0.75 | F60: share renewing | G60: 0.65 | H60: 0.85 | I60: proposed | J60: A01 | K60: 2026-10-27
A61: annual_renewal_later | B61: churn | C61: ANNUAL | D61: downside | E61: 0.55 | F61: share renewing | G61: 0.45 | H61: 0.65 | I61: proposed | J61: A01 | K61: 2026-10-27
A62: react_rate | B62: reactivation | C62: all | D62: base | E62: 0.015 | F62: share of churned pool / month | G62: 0.005 | H62: 0.03 | I62: proposed | J62: A01 | K62: 2026-10-27 | L62: No public win-back data; churned users within the window return at this rate
A63: react_rate | B63: reactivation | C63: all | D63: upside | E63: 0.02 | F63: share of churned pool / month | G63: 0.01 | H63: 0.03 | I63: proposed | J63: A01 | K63: 2026-10-27
A64: react_rate | B64: reactivation | C64: all | D64: downside | E64: 0.01 | F64: share of churned pool / month | G64: 0.005 | H64: 0.02 | I64: proposed | J64: A01 | K64: 2026-10-27
A65: react_window_months | B65: reactivation | C65: all | D65: all | E65: 24 | F65: months | G65: 12 | H65: 36 | I65: proposed | J65: A01 | K65: 2026-10-27 | L65: Churned users older than this drop out of the pool
A66: react_churn_tail | B66: reactivation | C66: all | D66: all | E66: 0.07 | F66: share of survivors / month | G66: 0.05 | H66: 0.1 | I66: proposed | J66: A01 | K66: 2026-10-27 | L66: Reactivated users rejoin on monthly plans; flatter than new-user month-1 churn but above base tail
A67: open_subs | B67: opening_book | C67: all | D67: all | E67: 6.75 | F67: M subscribers | G67: 6 | H67: 7.3 | I67: derived | J67: S01;S02;S03 | K67: 2026-10-27 | L67: Jan 2025 book = 7.3M mid-2025 / 1.17^0.5 (17% YoY growth per Feedough)
A68: open_plan_mix | B68: opening_book | C68: NITRO_M | D68: all | E68: 0.4 | F68: share | G68: 0.3 | H68: 0.5 | I68: proposed | J68: A01 | K68: 2026-10-27 | L68: Tenured book skews to annual vs gross adds
A69: open_plan_mix | B69: opening_book | C69: NITRO_A | D69: all | E69: 0.22 | F69: share | G69: 0.12 | H69: 0.3 | I69: proposed | J69: A01 | K69: 2026-10-27
A70: open_plan_mix | B70: opening_book | C70: BASIC_M | D70: all | E70: 0.28 | F70: share | G70: 0.2 | H70: 0.4 | I70: proposed | J70: A01 | K70: 2026-10-27
A71: open_plan_mix | B71: opening_book | C71: BASIC_A | D71: all | E71: 0.1 | F71: share | G71: 0.05 | H71: 0.15 | I71: proposed | J71: A01 | K71: 2026-10-27
A72: open_region_mix | B72: opening_book | C72: US_CA | D72: all | E72: 0.45 | F72: share | G72: 0.38 | H72: 0.52 | I72: proposed | J72: A01 | K72: 2026-10-27 | L72: Payers skew to high-income regions vs MAU mix
A73: open_region_mix | B73: opening_book | C73: EUROPE | D73: all | E73: 0.3 | F73: share | G73: 0.25 | H73: 0.35 | I73: proposed | J73: A01 | K73: 2026-10-27
A74: open_region_mix | B74: opening_book | C74: LATAM | D74: all | E74: 0.08 | F74: share | G74: 0.05 | H74: 0.12 | I74: proposed | J74: A01 | K74: 2026-10-27
A75: open_region_mix | B75: opening_book | C75: APAC | D75: all | E75: 0.1 | F75: share | G75: 0.06 | H75: 0.14 | I75: proposed | J75: A01 | K75: 2026-10-27
A76: open_region_mix | B76: opening_book | C76: ROW | D76: all | E76: 0.07 | F76: share | G76: 0.04 | H76: 0.1 | I76: proposed | J76: A01 | K76: 2026-10-27
A77: open_y1_share | B77: opening_book | C77: all | D77: all | E77: 0.35 | F77: share of book in first year of tenure | G77: 0.25 | H77: 0.45 | I77: proposed | J77: A01 | K77: 2026-10-28 | L77: Drives the Apple 30% vs 15% fee split for the opening book only; new cohorts get tenure from the cohort engine
A78: open_churn_tail | B78: opening_book | C78: MONTHLY | D78: base | E78: 0.035 | F78: share / month | G78: 0.025 | H78: 0.05 | I78: benchmark | J78: S13;S14 | K78: 2026-10-27 | L78: Tenured monthly subscribers: between Spotify global (3.9%) and mature (1-2%)
A79: open_churn_tail | B79: opening_book | C79: MONTHLY | D79: upside | E79: 0.025 | F79: share / month | G79: 0.015 | H79: 0.035 | I79: benchmark | J79: S14 | K79: 2026-10-27
A80: open_churn_tail | B80: opening_book | C80: MONTHLY | D80: downside | E80: 0.05 | F80: share / month | G80: 0.035 | H80: 0.06 | I80: benchmark | J80: S13 | K80: 2026-10-27
A81: list_price | B81: pricing | C81: NITRO_M | D81: all | E81: 9.99 | F81: USD / month | I81: verified | J81: S08;S09 | K81: 2026-07-01 | L81: US list price; unchanged for years
A82: list_price | B82: pricing | C82: NITRO_A | D82: all | E82: 99.99 | F82: USD / year | I82: verified | J82: S08;S09 | K82: 2026-07-01 | L82: ~17% below 12x monthly
A83: list_price | B83: pricing | C83: BASIC_M | D83: all | E83: 2.99 | F83: USD / month | I83: verified | J83: S08;S09 | K83: 2026-07-01
A84: list_price | B84: pricing | C84: BASIC_A | D84: all | E84: 29.99 | F84: USD / year | I84: verified | J84: S08;S09 | K84: 2026-07-01
A85: price_index | B85: pricing | C85: US_CA | D85: all | E85: 1 | F85: x US price in USD at 2025 avg FX | I85: design | J85: P01 | K85: 2026-10-27 | L85: Reference market
A86: price_index | B86: pricing | C86: EUROPE | D86: all | E86: 1.1 | F86: x US price in USD at 2025 avg FX | G86: 1 | H86: 1.15 | I86: proposed | J86: A01 | K86: 2026-10-27 | L86: Assumes EUR 9.99 VAT-inclusive (~$11.30 at 2025 avg FX). EUR price NOT verified: check at checkout
A87: price_index | B87: pricing | C87: LATAM | D87: all | E87: 0.45 | F87: x US price in USD at 2025 avg FX | G87: 0.3 | H87: 0.6 | I87: proposed | J87: S10;A01 | K87: 2026-10-27 | L87: Localized pricing exists in Brazil per forum posts; level unverified
A88: price_index | B88: pricing | C88: APAC | D88: all | E88: 0.75 | F88: x US price in USD at 2025 avg FX | G88: 0.5 | H88: 1 | I88: proposed | J88: S10;A01 | K88: 2026-10-27 | L88: Japan localized; India reportedly not localized (~INR 850 = ~$10)
A89: price_index | B89: pricing | C89: ROW | D89: all | E89: 0.6 | F89: x US price in USD at 2025 avg FX | G89: 0.3 | H89: 0.8 | I89: proposed | J89: S10;A01 | K89: 2026-10-27 | L89: Turkey ~$3.20 per forum anecdote; RoW blends deep and no discounts
A90: indirect_tax | B90: pricing | C90: US_CA | D90: all | E90: 0 | F90: share of gross price | I90: design | J90: P01 | K90: 2026-10-27 | L90: US sales tax is added on top of list price so it is not in revenue
A91: indirect_tax | B91: pricing | C91: EUROPE | D91: all | E91: 0.167 | F91: share of gross price | G91: 0.15 | H91: 0.18 | I91: proposed | J91: A01 | K91: 2026-10-27 | L91: Prices shown VAT-inclusive. A ~20% VAT rate removes 0.20/1.20 = 16.7% of the gross price; EU rates run 17-27%
A92: indirect_tax | B92: pricing | C92: LATAM | D92: all | E92: 0.12 | F92: share of gross price | G92: 0.05 | H92: 0.2 | I92: proposed | J92: A01 | K92: 2026-10-27 | L92: Digital services taxes vary by country
A93: indirect_tax | B93: pricing | C93: APAC | D93: all | E93: 0.1 | F93: share of gross price | G93: 0.05 | H93: 0.15 | I93: proposed | J93: A01 | K93: 2026-10-27 | L93: Japan consumption tax 10%; India GST 18%
A94: indirect_tax | B94: pricing | C94: ROW | D94: all | E94: 0.1 | F94: share of gross price | G94: 0.05 | H94: 0.2 | I94: proposed | J94: A01 | K94: 2026-10-27
A95: trial_share | B95: promo | C95: all | D95: all | E95: 0.15 | F95: share of gross adds starting on a free trial | G95: 0 | H95: 0.4 | I95: proposed | J95: A01 | K95: 2026-10-28 | L95: Partner promos and free trial months. Trialists pay $0 while in trial, then convert or leave
A96: trial_months | B96: promo | C96: all | D96: all | E96: 1 | F96: months | G96: 1 | H96: 3 | I96: proposed | J96: A01 | K96: 2026-10-28 | L96: Length of the free period
A97: trial_to_paid | B97: promo | C97: all | D97: base | E97: 0.4 | F97: share of trialists converting to paid | G97: 0.25 | H97: 0.6 | I97: proposed | J97: S16;A01 | K97: 2026-10-28 | L97: No public Discord rate. RevenueCat (S16) shows trial conversion clusters at install day but the rate is not in the public preview
A98: trial_to_paid | B98: promo | C98: all | D98: upside | E98: 0.5 | F98: share of trialists converting to paid | G98: 0.25 | H98: 0.6 | I98: proposed | J98: A01 | K98: 2026-10-28
A99: trial_to_paid | B99: promo | C99: all | D99: downside | E99: 0.3 | F99: share of trialists converting to paid | G99: 0.25 | H99: 0.6 | I99: proposed | J99: A01 | K99: 2026-10-28
A100: count_trials_as_subs | B100: promo | C100: all | D100: all | E100: 1 | F100: flag | G100: 0 | H100: 1 | I100: proposed | J100: S13;A01 | K100: 2026-10-28 | L100: Definition: does the 7.3M anchor count trialists? Spotify counts trialists as subscribers (S13). Unknown for the third-party Discord figure
...

Sheet Params
A1: param | B1: value | C1: linked to
A2: mau0 | B2: =Assumptions!$E$5*1e+06 | C2: mau_jan2025[all]
A3: mau_growth_first | B3: =Assumptions!$E$11 | C3: mau_growth_first[all]
A4: mau_growth_last | B4: =Assumptions!$E$14 | C4: mau_growth_last[all]
A5: conv_multiplier | B5: =Assumptions!$E$22 | C5: conv_multiplier[all]
A6: trial_share | B6: =Assumptions!$E$95 | C6: trial_share[all]
A7: trial_months | B7: =Assumptions!$E$96 | C7: trial_months[all]
A8: trial_to_paid | B8: =Assumptions!$E$97 | C8: trial_to_paid[all]
A9: count_trials_as_subs | B9: =Assumptions!$E$100 | C9: count_trials_as_subs[all]
A10: churn_m1 | B10: =Assumptions!$E$44 | C10: churn_m1[MONTHLY]
A11: churn_m2 | B11: =Assumptions!$E$47 | C11: churn_m2[MONTHLY]
A12: churn_m3 | B12: =Assumptions!$E$50 | C12: churn_m3[MONTHLY]
A13: churn_tail | B13: =Assumptions!$E$53 | C13: churn_tail[MONTHLY]
A14: annual_renewal_first | B14: =Assumptions!$E$56 | C14: annual_renewal_first[ANNUAL]
A15: annual_renewal_later | B15: =Assumptions!$E$59 | C15: annual_renewal_later[ANNUAL]
A16: react_rate | B16: =Assumptions!$E$62 | C16: react_rate[all]
A17: react_window_months | B17: =Assumptions!$E$65 | C17: react_window_months[all]
A18: react_churn_tail | B18: =Assumptions!$E$66 | C18: react_churn_tail[all]
A19: open_subs | B19: =Assumptions!$E$67*1e+06 | C19: open_subs[all]
A20: open_churn_tail | B20: =Assumptions!$E$78 | C20: open_churn_tail[MONTHLY]
A21: open_y1_share | B21: =Assumptions!$E$77 | C21: open_y1_share[all]
A22: avg_discount | B22: =Assumptions!$E$101 | C22: avg_discount[all]
A23: fee_web | B23: =Assumptions!$E$105 | C23: store_fee[WEB]
A24: fee_ios_y1 | B24: =Assumptions!$E$102 | C24: store_fee[IOS_Y1]
A25: fee_ios_later | B25: =Assumptions!$E$103 | C25: store_fee[IOS_LATER]
A26: fee_android | B26: =Assumptions!$E$104 | C26: store_fee[ANDROID]
A27: cal_target_subs | B27: =Assumptions!$E$134*1e+06 | C27: cal_subs_mid2025[all]
A28: cal_month_index | B28: =Assumptions!$E$135 | C28: cal_month_index[all]
A29: cal_rev_low | B29: =Assumptions!$G$137*1000000 | C29: cal_nitro_rev_2025 low
A30: cal_rev_high | B30: =Assumptions!$H$137*1000000 | C30: cal_nitro_rev_2025 high
A31: mau_share[US_CA] | B31: =Assumptions!$E$6 | C31: mau_share[US_CA]
A32: mau_share[EUROPE] | B32: =Assumptions!$E$7 | C32: mau_share[EUROPE]
A33: mau_share[LATAM] | B33: =Assumptions!$E$8 | C33: mau_share[LATAM]
A34: mau_share[APAC] | B34: =Assumptions!$E$9 | C34: mau_share[APAC]
A35: mau_share[ROW] | B35: =Assumptions!$E$10 | C35: mau_share[ROW]
A36: conv_rate[US_CA] | B36: =Assumptions!$E$17 | C36: conv_rate[US_CA]
A37: conv_rate[EUROPE] | B37: =Assumptions!$E$18 | C37: conv_rate[EUROPE]
A38: conv_rate[LATAM] | B38: =Assumptions!$E$19 | C38: conv_rate[LATAM]
A39: conv_rate[APAC] | B39: =Assumptions!$E$20 | C39: conv_rate[APAC]
A40: conv_rate[ROW] | B40: =Assumptions!$E$21 | C40: conv_rate[ROW]
A41: price_index[US_CA] | B41: =Assumptions!$E$85 | C41: price_index[US_CA]
A42: price_index[EUROPE] | B42: =Assumptions!$E$86 | C42: price_index[EUROPE]
A43: price_index[LATAM] | B43: =Assumptions!$E$87 | C43: price_index[LATAM]
A44: price_index[APAC] | B44: =Assumptions!$E$88 | C44: price_index[APAC]
A45: price_index[ROW] | B45: =Assumptions!$E$89 | C45: price_index[ROW]
A46: indirect_tax[US_CA] | B46: =Assumptions!$E$90 | C46: indirect_tax[US_CA]
A47: indirect_tax[EUROPE] | B47: =Assumptions!$E$91 | C47: indirect_tax[EUROPE]
A48: indirect_tax[LATAM] | B48: =Assumptions!$E$92 | C48: indirect_tax[LATAM]
A49: indirect_tax[APAC] | B49: =Assumptions!$E$93 | C49: indirect_tax[APAC]
A50: indirect_tax[ROW] | B50: =Assumptions!$E$94 | C50: indirect_tax[ROW]
A51: open_region_mix[US_CA] | B51: =Assumptions!$E$72 | C51: open_region_mix[US_CA]
A52: open_region_mix[EUROPE] | B52: =Assumptions!$E$73 | C52: open_region_mix[EUROPE]
A53: open_region_mix[LATAM] | B53: =Assumptions!$E$74 | C53: open_region_mix[LATAM]
A54: open_region_mix[APAC] | B54: =Assumptions!$E$75 | C54: open_region_mix[APAC]
A55: open_region_mix[ROW] | B55: =Assumptions!$E$76 | C55: open_region_mix[ROW]
A56: platform_mix[US_CA|WEB] | B56: =Assumptions!$E$29 | C56: platform_mix[US_CA|WEB]
A57: platform_mix[US_CA|IOS] | B57: =Assumptions!$E$30 | C57: platform_mix[US_CA|IOS]
A58: platform_mix[US_CA|ANDROID] | B58: =Assumptions!$E$31 | C58: platform_mix[US_CA|ANDROID]
A59: platform_mix[EUROPE|WEB] | B59: =Assumptions!$E$32 | C59: platform_mix[EUROPE|WEB]
A60: platform_mix[EUROPE|IOS] | B60: =Assumptions!$E$33 | C60: platform_mix[EUROPE|IOS]
A61: platform_mix[EUROPE|ANDROID] | B61: =Assumptions!$E$34 | C61: platform_mix[EUROPE|ANDROID]
A62: platform_mix[LATAM|WEB] | B62: =Assumptions!$E$35 | C62: platform_mix[LATAM|WEB]
A63: platform_mix[LATAM|IOS] | B63: =Assumptions!$E$36 | C63: platform_mix[LATAM|IOS]
A64: platform_mix[LATAM|ANDROID] | B64: =Assumptions!$E$37 | C64: platform_mix[LATAM|ANDROID]
A65: platform_mix[APAC|WEB] | B65: =Assumptions!$E$38 | C65: platform_mix[APAC|WEB]
A66: platform_mix[APAC|IOS] | B66: =Assumptions!$E$39 | C66: platform_mix[APAC|IOS]
A67: platform_mix[APAC|ANDROID] | B67: =Assumptions!$E$40 | C67: platform_mix[APAC|ANDROID]
A68: platform_mix[ROW|WEB] | B68: =Assumptions!$E$41 | C68: platform_mix[ROW|WEB]
A69: platform_mix[ROW|IOS] | B69: =Assumptions!$E$42 | C69: platform_mix[ROW|IOS]
A70: platform_mix[ROW|ANDROID] | B70: =Assumptions!$E$43 | C70: platform_mix[ROW|ANDROID]
A71: plan_mix[NITRO_M] | B71: =Assumptions!$E$25 | C71: plan_mix[NITRO_M]
A72: plan_mix[NITRO_A] | B72: =Assumptions!$E$26 | C72: plan_mix[NITRO_A]
A73: plan_mix[BASIC_M] | B73: =Assumptions!$E$27 | C73: plan_mix[BASIC_M]
A74: plan_mix[BASIC_A] | B74: =Assumptions!$E$28 | C74: plan_mix[BASIC_A]
A75: open_plan_mix[NITRO_M] | B75: =Assumptions!$E$68 | C75: open_plan_mix[NITRO_M]
A76: open_plan_mix[NITRO_A] | B76: =Assumptions!$E$69 | C76: open_plan_mix[NITRO_A]
A77: open_plan_mix[BASIC_M] | B77: =Assumptions!$E$70 | C77: open_plan_mix[BASIC_M]
A78: open_plan_mix[BASIC_A] | B78: =Assumptions!$E$71 | C78: open_plan_mix[BASIC_A]
A79: list_price[NITRO_M] | B79: =Assumptions!$E$81 | C79: list_price[NITRO_M]
A80: list_price[NITRO_A] | B80: =Assumptions!$E$82 | C80: list_price[NITRO_A]
A81: list_price[BASIC_M] | B81: =Assumptions!$E$83 | C81: list_price[BASIC_M]
A82: list_price[BASIC_A] | B82: =Assumptions!$E$84 | C82: list_price[BASIC_A]
A83: billing_months[NITRO_M] | B83: 1 | C83: structural: 1 = monthly, 12 = annual (recognized ratably)
A84: billing_months[NITRO_A] | B84: 12 | C84: structural: 1 = monthly, 12 = annual (recognized ratably)
A85: billing_months[BASIC_M] | B85: 1 | C85: structural: 1 = monthly, 12 = annual (recognized ratably)
A86: billing_months[BASIC_A] | B86: 12 | C86: structural: 1 = monthly, 12 = annual (recognized ratably)
A87: k_cal | B87: 0.63307122 | C87: SOLVED in Python: conversion scalar that hits the subscriber anchor (see Checks)

Sheet Curves
A1: curve | B1: age (months) -> | C1: 0 | D1: 1 | E1: 2 | F1: 3 | G1: 4 | H1: 5 | I1: 6 | J1: 7 | K1: 8 | L1: 9 | M1: 10 | N1: 11 | O1: 12 | P1: 13 | Q1: 14 | R1: 15 | S1: 16 | T1: 17 | U1: 18 | V1: 19 | W1: 20 | X1: 21 | Y1: 22 | Z1: 23 | AA1: 24 | AB1: 25 | AC1: 26 | AD1: 27 | AE1: 28 | AF1: 29 | AG1: 30 | AH1: 31 | AI1: 32 | AJ1: 33 | AK1: 34 | AL1: 35 | AM1: 36 | AN1: 37 | AO1: 38 | AP1: 39 | AQ1: 40 | AR1: 41 | AS1: 42 | AT1: 43 | AU1: 44 | AV1: 45 | AW1: 46 | AX1: 47 | AY1: 48 | AZ1: 49 | BA1: 50 | BB1: 51 | BC1: 52 | BD1: 53 | BE1: 54 | BF1: 55 | BG1: 56 | BH1: 57 | BI1: 58 | BJ1: 59 | BK1: 60 | BL1: 61 | BM1: 62 | BN1: 63 | BO1: 64 | BP1: 65 | BQ1: 66 | BR1: 67 | BS1: 68 | BT1: 69 | BU1: 70 | BV1: 71
A2: S_MONTHLY | C2: =1 | D2: =C2*(1-IF(D$1=1,Params!$B$10,IF(D$1=2,Params!$B$11,IF(D$1=3,Params!$B$12,Params!$B$13)))) | E2: =D2*(1-IF(E$1=1,Params!$B$10,IF(E$1=2,Params!$B$11,IF(E$1=3,Params!$B$12,Params!$B$13)))) | F2: =E2*(1-IF(F$1=1,Params!$B$10,IF(F$1=2,Params!$B$11,IF(F$1=3,Params!$B$12,Params!$B$13)))) | G2: =F2*(1-IF(G$1=1,Params!$B$10,IF(G$1=2,Params!$B$11,IF(G$1=3,Params!$B$12,Params!$B$13)))) | H2: =G2*(1-IF(H$1=1,Params!$B$10,IF(H$1=2,Params!$B$11,IF(H$1=3,Params!$B$12,Params!$B$13)))) | I2: =H2*(1-IF(I$1=1,Params!$B$10,IF(I$1=2,Params!$B$11,IF(I$1=3,Params!$B$12,Params!$B$13)))) | J2: =I2*(1-IF(J$1=1,Params!$B$10,IF(J$1=2,Params!$B$11,IF(J$1=3,Params!$B$12,Params!$B$13)))) | K2: =J2*(1-IF(K$1=1,Params!$B$10,IF(K$1=2,Params!$B$11,IF(K$1=3,Params!$B$12,Params!$B$13)))) | ... BV2: =BU2*(1-IF(BV$1=1,Params!$B$10,IF(BV$1=2,Params!$B$11,IF(BV$1=3,Params!$B$12,Params!$B$13))))
A3: S_ANNUAL | C3: =IF(C$1<12,1,Params!$B$14*Params!$B$15^(INT(C$1/12)-1)) | D3: =IF(D$1<12,1,Params!$B$14*Params!$B$15^(INT(D$1/12)-1)) | E3: =IF(E$1<12,1,Params!$B$14*Params!$B$15^(INT(E$1/12)-1)) | F3: =IF(F$1<12,1,Params!$B$14*Params!$B$15^(INT(F$1/12)-1)) | G3: =IF(G$1<12,1,Params!$B$14*Params!$B$15^(INT(G$1/12)-1)) | H3: =IF(H$1<12,1,Params!$B$14*Params!$B$15^(INT(H$1/12)-1)) | I3: =IF(I$1<12,1,Params!$B$14*Params!$B$15^(INT(I$1/12)-1)) | J3: =IF(J$1<12,1,Params!$B$14*Params!$B$15^(INT(J$1/12)-1)) | ... BV3: =IF(BV$1<12,1,Params!$B$14*Params!$B$15^(INT(BV$1/12)-1))
A4: D_MONTHLY | C4: =0 | D4: =C2-D2 | E4: =D2-E2 | F4: =E2-F2 | G4: =F2-G2 | H4: =G2-H2 | I4: =H2-I2 | J4: =I2-J2 | K4: =J2-K2 | ... BV4: =BU2-BV2
A5: D_ANNUAL | C5: =0 | D5: =C3-D3 | E5: =D3-E3 | F5: =E3-F3 | G5: =F3-G3 | H5: =G3-H3 | I5: =H3-I3 | J5: =I3-J3 | K5: =J3-K3 | ... BV5: =BU3-BV3
A6: S_REACT | C6: =(1-Params!$B$18)^C$1 | D6: =(1-Params!$B$18)^D$1 | E6: =(1-Params!$B$18)^E$1 | F6: =(1-Params!$B$18)^F$1 | G6: =(1-Params!$B$18)^G$1 | H6: =(1-Params!$B$18)^H$1 | I6: =(1-Params!$B$18)^I$1 | J6: =(1-Params!$B$18)^J$1 | ... BV6: =(1-Params!$B$18)^BV$1
A7: D_REACT | C7: =0 | D7: =C6-D6 | E7: =D6-E6 | F7: =E6-F6 | G7: =F6-G6 | H7: =G6-H6 | I7: =H6-I6 | J7: =I6-J6 | K7: =J6-K6 | ... BV7: =BU6-BV6
A8: K_REACT | C8: =IF(AND(C$1>=1,C$1<=Params!$B$17),Params!$B$16*(1-Params!$B$16)^(C$1-1),0) | D8: =IF(AND(D$1>=1,D$1<=Params!$B$17),Params!$B$16*(1-Params!$B$16)^(D$1-1),0) | E8: =IF(AND(E$1>=1,E$1<=Params!$B$17),Params!$B$16*(1-Params!$B$16)^(E$1-1),0) | F8: =IF(AND(F$1>=1,F$1<=Params!$B$17),Params!$B$16*(1-Params!$B$16)^(F$1-1),0) | G8: =IF(AND(G$1>=1,G$1<=Params!$B$17),Params!$B$16*(1-Params!$B$16)^(G$1-1),0) | H8: =IF(AND(H$1>=1,H$1<=Params!$B$17),Params!$B$16*(1-Params!$B$16)^(H$1-1),0) | I8: =IF(AND(I$1>=1,I$1<=Params!$B$17),Params!$B$16*(1-Params!$B$16)^(I$1-1),0) | J8: =IF(AND(J$1>=1,J$1<=Params!$B$17),Params!$B$16*(1-Params!$B$16)^(J$1-1),0) | ... BV8: =IF(AND(BV$1>=1,BV$1<=Params!$B$17),Params!$B$16*(1-Params!$B$16)^(BV$1-1),0)
A9: S_MONTHLY_Y1 | C9: =IF(C$1<12,C2,0) | D9: =IF(D$1<12,D2,0) | E9: =IF(E$1<12,E2,0) | F9: =IF(F$1<12,F2,0) | G9: =IF(G$1<12,G2,0) | H9: =IF(H$1<12,H2,0) | I9: =IF(I$1<12,I2,0) | J9: =IF(J$1<12,J2,0) | ... BV9: =IF(BV$1<12,BV2,0)
A10: S_ANNUAL_Y1 | C10: =IF(C$1<12,C3,0) | D10: =IF(D$1<12,D3,0) | E10: =IF(E$1<12,E3,0) | F10: =IF(F$1<12,F3,0) | G10: =IF(G$1<12,G3,0) | H10: =IF(H$1<12,H3,0) | I10: =IF(I$1<12,I3,0) | J10: =IF(J$1<12,J3,0) | ... BV10: =IF(BV$1<12,BV3,0)
A11: S_REACT_Y1 | C11: =IF(C$1<12,C6,0) | D11: =IF(D$1<12,D6,0) | E11: =IF(E$1<12,E6,0) | F11: =IF(F$1<12,F6,0) | G11: =IF(G$1<12,G6,0) | H11: =IF(H$1<12,H6,0) | I11: =IF(I$1<12,I6,0) | J11: =IF(J$1<12,J6,0) | ... BV11: =IF(BV$1<12,BV6,0)
A12: Reversed rows run oldest age first so SUMPRODUCT can pair them with sign-ups to date.
A13: S_MONTHLY reversed | C13: =INDEX($C$2:$BV$2,72) | D13: =INDEX($C$2:$BV$2,71) | E13: =INDEX($C$2:$BV$2,70) | F13: =INDEX($C$2:$BV$2,69) | G13: =INDEX($C$2:$BV$2,68) | H13: =INDEX($C$2:$BV$2,67) | I13: =INDEX($C$2:$BV$2,66) | J13: =INDEX($C$2:$BV$2,65) | K13: =INDEX($C$2:$BV$2,64) | L13: =INDEX($C$2:$BV$2,63) | M13: =INDEX($C$2:$BV$2,62) | N13: =INDEX($C$2:$BV$2,61) | O13: =INDEX($C$2:$BV$2,60) | P13: =INDEX($C$2:$BV$2,59) | Q13: =INDEX($C$2:$BV$2,58) | R13: =INDEX($C$2:$BV$2,57) | S13: =INDEX($C$2:$BV$2,56) | T13: =INDEX($C$2:$BV$2,55) | U13: =INDEX($C$2:$BV$2,54) | V13: =INDEX($C$2:$BV$2,53) | W13: =INDEX($C$2:$BV$2,52) | X13: =INDEX($C$2:$BV$2,51) | Y13: =INDEX($C$2:$BV$2,50) | Z13: =INDEX($C$2:$BV$2,49) | AA13: =INDEX($C$2:$BV$2,48) | AB13: =INDEX($C$2:$BV$2,47) | AC13: =INDEX($C$2:$BV$2,46) | AD13: =INDEX($C$2:$BV$2,45) | AE13: =INDEX($C$2:$BV$2,44) | AF13: =INDEX($C$2:$BV$2,43) | AG13: =INDEX($C$2:$BV$2,42) | AH13: =INDEX($C$2:$BV$2,41) | AI13: =INDEX($C$2:$BV$2,40) | AJ13: =INDEX($C$2:$BV$2,39) | AK13: =INDEX($C$2:$BV$2,38) | AL13: =INDEX($C$2:$BV$2,37) | AM13: =INDEX($C$2:$BV$2,36) | AN13: =INDEX($C$2:$BV$2,35) | AO13: =INDEX($C$2:$BV$2,34) | AP13: =INDEX($C$2:$BV$2,33) | AQ13: =INDEX($C$2:$BV$2,32) | AR13: =INDEX($C$2:$BV$2,31) | AS13: =INDEX($C$2:$BV$2,30) | AT13: =INDEX($C$2:$BV$2,29) | AU13: =INDEX($C$2:$BV$2,28) | AV13: =INDEX($C$2:$BV$2,27) | AW13: =INDEX($C$2:$BV$2,26) | AX13: =INDEX($C$2:$BV$2,25) | AY13: =INDEX($C$2:$BV$2,24) | AZ13: =INDEX($C$2:$BV$2,23) | BA13: =INDEX($C$2:$BV$2,22) | BB13: =INDEX($C$2:$BV$2,21) | BC13: =INDEX($C$2:$BV$2,20) | BD13: =INDEX($C$2:$BV$2,19) | BE13: =INDEX($C$2:$BV$2,18) | BF13: =INDEX($C$2:$BV$2,17) | BG13: =INDEX($C$2:$BV$2,16) | BH13: =INDEX($C$2:$BV$2,15) | BI13: =INDEX($C$2:$BV$2,14) | BJ13: =INDEX($C$2:$BV$2,13) | BK13: =INDEX($C$2:$BV$2,12) | BL13: =INDEX($C$2:$BV$2,11) | BM13: =INDEX($C$2:$BV$2,10) | BN13: =INDEX($C$2:$BV$2,9) | BO13: =INDEX($C$2:$BV$2,8) | BP13: =INDEX($C$2:$BV$2,7) | BQ13: =INDEX($C$2:$BV$2,6) | BR13: =INDEX($C$2:$BV$2,5) | BS13: =INDEX($C$2:$BV$2,4) | BT13: =INDEX($C$2:$BV$2,3) | BU13: =INDEX($C$2:$BV$2,2) | BV13: =INDEX($C$2:$BV$2,1)
A14: S_ANNUAL reversed | C14: =INDEX($C$3:$BV$3,72) | D14: =INDEX($C$3:$BV$3,71) | E14: =INDEX($C$3:$BV$3,70) | F14: =INDEX($C$3:$BV$3,69) | G14: =INDEX($C$3:$BV$3,68) | H14: =INDEX($C$3:$BV$3,67) | I14: =INDEX($C$3:$BV$3,66) | J14: =INDEX($C$3:$BV$3,65) | K14: =INDEX($C$3:$BV$3,64) | L14: =INDEX($C$3:$BV$3,63) | M14: =INDEX($C$3:$BV$3,62) | N14: =INDEX($C$3:$BV$3,61) | O14: =INDEX($C$3:$BV$3,60) | P14: =INDEX($C$3:$BV$3,59) | Q14: =INDEX($C$3:$BV$3,58) | R14: =INDEX($C$3:$BV$3,57) | S14: =INDEX($C$3:$BV$3,56) | T14: =INDEX($C$3:$BV$3,55) | U14: =INDEX($C$3:$BV$3,54) | V14: =INDEX($C$3:$BV$3,53) | W14: =INDEX($C$3:$BV$3,52) | X14: =INDEX($C$3:$BV$3,51) | Y14: =INDEX($C$3:$BV$3,50) | Z14: =INDEX($C$3:$BV$3,49) | AA14: =INDEX($C$3:$BV$3,48) | AB14: =INDEX($C$3:$BV$3,47) | AC14: =INDEX($C$3:$BV$3,46) | AD14: =INDEX($C$3:$BV$3,45) | AE14: =INDEX($C$3:$BV$3,44) | AF14: =INDEX($C$3:$BV$3,43) | AG14: =INDEX($C$3:$BV$3,42) | AH14: =INDEX($C$3:$BV$3,41) | AI14: =INDEX($C$3:$BV$3,40) | AJ14: =INDEX($C$3:$BV$3,39) | AK14: =INDEX($C$3:$BV$3,38) | AL14: =INDEX($C$3:$BV$3,37) | AM14: =INDEX($C$3:$BV$3,36) | AN14: =INDEX($C$3:$BV$3,35) | AO14: =INDEX($C$3:$BV$3,34) | AP14: =INDEX($C$3:$BV$3,33) | AQ14: =INDEX($C$3:$BV$3,32) | AR14: =INDEX($C$3:$BV$3,31) | AS14: =INDEX($C$3:$BV$3,30) | AT14: =INDEX($C$3:$BV$3,29) | AU14: =INDEX($C$3:$BV$3,28) | AV14: =INDEX($C$3:$BV$3,27) | AW14: =INDEX($C$3:$BV$3,26) | AX14: =INDEX($C$3:$BV$3,25) | AY14: =INDEX($C$3:$BV$3,24) | AZ14: =INDEX($C$3:$BV$3,23) | BA14: =INDEX($C$3:$BV$3,22) | BB14: =INDEX($C$3:$BV$3,21) | BC14: =INDEX($C$3:$BV$3,20) | BD14: =INDEX($C$3:$BV$3,19) | BE14: =INDEX($C$3:$BV$3,18) | BF14: =INDEX($C$3:$BV$3,17) | BG14: =INDEX($C$3:$BV$3,16) | BH14: =INDEX($C$3:$BV$3,15) | BI14: =INDEX($C$3:$BV$3,14) | BJ14: =INDEX($C$3:$BV$3,13) | BK14: =INDEX($C$3:$BV$3,12) | BL14: =INDEX($C$3:$BV$3,11) | BM14: =INDEX($C$3:$BV$3,10) | BN14: =INDEX($C$3:$BV$3,9) | BO14: =INDEX($C$3:$BV$3,8) | BP14: =INDEX($C$3:$BV$3,7) | BQ14: =INDEX($C$3:$BV$3,6) | BR14: =INDEX($C$3:$BV$3,5) | BS14: =INDEX($C$3:$BV$3,4) | BT14: =INDEX($C$3:$BV$3,3) | BU14: =INDEX($C$3:$BV$3,2) | BV14: =INDEX($C$3:$BV$3,1)
A15: D_MONTHLY reversed | C15: =INDEX($C$4:$BV$4,72) | D15: =INDEX($C$4:$BV$4,71) | E15: =INDEX($C$4:$BV$4,70) | F15: =INDEX($C$4:$BV$4,69) | G15: =INDEX($C$4:$BV$4,68) | H15: =INDEX($C$4:$BV$4,67) | I15: =INDEX($C$4:$BV$4,66) | J15: =INDEX($C$4:$BV$4,65) | K15: =INDEX($C$4:$BV$4,64) | L15: =INDEX($C$4:$BV$4,63) | M15: =INDEX($C$4:$BV$4,62) | N15: =INDEX($C$4:$BV$4,61) | O15: =INDEX($C$4:$BV$4,60) | P15: =INDEX($C$4:$BV$4,59) | Q15: =INDEX($C$4:$BV$4,58) | R15: =INDEX($C$4:$BV$4,57) | S15: =INDEX($C$4:$BV$4,56) | T15: =INDEX($C$4:$BV$4,55) | U15: =INDEX($C$4:$BV$4,54) | V15: =INDEX($C$4:$BV$4,53) | W15: =INDEX($C$4:$BV$4,52) | X15: =INDEX($C$4:$BV$4,51) | Y15: =INDEX($C$4:$BV$4,50) | Z15: =INDEX($C$4:$BV$4,49) | AA15: =INDEX($C$4:$BV$4,48) | AB15: =INDEX($C$4:$BV$4,47) | AC15: =INDEX($C$4:$BV$4,46) | AD15: =INDEX($C$4:$BV$4,45) | AE15: =INDEX($C$4:$BV$4,44) | AF15: =INDEX($C$4:$BV$4,43) | AG15: =INDEX($C$4:$BV$4,42) | AH15: =INDEX($C$4:$BV$4,41) | AI15: =INDEX($C$4:$BV$4,40) | AJ15: =INDEX($C$4:$BV$4,39) | AK15: =INDEX($C$4:$BV$4,38) | AL15: =INDEX($C$4:$BV$4,37) | AM15: =INDEX($C$4:$BV$4,36) | AN15: =INDEX($C$4:$BV$4,35) | AO15: =INDEX($C$4:$BV$4,34) | AP15: =INDEX($C$4:$BV$4,33) | AQ15: =INDEX($C$4:$BV$4,32) | AR15: =INDEX($C$4:$BV$4,31) | AS15: =INDEX($C$4:$BV$4,30) | AT15: =INDEX($C$4:$BV$4,29) | AU15: =INDEX($C$4:$BV$4,28) | AV15: =INDEX($C$4:$BV$4,27) | AW15: =INDEX($C$4:$BV$4,26) | AX15: =INDEX($C$4:$BV$4,25) | AY15: =INDEX($C$4:$BV$4,24) | AZ15: =INDEX($C$4:$BV$4,23) | BA15: =INDEX($C$4:$BV$4,22) | BB15: =INDEX($C$4:$BV$4,21) | BC15: =INDEX($C$4:$BV$4,20) | BD15: =INDEX($C$4:$BV$4,19) | BE15: =INDEX($C$4:$BV$4,18) | BF15: =INDEX($C$4:$BV$4,17) | BG15: =INDEX($C$4:$BV$4,16) | BH15: =INDEX($C$4:$BV$4,15) | BI15: =INDEX($C$4:$BV$4,14) | BJ15: =INDEX($C$4:$BV$4,13) | BK15: =INDEX($C$4:$BV$4,12) | BL15: =INDEX($C$4:$BV$4,11) | BM15: =INDEX($C$4:$BV$4,10) | BN15: =INDEX($C$4:$BV$4,9) | BO15: =INDEX($C$4:$BV$4,8) | BP15: =INDEX($C$4:$BV$4,7) | BQ15: =INDEX($C$4:$BV$4,6) | BR15: =INDEX($C$4:$BV$4,5) | BS15: =INDEX($C$4:$BV$4,4) | BT15: =INDEX($C$4:$BV$4,3) | BU15: =INDEX($C$4:$BV$4,2) | BV15: =INDEX($C$4:$BV$4,1)
A16: D_ANNUAL reversed | C16: =INDEX($C$5:$BV$5,72) | D16: =INDEX($C$5:$BV$5,71) | E16: =INDEX($C$5:$BV$5,70) | F16: =INDEX($C$5:$BV$5,69) | G16: =INDEX($C$5:$BV$5,68) | H16: =INDEX($C$5:$BV$5,67) | I16: =INDEX($C$5:$BV$5,66) | J16: =INDEX($C$5:$BV$5,65) | K16: =INDEX($C$5:$BV$5,64) | L16: =INDEX($C$5:$BV$5,63) | M16: =INDEX($C$5:$BV$5,62) | N16: =INDEX($C$5:$BV$5,61) | O16: =INDEX($C$5:$BV$5,60) | P16: =INDEX($C$5:$BV$5,59) | Q16: =INDEX($C$5:$BV$5,58) | R16: =INDEX($C$5:$BV$5,57) | S16: =INDEX($C$5:$BV$5,56) | T16: =INDEX($C$5:$BV$5,55) | U16: =INDEX($C$5:$BV$5,54) | V16: =INDEX($C$5:$BV$5,53) | W16: =INDEX($C$5:$BV$5,52) | X16: =INDEX($C$5:$BV$5,51) | Y16: =INDEX($C$5:$BV$5,50) | Z16: =INDEX($C$5:$BV$5,49) | AA16: =INDEX($C$5:$BV$5,48) | AB16: =INDEX($C$5:$BV$5,47) | AC16: =INDEX($C$5:$BV$5,46) | AD16: =INDEX($C$5:$BV$5,45) | AE16: =INDEX($C$5:$BV$5,44) | AF16: =INDEX($C$5:$BV$5,43) | AG16: =INDEX($C$5:$BV$5,42) | AH16: =INDEX($C$5:$BV$5,41) | AI16: =INDEX($C$5:$BV$5,40) | AJ16: =INDEX($C$5:$BV$5,39) | AK16: =INDEX($C$5:$BV$5,38) | AL16: =INDEX($C$5:$BV$5,37) | AM16: =INDEX($C$5:$BV$5,36) | AN16: =INDEX($C$5:$BV$5,35) | AO16: =INDEX($C$5:$BV$5,34) | AP16: =INDEX($C$5:$BV$5,33) | AQ16: =INDEX($C$5:$BV$5,32) | AR16: =INDEX($C$5:$BV$5,31) | AS16: =INDEX($C$5:$BV$5,30) | AT16: =INDEX($C$5:$BV$5,29) | AU16: =INDEX($C$5:$BV$5,28) | AV16: =INDEX($C$5:$BV$5,27) | AW16: =INDEX($C$5:$BV$5,26) | AX16: =INDEX($C$5:$BV$5,25) | AY16: =INDEX($C$5:$BV$5,24) | AZ16: =INDEX($C$5:$BV$5,23) | BA16: =INDEX($C$5:$BV$5,22) | BB16: =INDEX($C$5:$BV$5,21) | BC16: =INDEX($C$5:$BV$5,20) | BD16: =INDEX($C$5:$BV$5,19) | BE16: =INDEX($C$5:$BV$5,18) | BF16: =INDEX($C$5:$BV$5,17) | BG16: =INDEX($C$5:$BV$5,16) | BH16: =INDEX($C$5:$BV$5,15) | BI16: =INDEX($C$5:$BV$5,14) | BJ16: =INDEX($C$5:$BV$5,13) | BK16: =INDEX($C$5:$BV$5,12) | BL16: =INDEX($C$5:$BV$5,11) | BM16: =INDEX($C$5:$BV$5,10) | BN16: =INDEX($C$5:$BV$5,9) | BO16: =INDEX($C$5:$BV$5,8) | BP16: =INDEX($C$5:$BV$5,7) | BQ16: =INDEX($C$5:$BV$5,6) | BR16: =INDEX($C$5:$BV$5,5) | BS16: =INDEX($C$5:$BV$5,4) | BT16: =INDEX($C$5:$BV$5,3) | BU16: =INDEX($C$5:$BV$5,2) | BV16: =INDEX($C$5:$BV$5,1)
A17: S_REACT reversed | C17: =INDEX($C$6:$BV$6,72) | D17: =INDEX($C$6:$BV$6,71) | E17: =INDEX($C$6:$BV$6,70) | F17: =INDEX($C$6:$BV$6,69) | G17: =INDEX($C$6:$BV$6,68) | H17: =INDEX($C$6:$BV$6,67) | I17: =INDEX($C$6:$BV$6,66) | J17: =INDEX($C$6:$BV$6,65) | K17: =INDEX($C$6:$BV$6,64) | L17: =INDEX($C$6:$BV$6,63) | M17: =INDEX($C$6:$BV$6,62) | N17: =INDEX($C$6:$BV$6,61) | O17: =INDEX($C$6:$BV$6,60) | P17: =INDEX($C$6:$BV$6,59) | Q17: =INDEX($C$6:$BV$6,58) | R17: =INDEX($C$6:$BV$6,57) | S17: =INDEX($C$6:$BV$6,56) | T17: =INDEX($C$6:$BV$6,55) | U17: =INDEX($C$6:$BV$6,54) | V17: =INDEX($C$6:$BV$6,53) | W17: =INDEX($C$6:$BV$6,52) | X17: =INDEX($C$6:$BV$6,51) | Y17: =INDEX($C$6:$BV$6,50) | Z17: =INDEX($C$6:$BV$6,49) | AA17: =INDEX($C$6:$BV$6,48) | AB17: =INDEX($C$6:$BV$6,47) | AC17: =INDEX($C$6:$BV$6,46) | AD17: =INDEX($C$6:$BV$6,45) | AE17: =INDEX($C$6:$BV$6,44) | AF17: =INDEX($C$6:$BV$6,43) | AG17: =INDEX($C$6:$BV$6,42) | AH17: =INDEX($C$6:$BV$6,41) | AI17: =INDEX($C$6:$BV$6,40) | AJ17: =INDEX($C$6:$BV$6,39) | AK17: =INDEX($C$6:$BV$6,38) | AL17: =INDEX($C$6:$BV$6,37) | AM17: =INDEX($C$6:$BV$6,36) | AN17: =INDEX($C$6:$BV$6,35) | AO17: =INDEX($C$6:$BV$6,34) | AP17: =INDEX($C$6:$BV$6,33) | AQ17: =INDEX($C$6:$BV$6,32) | AR17: =INDEX($C$6:$BV$6,31) | AS17: =INDEX($C$6:$BV$6,30) | AT17: =INDEX($C$6:$BV$6,29) | AU17: =INDEX($C$6:$BV$6,28) | AV17: =INDEX($C$6:$BV$6,27) | AW17: =INDEX($C$6:$BV$6,26) | AX17: =INDEX($C$6:$BV$6,25) | AY17: =INDEX($C$6:$BV$6,24) | AZ17: =INDEX($C$6:$BV$6,23) | BA17: =INDEX($C$6:$BV$6,22) | BB17: =INDEX($C$6:$BV$6,21) | BC17: =INDEX($C$6:$BV$6,20) | BD17: =INDEX($C$6:$BV$6,19) | BE17: =INDEX($C$6:$BV$6,18) | BF17: =INDEX($C$6:$BV$6,17) | BG17: =INDEX($C$6:$BV$6,16) | BH17: =INDEX($C$6:$BV$6,15) | BI17: =INDEX($C$6:$BV$6,14) | BJ17: =INDEX($C$6:$BV$6,13) | BK17: =INDEX($C$6:$BV$6,12) | BL17: =INDEX($C$6:$BV$6,11) | BM17: =INDEX($C$6:$BV$6,10) | BN17: =INDEX($C$6:$BV$6,9) | BO17: =INDEX($C$6:$BV$6,8) | BP17: =INDEX($C$6:$BV$6,7) | BQ17: =INDEX($C$6:$BV$6,6) | BR17: =INDEX($C$6:$BV$6,5) | BS17: =INDEX($C$6:$BV$6,4) | BT17: =INDEX($C$6:$BV$6,3) | BU17: =INDEX($C$6:$BV$6,2) | BV17: =INDEX($C$6:$BV$6,1)
A18: D_REACT reversed | C18: =INDEX($C$7:$BV$7,72) | D18: =INDEX($C$7:$BV$7,71) | E18: =INDEX($C$7:$BV$7,70) | F18: =INDEX($C$7:$BV$7,69) | G18: =INDEX($C$7:$BV$7,68) | H18: =INDEX($C$7:$BV$7,67) | I18: =INDEX($C$7:$BV$7,66) | J18: =INDEX($C$7:$BV$7,65) | K18: =INDEX($C$7:$BV$7,64) | L18: =INDEX($C$7:$BV$7,63) | M18: =INDEX($C$7:$BV$7,62) | N18: =INDEX($C$7:$BV$7,61) | O18: =INDEX($C$7:$BV$7,60) | P18: =INDEX($C$7:$BV$7,59) | Q18: =INDEX($C$7:$BV$7,58) | R18: =INDEX($C$7:$BV$7,57) | S18: =INDEX($C$7:$BV$7,56) | T18: =INDEX($C$7:$BV$7,55) | U18: =INDEX($C$7:$BV$7,54) | V18: =INDEX($C$7:$BV$7,53) | W18: =INDEX($C$7:$BV$7,52) | X18: =INDEX($C$7:$BV$7,51) | Y18: =INDEX($C$7:$BV$7,50) | Z18: =INDEX($C$7:$BV$7,49) | AA18: =INDEX($C$7:$BV$7,48) | AB18: =INDEX($C$7:$BV$7,47) | AC18: =INDEX($C$7:$BV$7,46) | AD18: =INDEX($C$7:$BV$7,45) | AE18: =INDEX($C$7:$BV$7,44) | AF18: =INDEX($C$7:$BV$7,43) | AG18: =INDEX($C$7:$BV$7,42) | AH18: =INDEX($C$7:$BV$7,41) | AI18: =INDEX($C$7:$BV$7,40) | AJ18: =INDEX($C$7:$BV$7,39) | AK18: =INDEX($C$7:$BV$7,38) | AL18: =INDEX($C$7:$BV$7,37) | AM18: =INDEX($C$7:$BV$7,36) | AN18: =INDEX($C$7:$BV$7,35) | AO18: =INDEX($C$7:$BV$7,34) | AP18: =INDEX($C$7:$BV$7,33) | AQ18: =INDEX($C$7:$BV$7,32) | AR18: =INDEX($C$7:$BV$7,31) | AS18: =INDEX($C$7:$BV$7,30) | AT18: =INDEX($C$7:$BV$7,29) | AU18: =INDEX($C$7:$BV$7,28) | AV18: =INDEX($C$7:$BV$7,27) | AW18: =INDEX($C$7:$BV$7,26) | AX18: =INDEX($C$7:$BV$7,25) | AY18: =INDEX($C$7:$BV$7,24) | AZ18: =INDEX($C$7:$BV$7,23) | BA18: =INDEX($C$7:$BV$7,22) | BB18: =INDEX($C$7:$BV$7,21) | BC18: =INDEX($C$7:$BV$7,20) | BD18: =INDEX($C$7:$BV$7,19) | BE18: =INDEX($C$7:$BV$7,18) | BF18: =INDEX($C$7:$BV$7,17) | BG18: =INDEX($C$7:$BV$7,16) | BH18: =INDEX($C$7:$BV$7,15) | BI18: =INDEX($C$7:$BV$7,14) | BJ18: =INDEX($C$7:$BV$7,13) | BK18: =INDEX($C$7:$BV$7,12) | BL18: =INDEX($C$7:$BV$7,11) | BM18: =INDEX($C$7:$BV$7,10) | BN18: =INDEX($C$7:$BV$7,9) | BO18: =INDEX($C$7:$BV$7,8) | BP18: =INDEX($C$7:$BV$7,7) | BQ18: =INDEX($C$7:$BV$7,6) | BR18: =INDEX($C$7:$BV$7,5) | BS18: =INDEX($C$7:$BV$7,4) | BT18: =INDEX($C$7:$BV$7,3) | BU18: =INDEX($C$7:$BV$7,2) | BV18: =INDEX($C$7:$BV$7,1)
A19: K_REACT reversed | C19: =INDEX($C$8:$BV$8,72) | D19: =INDEX($C$8:$BV$8,71) | E19: =INDEX($C$8:$BV$8,70) | F19: =INDEX($C$8:$BV$8,69) | G19: =INDEX($C$8:$BV$8,68) | H19: =INDEX($C$8:$BV$8,67) | I19: =INDEX($C$8:$BV$8,66) | J19: =INDEX($C$8:$BV$8,65) | K19: =INDEX($C$8:$BV$8,64) | L19: =INDEX($C$8:$BV$8,63) | M19: =INDEX($C$8:$BV$8,62) | N19: =INDEX($C$8:$BV$8,61) | O19: =INDEX($C$8:$BV$8,60) | P19: =INDEX($C$8:$BV$8,59) | Q19: =INDEX($C$8:$BV$8,58) | R19: =INDEX($C$8:$BV$8,57) | S19: =INDEX($C$8:$BV$8,56) | T19: =INDEX($C$8:$BV$8,55) | U19: =INDEX($C$8:$BV$8,54) | V19: =INDEX($C$8:$BV$8,53) | W19: =INDEX($C$8:$BV$8,52) | X19: =INDEX($C$8:$BV$8,51) | Y19: =INDEX($C$8:$BV$8,50) | Z19: =INDEX($C$8:$BV$8,49) | AA19: =INDEX($C$8:$BV$8,48) | AB19: =INDEX($C$8:$BV$8,47) | AC19: =INDEX($C$8:$BV$8,46) | AD19: =INDEX($C$8:$BV$8,45) | AE19: =INDEX($C$8:$BV$8,44) | AF19: =INDEX($C$8:$BV$8,43) | AG19: =INDEX($C$8:$BV$8,42) | AH19: =INDEX($C$8:$BV$8,41) | AI19: =INDEX($C$8:$BV$8,40) | AJ19: =INDEX($C$8:$BV$8,39) | AK19: =INDEX($C$8:$BV$8,38) | AL19: =INDEX($C$8:$BV$8,37) | AM19: =INDEX($C$8:$BV$8,36) | AN19: =INDEX($C$8:$BV$8,35) | AO19: =INDEX($C$8:$BV$8,34) | AP19: =INDEX($C$8:$BV$8,33) | AQ19: =INDEX($C$8:$BV$8,32) | AR19: =INDEX($C$8:$BV$8,31) | AS19: =INDEX($C$8:$BV$8,30) | AT19: =INDEX($C$8:$BV$8,29) | AU19: =INDEX($C$8:$BV$8,28) | AV19: =INDEX($C$8:$BV$8,27) | AW19: =INDEX($C$8:$BV$8,26) | AX19: =INDEX($C$8:$BV$8,25) | AY19: =INDEX($C$8:$BV$8,24) | AZ19: =INDEX($C$8:$BV$8,23) | BA19: =INDEX($C$8:$BV$8,22) | BB19: =INDEX($C$8:$BV$8,21) | BC19: =INDEX($C$8:$BV$8,20) | BD19: =INDEX($C$8:$BV$8,19) | BE19: =INDEX($C$8:$BV$8,18) | BF19: =INDEX($C$8:$BV$8,17) | BG19: =INDEX($C$8:$BV$8,16) | BH19: =INDEX($C$8:$BV$8,15) | BI19: =INDEX($C$8:$BV$8,14) | BJ19: =INDEX($C$8:$BV$8,13) | BK19: =INDEX($C$8:$BV$8,12) | BL19: =INDEX($C$8:$BV$8,11) | BM19: =INDEX($C$8:$BV$8,10) | BN19: =INDEX($C$8:$BV$8,9) | BO19: =INDEX($C$8:$BV$8,8) | BP19: =INDEX($C$8:$BV$8,7) | BQ19: =INDEX($C$8:$BV$8,6) | BR19: =INDEX($C$8:$BV$8,5) | BS19: =INDEX($C$8:$BV$8,4) | BT19: =INDEX($C$8:$BV$8,3) | BU19: =INDEX($C$8:$BV$8,2) | BV19: =INDEX($C$8:$BV$8,1)
A20: S_MONTHLY_Y1 reversed | C20: =INDEX($C$9:$BV$9,72) | D20: =INDEX($C$9:$BV$9,71) | E20: =INDEX($C$9:$BV$9,70) | F20: =INDEX($C$9:$BV$9,69) | G20: =INDEX($C$9:$BV$9,68) | H20: =INDEX($C$9:$BV$9,67) | I20: =INDEX($C$9:$BV$9,66) | J20: =INDEX($C$9:$BV$9,65) | K20: =INDEX($C$9:$BV$9,64) | L20: =INDEX($C$9:$BV$9,63) | M20: =INDEX($C$9:$BV$9,62) | N20: =INDEX($C$9:$BV$9,61) | O20: =INDEX($C$9:$BV$9,60) | P20: =INDEX($C$9:$BV$9,59) | Q20: =INDEX($C$9:$BV$9,58) | R20: =INDEX($C$9:$BV$9,57) | S20: =INDEX($C$9:$BV$9,56) | T20: =INDEX($C$9:$BV$9,55) | U20: =INDEX($C$9:$BV$9,54) | V20: =INDEX($C$9:$BV$9,53) | W20: =INDEX($C$9:$BV$9,52) | X20: =INDEX($C$9:$BV$9,51) | Y20: =INDEX($C$9:$BV$9,50) | Z20: =INDEX($C$9:$BV$9,49) | AA20: =INDEX($C$9:$BV$9,48) | AB20: =INDEX($C$9:$BV$9,47) | AC20: =INDEX($C$9:$BV$9,46) | AD20: =INDEX($C$9:$BV$9,45) | AE20: =INDEX($C$9:$BV$9,44) | AF20: =INDEX($C$9:$BV$9,43) | AG20: =INDEX($C$9:$BV$9,42) | AH20: =INDEX($C$9:$BV$9,41) | AI20: =INDEX($C$9:$BV$9,40) | AJ20: =INDEX($C$9:$BV$9,39) | AK20: =INDEX($C$9:$BV$9,38) | AL20: =INDEX($C$9:$BV$9,37) | AM20: =INDEX($C$9:$BV$9,36) | AN20: =INDEX($C$9:$BV$9,35) | AO20: =INDEX($C$9:$BV$9,34) | AP20: =INDEX($C$9:$BV$9,33) | AQ20: =INDEX($C$9:$BV$9,32) | AR20: =INDEX($C$9:$BV$9,31) | AS20: =INDEX($C$9:$BV$9,30) | AT20: =INDEX($C$9:$BV$9,29) | AU20: =INDEX($C$9:$BV$9,28) | AV20: =INDEX($C$9:$BV$9,27) | AW20: =INDEX($C$9:$BV$9,26) | AX20: =INDEX($C$9:$BV$9,25) | AY20: =INDEX($C$9:$BV$9,24) | AZ20: =INDEX($C$9:$BV$9,23) | BA20: =INDEX($C$9:$BV$9,22) | BB20: =INDEX($C$9:$BV$9,21) | BC20: =INDEX($C$9:$BV$9,20) | BD20: =INDEX($C$9:$BV$9,19) | BE20: =INDEX($C$9:$BV$9,18) | BF20: =INDEX($C$9:$BV$9,17) | BG20: =INDEX($C$9:$BV$9,16) | BH20: =INDEX($C$9:$BV$9,15) | BI20: =INDEX($C$9:$BV$9,14) | BJ20: =INDEX($C$9:$BV$9,13) | BK20: =INDEX($C$9:$BV$9,12) | BL20: =INDEX($C$9:$BV$9,11) | BM20: =INDEX($C$9:$BV$9,10) | BN20: =INDEX($C$9:$BV$9,9) | BO20: =INDEX($C$9:$BV$9,8) | BP20: =INDEX($C$9:$BV$9,7) | BQ20: =INDEX($C$9:$BV$9,6) | BR20: =INDEX($C$9:$BV$9,5) | BS20: =INDEX($C$9:$BV$9,4) | BT20: =INDEX($C$9:$BV$9,3) | BU20: =INDEX($C$9:$BV$9,2) | BV20: =INDEX($C$9:$BV$9,1)
A21: S_ANNUAL_Y1 reversed | C21: =INDEX($C$10:$BV$10,72) | D21: =INDEX($C$10:$BV$10,71) | E21: =INDEX($C$10:$BV$10,70) | F21: =INDEX($C$10:$BV$10,69) | G21: =INDEX($C$10:$BV$10,68) | H21: =INDEX($C$10:$BV$10,67) | I21: =INDEX($C$10:$BV$10,66) | J21: =INDEX($C$10:$BV$10,65) | K21: =INDEX($C$10:$BV$10,64) | L21: =INDEX($C$10:$BV$10,63) | M21: =INDEX($C$10:$BV$10,62) | N21: =INDEX($C$10:$BV$10,61) | O21: =INDEX($C$10:$BV$10,60) | P21: =INDEX($C$10:$BV$10,59) | Q21: =INDEX($C$10:$BV$10,58) | R21: =INDEX($C$10:$BV$10,57) | S21: =INDEX($C$10:$BV$10,56) | T21: =INDEX($C$10:$BV$10,55) | U21: =INDEX($C$10:$BV$10,54) | V21: =INDEX($C$10:$BV$10,53) | W21: =INDEX($C$10:$BV$10,52) | X21: =INDEX($C$10:$BV$10,51) | Y21: =INDEX($C$10:$BV$10,50) | Z21: =INDEX($C$10:$BV$10,49) | AA21: =INDEX($C$10:$BV$10,48) | AB21: =INDEX($C$10:$BV$10,47) | AC21: =INDEX($C$10:$BV$10,46) | AD21: =INDEX($C$10:$BV$10,45) | AE21: =INDEX($C$10:$BV$10,44) | AF21: =INDEX($C$10:$BV$10,43) | AG21: =INDEX($C$10:$BV$10,42) | AH21: =INDEX($C$10:$BV$10,41) | AI21: =INDEX($C$10:$BV$10,40) | AJ21: =INDEX($C$10:$BV$10,39) | AK21: =INDEX($C$10:$BV$10,38) | AL21: =INDEX($C$10:$BV$10,37) | AM21: =INDEX($C$10:$BV$10,36) | AN21: =INDEX($C$10:$BV$10,35) | AO21: =INDEX($C$10:$BV$10,34) | AP21: =INDEX($C$10:$BV$10,33) | AQ21: =INDEX($C$10:$BV$10,32) | AR21: =INDEX($C$10:$BV$10,31) | AS21: =INDEX($C$10:$BV$10,30) | AT21: =INDEX($C$10:$BV$10,29) | AU21: =INDEX($C$10:$BV$10,28) | AV21: =INDEX($C$10:$BV$10,27) | AW21: =INDEX($C$10:$BV$10,26) | AX21: =INDEX($C$10:$BV$10,25) | AY21: =INDEX($C$10:$BV$10,24) | AZ21: =INDEX($C$10:$BV$10,23) | BA21: =INDEX($C$10:$BV$10,22) | BB21: =INDEX($C$10:$BV$10,21) | BC21: =INDEX($C$10:$BV$10,20) | BD21: =INDEX($C$10:$BV$10,19) | BE21: =INDEX($C$10:$BV$10,18) | BF21: =INDEX($C$10:$BV$10,17) | BG21: =INDEX($C$10:$BV$10,16) | BH21: =INDEX($C$10:$BV$10,15) | BI21: =INDEX($C$10:$BV$10,14) | BJ21: =INDEX($C$10:$BV$10,13) | BK21: =INDEX($C$10:$BV$10,12) | BL21: =INDEX($C$10:$BV$10,11) | BM21: =INDEX($C$10:$BV$10,10) | BN21: =INDEX($C$10:$BV$10,9) | BO21: =INDEX($C$10:$BV$10,8) | BP21: =INDEX($C$10:$BV$10,7) | BQ21: =INDEX($C$10:$BV$10,6) | BR21: =INDEX($C$10:$BV$10,5) | BS21: =INDEX($C$10:$BV$10,4) | BT21: =INDEX($C$10:$BV$10,3) | BU21: =INDEX($C$10:$BV$10,2) | BV21: =INDEX($C$10:$BV$10,1)
A22: S_REACT_Y1 reversed | C22: =INDEX($C$11:$BV$11,72) | D22: =INDEX($C$11:$BV$11,71) | E22: =INDEX($C$11:$BV$11,70) | F22: =INDEX($C$11:$BV$11,69) | G22: =INDEX($C$11:$BV$11,68) | H22: =INDEX($C$11:$BV$11,67) | I22: =INDEX($C$11:$BV$11,66) | J22: =INDEX($C$11:$BV$11,65) | K22: =INDEX($C$11:$BV$11,64) | L22: =INDEX($C$11:$BV$11,63) | M22: =INDEX($C$11:$BV$11,62) | N22: =INDEX($C$11:$BV$11,61) | O22: =INDEX($C$11:$BV$11,60) | P22: =INDEX($C$11:$BV$11,59) | Q22: =INDEX($C$11:$BV$11,58) | R22: =INDEX($C$11:$BV$11,57) | S22: =INDEX($C$11:$BV$11,56) | T22: =INDEX($C$11:$BV$11,55) | U22: =INDEX($C$11:$BV$11,54) | V22: =INDEX($C$11:$BV$11,53) | W22: =INDEX($C$11:$BV$11,52) | X22: =INDEX($C$11:$BV$11,51) | Y22: =INDEX($C$11:$BV$11,50) | Z22: =INDEX($C$11:$BV$11,49) | AA22: =INDEX($C$11:$BV$11,48) | AB22: =INDEX($C$11:$BV$11,47) | AC22: =INDEX($C$11:$BV$11,46) | AD22: =INDEX($C$11:$BV$11,45) | AE22: =INDEX($C$11:$BV$11,44) | AF22: =INDEX($C$11:$BV$11,43) | AG22: =INDEX($C$11:$BV$11,42) | AH22: =INDEX($C$11:$BV$11,41) | AI22: =INDEX($C$11:$BV$11,40) | AJ22: =INDEX($C$11:$BV$11,39) | AK22: =INDEX($C$11:$BV$11,38) | AL22: =INDEX($C$11:$BV$11,37) | AM22: =INDEX($C$11:$BV$11,36) | AN22: =INDEX($C$11:$BV$11,35) | AO22: =INDEX($C$11:$BV$11,34) | AP22: =INDEX($C$11:$BV$11,33) | AQ22: =INDEX($C$11:$BV$11,32) | AR22: =INDEX($C$11:$BV$11,31) | AS22: =INDEX($C$11:$BV$11,30) | AT22: =INDEX($C$11:$BV$11,29) | AU22: =INDEX($C$11:$BV$11,28) | AV22: =INDEX($C$11:$BV$11,27) | AW22: =INDEX($C$11:$BV$11,26) | AX22: =INDEX($C$11:$BV$11,25) | AY22: =INDEX($C$11:$BV$11,24) | AZ22: =INDEX($C$11:$BV$11,23) | BA22: =INDEX($C$11:$BV$11,22) | BB22: =INDEX($C$11:$BV$11,21) | BC22: =INDEX($C$11:$BV$11,20) | BD22: =INDEX($C$11:$BV$11,19) | BE22: =INDEX($C$11:$BV$11,18) | BF22: =INDEX($C$11:$BV$11,17) | BG22: =INDEX($C$11:$BV$11,16) | BH22: =INDEX($C$11:$BV$11,15) | BI22: =INDEX($C$11:$BV$11,14) | BJ22: =INDEX($C$11:$BV$11,13) | BK22: =INDEX($C$11:$BV$11,12) | BL22: =INDEX($C$11:$BV$11,11) | BM22: =INDEX($C$11:$BV$11,10) | BN22: =INDEX($C$11:$BV$11,9) | BO22: =INDEX($C$11:$BV$11,8) | BP22: =INDEX($C$11:$BV$11,7) | BQ22: =INDEX($C$11:$BV$11,6) | BR22: =INDEX($C$11:$BV$11,5) | BS22: =INDEX($C$11:$BV$11,4) | BT22: =INDEX($C$11:$BV$11,3) | BU22: =INDEX($C$11:$BV$11,2) | BV22: =INDEX($C$11:$BV$11,1)

Sheet MAU
A1: line | B1: segment | C1: 2025-01 | D1: 2025-02 | E1: 2025-03 | F1: 2025-04 | G1: 2025-05 | H1: 2025-06 | I1: 2025-07 | J1: 2025-08 | K1: 2025-09 | L1: 2025-10 | M1: 2025-11 | N1: 2025-12 | O1: 2026-01 | P1: 2026-02 | Q1: 2026-03 | R1: 2026-04 | S1: 2026-05 | T1: 2026-06 | U1: 2026-07 | V1: 2026-08 | W1: 2026-09 | X1: 2026-10 | Y1: 2026-11 | Z1: 2026-12 | AA1: 2027-01 | AB1: 2027-02 | AC1: 2027-03 | AD1: 2027-04 | AE1: 2027-05 | AF1: 2027-06 | AG1: 2027-07 | AH1: 2027-08 | AI1: 2027-09 | AJ1: 2027-10 | AK1: 2027-11 | AL1: 2027-12 | AM1: 2028-01 | AN1: 2028-02 | AO1: 2028-03 | AP1: 2028-04 | AQ1: 2028-05 | AR1: 2028-06 | AS1: 2028-07 | AT1: 2028-08 | AU1: 2028-09 | AV1: 2028-10 | AW1: 2028-11 | AX1: 2028-12 | AY1: 2029-01 | AZ1: 2029-02 | BA1: 2029-03 | BB1: 2029-04 | BC1: 2029-05 | BD1: 2029-06 | BE1: 2029-07 | BF1: 2029-08 | BG1: 2029-09 | BH1: 2029-10 | BI1: 2029-11 | BJ1: 2029-12 | BK1: 2030-01 | BL1: 2030-02 | BM1: 2030-03 | BN1: 2030-04 | BO1: 2030-05 | BP1: 2030-06 | BQ1: 2030-07 | BR1: 2030-08 | BS1: 2030-09 | BT1: 2030-10 | BU1: 2030-11 | BV1: 2030-12
A2: month index (0 = Jan 2025) | C2: 0 | D2: 1 | E2: 2 | F2: 3 | G2: 4 | H2: 5 | I2: 6 | J2: 7 | K2: 8 | L2: 9 | M2: 10 | N2: 11 | O2: 12 | P2: 13 | Q2: 14 | R2: 15 | S2: 16 | T2: 17 | U2: 18 | V2: 19 | W2: 20 | X2: 21 | Y2: 22 | Z2: 23 | AA2: 24 | AB2: 25 | AC2: 26 | AD2: 27 | AE2: 28 | AF2: 29 | AG2: 30 | AH2: 31 | AI2: 32 | AJ2: 33 | AK2: 34 | AL2: 35 | AM2: 36 | AN2: 37 | AO2: 38 | AP2: 39 | AQ2: 40 | AR2: 41 | AS2: 42 | AT2: 43 | AU2: 44 | AV2: 45 | AW2: 46 | AX2: 47 | AY2: 48 | AZ2: 49 | BA2: 50 | BB2: 51 | BC2: 52 | BD2: 53 | BE2: 54 | BF2: 55 | BG2: 56 | BH2: 57 | BI2: 58 | BJ2: 59 | BK2: 60 | BL2: 61 | BM2: 62 | BN2: 63 | BO2: 64 | BP2: 65 | BQ2: 66 | BR2: 67 | BS2: 68 | BT2: 69 | BU2: 70 | BV2: 71
A3: MAU total | B3: all | C3: =Params!$B$2 | D3: =C3*(1+(Params!$B$3+(Params!$B$4-Params!$B$3)*INT(D$2/12)/5))^(1/12) | E3: =D3*(1+(Params!$B$3+(Params!$B$4-Params!$B$3)*INT(E$2/12)/5))^(1/12) | F3: =E3*(1+(Params!$B$3+(Params!$B$4-Params!$B$3)*INT(F$2/12)/5))^(1/12) | G3: =F3*(1+(Params!$B$3+(Params!$B$4-Params!$B$3)*INT(G$2/12)/5))^(1/12) | H3: =G3*(1+(Params!$B$3+(Params!$B$4-Params!$B$3)*INT(H$2/12)/5))^(1/12) | I3: =H3*(1+(Params!$B$3+(Params!$B$4-Params!$B$3)*INT(I$2/12)/5))^(1/12) | J3: =I3*(1+(Params!$B$3+(Params!$B$4-Params!$B$3)*INT(J$2/12)/5))^(1/12) | K3: =J3*(1+(Params!$B$3+(Params!$B$4-Params!$B$3)*INT(K$2/12)/5))^(1/12) | ... BV3: =BU3*(1+(Params!$B$3+(Params!$B$4-Params!$B$3)*INT(BV$2/12)/5))^(1/12)
A4: MAU | B4: US_CA | C4: =C$3*Params!$B$31 | D4: =D$3*Params!$B$31 | E4: =E$3*Params!$B$31 | F4: =F$3*Params!$B$31 | G4: =G$3*Params!$B$31 | H4: =H$3*Params!$B$31 | I4: =I$3*Params!$B$31 | J4: =J$3*Params!$B$31 | ... BV4: =BV$3*Params!$B$31
A5: MAU | B5: EUROPE | C5: =C$3*Params!$B$32 | D5: =D$3*Params!$B$32 | E5: =E$3*Params!$B$32 | F5: =F$3*Params!$B$32 | G5: =G$3*Params!$B$32 | H5: =H$3*Params!$B$32 | I5: =I$3*Params!$B$32 | J5: =J$3*Params!$B$32 | ... BV5: =BV$3*Params!$B$32
A6: MAU | B6: LATAM | C6: =C$3*Params!$B$33 | D6: =D$3*Params!$B$33 | E6: =E$3*Params!$B$33 | F6: =F$3*Params!$B$33 | G6: =G$3*Params!$B$33 | H6: =H$3*Params!$B$33 | I6: =I$3*Params!$B$33 | J6: =J$3*Params!$B$33 | ... BV6: =BV$3*Params!$B$33
A7: MAU | B7: APAC | C7: =C$3*Params!$B$34 | D7: =D$3*Params!$B$34 | E7: =E$3*Params!$B$34 | F7: =F$3*Params!$B$34 | G7: =G$3*Params!$B$34 | H7: =H$3*Params!$B$34 | I7: =I$3*Params!$B$34 | J7: =J$3*Params!$B$34 | ... BV7: =BV$3*Params!$B$34
A8: MAU | B8: ROW | C8: =C$3*Params!$B$35 | D8: =D$3*Params!$B$35 | E8: =E$3*Params!$B$35 | F8: =F$3*Params!$B$35 | G8: =G$3*Params!$B$35 | H8: =H$3*Params!$B$35 | I8: =I$3*Params!$B$35 | J8: =J$3*Params!$B$35 | ... BV8: =BV$3*Params!$B$35

Sheet Prices
A1: region | B1: plan | C1: list $/mo | D1: x regional index | E1: after discount & VAT | F1: keep after fees (yr 1) | G1: keep after fees (later) | H1: net $/mo (yr 1) | I1: net $/mo (later)
A2: US_CA | B2: NITRO_M | C2: =Params!$B$79/Params!$B$83 | D2: =C2*Params!$B$41 | E2: =D2*(1-Params!$B$22)*(1-Params!$B$46) | F2: =Params!$B$56*(1-Params!$B$23)+Params!$B$57*(1-Params!$B$24)+Params!$B$58*(1-Params!$B$26) | G2: =Params!$B$56*(1-Params!$B$23)+Params!$B$57*(1-Params!$B$25)+Params!$B$58*(1-Params!$B$26) | H2: =E2*F2 | I2: =E2*G2
A3: US_CA | B3: NITRO_A | C3: =Params!$B$80/Params!$B$84 | D3: =C3*Params!$B$41 | E3: =D3*(1-Params!$B$22)*(1-Params!$B$46) | F3: =Params!$B$56*(1-Params!$B$23)+Params!$B$57*(1-Params!$B$24)+Params!$B$58*(1-Params!$B$26) | G3: =Params!$B$56*(1-Params!$B$23)+Params!$B$57*(1-Params!$B$25)+Params!$B$58*(1-Params!$B$26) | H3: =E3*F3 | I3: =E3*G3
A4: US_CA | B4: BASIC_M | C4: =Params!$B$81/Params!$B$85 | D4: =C4*Params!$B$41 | E4: =D4*(1-Params!$B$22)*(1-Params!$B$46) | F4: =Params!$B$56*(1-Params!$B$23)+Params!$B$57*(1-Params!$B$24)+Params!$B$58*(1-Params!$B$26) | G4: =Params!$B$56*(1-Params!$B$23)+Params!$B$57*(1-Params!$B$25)+Params!$B$58*(1-Params!$B$26) | H4: =E4*F4 | I4: =E4*G4
A5: US_CA | B5: BASIC_A | C5: =Params!$B$82/Params!$B$86 | D5: =C5*Params!$B$41 | E5: =D5*(1-Params!$B$22)*(1-Params!$B$46) | F5: =Params!$B$56*(1-Params!$B$23)+Params!$B$57*(1-Params!$B$24)+Params!$B$58*(1-Params!$B$26) | G5: =Params!$B$56*(1-Params!$B$23)+Params!$B$57*(1-Params!$B$25)+Params!$B$58*(1-Params!$B$26) | H5: =E5*F5 | I5: =E5*G5
A6: EUROPE | B6: NITRO_M | C6: =Params!$B$79/Params!$B$83 | D6: =C6*Params!$B$42 | E6: =D6*(1-Params!$B$22)*(1-Params!$B$47) | F6: =Params!$B$59*(1-Params!$B$23)+Params!$B$60*(1-Params!$B$24)+Params!$B$61*(1-Params!$B$26) | G6: =Params!$B$59*(1-Params!$B$23)+Params!$B$60*(1-Params!$B$25)+Params!$B$61*(1-Params!$B$26) | H6: =E6*F6 | I6: =E6*G6
A7: EUROPE | B7: NITRO_A | C7: =Params!$B$80/Params!$B$84 | D7: =C7*Params!$B$42 | E7: =D7*(1-Params!$B$22)*(1-Params!$B$47) | F7: =Params!$B$59*(1-Params!$B$23)+Params!$B$60*(1-Params!$B$24)+Params!$B$61*(1-Params!$B$26) | G7: =Params!$B$59*(1-Params!$B$23)+Params!$B$60*(1-Params!$B$25)+Params!$B$61*(1-Params!$B$26) | H7: =E7*F7 | I7: =E7*G7
A8: EUROPE | B8: BASIC_M | C8: =Params!$B$81/Params!$B$85 | D8: =C8*Params!$B$42 | E8: =D8*(1-Params!$B$22)*(1-Params!$B$47) | F8: =Params!$B$59*(1-Params!$B$23)+Params!$B$60*(1-Params!$B$24)+Params!$B$61*(1-Params!$B$26) | G8: =Params!$B$59*(1-Params!$B$23)+Params!$B$60*(1-Params!$B$25)+Params!$B$61*(1-Params!$B$26) | H8: =E8*F8 | I8: =E8*G8
A9: EUROPE | B9: BASIC_A | C9: =Params!$B$82/Params!$B$86 | D9: =C9*Params!$B$42 | E9: =D9*(1-Params!$B$22)*(1-Params!$B$47) | F9: =Params!$B$59*(1-Params!$B$23)+Params!$B$60*(1-Params!$B$24)+Params!$B$61*(1-Params!$B$26) | G9: =Params!$B$59*(1-Params!$B$23)+Params!$B$60*(1-Params!$B$25)+Params!$B$61*(1-Params!$B$26) | H9: =E9*F9 | I9: =E9*G9
A10: LATAM | B10: NITRO_M | C10: =Params!$B$79/Params!$B$83 | D10: =C10*Params!$B$43 | E10: =D10*(1-Params!$B$22)*(1-Params!$B$48) | F10: =Params!$B$62*(1-Params!$B$23)+Params!$B$63*(1-Params!$B$24)+Params!$B$64*(1-Params!$B$26) | G10: =Params!$B$62*(1-Params!$B$23)+Params!$B$63*(1-Params!$B$25)+Params!$B$64*(1-Params!$B$26) | H10: =E10*F10 | I10: =E10*G10
A11: LATAM | B11: NITRO_A | C11: =Params!$B$80/Params!$B$84 | D11: =C11*Params!$B$43 | E11: =D11*(1-Params!$B$22)*(1-Params!$B$48) | F11: =Params!$B$62*(1-Params!$B$23)+Params!$B$63*(1-Params!$B$24)+Params!$B$64*(1-Params!$B$26) | G11: =Params!$B$62*(1-Params!$B$23)+Params!$B$63*(1-Params!$B$25)+Params!$B$64*(1-Params!$B$26) | H11: =E11*F11 | I11: =E11*G11
A12: LATAM | B12: BASIC_M | C12: =Params!$B$81/Params!$B$85 | D12: =C12*Params!$B$43 | E12: =D12*(1-Params!$B$22)*(1-Params!$B$48) | F12: =Params!$B$62*(1-Params!$B$23)+Params!$B$63*(1-Params!$B$24)+Params!$B$64*(1-Params!$B$26) | G12: =Params!$B$62*(1-Params!$B$23)+Params!$B$63*(1-Params!$B$25)+Params!$B$64*(1-Params!$B$26) | H12: =E12*F12 | I12: =E12*G12
A13: LATAM | B13: BASIC_A | C13: =Params!$B$82/Params!$B$86 | D13: =C13*Params!$B$43 | E13: =D13*(1-Params!$B$22)*(1-Params!$B$48) | F13: =Params!$B$62*(1-Params!$B$23)+Params!$B$63*(1-Params!$B$24)+Params!$B$64*(1-Params!$B$26) | G13: =Params!$B$62*(1-Params!$B$23)+Params!$B$63*(1-Params!$B$25)+Params!$B$64*(1-Params!$B$26) | H13: =E13*F13 | I13: =E13*G13
A14: APAC | B14: NITRO_M | C14: =Params!$B$79/Params!$B$83 | D14: =C14*Params!$B$44 | E14: =D14*(1-Params!$B$22)*(1-Params!$B$49) | F14: =Params!$B$65*(1-Params!$B$23)+Params!$B$66*(1-Params!$B$24)+Params!$B$67*(1-Params!$B$26) | G14: =Params!$B$65*(1-Params!$B$23)+Params!$B$66*(1-Params!$B$25)+Params!$B$67*(1-Params!$B$26) | H14: =E14*F14 | I14: =E14*G14
A15: APAC | B15: NITRO_A | C15: =Params!$B$80/Params!$B$84 | D15: =C15*Params!$B$44 | E15: =D15*(1-Params!$B$22)*(1-Params!$B$49) | F15: =Params!$B$65*(1-Params!$B$23)+Params!$B$66*(1-Params!$B$24)+Params!$B$67*(1-Params!$B$26) | G15: =Params!$B$65*(1-Params!$B$23)+Params!$B$66*(1-Params!$B$25)+Params!$B$67*(1-Params!$B$26) | H15: =E15*F15 | I15: =E15*G15
A16: APAC | B16: BASIC_M | C16: =Params!$B$81/Params!$B$85 | D16: =C16*Params!$B$44 | E16: =D16*(1-Params!$B$22)*(1-Params!$B$49) | F16: =Params!$B$65*(1-Params!$B$23)+Params!$B$66*(1-Params!$B$24)+Params!$B$67*(1-Params!$B$26) | G16: =Params!$B$65*(1-Params!$B$23)+Params!$B$66*(1-Params!$B$25)+Params!$B$67*(1-Params!$B$26) | H16: =E16*F16 | I16: =E16*G16
A17: APAC | B17: BASIC_A | C17: =Params!$B$82/Params!$B$86 | D17: =C17*Params!$B$44 | E17: =D17*(1-Params!$B$22)*(1-Params!$B$49) | F17: =Params!$B$65*(1-Params!$B$23)+Params!$B$66*(1-Params!$B$24)+Params!$B$67*(1-Params!$B$26) | G17: =Params!$B$65*(1-Params!$B$23)+Params!$B$66*(1-Params!$B$25)+Params!$B$67*(1-Params!$B$26) | H17: =E17*F17 | I17: =E17*G17
A18: ROW | B18: NITRO_M | C18: =Params!$B$79/Params!$B$83 | D18: =C18*Params!$B$45 | E18: =D18*(1-Params!$B$22)*(1-Params!$B$50) | F18: =Params!$B$68*(1-Params!$B$23)+Params!$B$69*(1-Params!$B$24)+Params!$B$70*(1-Params!$B$26) | G18: =Params!$B$68*(1-Params!$B$23)+Params!$B$69*(1-Params!$B$25)+Params!$B$70*(1-Params!$B$26) | H18: =E18*F18 | I18: =E18*G18
A19: ROW | B19: NITRO_A | C19: =Params!$B$80/Params!$B$84 | D19: =C19*Params!$B$45 | E19: =D19*(1-Params!$B$22)*(1-Params!$B$50) | F19: =Params!$B$68*(1-Params!$B$23)+Params!$B$69*(1-Params!$B$24)+Params!$B$70*(1-Params!$B$26) | G19: =Params!$B$68*(1-Params!$B$23)+Params!$B$69*(1-Params!$B$25)+Params!$B$70*(1-Params!$B$26) | H19: =E19*F19 | I19: =E19*G19
A20: ROW | B20: BASIC_M | C20: =Params!$B$81/Params!$B$85 | D20: =C20*Params!$B$45 | E20: =D20*(1-Params!$B$22)*(1-Params!$B$50) | F20: =Params!$B$68*(1-Params!$B$23)+Params!$B$69*(1-Params!$B$24)+Params!$B$70*(1-Params!$B$26) | G20: =Params!$B$68*(1-Params!$B$23)+Params!$B$69*(1-Params!$B$25)+Params!$B$70*(1-Params!$B$26) | H20: =E20*F20 | I20: =E20*G20
A21: ROW | B21: BASIC_A | C21: =Params!$B$82/Params!$B$86 | D21: =C21*Params!$B$45 | E21: =D21*(1-Params!$B$22)*(1-Params!$B$50) | F21: =Params!$B$68*(1-Params!$B$23)+Params!$B$69*(1-Params!$B$24)+Params!$B$70*(1-Params!$B$26) | G21: =Params!$B$68*(1-Params!$B$23)+Params!$B$69*(1-Params!$B$25)+Params!$B$70*(1-Params!$B$26) | H21: =E21*F21 | I21: =E21*G21

Sheet Adds
A1: line | B1: segment | C1: 2025-01 | D1: 2025-02 | E1: 2025-03 | F1: 2025-04 | G1: 2025-05 | H1: 2025-06 | I1: 2025-07 | J1: 2025-08 | K1: 2025-09 | L1: 2025-10 | M1: 2025-11 | N1: 2025-12 | O1: 2026-01 | P1: 2026-02 | Q1: 2026-03 | R1: 2026-04 | S1: 2026-05 | T1: 2026-06 | U1: 2026-07 | V1: 2026-08 | W1: 2026-09 | X1: 2026-10 | Y1: 2026-11 | Z1: 2026-12 | AA1: 2027-01 | AB1: 2027-02 | AC1: 2027-03 | AD1: 2027-04 | AE1: 2027-05 | AF1: 2027-06 | AG1: 2027-07 | AH1: 2027-08 | AI1: 2027-09 | AJ1: 2027-10 | AK1: 2027-11 | AL1: 2027-12 | AM1: 2028-01 | AN1: 2028-02 | AO1: 2028-03 | AP1: 2028-04 | AQ1: 2028-05 | AR1: 2028-06 | AS1: 2028-07 | AT1: 2028-08 | AU1: 2028-09 | AV1: 2028-10 | AW1: 2028-11 | AX1: 2028-12 | AY1: 2029-01 | AZ1: 2029-02 | BA1: 2029-03 | BB1: 2029-04 | BC1: 2029-05 | BD1: 2029-06 | BE1: 2029-07 | BF1: 2029-08 | BG1: 2029-09 | BH1: 2029-10 | BI1: 2029-11 | BJ1: 2029-12 | BK1: 2030-01 | BL1: 2030-02 | BM1: 2030-03 | BN1: 2030-04 | BO1: 2030-05 | BP1: 2030-06 | BQ1: 2030-07 | BR1: 2030-08 | BS1: 2030-09 | BT1: 2030-10 | BU1: 2030-11 | BV1: 2030-12
A2: month index (0 = Jan 2025) | C2: 0 | D2: 1 | E2: 2 | F2: 3 | G2: 4 | H2: 5 | I2: 6 | J2: 7 | K2: 8 | L2: 9 | M2: 10 | N2: 11 | O2: 12 | P2: 13 | Q2: 14 | R2: 15 | S2: 16 | T2: 17 | U2: 18 | V2: 19 | W2: 20 | X2: 21 | Y2: 22 | Z2: 23 | AA2: 24 | AB2: 25 | AC2: 26 | AD2: 27 | AE2: 28 | AF2: 29 | AG2: 30 | AH2: 31 | AI2: 32 | AJ2: 33 | AK2: 34 | AL2: 35 | AM2: 36 | AN2: 37 | AO2: 38 | AP2: 39 | AQ2: 40 | AR2: 41 | AS2: 42 | AT2: 43 | AU2: 44 | AV2: 45 | AW2: 46 | AX2: 47 | AY2: 48 | AZ2: 49 | BA2: 50 | BB2: 51 | BC2: 52 | BD2: 53 | BE2: 54 | BF2: 55 | BG2: 56 | BH2: 57 | BI2: 58 | BJ2: 59 | BK2: 60 | BL2: 61 | BM2: 62 | BN2: 63 | BO2: 64 | BP2: 65 | BQ2: 66 | BR2: 67 | BS2: 68 | BT2: 69 | BU2: 70 | BV2: 71
A3: gross adds | B3: US_CA|NITRO_M | C3: =MAU!C4*Params!$B$36*Params!$B$5*Params!$B$87*Params!$B$71 | D3: =MAU!D4*Params!$B$36*Params!$B$5*Params!$B$87*Params!$B$71 | E3: =MAU!E4*Params!$B$36*Params!$B$5*Params!$B$87*Params!$B$71 | F3: =MAU!F4*Params!$B$36*Params!$B$5*Params!$B$87*Params!$B$71 | G3: =MAU!G4*Params!$B$36*Params!$B$5*Params!$B$87*Params!$B$71 | H3: =MAU!H4*Params!$B$36*Params!$B$5*Params!$B$87*Params!$B$71 | I3: =MAU!I4*Params!$B$36*Params!$B$5*Params!$B$87*Params!$B$71 | J3: =MAU!J4*Params!$B$36*Params!$B$5*Params!$B$87*Params!$B$71 | ... BV3: =MAU!BV4*Params!$B$36*Params!$B$5*Params!$B$87*Params!$B$71
A4: trial starts | B4: US_CA|NITRO_M | C4: =C3*Params!$B$6 | D4: =D3*Params!$B$6 | E4: =E3*Params!$B$6 | F4: =F3*Params!$B$6 | G4: =G3*Params!$B$6 | H4: =H3*Params!$B$6 | I4: =I3*Params!$B$6 | J4: =J3*Params!$B$6 | ... BV4: =BV3*Params!$B$6
A5: direct paid starts | B5: US_CA|NITRO_M | C5: =C3-C4 | D5: =D3-D4 | E5: =E3-E4 | F5: =F3-F4 | G5: =G3-G4 | H5: =H3-H4 | I5: =I3-I4 | J5: =J3-J4 | ... BV5: =BV3-BV4
A6: trials ending | B6: US_CA|NITRO_M | C6: =IF(C$2>=Params!$B$7,INDEX($C$4:$BV$4,C$2-Params!$B$7+1),0) | D6: =IF(D$2>=Params!$B$7,INDEX($C$4:$BV$4,D$2-Params!$B$7+1),0) | E6: =IF(E$2>=Params!$B$7,INDEX($C$4:$BV$4,E$2-Params!$B$7+1),0) | F6: =IF(F$2>=Params!$B$7,INDEX($C$4:$BV$4,F$2-Params!$B$7+1),0) | G6: =IF(G$2>=Params!$B$7,INDEX($C$4:$BV$4,G$2-Params!$B$7+1),0) | H6: =IF(H$2>=Params!$B$7,INDEX($C$4:$BV$4,H$2-Params!$B$7+1),0) | I6: =IF(I$2>=Params!$B$7,INDEX($C$4:$BV$4,I$2-Params!$B$7+1),0) | J6: =IF(J$2>=Params!$B$7,INDEX($C$4:$BV$4,J$2-Params!$B$7+1),0) | ... BV6: =IF(BV$2>=Params!$B$7,INDEX($C$4:$BV$4,BV$2-Params!$B$7+1),0)
A7: trials converted | B7: US_CA|NITRO_M | C7: =C6*Params!$B$8 | D7: =D6*Params!$B$8 | E7: =E6*Params!$B$8 | F7: =F6*Params!$B$8 | G7: =G6*Params!$B$8 | H7: =H6*Params!$B$8 | I7: =I6*Params!$B$8 | J7: =J6*Params!$B$8 | ... BV7: =BV6*Params!$B$8
A8: trials lost | B8: US_CA|NITRO_M | C8: =C6-C7 | D8: =D6-D7 | E8: =E6-E7 | F8: =F6-F7 | G8: =G6-G7 | H8: =H6-H7 | I8: =I6-I7 | J8: =J6-J7 | ... BV8: =BV6-BV7
A9: cum trial starts | B9: US_CA|NITRO_M | C9: =SUM($C4:C4) | D9: =SUM($C4:D4) | E9: =SUM($C4:E4) | F9: =SUM($C4:F4) | G9: =SUM($C4:G4) | H9: =SUM($C4:H4) | I9: =SUM($C4:I4) | J9: =SUM($C4:J4) | ... BV9: =SUM($C4:BV4)
A10: cum trials ending | B10: US_CA|NITRO_M | C10: =SUM($C6:C6) | D10: =SUM($C6:D6) | E10: =SUM($C6:E6) | F10: =SUM($C6:F6) | G10: =SUM($C6:G6) | H10: =SUM($C6:H6) | I10: =SUM($C6:I6) | J10: =SUM($C6:J6) | ... BV10: =SUM($C6:BV6)
A11: trials active | B11: US_CA|NITRO_M | C11: =C9-C10 | D11: =D9-D10 | E11: =E9-E10 | F11: =F9-F10 | G11: =G9-G10 | H11: =H9-H10 | I11: =I9-I10 | J11: =J9-J10 | ... BV11: =BV9-BV10
A12: paid starts | B12: US_CA|NITRO_M | C12: =C5+C7 | D12: =D5+D7 | E12: =E5+E7 | F12: =F5+F7 | G12: =G5+G7 | H12: =H5+H7 | I12: =I5+I7 | J12: =J5+J7 | ... BV12: =BV5+BV7
A14: gross adds | B14: US_CA|NITRO_A | C14: =MAU!C4*Params!$B$36*Params!$B$5*Params!$B$87*Params!$B$72 | D14: =MAU!D4*Params!$B$36*Params!$B$5*Params!$B$87*Params!$B$72 | E14: =MAU!E4*Params!$B$36*Params!$B$5*Params!$B$87*Params!$B$72 | F14: =MAU!F4*Params!$B$36*Params!$B$5*Params!$B$87*Params!$B$72 | G14: =MAU!G4*Params!$B$36*Params!$B$5*Params!$B$87*Params!$B$72 | H14: =MAU!H4*Params!$B$36*Params!$B$5*Params!$B$87*Params!$B$72 | I14: =MAU!I4*Params!$B$36*Params!$B$5*Params!$B$87*Params!$B$72 | J14: =MAU!J4*Params!$B$36*Params!$B$5*Params!$B$87*Params!$B$72 | ... BV14: =MAU!BV4*Params!$B$36*Params!$B$5*Params!$B$87*Params!$B$72
A15: trial starts | B15: US_CA|NITRO_A | C15: =C14*Params!$B$6 | D15: =D14*Params!$B$6 | E15: =E14*Params!$B$6 | F15: =F14*Params!$B$6 | G15: =G14*Params!$B$6 | H15: =H14*Params!$B$6 | I15: =I14*Params!$B$6 | J15: =J14*Params!$B$6 | ... BV15: =BV14*Params!$B$6
A16: direct paid starts | B16: US_CA|NITRO_A | C16: =C14-C15 | D16: =D14-D15 | E16: =E14-E15 | F16: =F14-F15 | G16: =G14-G15 | H16: =H14-H15 | I16: =I14-I15 | J16: =J14-J15 | ... BV16: =BV14-BV15
A17: trials ending | B17: US_CA|NITRO_A | C17: =IF(C$2>=Params!$B$7,INDEX($C$15:$BV$15,C$2-Params!$B$7+1),0) | D17: =IF(D$2>=Params!$B$7,INDEX($C$15:$BV$15,D$2-Params!$B$7+1),0) | E17: =IF(E$2>=Params!$B$7,INDEX($C$15:$BV$15,E$2-Params!$B$7+1),0) | F17: =IF(F$2>=Params!$B$7,INDEX($C$15:$BV$15,F$2-Params!$B$7+1),0) | G17: =IF(G$2>=Params!$B$7,INDEX($C$15:$BV$15,G$2-Params!$B$7+1),0) | H17: =IF(H$2>=Params!$B$7,INDEX($C$15:$BV$15,H$2-Params!$B$7+1),0) | I17: =IF(I$2>=Params!$B$7,INDEX($C$15:$BV$15,I$2-Params!$B$7+1),0) | J17: =IF(J$2>=Params!$B$7,INDEX($C$15:$BV$15,J$2-Params!$B$7+1),0) | ... BV17: =IF(BV$2>=Params!$B$7,INDEX($C$15:$BV$15,BV$2-Params!$B$7+1),0)
A18: trials converted | B18: US_CA|NITRO_A | C18: =C17*Params!$B$8 | D18: =D17*Params!$B$8 | E18: =E17*Params!$B$8 | F18: =F17*Params!$B$8 | G18: =G17*Params!$B$8 | H18: =H17*Params!$B$8 | I18: =I17*Params!$B$8 | J18: =J17*Params!$B$8 | ... BV18: =BV17*Params!$B$8
A19: trials lost | B19: US_CA|NITRO_A | C19: =C17-C18 | D19: =D17-D18 | E19: =E17-E18 | F19: =F17-F18 | G19: =G17-G18 | H19: =H17-H18 | I19: =I17-I18 | J19: =J17-J18 | ... BV19: =BV17-BV18
A20: cum trial starts | B20: US_CA|NITRO_A | C20: =SUM($C15:C15) | D20: =SUM($C15:D15) | E20: =SUM($C15:E15) | F20: =SUM($C15:F15) | G20: =SUM($C15:G15) | H20: =SUM($C15:H15) | I20: =SUM($C15:I15) | J20: =SUM($C15:J15) | ... BV20: =SUM($C15:BV15)
A21: cum trials ending | B21: US_CA|NITRO_A | C21: =SUM($C17:C17) | D21: =SUM($C17:D17) | E21: =SUM($C17:E17) | F21: =SUM($C17:F17) | G21: =SUM($C17:G17) | H21: =SUM($C17:H17) | I21: =SUM($C17:I17) | J21: =SUM($C17:J17) | ... BV21: =SUM($C17:BV17)
A22: trials active | B22: US_CA|NITRO_A | C22: =C20-C21 | D22: =D20-D21 | E22: =E20-E21 | F22: =F20-F21 | G22: =G20-G21 | H22: =H20-H21 | I22: =I20-I21 | J22: =J20-J21 | ... BV22: =BV20-BV21
A23: paid starts | B23: US_CA|NITRO_A | C23: =C16+C18 | D23: =D16+D18 | E23: =E16+E18 | F23: =F16+F18 | G23: =G16+G18 | H23: =H16+H18 | I23: =I16+I18 | J23: =J16+J18 | ... BV23: =BV16+BV18
A25: gross adds | B25: US_CA|BASIC_M | C25: =MAU!C4*Params!$B$36*Params!$B$5*Params!$B$87*Params!$B$73 | D25: =MAU!D4*Params!$B$36*Params!$B$5*Params!$B$87*Params!$B$73 | E25: =MAU!E4*Params!$B$36*Params!$B$5*Params!$B$87*Params!$B$73 | F25: =MAU!F4*Params!$B$36*Params!$B$5*Params!$B$87*Params!$B$73 | G25: =MAU!G4*Params!$B$36*Params!$B$5*Params!$B$87*Params!$B$73 | H25: =MAU!H4*Params!$B$36*Params!$B$5*Params!$B$87*Params!$B$73 | I25: =MAU!I4*Params!$B$36*Params!$B$5*Params!$B$87*Params!$B$73 | J25: =MAU!J4*Params!$B$36*Params!$B$5*Params!$B$87*Params!$B$73 | ... BV25: =MAU!BV4*Params!$B$36*Params!$B$5*Params!$B$87*Params!$B$73
A26: trial starts | B26: US_CA|BASIC_M | C26: =C25*Params!$B$6 | D26: =D25*Params!$B$6 | E26: =E25*Params!$B$6 | F26: =F25*Params!$B$6 | G26: =G25*Params!$B$6 | H26: =H25*Params!$B$6 | I26: =I25*Params!$B$6 | J26: =J25*Params!$B$6 | ... BV26: =BV25*Params!$B$6
A27: direct paid starts | B27: US_CA|BASIC_M | C27: =C25-C26 | D27: =D25-D26 | E27: =E25-E26 | F27: =F25-F26 | G27: =G25-G26 | H27: =H25-H26 | I27: =I25-I26 | J27: =J25-J26 | ... BV27: =BV25-BV26
A28: trials ending | B28: US_CA|BASIC_M | C28: =IF(C$2>=Params!$B$7,INDEX($C$26:$BV$26,C$2-Params!$B$7+1),0) | D28: =IF(D$2>=Params!$B$7,INDEX($C$26:$BV$26,D$2-Params!$B$7+1),0) | E28: =IF(E$2>=Params!$B$7,INDEX($C$26:$BV$26,E$2-Params!$B$7+1),0) | F28: =IF(F$2>=Params!$B$7,INDEX($C$26:$BV$26,F$2-Params!$B$7+1),0) | G28: =IF(G$2>=Params!$B$7,INDEX($C$26:$BV$26,G$2-Params!$B$7+1),0) | H28: =IF(H$2>=Params!$B$7,INDEX($C$26:$BV$26,H$2-Params!$B$7+1),0) | I28: =IF(I$2>=Params!$B$7,INDEX($C$26:$BV$26,I$2-Params!$B$7+1),0) | J28: =IF(J$2>=Params!$B$7,INDEX($C$26:$BV$26,J$2-Params!$B$7+1),0) | ... BV28: =IF(BV$2>=Params!$B$7,INDEX($C$26:$BV$26,BV$2-Params!$B$7+1),0)
A29: trials converted | B29: US_CA|BASIC_M | C29: =C28*Params!$B$8 | D29: =D28*Params!$B$8 | E29: =E28*Params!$B$8 | F29: =F28*Params!$B$8 | G29: =G28*Params!$B$8 | H29: =H28*Params!$B$8 | I29: =I28*Params!$B$8 | J29: =J28*Params!$B$8 | ... BV29: =BV28*Params!$B$8
A30: trials lost | B30: US_CA|BASIC_M | C30: =C28-C29 | D30: =D28-D29 | E30: =E28-E29 | F30: =F28-F29 | G30: =G28-G29 | H30: =H28-H29 | I30: =I28-I29 | J30: =J28-J29 | ... BV30: =BV28-BV29
A31: cum trial starts | B31: US_CA|BASIC_M | C31: =SUM($C26:C26) | D31: =SUM($C26:D26) | E31: =SUM($C26:E26) | F31: =SUM($C26:F26) | G31: =SUM($C26:G26) | H31: =SUM($C26:H26) | I31: =SUM($C26:I26) | J31: =SUM($C26:J26) | ... BV31: =SUM($C26:BV26)
A32: cum trials ending | B32: US_CA|BASIC_M | C32: =SUM($C28:C28) | D32: =SUM($C28:D28) | E32: =SUM($C28:E28) | F32: =SUM($C28:F28) | G32: =SUM($C28:G28) | H32: =SUM($C28:H28) | I32: =SUM($C28:I28) | J32: =SUM($C28:J28) | ... BV32: =SUM($C28:BV28)
A33: trials active | B33: US_CA|BASIC_M | C33: =C31-C32 | D33: =D31-D32 | E33: =E31-E32 | F33: =F31-F32 | G33: =G31-G32 | H33: =H31-H32 | I33: =I31-I32 | J33: =J31-J32 | ... BV33: =BV31-BV32
A34: paid starts | B34: US_CA|BASIC_M | C34: =C27+C29 | D34: =D27+D29 | E34: =E27+E29 | F34: =F27+F29 | G34: =G27+G29 | H34: =H27+H29 | I34: =I27+I29 | J34: =J27+J29 | ... BV34: =BV27+BV29
A36: gross adds | B36: US_CA|BASIC_A | C36: =MAU!C4*Params!$B$36*Params!$B$5*Params!$B$87*Params!$B$74 | D36: =MAU!D4*Params!$B$36*Params!$B$5*Params!$B$87*Params!$B$74 | E36: =MAU!E4*Params!$B$36*Params!$B$5*Params!$B$87*Params!$B$74 | F36: =MAU!F4*Params!$B$36*Params!$B$5*Params!$B$87*Params!$B$74 | G36: =MAU!G4*Params!$B$36*Params!$B$5*Params!$B$87*Params!$B$74 | H36: =MAU!H4*Params!$B$36*Params!$B$5*Params!$B$87*Params!$B$74 | I36: =MAU!I4*Params!$B$36*Params!$B$5*Params!$B$87*Params!$B$74 | J36: =MAU!J4*Params!$B$36*Params!$B$5*Params!$B$87*Params!$B$74 | ... BV36: =MAU!BV4*Params!$B$36*Params!$B$5*Params!$B$87*Params!$B$74
A37: trial starts | B37: US_CA|BASIC_A | C37: =C36*Params!$B$6 | D37: =D36*Params!$B$6 | E37: =E36*Params!$B$6 | F37: =F36*Params!$B$6 | G37: =G36*Params!$B$6 | H37: =H36*Params!$B$6 | I37: =I36*Params!$B$6 | J37: =J36*Params!$B$6 | ... BV37: =BV36*Params!$B$6
A38: direct paid starts | B38: US_CA|BASIC_A | C38: =C36-C37 | D38: =D36-D37 | E38: =E36-E37 | F38: =F36-F37 | G38: =G36-G37 | H38: =H36-H37 | I38: =I36-I37 | J38: =J36-J37 | ... BV38: =BV36-BV37
A39: trials ending | B39: US_CA|BASIC_A | C39: =IF(C$2>=Params!$B$7,INDEX($C$37:$BV$37,C$2-Params!$B$7+1),0) | D39: =IF(D$2>=Params!$B$7,INDEX($C$37:$BV$37,D$2-Params!$B$7+1),0) | E39: =IF(E$2>=Params!$B$7,INDEX($C$37:$BV$37,E$2-Params!$B$7+1),0) | F39: =IF(F$2>=Params!$B$7,INDEX($C$37:$BV$37,F$2-Params!$B$7+1),0) | G39: =IF(G$2>=Params!$B$7,INDEX($C$37:$BV$37,G$2-Params!$B$7+1),0) | H39: =IF(H$2>=Params!$B$7,INDEX($C$37:$BV$37,H$2-Params!$B$7+1),0) | I39: =IF(I$2>=Params!$B$7,INDEX($C$37:$BV$37,I$2-Params!$B$7+1),0) | J39: =IF(J$2>=Params!$B$7,INDEX($C$37:$BV$37,J$2-Params!$B$7+1),0) | ... BV39: =IF(BV$2>=Params!$B$7,INDEX($C$37:$BV$37,BV$2-Params!$B$7+1),0)
A40: trials converted | B40: US_CA|BASIC_A | C40: =C39*Params!$B$8 | D40: =D39*Params!$B$8 | E40: =E39*Params!$B$8 | F40: =F39*Params!$B$8 | G40: =G39*Params!$B$8 | H40: =H39*Params!$B$8 | I40: =I39*Params!$B$8 | J40: =J39*Params!$B$8 | ... BV40: =BV39*Params!$B$8
A41: trials lost | B41: US_CA|BASIC_A | C41: =C39-C40 | D41: =D39-D40 | E41: =E39-E40 | F41: =F39-F40 | G41: =G39-G40 | H41: =H39-H40 | I41: =I39-I40 | J41: =J39-J40 | ... BV41: =BV39-BV40
A42: cum trial starts | B42: US_CA|BASIC_A | C42: =SUM($C37:C37) | D42: =SUM($C37:D37) | E42: =SUM($C37:E37) | F42: =SUM($C37:F37) | G42: =SUM($C37:G37) | H42: =SUM($C37:H37) | I42: =SUM($C37:I37) | J42: =SUM($C37:J37) | ... BV42: =SUM($C37:BV37)
A43: cum trials ending | B43: US_CA|BASIC_A | C43: =SUM($C39:C39) | D43: =SUM($C39:D39) | E43: =SUM($C39:E39) | F43: =SUM($C39:F39) | G43: =SUM($C39:G39) | H43: =SUM($C39:H39) | I43: =SUM($C39:I39) | J43: =SUM($C39:J39) | ... BV43: =SUM($C39:BV39)
A44: trials active | B44: US_CA|BASIC_A | C44: =C42-C43 | D44: =D42-D43 | E44: =E42-E43 | F44: =F42-F43 | G44: =G42-G43 | H44: =H42-H43 | I44: =I42-I43 | J44: =J42-J43 | ... BV44: =BV42-BV43
A45: paid starts | B45: US_CA|BASIC_A | C45: =C38+C40 | D45: =D38+D40 | E45: =E38+E40 | F45: =F38+F40 | G45: =G38+G40 | H45: =H38+H40 | I45: =I38+I40 | J45: =J38+J40 | ... BV45: =BV38+BV40
A47: gross adds | B47: EUROPE|NITRO_M | C47: =MAU!C5*Params!$B$37*Params!$B$5*Params!$B$87*Params!$B$71 | D47: =MAU!D5*Params!$B$37*Params!$B$5*Params!$B$87*Params!$B$71 | E47: =MAU!E5*Params!$B$37*Params!$B$5*Params!$B$87*Params!$B$71 | F47: =MAU!F5*Params!$B$37*Params!$B$5*Params!$B$87*Params!$B$71 | G47: =MAU!G5*Params!$B$37*Params!$B$5*Params!$B$87*Params!$B$71 | H47: =MAU!H5*Params!$B$37*Params!$B$5*Params!$B$87*Params!$B$71 | I47: =MAU!I5*Params!$B$37*Params!$B$5*Params!$B$87*Params!$B$71 | J47: =MAU!J5*Params!$B$37*Params!$B$5*Params!$B$87*Params!$B$71 | ... BV47: =MAU!BV5*Params!$B$37*Params!$B$5*Params!$B$87*Params!$B$71
A48: trial starts | B48: EUROPE|NITRO_M | C48: =C47*Params!$B$6 | D48: =D47*Params!$B$6 | E48: =E47*Params!$B$6 | F48: =F47*Params!$B$6 | G48: =G47*Params!$B$6 | H48: =H47*Params!$B$6 | I48: =I47*Params!$B$6 | J48: =J47*Params!$B$6 | ... BV48: =BV47*Params!$B$6
A49: direct paid starts | B49: EUROPE|NITRO_M | C49: =C47-C48 | D49: =D47-D48 | E49: =E47-E48 | F49: =F47-F48 | G49: =G47-G48 | H49: =H47-H48 | I49: =I47-I48 | J49: =J47-J48 | ... BV49: =BV47-BV48
A50: trials ending | B50: EUROPE|NITRO_M | C50: =IF(C$2>=Params!$B$7,INDEX($C$48:$BV$48,C$2-Params!$B$7+1),0) | D50: =IF(D$2>=Params!$B$7,INDEX($C$48:$BV$48,D$2-Params!$B$7+1),0) | E50: =IF(E$2>=Params!$B$7,INDEX($C$48:$BV$48,E$2-Params!$B$7+1),0) | F50: =IF(F$2>=Params!$B$7,INDEX($C$48:$BV$48,F$2-Params!$B$7+1),0) | G50: =IF(G$2>=Params!$B$7,INDEX($C$48:$BV$48,G$2-Params!$B$7+1),0) | H50: =IF(H$2>=Params!$B$7,INDEX($C$48:$BV$48,H$2-Params!$B$7+1),0) | I50: =IF(I$2>=Params!$B$7,INDEX($C$48:$BV$48,I$2-Params!$B$7+1),0) | J50: =IF(J$2>=Params!$B$7,INDEX($C$48:$BV$48,J$2-Params!$B$7+1),0) | ... BV50: =IF(BV$2>=Params!$B$7,INDEX($C$48:$BV$48,BV$2-Params!$B$7+1),0)
A51: trials converted | B51: EUROPE|NITRO_M | C51: =C50*Params!$B$8 | D51: =D50*Params!$B$8 | E51: =E50*Params!$B$8 | F51: =F50*Params!$B$8 | G51: =G50*Params!$B$8 | H51: =H50*Params!$B$8 | I51: =I50*Params!$B$8 | J51: =J50*Params!$B$8 | ... BV51: =BV50*Params!$B$8
A52: trials lost | B52: EUROPE|NITRO_M | C52: =C50-C51 | D52: =D50-D51 | E52: =E50-E51 | F52: =F50-F51 | G52: =G50-G51 | H52: =H50-H51 | I52: =I50-I51 | J52: =J50-J51 | ... BV52: =BV50-BV51
A53: cum trial starts | B53: EUROPE|NITRO_M | C53: =SUM($C48:C48) | D53: =SUM($C48:D48) | E53: =SUM($C48:E48) | F53: =SUM($C48:F48) | G53: =SUM($C48:G48) | H53: =SUM($C48:H48) | I53: =SUM($C48:I48) | J53: =SUM($C48:J48) | ... BV53: =SUM($C48:BV48)
A54: cum trials ending | B54: EUROPE|NITRO_M | C54: =SUM($C50:C50) | D54: =SUM($C50:D50) | E54: =SUM($C50:E50) | F54: =SUM($C50:F50) | G54: =SUM($C50:G50) | H54: =SUM($C50:H50) | I54: =SUM($C50:I50) | J54: =SUM($C50:J50) | ... BV54: =SUM($C50:BV50)
A55: trials active | B55: EUROPE|NITRO_M | C55: =C53-C54 | D55: =D53-D54 | E55: =E53-E54 | F55: =F53-F54 | G55: =G53-G54 | H55: =H53-H54 | I55: =I53-I54 | J55: =J53-J54 | ... BV55: =BV53-BV54
A56: paid starts | B56: EUROPE|NITRO_M | C56: =C49+C51 | D56: =D49+D51 | E56: =E49+E51 | F56: =F49+F51 | G56: =G49+G51 | H56: =H49+H51 | I56: =I49+I51 | J56: =J49+J51 | ... BV56: =BV49+BV51
A58: gross adds | B58: EUROPE|NITRO_A | C58: =MAU!C5*Params!$B$37*Params!$B$5*Params!$B$87*Params!$B$72 | D58: =MAU!D5*Params!$B$37*Params!$B$5*Params!$B$87*Params!$B$72 | E58: =MAU!E5*Params!$B$37*Params!$B$5*Params!$B$87*Params!$B$72 | F58: =MAU!F5*Params!$B$37*Params!$B$5*Params!$B$87*Params!$B$72 | G58: =MAU!G5*Params!$B$37*Params!$B$5*Params!$B$87*Params!$B$72 | H58: =MAU!H5*Params!$B$37*Params!$B$5*Params!$B$87*Params!$B$72 | I58: =MAU!I5*Params!$B$37*Params!$B$5*Params!$B$87*Params!$B$72 | J58: =MAU!J5*Params!$B$37*Params!$B$5*Params!$B$87*Params!$B$72 | ... BV58: =MAU!BV5*Params!$B$37*Params!$B$5*Params!$B$87*Params!$B$72
A59: trial starts | B59: EUROPE|NITRO_A | C59: =C58*Params!$B$6 | D59: =D58*Params!$B$6 | E59: =E58*Params!$B$6 | F59: =F58*Params!$B$6 | G59: =G58*Params!$B$6 | H59: =H58*Params!$B$6 | I59: =I58*Params!$B$6 | J59: =J58*Params!$B$6 | ... BV59: =BV58*Params!$B$6
A60: direct paid starts | B60: EUROPE|NITRO_A | C60: =C58-C59 | D60: =D58-D59 | E60: =E58-E59 | F60: =F58-F59 | G60: =G58-G59 | H60: =H58-H59 | I60: =I58-I59 | J60: =J58-J59 | ... BV60: =BV58-BV59
A61: trials ending | B61: EUROPE|NITRO_A | C61: =IF(C$2>=Params!$B$7,INDEX($C$59:$BV$59,C$2-Params!$B$7+1),0) | D61: =IF(D$2>=Params!$B$7,INDEX($C$59:$BV$59,D$2-Params!$B$7+1),0) | E61: =IF(E$2>=Params!$B$7,INDEX($C$59:$BV$59,E$2-Params!$B$7+1),0) | F61: =IF(F$2>=Params!$B$7,INDEX($C$59:$BV$59,F$2-Params!$B$7+1),0) | G61: =IF(G$2>=Params!$B$7,INDEX($C$59:$BV$59,G$2-Params!$B$7+1),0) | H61: =IF(H$2>=Params!$B$7,INDEX($C$59:$BV$59,H$2-Params!$B$7+1),0) | I61: =IF(I$2>=Params!$B$7,INDEX($C$59:$BV$59,I$2-Params!$B$7+1),0) | J61: =IF(J$2>=Params!$B$7,INDEX($C$59:$BV$59,J$2-Params!$B$7+1),0) | ... BV61: =IF(BV$2>=Params!$B$7,INDEX($C$59:$BV$59,BV$2-Params!$B$7+1),0)
A62: trials converted | B62: EUROPE|NITRO_A | C62: =C61*Params!$B$8 | D62: =D61*Params!$B$8 | E62: =E61*Params!$B$8 | F62: =F61*Params!$B$8 | G62: =G61*Params!$B$8 | H62: =H61*Params!$B$8 | I62: =I61*Params!$B$8 | J62: =J61*Params!$B$8 | ... BV62: =BV61*Params!$B$8
A63: trials lost | B63: EUROPE|NITRO_A | C63: =C61-C62 | D63: =D61-D62 | E63: =E61-E62 | F63: =F61-F62 | G63: =G61-G62 | H63: =H61-H62 | I63: =I61-I62 | J63: =J61-J62 | ... BV63: =BV61-BV62
A64: cum trial starts | B64: EUROPE|NITRO_A | C64: =SUM($C59:C59) | D64: =SUM($C59:D59) | E64: =SUM($C59:E59) | F64: =SUM($C59:F59) | G64: =SUM($C59:G59) | H64: =SUM($C59:H59) | I64: =SUM($C59:I59) | J64: =SUM($C59:J59) | ... BV64: =SUM($C59:BV59)
A65: cum trials ending | B65: EUROPE|NITRO_A | C65: =SUM($C61:C61) | D65: =SUM($C61:D61) | E65: =SUM($C61:E61) | F65: =SUM($C61:F61) | G65: =SUM($C61:G61) | H65: =SUM($C61:H61) | I65: =SUM($C61:I61) | J65: =SUM($C61:J61) | ... BV65: =SUM($C61:BV61)
A66: trials active | B66: EUROPE|NITRO_A | C66: =C64-C65 | D66: =D64-D65 | E66: =E64-E65 | F66: =F64-F65 | G66: =G64-G65 | H66: =H64-H65 | I66: =I64-I65 | J66: =J64-J65 | ... BV66: =BV64-BV65
A67: paid starts | B67: EUROPE|NITRO_A | C67: =C60+C62 | D67: =D60+D62 | E67: =E60+E62 | F67: =F60+F62 | G67: =G60+G62 | H67: =H60+H62 | I67: =I60+I62 | J67: =J60+J62 | ... BV67: =BV60+BV62
A69: gross adds | B69: EUROPE|BASIC_M | C69: =MAU!C5*Params!$B$37*Params!$B$5*Params!$B$87*Params!$B$73 | D69: =MAU!D5*Params!$B$37*Params!$B$5*Params!$B$87*Params!$B$73 | E69: =MAU!E5*Params!$B$37*Params!$B$5*Params!$B$87*Params!$B$73 | F69: =MAU!F5*Params!$B$37*Params!$B$5*Params!$B$87*Params!$B$73 | G69: =MAU!G5*Params!$B$37*Params!$B$5*Params!$B$87*Params!$B$73 | H69: =MAU!H5*Params!$B$37*Params!$B$5*Params!$B$87*Params!$B$73 | I69: =MAU!I5*Params!$B$37*Params!$B$5*Params!$B$87*Params!$B$73 | J69: =MAU!J5*Params!$B$37*Params!$B$5*Params!$B$87*Params!$B$73 | ... BV69: =MAU!BV5*Params!$B$37*Params!$B$5*Params!$B$87*Params!$B$73
A70: trial starts | B70: EUROPE|BASIC_M | C70: =C69*Params!$B$6 | D70: =D69*Params!$B$6 | E70: =E69*Params!$B$6 | F70: =F69*Params!$B$6 | G70: =G69*Params!$B$6 | H70: =H69*Params!$B$6 | I70: =I69*Params!$B$6 | J70: =J69*Params!$B$6 | ... BV70: =BV69*Params!$B$6
A71: direct paid starts | B71: EUROPE|BASIC_M | C71: =C69-C70 | D71: =D69-D70 | E71: =E69-E70 | F71: =F69-F70 | G71: =G69-G70 | H71: =H69-H70 | I71: =I69-I70 | J71: =J69-J70 | ... BV71: =BV69-BV70
A72: trials ending | B72: EUROPE|BASIC_M | C72: =IF(C$2>=Params!$B$7,INDEX($C$70:$BV$70,C$2-Params!$B$7+1),0) | D72: =IF(D$2>=Params!$B$7,INDEX($C$70:$BV$70,D$2-Params!$B$7+1),0) | E72: =IF(E$2>=Params!$B$7,INDEX($C$70:$BV$70,E$2-Params!$B$7+1),0) | F72: =IF(F$2>=Params!$B$7,INDEX($C$70:$BV$70,F$2-Params!$B$7+1),0) | G72: =IF(G$2>=Params!$B$7,INDEX($C$70:$BV$70,G$2-Params!$B$7+1),0) | H72: =IF(H$2>=Params!$B$7,INDEX($C$70:$BV$70,H$2-Params!$B$7+1),0) | I72: =IF(I$2>=Params!$B$7,INDEX($C$70:$BV$70,I$2-Params!$B$7+1),0) | J72: =IF(J$2>=Params!$B$7,INDEX($C$70:$BV$70,J$2-Params!$B$7+1),0) | ... BV72: =IF(BV$2>=Params!$B$7,INDEX($C$70:$BV$70,BV$2-Params!$B$7+1),0)
A73: trials converted | B73: EUROPE|BASIC_M | C73: =C72*Params!$B$8 | D73: =D72*Params!$B$8 | E73: =E72*Params!$B$8 | F73: =F72*Params!$B$8 | G73: =G72*Params!$B$8 | H73: =H72*Params!$B$8 | I73: =I72*Params!$B$8 | J73: =J72*Params!$B$8 | ... BV73: =BV72*Params!$B$8
A74: trials lost | B74: EUROPE|BASIC_M | C74: =C72-C73 | D74: =D72-D73 | E74: =E72-E73 | F74: =F72-F73 | G74: =G72-G73 | H74: =H72-H73 | I74: =I72-I73 | J74: =J72-J73 | ... BV74: =BV72-BV73
A75: cum trial starts | B75: EUROPE|BASIC_M | C75: =SUM($C70:C70) | D75: =SUM($C70:D70) | E75: =SUM($C70:E70) | F75: =SUM($C70:F70) | G75: =SUM($C70:G70) | H75: =SUM($C70:H70) | I75: =SUM($C70:I70) | J75: =SUM($C70:J70) | ... BV75: =SUM($C70:BV70)
A76: cum trials ending | B76: EUROPE|BASIC_M | C76: =SUM($C72:C72) | D76: =SUM($C72:D72) | E76: =SUM($C72:E72) | F76: =SUM($C72:F72) | G76: =SUM($C72:G72) | H76: =SUM($C72:H72) | I76: =SUM($C72:I72) | J76: =SUM($C72:J72) | ... BV76: =SUM($C72:BV72)
A77: trials active | B77: EUROPE|BASIC_M | C77: =C75-C76 | D77: =D75-D76 | E77: =E75-E76 | F77: =F75-F76 | G77: =G75-G76 | H77: =H75-H76 | I77: =I75-I76 | J77: =J75-J76 | ... BV77: =BV75-BV76
A78: paid starts | B78: EUROPE|BASIC_M | C78: =C71+C73 | D78: =D71+D73 | E78: =E71+E73 | F78: =F71+F73 | G78: =G71+G73 | H78: =H71+H73 | I78: =I71+I73 | J78: =J71+J73 | ... BV78: =BV71+BV73
A80: gross adds | B80: EUROPE|BASIC_A | C80: =MAU!C5*Params!$B$37*Params!$B$5*Params!$B$87*Params!$B$74 | D80: =MAU!D5*Params!$B$37*Params!$B$5*Params!$B$87*Params!$B$74 | E80: =MAU!E5*Params!$B$37*Params!$B$5*Params!$B$87*Params!$B$74 | F80: =MAU!F5*Params!$B$37*Params!$B$5*Params!$B$87*Params!$B$74 | G80: =MAU!G5*Params!$B$37*Params!$B$5*Params!$B$87*Params!$B$74 | H80: =MAU!H5*Params!$B$37*Params!$B$5*Params!$B$87*Params!$B$74 | I80: =MAU!I5*Params!$B$37*Params!$B$5*Params!$B$87*Params!$B$74 | J80: =MAU!J5*Params!$B$37*Params!$B$5*Params!$B$87*Params!$B$74 | ... BV80: =MAU!BV5*Params!$B$37*Params!$B$5*Params!$B$87*Params!$B$74
A81: trial starts | B81: EUROPE|BASIC_A | C81: =C80*Params!$B$6 | D81: =D80*Params!$B$6 | E81: =E80*Params!$B$6 | F81: =F80*Params!$B$6 | G81: =G80*Params!$B$6 | H81: =H80*Params!$B$6 | I81: =I80*Params!$B$6 | J81: =J80*Params!$B$6 | ... BV81: =BV80*Params!$B$6
A82: direct paid starts | B82: EUROPE|BASIC_A | C82: =C80-C81 | D82: =D80-D81 | E82: =E80-E81 | F82: =F80-F81 | G82: =G80-G81 | H82: =H80-H81 | I82: =I80-I81 | J82: =J80-J81 | ... BV82: =BV80-BV81
A83: trials ending | B83: EUROPE|BASIC_A | C83: =IF(C$2>=Params!$B$7,INDEX($C$81:$BV$81,C$2-Params!$B$7+1),0) | D83: =IF(D$2>=Params!$B$7,INDEX($C$81:$BV$81,D$2-Params!$B$7+1),0) | E83: =IF(E$2>=Params!$B$7,INDEX($C$81:$BV$81,E$2-Params!$B$7+1),0) | F83: =IF(F$2>=Params!$B$7,INDEX($C$81:$BV$81,F$2-Params!$B$7+1),0) | G83: =IF(G$2>=Params!$B$7,INDEX($C$81:$BV$81,G$2-Params!$B$7+1),0) | H83: =IF(H$2>=Params!$B$7,INDEX($C$81:$BV$81,H$2-Params!$B$7+1),0) | I83: =IF(I$2>=Params!$B$7,INDEX($C$81:$BV$81,I$2-Params!$B$7+1),0) | J83: =IF(J$2>=Params!$B$7,INDEX($C$81:$BV$81,J$2-Params!$B$7+1),0) | ... BV83: =IF(BV$2>=Params!$B$7,INDEX($C$81:$BV$81,BV$2-Params!$B$7+1),0)
A84: trials converted | B84: EUROPE|BASIC_A | C84: =C83*Params!$B$8 | D84: =D83*Params!$B$8 | E84: =E83*Params!$B$8 | F84: =F83*Params!$B$8 | G84: =G83*Params!$B$8 | H84: =H83*Params!$B$8 | I84: =I83*Params!$B$8 | J84: =J83*Params!$B$8 | ... BV84: =BV83*Params!$B$8
A85: trials lost | B85: EUROPE|BASIC_A | C85: =C83-C84 | D85: =D83-D84 | E85: =E83-E84 | F85: =F83-F84 | G85: =G83-G84 | H85: =H83-H84 | I85: =I83-I84 | J85: =J83-J84 | ... BV85: =BV83-BV84
A86: cum trial starts | B86: EUROPE|BASIC_A | C86: =SUM($C81:C81) | D86: =SUM($C81:D81) | E86: =SUM($C81:E81) | F86: =SUM($C81:F81) | G86: =SUM($C81:G81) | H86: =SUM($C81:H81) | I86: =SUM($C81:I81) | J86: =SUM($C81:J81) | ... BV86: =SUM($C81:BV81)
A87: cum trials ending | B87: EUROPE|BASIC_A | C87: =SUM($C83:C83) | D87: =SUM($C83:D83) | E87: =SUM($C83:E83) | F87: =SUM($C83:F83) | G87: =SUM($C83:G83) | H87: =SUM($C83:H83) | I87: =SUM($C83:I83) | J87: =SUM($C83:J83) | ... BV87: =SUM($C83:BV83)
A88: trials active | B88: EUROPE|BASIC_A | C88: =C86-C87 | D88: =D86-D87 | E88: =E86-E87 | F88: =F86-F87 | G88: =G86-G87 | H88: =H86-H87 | I88: =I86-I87 | J88: =J86-J87 | ... BV88: =BV86-BV87
A89: paid starts | B89: EUROPE|BASIC_A | C89: =C82+C84 | D89: =D82+D84 | E89: =E82+E84 | F89: =F82+F84 | G89: =G82+G84 | H89: =H82+H84 | I89: =I82+I84 | J89: =J82+J84 | ... BV89: =BV82+BV84
A91: gross adds | B91: LATAM|NITRO_M | C91: =MAU!C6*Params!$B$38*Params!$B$5*Params!$B$87*Params!$B$71 | D91: =MAU!D6*Params!$B$38*Params!$B$5*Params!$B$87*Params!$B$71 | E91: =MAU!E6*Params!$B$38*Params!$B$5*Params!$B$87*Params!$B$71 | F91: =MAU!F6*Params!$B$38*Params!$B$5*Params!$B$87*Params!$B$71 | G91: =MAU!G6*Params!$B$38*Params!$B$5*Params!$B$87*Params!$B$71 | H91: =MAU!H6*Params!$B$38*Params!$B$5*Params!$B$87*Params!$B$71 | I91: =MAU!I6*Params!$B$38*Params!$B$5*Params!$B$87*Params!$B$71 | J91: =MAU!J6*Params!$B$38*Params!$B$5*Params!$B$87*Params!$B$71 | ... BV91: =MAU!BV6*Params!$B$38*Params!$B$5*Params!$B$87*Params!$B$71
A92: trial starts | B92: LATAM|NITRO_M | C92: =C91*Params!$B$6 | D92: =D91*Params!$B$6 | E92: =E91*Params!$B$6 | F92: =F91*Params!$B$6 | G92: =G91*Params!$B$6 | H92: =H91*Params!$B$6 | I92: =I91*Params!$B$6 | J92: =J91*Params!$B$6 | ... BV92: =BV91*Params!$B$6
A93: direct paid starts | B93: LATAM|NITRO_M | C93: =C91-C92 | D93: =D91-D92 | E93: =E91-E92 | F93: =F91-F92 | G93: =G91-G92 | H93: =H91-H92 | I93: =I91-I92 | J93: =J91-J92 | ... BV93: =BV91-BV92
A94: trials ending | B94: LATAM|NITRO_M | C94: =IF(C$2>=Params!$B$7,INDEX($C$92:$BV$92,C$2-Params!$B$7+1),0) | D94: =IF(D$2>=Params!$B$7,INDEX($C$92:$BV$92,D$2-Params!$B$7+1),0) | E94: =IF(E$2>=Params!$B$7,INDEX($C$92:$BV$92,E$2-Params!$B$7+1),0) | F94: =IF(F$2>=Params!$B$7,INDEX($C$92:$BV$92,F$2-Params!$B$7+1),0) | G94: =IF(G$2>=Params!$B$7,INDEX($C$92:$BV$92,G$2-Params!$B$7+1),0) | H94: =IF(H$2>=Params!$B$7,INDEX($C$92:$BV$92,H$2-Params!$B$7+1),0) | I94: =IF(I$2>=Params!$B$7,INDEX($C$92:$BV$92,I$2-Params!$B$7+1),0) | J94: =IF(J$2>=Params!$B$7,INDEX($C$92:$BV$92,J$2-Params!$B$7+1),0) | ... BV94: =IF(BV$2>=Params!$B$7,INDEX($C$92:$BV$92,BV$2-Params!$B$7+1),0)
A95: trials converted | B95: LATAM|NITRO_M | C95: =C94*Params!$B$8 | D95: =D94*Params!$B$8 | E95: =E94*Params!$B$8 | F95: =F94*Params!$B$8 | G95: =G94*Params!$B$8 | H95: =H94*Params!$B$8 | I95: =I94*Params!$B$8 | J95: =J94*Params!$B$8 | ... BV95: =BV94*Params!$B$8
A96: trials lost | B96: LATAM|NITRO_M | C96: =C94-C95 | D96: =D94-D95 | E96: =E94-E95 | F96: =F94-F95 | G96: =G94-G95 | H96: =H94-H95 | I96: =I94-I95 | J96: =J94-J95 | ... BV96: =BV94-BV95
A97: cum trial starts | B97: LATAM|NITRO_M | C97: =SUM($C92:C92) | D97: =SUM($C92:D92) | E97: =SUM($C92:E92) | F97: =SUM($C92:F92) | G97: =SUM($C92:G92) | H97: =SUM($C92:H92) | I97: =SUM($C92:I92) | J97: =SUM($C92:J92) | ... BV97: =SUM($C92:BV92)
A98: cum trials ending | B98: LATAM|NITRO_M | C98: =SUM($C94:C94) | D98: =SUM($C94:D94) | E98: =SUM($C94:E94) | F98: =SUM($C94:F94) | G98: =SUM($C94:G94) | H98: =SUM($C94:H94) | I98: =SUM($C94:I94) | J98: =SUM($C94:J94) | ... BV98: =SUM($C94:BV94)
A99: trials active | B99: LATAM|NITRO_M | C99: =C97-C98 | D99: =D97-D98 | E99: =E97-E98 | F99: =F97-F98 | G99: =G97-G98 | H99: =H97-H98 | I99: =I97-I98 | J99: =J97-J98 | ... BV99: =BV97-BV98
A100: paid starts | B100: LATAM|NITRO_M | C100: =C93+C95 | D100: =D93+D95 | E100: =E93+E95 | F100: =F93+F95 | G100: =G93+G95 | H100: =H93+H95 | I100: =I93+I95 | J100: =J93+J95 | ... BV100: =BV93+BV95
A102: gross adds | B102: LATAM|NITRO_A | C102: =MAU!C6*Params!$B$38*Params!$B$5*Params!$B$87*Params!$B$72 | D102: =MAU!D6*Params!$B$38*Params!$B$5*Params!$B$87*Params!$B$72 | E102: =MAU!E6*Params!$B$38*Params!$B$5*Params!$B$87*Params!$B$72 | F102: =MAU!F6*Params!$B$38*Params!$B$5*Params!$B$87*Params!$B$72 | G102: =MAU!G6*Params!$B$38*Params!$B$5*Params!$B$87*Params!$B$72 | H102: =MAU!H6*Params!$B$38*Params!$B$5*Params!$B$87*Params!$B$72 | I102: =MAU!I6*Params!$B$38*Params!$B$5*Params!$B$87*Params!$B$72 | J102: =MAU!J6*Params!$B$38*Params!$B$5*Params!$B$87*Params!$B$72 | ... BV102: =MAU!BV6*Params!$B$38*Params!$B$5*Params!$B$87*Params!$B$72
A103: trial starts | B103: LATAM|NITRO_A | C103: =C102*Params!$B$6 | D103: =D102*Params!$B$6 | E103: =E102*Params!$B$6 | F103: =F102*Params!$B$6 | G103: =G102*Params!$B$6 | H103: =H102*Params!$B$6 | I103: =I102*Params!$B$6 | J103: =J102*Params!$B$6 | ... BV103: =BV102*Params!$B$6
A104: direct paid starts | B104: LATAM|NITRO_A | C104: =C102-C103 | D104: =D102-D103 | E104: =E102-E103 | F104: =F102-F103 | G104: =G102-G103 | H104: =H102-H103 | I104: =I102-I103 | J104: =J102-J103 | ... BV104: =BV102-BV103
A105: trials ending | B105: LATAM|NITRO_A | C105: =IF(C$2>=Params!$B$7,INDEX($C$103:$BV$103,C$2-Params!$B$7+1),0) | D105: =IF(D$2>=Params!$B$7,INDEX($C$103:$BV$103,D$2-Params!$B$7+1),0) | E105: =IF(E$2>=Params!$B$7,INDEX($C$103:$BV$103,E$2-Params!$B$7+1),0) | F105: =IF(F$2>=Params!$B$7,INDEX($C$103:$BV$103,F$2-Params!$B$7+1),0) | G105: =IF(G$2>=Params!$B$7,INDEX($C$103:$BV$103,G$2-Params!$B$7+1),0) | H105: =IF(H$2>=Params!$B$7,INDEX($C$103:$BV$103,H$2-Params!$B$7+1),0) | I105: =IF(I$2>=Params!$B$7,INDEX($C$103:$BV$103,I$2-Params!$B$7+1),0) | J105: =IF(J$2>=Params!$B$7,INDEX($C$103:$BV$103,J$2-Params!$B$7+1),0) | ... BV105: =IF(BV$2>=Params!$B$7,INDEX($C$103:$BV$103,BV$2-Params!$B$7+1),0)
A106: trials converted | B106: LATAM|NITRO_A | C106: =C105*Params!$B$8 | D106: =D105*Params!$B$8 | E106: =E105*Params!$B$8 | F106: =F105*Params!$B$8 | G106: =G105*Params!$B$8 | H106: =H105*Params!$B$8 | I106: =I105*Params!$B$8 | J106: =J105*Params!$B$8 | ... BV106: =BV105*Params!$B$8
A107: trials lost | B107: LATAM|NITRO_A | C107: =C105-C106 | D107: =D105-D106 | E107: =E105-E106 | F107: =F105-F106 | G107: =G105-G106 | H107: =H105-H106 | I107: =I105-I106 | J107: =J105-J106 | ... BV107: =BV105-BV106
A108: cum trial starts | B108: LATAM|NITRO_A | C108: =SUM($C103:C103) | D108: =SUM($C103:D103) | E108: =SUM($C103:E103) | F108: =SUM($C103:F103) | G108: =SUM($C103:G103) | H108: =SUM($C103:H103) | I108: =SUM($C103:I103) | J108: =SUM($C103:J103) | ... BV108: =SUM($C103:BV103)
A109: cum trials ending | B109: LATAM|NITRO_A | C109: =SUM($C105:C105) | D109: =SUM($C105:D105) | E109: =SUM($C105:E105) | F109: =SUM($C105:F105) | G109: =SUM($C105:G105) | H109: =SUM($C105:H105) | I109: =SUM($C105:I105) | J109: =SUM($C105:J105) | ... BV109: =SUM($C105:BV105)
...

Sheet Paid
A1: line | B1: segment | C1: 2025-01 | D1: 2025-02 | E1: 2025-03 | F1: 2025-04 | G1: 2025-05 | H1: 2025-06 | I1: 2025-07 | J1: 2025-08 | K1: 2025-09 | L1: 2025-10 | M1: 2025-11 | N1: 2025-12 | O1: 2026-01 | P1: 2026-02 | Q1: 2026-03 | R1: 2026-04 | S1: 2026-05 | T1: 2026-06 | U1: 2026-07 | V1: 2026-08 | W1: 2026-09 | X1: 2026-10 | Y1: 2026-11 | Z1: 2026-12 | AA1: 2027-01 | AB1: 2027-02 | AC1: 2027-03 | AD1: 2027-04 | AE1: 2027-05 | AF1: 2027-06 | AG1: 2027-07 | AH1: 2027-08 | AI1: 2027-09 | AJ1: 2027-10 | AK1: 2027-11 | AL1: 2027-12 | AM1: 2028-01 | AN1: 2028-02 | AO1: 2028-03 | AP1: 2028-04 | AQ1: 2028-05 | AR1: 2028-06 | AS1: 2028-07 | AT1: 2028-08 | AU1: 2028-09 | AV1: 2028-10 | AW1: 2028-11 | AX1: 2028-12 | AY1: 2029-01 | AZ1: 2029-02 | BA1: 2029-03 | BB1: 2029-04 | BC1: 2029-05 | BD1: 2029-06 | BE1: 2029-07 | BF1: 2029-08 | BG1: 2029-09 | BH1: 2029-10 | BI1: 2029-11 | BJ1: 2029-12 | BK1: 2030-01 | BL1: 2030-02 | BM1: 2030-03 | BN1: 2030-04 | BO1: 2030-05 | BP1: 2030-06 | BQ1: 2030-07 | BR1: 2030-08 | BS1: 2030-09 | BT1: 2030-10 | BU1: 2030-11 | BV1: 2030-12
A2: month index (0 = Jan 2025) | C2: 0 | D2: 1 | E2: 2 | F2: 3 | G2: 4 | H2: 5 | I2: 6 | J2: 7 | K2: 8 | L2: 9 | M2: 10 | N2: 11 | O2: 12 | P2: 13 | Q2: 14 | R2: 15 | S2: 16 | T2: 17 | U2: 18 | V2: 19 | W2: 20 | X2: 21 | Y2: 22 | Z2: 23 | AA2: 24 | AB2: 25 | AC2: 26 | AD2: 27 | AE2: 28 | AF2: 29 | AG2: 30 | AH2: 31 | AI2: 32 | AJ2: 33 | AK2: 34 | AL2: 35 | AM2: 36 | AN2: 37 | AO2: 38 | AP2: 39 | AQ2: 40 | AR2: 41 | AS2: 42 | AT2: 43 | AU2: 44 | AV2: 45 | AW2: 46 | AX2: 47 | AY2: 48 | AZ2: 49 | BA2: 50 | BB2: 51 | BC2: 52 | BD2: 53 | BE2: 54 | BF2: 55 | BG2: 56 | BH2: 57 | BI2: 58 | BJ2: 59 | BK2: 60 | BL2: 61 | BM2: 62 | BN2: 63 | BO2: 64 | BP2: 65 | BQ2: 66 | BR2: 67 | BS2: 68 | BT2: 69 | BU2: 70 | BV2: 71
A3: active | B3: US_CA|NITRO_M | C3: =Adds!$C$12*Curves!$BV$13 | D3: =SUMPRODUCT(Adds!$C$12:$D$12,Curves!$BU$13:$BV$13) | E3: =SUMPRODUCT(Adds!$C$12:$E$12,Curves!$BT$13:$BV$13) | F3: =SUMPRODUCT(Adds!$C$12:$F$12,Curves!$BS$13:$BV$13) | G3: =SUMPRODUCT(Adds!$C$12:$G$12,Curves!$BR$13:$BV$13) | H3: =SUMPRODUCT(Adds!$C$12:$H$12,Curves!$BQ$13:$BV$13) | I3: =SUMPRODUCT(Adds!$C$12:$I$12,Curves!$BP$13:$BV$13) | J3: =SUMPRODUCT(Adds!$C$12:$J$12,Curves!$BO$13:$BV$13) | K3: =SUMPRODUCT(Adds!$C$12:$K$12,Curves!$BN$13:$BV$13) | L3: =SUMPRODUCT(Adds!$C$12:$L$12,Curves!$BM$13:$BV$13) | M3: =SUMPRODUCT(Adds!$C$12:$M$12,Curves!$BL$13:$BV$13) | N3: =SUMPRODUCT(Adds!$C$12:$N$12,Curves!$BK$13:$BV$13) | O3: =SUMPRODUCT(Adds!$C$12:$O$12,Curves!$BJ$13:$BV$13) | P3: =SUMPRODUCT(Adds!$C$12:$P$12,Curves!$BI$13:$BV$13) | Q3: =SUMPRODUCT(Adds!$C$12:$Q$12,Curves!$BH$13:$BV$13) | R3: =SUMPRODUCT(Adds!$C$12:$R$12,Curves!$BG$13:$BV$13) | S3: =SUMPRODUCT(Adds!$C$12:$S$12,Curves!$BF$13:$BV$13) | T3: =SUMPRODUCT(Adds!$C$12:$T$12,Curves!$BE$13:$BV$13) | U3: =SUMPRODUCT(Adds!$C$12:$U$12,Curves!$BD$13:$BV$13) | V3: =SUMPRODUCT(Adds!$C$12:$V$12,Curves!$BC$13:$BV$13) | W3: =SUMPRODUCT(Adds!$C$12:$W$12,Curves!$BB$13:$BV$13) | X3: =SUMPRODUCT(Adds!$C$12:$X$12,Curves!$BA$13:$BV$13) | Y3: =SUMPRODUCT(Adds!$C$12:$Y$12,Curves!$AZ$13:$BV$13) | Z3: =SUMPRODUCT(Adds!$C$12:$Z$12,Curves!$AY$13:$BV$13) | AA3: =SUMPRODUCT(Adds!$C$12:$AA$12,Curves!$AX$13:$BV$13) | AB3: =SUMPRODUCT(Adds!$C$12:$AB$12,Curves!$AW$13:$BV$13) | AC3: =SUMPRODUCT(Adds!$C$12:$AC$12,Curves!$AV$13:$BV$13) | AD3: =SUMPRODUCT(Adds!$C$12:$AD$12,Curves!$AU$13:$BV$13) | AE3: =SUMPRODUCT(Adds!$C$12:$AE$12,Curves!$AT$13:$BV$13) | AF3: =SUMPRODUCT(Adds!$C$12:$AF$12,Curves!$AS$13:$BV$13) | AG3: =SUMPRODUCT(Adds!$C$12:$AG$12,Curves!$AR$13:$BV$13) | AH3: =SUMPRODUCT(Adds!$C$12:$AH$12,Curves!$AQ$13:$BV$13) | AI3: =SUMPRODUCT(Adds!$C$12:$AI$12,Curves!$AP$13:$BV$13) | AJ3: =SUMPRODUCT(Adds!$C$12:$AJ$12,Curves!$AO$13:$BV$13) | AK3: =SUMPRODUCT(Adds!$C$12:$AK$12,Curves!$AN$13:$BV$13) | AL3: =SUMPRODUCT(Adds!$C$12:$AL$12,Curves!$AM$13:$BV$13) | AM3: =SUMPRODUCT(Adds!$C$12:$AM$12,Curves!$AL$13:$BV$13) | AN3: =SUMPRODUCT(Adds!$C$12:$AN$12,Curves!$AK$13:$BV$13) | AO3: =SUMPRODUCT(Adds!$C$12:$AO$12,Curves!$AJ$13:$BV$13) | AP3: =SUMPRODUCT(Adds!$C$12:$AP$12,Curves!$AI$13:$BV$13) | AQ3: =SUMPRODUCT(Adds!$C$12:$AQ$12,Curves!$AH$13:$BV$13) | AR3: =SUMPRODUCT(Adds!$C$12:$AR$12,Curves!$AG$13:$BV$13) | AS3: =SUMPRODUCT(Adds!$C$12:$AS$12,Curves!$AF$13:$BV$13) | AT3: =SUMPRODUCT(Adds!$C$12:$AT$12,Curves!$AE$13:$BV$13) | AU3: =SUMPRODUCT(Adds!$C$12:$AU$12,Curves!$AD$13:$BV$13) | AV3: =SUMPRODUCT(Adds!$C$12:$AV$12,Curves!$AC$13:$BV$13) | AW3: =SUMPRODUCT(Adds!$C$12:$AW$12,Curves!$AB$13:$BV$13) | AX3: =SUMPRODUCT(Adds!$C$12:$AX$12,Curves!$AA$13:$BV$13) | AY3: =SUMPRODUCT(Adds!$C$12:$AY$12,Curves!$Z$13:$BV$13) | AZ3: =SUMPRODUCT(Adds!$C$12:$AZ$12,Curves!$Y$13:$BV$13) | BA3: =SUMPRODUCT(Adds!$C$12:$BA$12,Curves!$X$13:$BV$13) | BB3: =SUMPRODUCT(Adds!$C$12:$BB$12,Curves!$W$13:$BV$13) | BC3: =SUMPRODUCT(Adds!$C$12:$BC$12,Curves!$V$13:$BV$13) | BD3: =SUMPRODUCT(Adds!$C$12:$BD$12,Curves!$U$13:$BV$13) | BE3: =SUMPRODUCT(Adds!$C$12:$BE$12,Curves!$T$13:$BV$13) | BF3: =SUMPRODUCT(Adds!$C$12:$BF$12,Curves!$S$13:$BV$13) | BG3: =SUMPRODUCT(Adds!$C$12:$BG$12,Curves!$R$13:$BV$13) | BH3: =SUMPRODUCT(Adds!$C$12:$BH$12,Curves!$Q$13:$BV$13) | BI3: =SUMPRODUCT(Adds!$C$12:$BI$12,Curves!$P$13:$BV$13) | BJ3: =SUMPRODUCT(Adds!$C$12:$BJ$12,Curves!$O$13:$BV$13) | BK3: =SUMPRODUCT(Adds!$C$12:$BK$12,Curves!$N$13:$BV$13) | BL3: =SUMPRODUCT(Adds!$C$12:$BL$12,Curves!$M$13:$BV$13) | BM3: =SUMPRODUCT(Adds!$C$12:$BM$12,Curves!$L$13:$BV$13) | BN3: =SUMPRODUCT(Adds!$C$12:$BN$12,Curves!$K$13:$BV$13) | BO3: =SUMPRODUCT(Adds!$C$12:$BO$12,Curves!$J$13:$BV$13) | BP3: =SUMPRODUCT(Adds!$C$12:$BP$12,Curves!$I$13:$BV$13) | BQ3: =SUMPRODUCT(Adds!$C$12:$BQ$12,Curves!$H$13:$BV$13) | BR3: =SUMPRODUCT(Adds!$C$12:$BR$12,Curves!$G$13:$BV$13) | BS3: =SUMPRODUCT(Adds!$C$12:$BS$12,Curves!$F$13:$BV$13) | BT3: =SUMPRODUCT(Adds!$C$12:$BT$12,Curves!$E$13:$BV$13) | BU3: =SUMPRODUCT(Adds!$C$12:$BU$12,Curves!$D$13:$BV$13) | BV3: =SUMPRODUCT(Adds!$C$12:$BV$12,Curves!$C$13:$BV$13)
A4: active yr 1 | B4: US_CA|NITRO_M | C4: =Adds!$C$12*Curves!$BV$20 | D4: =SUMPRODUCT(Adds!$C$12:$D$12,Curves!$BU$20:$BV$20) | E4: =SUMPRODUCT(Adds!$C$12:$E$12,Curves!$BT$20:$BV$20) | F4: =SUMPRODUCT(Adds!$C$12:$F$12,Curves!$BS$20:$BV$20) | G4: =SUMPRODUCT(Adds!$C$12:$G$12,Curves!$BR$20:$BV$20) | H4: =SUMPRODUCT(Adds!$C$12:$H$12,Curves!$BQ$20:$BV$20) | I4: =SUMPRODUCT(Adds!$C$12:$I$12,Curves!$BP$20:$BV$20) | J4: =SUMPRODUCT(Adds!$C$12:$J$12,Curves!$BO$20:$BV$20) | K4: =SUMPRODUCT(Adds!$C$12:$K$12,Curves!$BN$20:$BV$20) | L4: =SUMPRODUCT(Adds!$C$12:$L$12,Curves!$BM$20:$BV$20) | M4: =SUMPRODUCT(Adds!$C$12:$M$12,Curves!$BL$20:$BV$20) | N4: =SUMPRODUCT(Adds!$C$12:$N$12,Curves!$BK$20:$BV$20) | O4: =SUMPRODUCT(Adds!$C$12:$O$12,Curves!$BJ$20:$BV$20) | P4: =SUMPRODUCT(Adds!$C$12:$P$12,Curves!$BI$20:$BV$20) | Q4: =SUMPRODUCT(Adds!$C$12:$Q$12,Curves!$BH$20:$BV$20) | R4: =SUMPRODUCT(Adds!$C$12:$R$12,Curves!$BG$20:$BV$20) | S4: =SUMPRODUCT(Adds!$C$12:$S$12,Curves!$BF$20:$BV$20) | T4: =SUMPRODUCT(Adds!$C$12:$T$12,Curves!$BE$20:$BV$20) | U4: =SUMPRODUCT(Adds!$C$12:$U$12,Curves!$BD$20:$BV$20) | V4: =SUMPRODUCT(Adds!$C$12:$V$12,Curves!$BC$20:$BV$20) | W4: =SUMPRODUCT(Adds!$C$12:$W$12,Curves!$BB$20:$BV$20) | X4: =SUMPRODUCT(Adds!$C$12:$X$12,Curves!$BA$20:$BV$20) | Y4: =SUMPRODUCT(Adds!$C$12:$Y$12,Curves!$AZ$20:$BV$20) | Z4: =SUMPRODUCT(Adds!$C$12:$Z$12,Curves!$AY$20:$BV$20) | AA4: =SUMPRODUCT(Adds!$C$12:$AA$12,Curves!$AX$20:$BV$20) | AB4: =SUMPRODUCT(Adds!$C$12:$AB$12,Curves!$AW$20:$BV$20) | AC4: =SUMPRODUCT(Adds!$C$12:$AC$12,Curves!$AV$20:$BV$20) | AD4: =SUMPRODUCT(Adds!$C$12:$AD$12,Curves!$AU$20:$BV$20) | AE4: =SUMPRODUCT(Adds!$C$12:$AE$12,Curves!$AT$20:$BV$20) | AF4: =SUMPRODUCT(Adds!$C$12:$AF$12,Curves!$AS$20:$BV$20) | AG4: =SUMPRODUCT(Adds!$C$12:$AG$12,Curves!$AR$20:$BV$20) | AH4: =SUMPRODUCT(Adds!$C$12:$AH$12,Curves!$AQ$20:$BV$20) | AI4: =SUMPRODUCT(Adds!$C$12:$AI$12,Curves!$AP$20:$BV$20) | AJ4: =SUMPRODUCT(Adds!$C$12:$AJ$12,Curves!$AO$20:$BV$20) | AK4: =SUMPRODUCT(Adds!$C$12:$AK$12,Curves!$AN$20:$BV$20) | AL4: =SUMPRODUCT(Adds!$C$12:$AL$12,Curves!$AM$20:$BV$20) | AM4: =SUMPRODUCT(Adds!$C$12:$AM$12,Curves!$AL$20:$BV$20) | AN4: =SUMPRODUCT(Adds!$C$12:$AN$12,Curves!$AK$20:$BV$20) | AO4: =SUMPRODUCT(Adds!$C$12:$AO$12,Curves!$AJ$20:$BV$20) | AP4: =SUMPRODUCT(Adds!$C$12:$AP$12,Curves!$AI$20:$BV$20) | AQ4: =SUMPRODUCT(Adds!$C$12:$AQ$12,Curves!$AH$20:$BV$20) | AR4: =SUMPRODUCT(Adds!$C$12:$AR$12,Curves!$AG$20:$BV$20) | AS4: =SUMPRODUCT(Adds!$C$12:$AS$12,Curves!$AF$20:$BV$20) | AT4: =SUMPRODUCT(Adds!$C$12:$AT$12,Curves!$AE$20:$BV$20) | AU4: =SUMPRODUCT(Adds!$C$12:$AU$12,Curves!$AD$20:$BV$20) | AV4: =SUMPRODUCT(Adds!$C$12:$AV$12,Curves!$AC$20:$BV$20) | AW4: =SUMPRODUCT(Adds!$C$12:$AW$12,Curves!$AB$20:$BV$20) | AX4: =SUMPRODUCT(Adds!$C$12:$AX$12,Curves!$AA$20:$BV$20) | AY4: =SUMPRODUCT(Adds!$C$12:$AY$12,Curves!$Z$20:$BV$20) | AZ4: =SUMPRODUCT(Adds!$C$12:$AZ$12,Curves!$Y$20:$BV$20) | BA4: =SUMPRODUCT(Adds!$C$12:$BA$12,Curves!$X$20:$BV$20) | BB4: =SUMPRODUCT(Adds!$C$12:$BB$12,Curves!$W$20:$BV$20) | BC4: =SUMPRODUCT(Adds!$C$12:$BC$12,Curves!$V$20:$BV$20) | BD4: =SUMPRODUCT(Adds!$C$12:$BD$12,Curves!$U$20:$BV$20) | BE4: =SUMPRODUCT(Adds!$C$12:$BE$12,Curves!$T$20:$BV$20) | BF4: =SUMPRODUCT(Adds!$C$12:$BF$12,Curves!$S$20:$BV$20) | BG4: =SUMPRODUCT(Adds!$C$12:$BG$12,Curves!$R$20:$BV$20) | BH4: =SUMPRODUCT(Adds!$C$12:$BH$12,Curves!$Q$20:$BV$20) | BI4: =SUMPRODUCT(Adds!$C$12:$BI$12,Curves!$P$20:$BV$20) | BJ4: =SUMPRODUCT(Adds!$C$12:$BJ$12,Curves!$O$20:$BV$20) | BK4: =SUMPRODUCT(Adds!$C$12:$BK$12,Curves!$N$20:$BV$20) | BL4: =SUMPRODUCT(Adds!$C$12:$BL$12,Curves!$M$20:$BV$20) | BM4: =SUMPRODUCT(Adds!$C$12:$BM$12,Curves!$L$20:$BV$20) | BN4: =SUMPRODUCT(Adds!$C$12:$BN$12,Curves!$K$20:$BV$20) | BO4: =SUMPRODUCT(Adds!$C$12:$BO$12,Curves!$J$20:$BV$20) | BP4: =SUMPRODUCT(Adds!$C$12:$BP$12,Curves!$I$20:$BV$20) | BQ4: =SUMPRODUCT(Adds!$C$12:$BQ$12,Curves!$H$20:$BV$20) | BR4: =SUMPRODUCT(Adds!$C$12:$BR$12,Curves!$G$20:$BV$20) | BS4: =SUMPRODUCT(Adds!$C$12:$BS$12,Curves!$F$20:$BV$20) | BT4: =SUMPRODUCT(Adds!$C$12:$BT$12,Curves!$E$20:$BV$20) | BU4: =SUMPRODUCT(Adds!$C$12:$BU$12,Curves!$D$20:$BV$20) | BV4: =SUMPRODUCT(Adds!$C$12:$BV$12,Curves!$C$20:$BV$20)
A5: churned | B5: US_CA|NITRO_M | C5: =Adds!$C$12*Curves!$BV$15 | D5: =SUMPRODUCT(Adds!$C$12:$D$12,Curves!$BU$15:$BV$15) | E5: =SUMPRODUCT(Adds!$C$12:$E$12,Curves!$BT$15:$BV$15) | F5: =SUMPRODUCT(Adds!$C$12:$F$12,Curves!$BS$15:$BV$15) | G5: =SUMPRODUCT(Adds!$C$12:$G$12,Curves!$BR$15:$BV$15) | H5: =SUMPRODUCT(Adds!$C$12:$H$12,Curves!$BQ$15:$BV$15) | I5: =SUMPRODUCT(Adds!$C$12:$I$12,Curves!$BP$15:$BV$15) | J5: =SUMPRODUCT(Adds!$C$12:$J$12,Curves!$BO$15:$BV$15) | K5: =SUMPRODUCT(Adds!$C$12:$K$12,Curves!$BN$15:$BV$15) | L5: =SUMPRODUCT(Adds!$C$12:$L$12,Curves!$BM$15:$BV$15) | M5: =SUMPRODUCT(Adds!$C$12:$M$12,Curves!$BL$15:$BV$15) | N5: =SUMPRODUCT(Adds!$C$12:$N$12,Curves!$BK$15:$BV$15) | O5: =SUMPRODUCT(Adds!$C$12:$O$12,Curves!$BJ$15:$BV$15) | P5: =SUMPRODUCT(Adds!$C$12:$P$12,Curves!$BI$15:$BV$15) | Q5: =SUMPRODUCT(Adds!$C$12:$Q$12,Curves!$BH$15:$BV$15) | R5: =SUMPRODUCT(Adds!$C$12:$R$12,Curves!$BG$15:$BV$15) | S5: =SUMPRODUCT(Adds!$C$12:$S$12,Curves!$BF$15:$BV$15) | T5: =SUMPRODUCT(Adds!$C$12:$T$12,Curves!$BE$15:$BV$15) | U5: =SUMPRODUCT(Adds!$C$12:$U$12,Curves!$BD$15:$BV$15) | V5: =SUMPRODUCT(Adds!$C$12:$V$12,Curves!$BC$15:$BV$15) | W5: =SUMPRODUCT(Adds!$C$12:$W$12,Curves!$BB$15:$BV$15) | X5: =SUMPRODUCT(Adds!$C$12:$X$12,Curves!$BA$15:$BV$15) | Y5: =SUMPRODUCT(Adds!$C$12:$Y$12,Curves!$AZ$15:$BV$15) | Z5: =SUMPRODUCT(Adds!$C$12:$Z$12,Curves!$AY$15:$BV$15) | AA5: =SUMPRODUCT(Adds!$C$12:$AA$12,Curves!$AX$15:$BV$15) | AB5: =SUMPRODUCT(Adds!$C$12:$AB$12,Curves!$AW$15:$BV$15) | AC5: =SUMPRODUCT(Adds!$C$12:$AC$12,Curves!$AV$15:$BV$15) | AD5: =SUMPRODUCT(Adds!$C$12:$AD$12,Curves!$AU$15:$BV$15) | AE5: =SUMPRODUCT(Adds!$C$12:$AE$12,Curves!$AT$15:$BV$15) | AF5: =SUMPRODUCT(Adds!$C$12:$AF$12,Curves!$AS$15:$BV$15) | AG5: =SUMPRODUCT(Adds!$C$12:$AG$12,Curves!$AR$15:$BV$15) | AH5: =SUMPRODUCT(Adds!$C$12:$AH$12,Curves!$AQ$15:$BV$15) | AI5: =SUMPRODUCT(Adds!$C$12:$AI$12,Curves!$AP$15:$BV$15) | AJ5: =SUMPRODUCT(Adds!$C$12:$AJ$12,Curves!$AO$15:$BV$15) | AK5: =SUMPRODUCT(Adds!$C$12:$AK$12,Curves!$AN$15:$BV$15) | AL5: =SUMPRODUCT(Adds!$C$12:$AL$12,Curves!$AM$15:$BV$15) | AM5: =SUMPRODUCT(Adds!$C$12:$AM$12,Curves!$AL$15:$BV$15) | AN5: =SUMPRODUCT(Adds!$C$12:$AN$12,Curves!$AK$15:$BV$15) | AO5: =SUMPRODUCT(Adds!$C$12:$AO$12,Curves!$AJ$15:$BV$15) | AP5: =SUMPRODUCT(Adds!$C$12:$AP$12,Curves!$AI$15:$BV$15) | AQ5: =SUMPRODUCT(Adds!$C$12:$AQ$12,Curves!$AH$15:$BV$15) | AR5: =SUMPRODUCT(Adds!$C$12:$AR$12,Curves!$AG$15:$BV$15) | AS5: =SUMPRODUCT(Adds!$C$12:$AS$12,Curves!$AF$15:$BV$15) | AT5: =SUMPRODUCT(Adds!$C$12:$AT$12,Curves!$AE$15:$BV$15) | AU5: =SUMPRODUCT(Adds!$C$12:$AU$12,Curves!$AD$15:$BV$15) | AV5: =SUMPRODUCT(Adds!$C$12:$AV$12,Curves!$AC$15:$BV$15) | AW5: =SUMPRODUCT(Adds!$C$12:$AW$12,Curves!$AB$15:$BV$15) | AX5: =SUMPRODUCT(Adds!$C$12:$AX$12,Curves!$AA$15:$BV$15) | AY5: =SUMPRODUCT(Adds!$C$12:$AY$12,Curves!$Z$15:$BV$15) | AZ5: =SUMPRODUCT(Adds!$C$12:$AZ$12,Curves!$Y$15:$BV$15) | BA5: =SUMPRODUCT(Adds!$C$12:$BA$12,Curves!$X$15:$BV$15) | BB5: =SUMPRODUCT(Adds!$C$12:$BB$12,Curves!$W$15:$BV$15) | BC5: =SUMPRODUCT(Adds!$C$12:$BC$12,Curves!$V$15:$BV$15) | BD5: =SUMPRODUCT(Adds!$C$12:$BD$12,Curves!$U$15:$BV$15) | BE5: =SUMPRODUCT(Adds!$C$12:$BE$12,Curves!$T$15:$BV$15) | BF5: =SUMPRODUCT(Adds!$C$12:$BF$12,Curves!$S$15:$BV$15) | BG5: =SUMPRODUCT(Adds!$C$12:$BG$12,Curves!$R$15:$BV$15) | BH5: =SUMPRODUCT(Adds!$C$12:$BH$12,Curves!$Q$15:$BV$15) | BI5: =SUMPRODUCT(Adds!$C$12:$BI$12,Curves!$P$15:$BV$15) | BJ5: =SUMPRODUCT(Adds!$C$12:$BJ$12,Curves!$O$15:$BV$15) | BK5: =SUMPRODUCT(Adds!$C$12:$BK$12,Curves!$N$15:$BV$15) | BL5: =SUMPRODUCT(Adds!$C$12:$BL$12,Curves!$M$15:$BV$15) | BM5: =SUMPRODUCT(Adds!$C$12:$BM$12,Curves!$L$15:$BV$15) | BN5: =SUMPRODUCT(Adds!$C$12:$BN$12,Curves!$K$15:$BV$15) | BO5: =SUMPRODUCT(Adds!$C$12:$BO$12,Curves!$J$15:$BV$15) | BP5: =SUMPRODUCT(Adds!$C$12:$BP$12,Curves!$I$15:$BV$15) | BQ5: =SUMPRODUCT(Adds!$C$12:$BQ$12,Curves!$H$15:$BV$15) | BR5: =SUMPRODUCT(Adds!$C$12:$BR$12,Curves!$G$15:$BV$15) | BS5: =SUMPRODUCT(Adds!$C$12:$BS$12,Curves!$F$15:$BV$15) | BT5: =SUMPRODUCT(Adds!$C$12:$BT$12,Curves!$E$15:$BV$15) | BU5: =SUMPRODUCT(Adds!$C$12:$BU$12,Curves!$D$15:$BV$15) | BV5: =SUMPRODUCT(Adds!$C$12:$BV$12,Curves!$C$15:$BV$15)
A7: active | B7: US_CA|NITRO_A | C7: =Adds!$C$23*Curves!$BV$14 | D7: =SUMPRODUCT(Adds!$C$23:$D$23,Curves!$BU$14:$BV$14) | E7: =SUMPRODUCT(Adds!$C$23:$E$23,Curves!$BT$14:$BV$14) | F7: =SUMPRODUCT(Adds!$C$23:$F$23,Curves!$BS$14:$BV$14) | G7: =SUMPRODUCT(Adds!$C$23:$G$23,Curves!$BR$14:$BV$14) | H7: =SUMPRODUCT(Adds!$C$23:$H$23,Curves!$BQ$14:$BV$14) | I7: =SUMPRODUCT(Adds!$C$23:$I$23,Curves!$BP$14:$BV$14) | J7: =SUMPRODUCT(Adds!$C$23:$J$23,Curves!$BO$14:$BV$14) | K7: =SUMPRODUCT(Adds!$C$23:$K$23,Curves!$BN$14:$BV$14) | L7: =SUMPRODUCT(Adds!$C$23:$L$23,Curves!$BM$14:$BV$14) | M7: =SUMPRODUCT(Adds!$C$23:$M$23,Curves!$BL$14:$BV$14) | N7: =SUMPRODUCT(Adds!$C$23:$N$23,Curves!$BK$14:$BV$14) | O7: =SUMPRODUCT(Adds!$C$23:$O$23,Curves!$BJ$14:$BV$14) | P7: =SUMPRODUCT(Adds!$C$23:$P$23,Curves!$BI$14:$BV$14) | Q7: =SUMPRODUCT(Adds!$C$23:$Q$23,Curves!$BH$14:$BV$14) | R7: =SUMPRODUCT(Adds!$C$23:$R$23,Curves!$BG$14:$BV$14) | S7: =SUMPRODUCT(Adds!$C$23:$S$23,Curves!$BF$14:$BV$14) | T7: =SUMPRODUCT(Adds!$C$23:$T$23,Curves!$BE$14:$BV$14) | U7: =SUMPRODUCT(Adds!$C$23:$U$23,Curves!$BD$14:$BV$14) | V7: =SUMPRODUCT(Adds!$C$23:$V$23,Curves!$BC$14:$BV$14) | W7: =SUMPRODUCT(Adds!$C$23:$W$23,Curves!$BB$14:$BV$14) | X7: =SUMPRODUCT(Adds!$C$23:$X$23,Curves!$BA$14:$BV$14) | Y7: =SUMPRODUCT(Adds!$C$23:$Y$23,Curves!$AZ$14:$BV$14) | Z7: =SUMPRODUCT(Adds!$C$23:$Z$23,Curves!$AY$14:$BV$14) | AA7: =SUMPRODUCT(Adds!$C$23:$AA$23,Curves!$AX$14:$BV$14) | AB7: =SUMPRODUCT(Adds!$C$23:$AB$23,Curves!$AW$14:$BV$14) | AC7: =SUMPRODUCT(Adds!$C$23:$AC$23,Curves!$AV$14:$BV$14) | AD7: =SUMPRODUCT(Adds!$C$23:$AD$23,Curves!$AU$14:$BV$14) | AE7: =SUMPRODUCT(Adds!$C$23:$AE$23,Curves!$AT$14:$BV$14) | AF7: =SUMPRODUCT(Adds!$C$23:$AF$23,Curves!$AS$14:$BV$14) | AG7: =SUMPRODUCT(Adds!$C$23:$AG$23,Curves!$AR$14:$BV$14) | AH7: =SUMPRODUCT(Adds!$C$23:$AH$23,Curves!$AQ$14:$BV$14) | AI7: =SUMPRODUCT(Adds!$C$23:$AI$23,Curves!$AP$14:$BV$14) | AJ7: =SUMPRODUCT(Adds!$C$23:$AJ$23,Curves!$AO$14:$BV$14) | AK7: =SUMPRODUCT(Adds!$C$23:$AK$23,Curves!$AN$14:$BV$14) | AL7: =SUMPRODUCT(Adds!$C$23:$AL$23,Curves!$AM$14:$BV$14) | AM7: =SUMPRODUCT(Adds!$C$23:$AM$23,Curves!$AL$14:$BV$14) | AN7: =SUMPRODUCT(Adds!$C$23:$AN$23,Curves!$AK$14:$BV$14) | AO7: =SUMPRODUCT(Adds!$C$23:$AO$23,Curves!$AJ$14:$BV$14) | AP7: =SUMPRODUCT(Adds!$C$23:$AP$23,Curves!$AI$14:$BV$14) | AQ7: =SUMPRODUCT(Adds!$C$23:$AQ$23,Curves!$AH$14:$BV$14) | AR7: =SUMPRODUCT(Adds!$C$23:$AR$23,Curves!$AG$14:$BV$14) | AS7: =SUMPRODUCT(Adds!$C$23:$AS$23,Curves!$AF$14:$BV$14) | AT7: =SUMPRODUCT(Adds!$C$23:$AT$23,Curves!$AE$14:$BV$14) | AU7: =SUMPRODUCT(Adds!$C$23:$AU$23,Curves!$AD$14:$BV$14) | AV7: =SUMPRODUCT(Adds!$C$23:$AV$23,Curves!$AC$14:$BV$14) | AW7: =SUMPRODUCT(Adds!$C$23:$AW$23,Curves!$AB$14:$BV$14) | AX7: =SUMPRODUCT(Adds!$C$23:$AX$23,Curves!$AA$14:$BV$14) | AY7: =SUMPRODUCT(Adds!$C$23:$AY$23,Curves!$Z$14:$BV$14) | AZ7: =SUMPRODUCT(Adds!$C$23:$AZ$23,Curves!$Y$14:$BV$14) | BA7: =SUMPRODUCT(Adds!$C$23:$BA$23,Curves!$X$14:$BV$14) | BB7: =SUMPRODUCT(Adds!$C$23:$BB$23,Curves!$W$14:$BV$14) | BC7: =SUMPRODUCT(Adds!$C$23:$BC$23,Curves!$V$14:$BV$14) | BD7: =SUMPRODUCT(Adds!$C$23:$BD$23,Curves!$U$14:$BV$14) | BE7: =SUMPRODUCT(Adds!$C$23:$BE$23,Curves!$T$14:$BV$14) | BF7: =SUMPRODUCT(Adds!$C$23:$BF$23,Curves!$S$14:$BV$14) | BG7: =SUMPRODUCT(Adds!$C$23:$BG$23,Curves!$R$14:$BV$14) | BH7: =SUMPRODUCT(Adds!$C$23:$BH$23,Curves!$Q$14:$BV$14) | BI7: =SUMPRODUCT(Adds!$C$23:$BI$23,Curves!$P$14:$BV$14) | BJ7: =SUMPRODUCT(Adds!$C$23:$BJ$23,Curves!$O$14:$BV$14) | BK7: =SUMPRODUCT(Adds!$C$23:$BK$23,Curves!$N$14:$BV$14) | BL7: =SUMPRODUCT(Adds!$C$23:$BL$23,Curves!$M$14:$BV$14) | BM7: =SUMPRODUCT(Adds!$C$23:$BM$23,Curves!$L$14:$BV$14) | BN7: =SUMPRODUCT(Adds!$C$23:$BN$23,Curves!$K$14:$BV$14) | BO7: =SUMPRODUCT(Adds!$C$23:$BO$23,Curves!$J$14:$BV$14) | BP7: =SUMPRODUCT(Adds!$C$23:$BP$23,Curves!$I$14:$BV$14) | BQ7: =SUMPRODUCT(Adds!$C$23:$BQ$23,Curves!$H$14:$BV$14) | BR7: =SUMPRODUCT(Adds!$C$23:$BR$23,Curves!$G$14:$BV$14) | BS7: =SUMPRODUCT(Adds!$C$23:$BS$23,Curves!$F$14:$BV$14) | BT7: =SUMPRODUCT(Adds!$C$23:$BT$23,Curves!$E$14:$BV$14) | BU7: =SUMPRODUCT(Adds!$C$23:$BU$23,Curves!$D$14:$BV$14) | BV7: =SUMPRODUCT(Adds!$C$23:$BV$23,Curves!$C$14:$BV$14)
A8: active yr 1 | B8: US_CA|NITRO_A | C8: =Adds!$C$23*Curves!$BV$21 | D8: =SUMPRODUCT(Adds!$C$23:$D$23,Curves!$BU$21:$BV$21) | E8: =SUMPRODUCT(Adds!$C$23:$E$23,Curves!$BT$21:$BV$21) | F8: =SUMPRODUCT(Adds!$C$23:$F$23,Curves!$BS$21:$BV$21) | G8: =SUMPRODUCT(Adds!$C$23:$G$23,Curves!$BR$21:$BV$21) | H8: =SUMPRODUCT(Adds!$C$23:$H$23,Curves!$BQ$21:$BV$21) | I8: =SUMPRODUCT(Adds!$C$23:$I$23,Curves!$BP$21:$BV$21) | J8: =SUMPRODUCT(Adds!$C$23:$J$23,Curves!$BO$21:$BV$21) | K8: =SUMPRODUCT(Adds!$C$23:$K$23,Curves!$BN$21:$BV$21) | L8: =SUMPRODUCT(Adds!$C$23:$L$23,Curves!$BM$21:$BV$21) | M8: =SUMPRODUCT(Adds!$C$23:$M$23,Curves!$BL$21:$BV$21) | N8: =SUMPRODUCT(Adds!$C$23:$N$23,Curves!$BK$21:$BV$21) | O8: =SUMPRODUCT(Adds!$C$23:$O$23,Curves!$BJ$21:$BV$21) | P8: =SUMPRODUCT(Adds!$C$23:$P$23,Curves!$BI$21:$BV$21) | Q8: =SUMPRODUCT(Adds!$C$23:$Q$23,Curves!$BH$21:$BV$21) | R8: =SUMPRODUCT(Adds!$C$23:$R$23,Curves!$BG$21:$BV$21) | S8: =SUMPRODUCT(Adds!$C$23:$S$23,Curves!$BF$21:$BV$21) | T8: =SUMPRODUCT(Adds!$C$23:$T$23,Curves!$BE$21:$BV$21) | U8: =SUMPRODUCT(Adds!$C$23:$U$23,Curves!$BD$21:$BV$21) | V8: =SUMPRODUCT(Adds!$C$23:$V$23,Curves!$BC$21:$BV$21) | W8: =SUMPRODUCT(Adds!$C$23:$W$23,Curves!$BB$21:$BV$21) | X8: =SUMPRODUCT(Adds!$C$23:$X$23,Curves!$BA$21:$BV$21) | Y8: =SUMPRODUCT(Adds!$C$23:$Y$23,Curves!$AZ$21:$BV$21) | Z8: =SUMPRODUCT(Adds!$C$23:$Z$23,Curves!$AY$21:$BV$21) | AA8: =SUMPRODUCT(Adds!$C$23:$AA$23,Curves!$AX$21:$BV$21) | AB8: =SUMPRODUCT(Adds!$C$23:$AB$23,Curves!$AW$21:$BV$21) | AC8: =SUMPRODUCT(Adds!$C$23:$AC$23,Curves!$AV$21:$BV$21) | AD8: =SUMPRODUCT(Adds!$C$23:$AD$23,Curves!$AU$21:$BV$21) | AE8: =SUMPRODUCT(Adds!$C$23:$AE$23,Curves!$AT$21:$BV$21) | AF8: =SUMPRODUCT(Adds!$C$23:$AF$23,Curves!$AS$21:$BV$21) | AG8: =SUMPRODUCT(Adds!$C$23:$AG$23,Curves!$AR$21:$BV$21) | AH8: =SUMPRODUCT(Adds!$C$23:$AH$23,Curves!$AQ$21:$BV$21) | AI8: =SUMPRODUCT(Adds!$C$23:$AI$23,Curves!$AP$21:$BV$21) | AJ8: =SUMPRODUCT(Adds!$C$23:$AJ$23,Curves!$AO$21:$BV$21) | AK8: =SUMPRODUCT(Adds!$C$23:$AK$23,Curves!$AN$21:$BV$21) | AL8: =SUMPRODUCT(Adds!$C$23:$AL$23,Curves!$AM$21:$BV$21) | AM8: =SUMPRODUCT(Adds!$C$23:$AM$23,Curves!$AL$21:$BV$21) | AN8: =SUMPRODUCT(Adds!$C$23:$AN$23,Curves!$AK$21:$BV$21) | AO8: =SUMPRODUCT(Adds!$C$23:$AO$23,Curves!$AJ$21:$BV$21) | AP8: =SUMPRODUCT(Adds!$C$23:$AP$23,Curves!$AI$21:$BV$21) | AQ8: =SUMPRODUCT(Adds!$C$23:$AQ$23,Curves!$AH$21:$BV$21) | AR8: =SUMPRODUCT(Adds!$C$23:$AR$23,Curves!$AG$21:$BV$21) | AS8: =SUMPRODUCT(Adds!$C$23:$AS$23,Curves!$AF$21:$BV$21) | AT8: =SUMPRODUCT(Adds!$C$23:$AT$23,Curves!$AE$21:$BV$21) | AU8: =SUMPRODUCT(Adds!$C$23:$AU$23,Curves!$AD$21:$BV$21) | AV8: =SUMPRODUCT(Adds!$C$23:$AV$23,Curves!$AC$21:$BV$21) | AW8: =SUMPRODUCT(Adds!$C$23:$AW$23,Curves!$AB$21:$BV$21) | AX8: =SUMPRODUCT(Adds!$C$23:$AX$23,Curves!$AA$21:$BV$21) | AY8: =SUMPRODUCT(Adds!$C$23:$AY$23,Curves!$Z$21:$BV$21) | AZ8: =SUMPRODUCT(Adds!$C$23:$AZ$23,Curves!$Y$21:$BV$21) | BA8: =SUMPRODUCT(Adds!$C$23:$BA$23,Curves!$X$21:$BV$21) | BB8: =SUMPRODUCT(Adds!$C$23:$BB$23,Curves!$W$21:$BV$21) | BC8: =SUMPRODUCT(Adds!$C$23:$BC$23,Curves!$V$21:$BV$21) | BD8: =SUMPRODUCT(Adds!$C$23:$BD$23,Curves!$U$21:$BV$21) | BE8: =SUMPRODUCT(Adds!$C$23:$BE$23,Curves!$T$21:$BV$21) | BF8: =SUMPRODUCT(Adds!$C$23:$BF$23,Curves!$S$21:$BV$21) | BG8: =SUMPRODUCT(Adds!$C$23:$BG$23,Curves!$R$21:$BV$21) | BH8: =SUMPRODUCT(Adds!$C$23:$BH$23,Curves!$Q$21:$BV$21) | BI8: =SUMPRODUCT(Adds!$C$23:$BI$23,Curves!$P$21:$BV$21) | BJ8: =SUMPRODUCT(Adds!$C$23:$BJ$23,Curves!$O$21:$BV$21) | BK8: =SUMPRODUCT(Adds!$C$23:$BK$23,Curves!$N$21:$BV$21) | BL8: =SUMPRODUCT(Adds!$C$23:$BL$23,Curves!$M$21:$BV$21) | BM8: =SUMPRODUCT(Adds!$C$23:$BM$23,Curves!$L$21:$BV$21) | BN8: =SUMPRODUCT(Adds!$C$23:$BN$23,Curves!$K$21:$BV$21) | BO8: =SUMPRODUCT(Adds!$C$23:$BO$23,Curves!$J$21:$BV$21) | BP8: =SUMPRODUCT(Adds!$C$23:$BP$23,Curves!$I$21:$BV$21) | BQ8: =SUMPRODUCT(Adds!$C$23:$BQ$23,Curves!$H$21:$BV$21) | BR8: =SUMPRODUCT(Adds!$C$23:$BR$23,Curves!$G$21:$BV$21) | BS8: =SUMPRODUCT(Adds!$C$23:$BS$23,Curves!$F$21:$BV$21) | BT8: =SUMPRODUCT(Adds!$C$23:$BT$23,Curves!$E$21:$BV$21) | BU8: =SUMPRODUCT(Adds!$C$23:$BU$23,Curves!$D$21:$BV$21) | BV8: =SUMPRODUCT(Adds!$C$23:$BV$23,Curves!$C$21:$BV$21)
A9: churned | B9: US_CA|NITRO_A | C9: =Adds!$C$23*Curves!$BV$16 | D9: =SUMPRODUCT(Adds!$C$23:$D$23,Curves!$BU$16:$BV$16) | E9: =SUMPRODUCT(Adds!$C$23:$E$23,Curves!$BT$16:$BV$16) | F9: =SUMPRODUCT(Adds!$C$23:$F$23,Curves!$BS$16:$BV$16) | G9: =SUMPRODUCT(Adds!$C$23:$G$23,Curves!$BR$16:$BV$16) | H9: =SUMPRODUCT(Adds!$C$23:$H$23,Curves!$BQ$16:$BV$16) | I9: =SUMPRODUCT(Adds!$C$23:$I$23,Curves!$BP$16:$BV$16) | J9: =SUMPRODUCT(Adds!$C$23:$J$23,Curves!$BO$16:$BV$16) | K9: =SUMPRODUCT(Adds!$C$23:$K$23,Curves!$BN$16:$BV$16) | L9: =SUMPRODUCT(Adds!$C$23:$L$23,Curves!$BM$16:$BV$16) | M9: =SUMPRODUCT(Adds!$C$23:$M$23,Curves!$BL$16:$BV$16) | N9: =SUMPRODUCT(Adds!$C$23:$N$23,Curves!$BK$16:$BV$16) | O9: =SUMPRODUCT(Adds!$C$23:$O$23,Curves!$BJ$16:$BV$16) | P9: =SUMPRODUCT(Adds!$C$23:$P$23,Curves!$BI$16:$BV$16) | Q9: =SUMPRODUCT(Adds!$C$23:$Q$23,Curves!$BH$16:$BV$16) | R9: =SUMPRODUCT(Adds!$C$23:$R$23,Curves!$BG$16:$BV$16) | S9: =SUMPRODUCT(Adds!$C$23:$S$23,Curves!$BF$16:$BV$16) | T9: =SUMPRODUCT(Adds!$C$23:$T$23,Curves!$BE$16:$BV$16) | U9: =SUMPRODUCT(Adds!$C$23:$U$23,Curves!$BD$16:$BV$16) | V9: =SUMPRODUCT(Adds!$C$23:$V$23,Curves!$BC$16:$BV$16) | W9: =SUMPRODUCT(Adds!$C$23:$W$23,Curves!$BB$16:$BV$16) | X9: =SUMPRODUCT(Adds!$C$23:$X$23,Curves!$BA$16:$BV$16) | Y9: =SUMPRODUCT(Adds!$C$23:$Y$23,Curves!$AZ$16:$BV$16) | Z9: =SUMPRODUCT(Adds!$C$23:$Z$23,Curves!$AY$16:$BV$16) | AA9: =SUMPRODUCT(Adds!$C$23:$AA$23,Curves!$AX$16:$BV$16) | AB9: =SUMPRODUCT(Adds!$C$23:$AB$23,Curves!$AW$16:$BV$16) | AC9: =SUMPRODUCT(Adds!$C$23:$AC$23,Curves!$AV$16:$BV$16) | AD9: =SUMPRODUCT(Adds!$C$23:$AD$23,Curves!$AU$16:$BV$16) | AE9: =SUMPRODUCT(Adds!$C$23:$AE$23,Curves!$AT$16:$BV$16) | AF9: =SUMPRODUCT(Adds!$C$23:$AF$23,Curves!$AS$16:$BV$16) | AG9: =SUMPRODUCT(Adds!$C$23:$AG$23,Curves!$AR$16:$BV$16) | AH9: =SUMPRODUCT(Adds!$C$23:$AH$23,Curves!$AQ$16:$BV$16) | AI9: =SUMPRODUCT(Adds!$C$23:$AI$23,Curves!$AP$16:$BV$16) | AJ9: =SUMPRODUCT(Adds!$C$23:$AJ$23,Curves!$AO$16:$BV$16) | AK9: =SUMPRODUCT(Adds!$C$23:$AK$23,Curves!$AN$16:$BV$16) | AL9: =SUMPRODUCT(Adds!$C$23:$AL$23,Curves!$AM$16:$BV$16) | AM9: =SUMPRODUCT(Adds!$C$23:$AM$23,Curves!$AL$16:$BV$16) | AN9: =SUMPRODUCT(Adds!$C$23:$AN$23,Curves!$AK$16:$BV$16) | AO9: =SUMPRODUCT(Adds!$C$23:$AO$23,Curves!$AJ$16:$BV$16) | AP9: =SUMPRODUCT(Adds!$C$23:$AP$23,Curves!$AI$16:$BV$16) | AQ9: =SUMPRODUCT(Adds!$C$23:$AQ$23,Curves!$AH$16:$BV$16) | AR9: =SUMPRODUCT(Adds!$C$23:$AR$23,Curves!$AG$16:$BV$16) | AS9: =SUMPRODUCT(Adds!$C$23:$AS$23,Curves!$AF$16:$BV$16) | AT9: =SUMPRODUCT(Adds!$C$23:$AT$23,Curves!$AE$16:$BV$16) | AU9: =SUMPRODUCT(Adds!$C$23:$AU$23,Curves!$AD$16:$BV$16) | AV9: =SUMPRODUCT(Adds!$C$23:$AV$23,Curves!$AC$16:$BV$16) | AW9: =SUMPRODUCT(Adds!$C$23:$AW$23,Curves!$AB$16:$BV$16) | AX9: =SUMPRODUCT(Adds!$C$23:$AX$23,Curves!$AA$16:$BV$16) | AY9: =SUMPRODUCT(Adds!$C$23:$AY$23,Curves!$Z$16:$BV$16) | AZ9: =SUMPRODUCT(Adds!$C$23:$AZ$23,Curves!$Y$16:$BV$16) | BA9: =SUMPRODUCT(Adds!$C$23:$BA$23,Curves!$X$16:$BV$16) | BB9: =SUMPRODUCT(Adds!$C$23:$BB$23,Curves!$W$16:$BV$16) | BC9: =SUMPRODUCT(Adds!$C$23:$BC$23,Curves!$V$16:$BV$16) | BD9: =SUMPRODUCT(Adds!$C$23:$BD$23,Curves!$U$16:$BV$16) | BE9: =SUMPRODUCT(Adds!$C$23:$BE$23,Curves!$T$16:$BV$16) | BF9: =SUMPRODUCT(Adds!$C$23:$BF$23,Curves!$S$16:$BV$16) | BG9: =SUMPRODUCT(Adds!$C$23:$BG$23,Curves!$R$16:$BV$16) | BH9: =SUMPRODUCT(Adds!$C$23:$BH$23,Curves!$Q$16:$BV$16) | BI9: =SUMPRODUCT(Adds!$C$23:$BI$23,Curves!$P$16:$BV$16) | BJ9: =SUMPRODUCT(Adds!$C$23:$BJ$23,Curves!$O$16:$BV$16) | BK9: =SUMPRODUCT(Adds!$C$23:$BK$23,Curves!$N$16:$BV$16) | BL9: =SUMPRODUCT(Adds!$C$23:$BL$23,Curves!$M$16:$BV$16) | BM9: =SUMPRODUCT(Adds!$C$23:$BM$23,Curves!$L$16:$BV$16) | BN9: =SUMPRODUCT(Adds!$C$23:$BN$23,Curves!$K$16:$BV$16) | BO9: =SUMPRODUCT(Adds!$C$23:$BO$23,Curves!$J$16:$BV$16) | BP9: =SUMPRODUCT(Adds!$C$23:$BP$23,Curves!$I$16:$BV$16) | BQ9: =SUMPRODUCT(Adds!$C$23:$BQ$23,Curves!$H$16:$BV$16) | BR9: =SUMPRODUCT(Adds!$C$23:$BR$23,Curves!$G$16:$BV$16) | BS9: =SUMPRODUCT(Adds!$C$23:$BS$23,Curves!$F$16:$BV$16) | BT9: =SUMPRODUCT(Adds!$C$23:$BT$23,Curves!$E$16:$BV$16) | BU9: =SUMPRODUCT(Adds!$C$23:$BU$23,Curves!$D$16:$BV$16) | BV9: =SUMPRODUCT(Adds!$C$23:$BV$23,Curves!$C$16:$BV$16)
A11: active | B11: US_CA|BASIC_M | C11: =Adds!$C$34*Curves!$BV$13 | D11: =SUMPRODUCT(Adds!$C$34:$D$34,Curves!$BU$13:$BV$13) | E11: =SUMPRODUCT(Adds!$C$34:$E$34,Curves!$BT$13:$BV$13) | F11: =SUMPRODUCT(Adds!$C$34:$F$34,Curves!$BS$13:$BV$13) | G11: =SUMPRODUCT(Adds!$C$34:$G$34,Curves!$BR$13:$BV$13) | H11: =SUMPRODUCT(Adds!$C$34:$H$34,Curves!$BQ$13:$BV$13) | I11: =SUMPRODUCT(Adds!$C$34:$I$34,Curves!$BP$13:$BV$13) | J11: =SUMPRODUCT(Adds!$C$34:$J$34,Curves!$BO$13:$BV$13) | K11: =SUMPRODUCT(Adds!$C$34:$K$34,Curves!$BN$13:$BV$13) | L11: =SUMPRODUCT(Adds!$C$34:$L$34,Curves!$BM$13:$BV$13) | M11: =SUMPRODUCT(Adds!$C$34:$M$34,Curves!$BL$13:$BV$13) | N11: =SUMPRODUCT(Adds!$C$34:$N$34,Curves!$BK$13:$BV$13) | O11: =SUMPRODUCT(Adds!$C$34:$O$34,Curves!$BJ$13:$BV$13) | P11: =SUMPRODUCT(Adds!$C$34:$P$34,Curves!$BI$13:$BV$13) | Q11: =SUMPRODUCT(Adds!$C$34:$Q$34,Curves!$BH$13:$BV$13) | R11: =SUMPRODUCT(Adds!$C$34:$R$34,Curves!$BG$13:$BV$13) | S11: =SUMPRODUCT(Adds!$C$34:$S$34,Curves!$BF$13:$BV$13) | T11: =SUMPRODUCT(Adds!$C$34:$T$34,Curves!$BE$13:$BV$13) | U11: =SUMPRODUCT(Adds!$C$34:$U$34,Curves!$BD$13:$BV$13) | V11: =SUMPRODUCT(Adds!$C$34:$V$34,Curves!$BC$13:$BV$13) | W11: =SUMPRODUCT(Adds!$C$34:$W$34,Curves!$BB$13:$BV$13) | X11: =SUMPRODUCT(Adds!$C$34:$X$34,Curves!$BA$13:$BV$13) | Y11: =SUMPRODUCT(Adds!$C$34:$Y$34,Curves!$AZ$13:$BV$13) | Z11: =SUMPRODUCT(Adds!$C$34:$Z$34,Curves!$AY$13:$BV$13) | AA11: =SUMPRODUCT(Adds!$C$34:$AA$34,Curves!$AX$13:$BV$13) | AB11: =SUMPRODUCT(Adds!$C$34:$AB$34,Curves!$AW$13:$BV$13) | AC11: =SUMPRODUCT(Adds!$C$34:$AC$34,Curves!$AV$13:$BV$13) | AD11: =SUMPRODUCT(Adds!$C$34:$AD$34,Curves!$AU$13:$BV$13) | AE11: =SUMPRODUCT(Adds!$C$34:$AE$34,Curves!$AT$13:$BV$13) | AF11: =SUMPRODUCT(Adds!$C$34:$AF$34,Curves!$AS$13:$BV$13) | AG11: =SUMPRODUCT(Adds!$C$34:$AG$34,Curves!$AR$13:$BV$13) | AH11: =SUMPRODUCT(Adds!$C$34:$AH$34,Curves!$AQ$13:$BV$13) | AI11: =SUMPRODUCT(Adds!$C$34:$AI$34,Curves!$AP$13:$BV$13) | AJ11: =SUMPRODUCT(Adds!$C$34:$AJ$34,Curves!$AO$13:$BV$13) | AK11: =SUMPRODUCT(Adds!$C$34:$AK$34,Curves!$AN$13:$BV$13) | AL11: =SUMPRODUCT(Adds!$C$34:$AL$34,Curves!$AM$13:$BV$13) | AM11: =SUMPRODUCT(Adds!$C$34:$AM$34,Curves!$AL$13:$BV$13) | AN11: =SUMPRODUCT(Adds!$C$34:$AN$34,Curves!$AK$13:$BV$13) | AO11: =SUMPRODUCT(Adds!$C$34:$AO$34,Curves!$AJ$13:$BV$13) | AP11: =SUMPRODUCT(Adds!$C$34:$AP$34,Curves!$AI$13:$BV$13) | AQ11: =SUMPRODUCT(Adds!$C$34:$AQ$34,Curves!$AH$13:$BV$13) | AR11: =SUMPRODUCT(Adds!$C$34:$AR$34,Curves!$AG$13:$BV$13) | AS11: =SUMPRODUCT(Adds!$C$34:$AS$34,Curves!$AF$13:$BV$13) | AT11: =SUMPRODUCT(Adds!$C$34:$AT$34,Curves!$AE$13:$BV$13) | AU11: =SUMPRODUCT(Adds!$C$34:$AU$34,Curves!$AD$13:$BV$13) | AV11: =SUMPRODUCT(Adds!$C$34:$AV$34,Curves!$AC$13:$BV$13) | AW11: =SUMPRODUCT(Adds!$C$34:$AW$34,Curves!$AB$13:$BV$13) | AX11: =SUMPRODUCT(Adds!$C$34:$AX$34,Curves!$AA$13:$BV$13) | AY11: =SUMPRODUCT(Adds!$C$34:$AY$34,Curves!$Z$13:$BV$13) | AZ11: =SUMPRODUCT(Adds!$C$34:$AZ$34,Curves!$Y$13:$BV$13) | BA11: =SUMPRODUCT(Adds!$C$34:$BA$34,Curves!$X$13:$BV$13) | BB11: =SUMPRODUCT(Adds!$C$34:$BB$34,Curves!$W$13:$BV$13) | BC11: =SUMPRODUCT(Adds!$C$34:$BC$34,Curves!$V$13:$BV$13) | BD11: =SUMPRODUCT(Adds!$C$34:$BD$34,Curves!$U$13:$BV$13) | BE11: =SUMPRODUCT(Adds!$C$34:$BE$34,Curves!$T$13:$BV$13) | BF11: =SUMPRODUCT(Adds!$C$34:$BF$34,Curves!$S$13:$BV$13) | BG11: =SUMPRODUCT(Adds!$C$34:$BG$34,Curves!$R$13:$BV$13) | BH11: =SUMPRODUCT(Adds!$C$34:$BH$34,Curves!$Q$13:$BV$13) | BI11: =SUMPRODUCT(Adds!$C$34:$BI$34,Curves!$P$13:$BV$13) | BJ11: =SUMPRODUCT(Adds!$C$34:$BJ$34,Curves!$O$13:$BV$13) | BK11: =SUMPRODUCT(Adds!$C$34:$BK$34,Curves!$N$13:$BV$13) | BL11: =SUMPRODUCT(Adds!$C$34:$BL$34,Curves!$M$13:$BV$13) | BM11: =SUMPRODUCT(Adds!$C$34:$BM$34,Curves!$L$13:$BV$13) | BN11: =SUMPRODUCT(Adds!$C$34:$BN$34,Curves!$K$13:$BV$13) | BO11: =SUMPRODUCT(Adds!$C$34:$BO$34,Curves!$J$13:$BV$13) | BP11: =SUMPRODUCT(Adds!$C$34:$BP$34,Curves!$I$13:$BV$13) | BQ11: =SUMPRODUCT(Adds!$C$34:$BQ$34,Curves!$H$13:$BV$13) | BR11: =SUMPRODUCT(Adds!$C$34:$BR$34,Curves!$G$13:$BV$13) | BS11: =SUMPRODUCT(Adds!$C$34:$BS$34,Curves!$F$13:$BV$13) | BT11: =SUMPRODUCT(Adds!$C$34:$BT$34,Curves!$E$13:$BV$13) | BU11: =SUMPRODUCT(Adds!$C$34:$BU$34,Curves!$D$13:$BV$13) | BV11: =SUMPRODUCT(Adds!$C$34:$BV$34,Curves!$C$13:$BV$13)
A12: active yr 1 | B12: US_CA|BASIC_M | C12: =Adds!$C$34*Curves!$BV$20 | D12: =SUMPRODUCT(Adds!$C$34:$D$34,Curves!$BU$20:$BV$20) | E12: =SUMPRODUCT(Adds!$C$34:$E$34,Curves!$BT$20:$BV$20) | F12: =SUMPRODUCT(Adds!$C$34:$F$34,Curves!$BS$20:$BV$20) | G12: =SUMPRODUCT(Adds!$C$34:$G$34,Curves!$BR$20:$BV$20) | H12: =SUMPRODUCT(Adds!$C$34:$H$34,Curves!$BQ$20:$BV$20) | I12: =SUMPRODUCT(Adds!$C$34:$I$34,Curves!$BP$20:$BV$20) | J12: =SUMPRODUCT(Adds!$C$34:$J$34,Curves!$BO$20:$BV$20) | K12: =SUMPRODUCT(Adds!$C$34:$K$34,Curves!$BN$20:$BV$20) | L12: =SUMPRODUCT(Adds!$C$34:$L$34,Curves!$BM$20:$BV$20) | M12: =SUMPRODUCT(Adds!$C$34:$M$34,Curves!$BL$20:$BV$20) | N12: =SUMPRODUCT(Adds!$C$34:$N$34,Curves!$BK$20:$BV$20) | O12: =SUMPRODUCT(Adds!$C$34:$O$34,Curves!$BJ$20:$BV$20) | P12: =SUMPRODUCT(Adds!$C$34:$P$34,Curves!$BI$20:$BV$20) | Q12: =SUMPRODUCT(Adds!$C$34:$Q$34,Curves!$BH$20:$BV$20) | R12: =SUMPRODUCT(Adds!$C$34:$R$34,Curves!$BG$20:$BV$20) | S12: =SUMPRODUCT(Adds!$C$34:$S$34,Curves!$BF$20:$BV$20) | T12: =SUMPRODUCT(Adds!$C$34:$T$34,Curves!$BE$20:$BV$20) | U12: =SUMPRODUCT(Adds!$C$34:$U$34,Curves!$BD$20:$BV$20) | V12: =SUMPRODUCT(Adds!$C$34:$V$34,Curves!$BC$20:$BV$20) | W12: =SUMPRODUCT(Adds!$C$34:$W$34,Curves!$BB$20:$BV$20) | X12: =SUMPRODUCT(Adds!$C$34:$X$34,Curves!$BA$20:$BV$20) | Y12: =SUMPRODUCT(Adds!$C$34:$Y$34,Curves!$AZ$20:$BV$20) | Z12: =SUMPRODUCT(Adds!$C$34:$Z$34,Curves!$AY$20:$BV$20) | AA12: =SUMPRODUCT(Adds!$C$34:$AA$34,Curves!$AX$20:$BV$20) | AB12: =SUMPRODUCT(Adds!$C$34:$AB$34,Curves!$AW$20:$BV$20) | AC12: =SUMPRODUCT(Adds!$C$34:$AC$34,Curves!$AV$20:$BV$20) | AD12: =SUMPRODUCT(Adds!$C$34:$AD$34,Curves!$AU$20:$BV$20) | AE12: =SUMPRODUCT(Adds!$C$34:$AE$34,Curves!$AT$20:$BV$20) | AF12: =SUMPRODUCT(Adds!$C$34:$AF$34,Curves!$AS$20:$BV$20) | AG12: =SUMPRODUCT(Adds!$C$34:$AG$34,Curves!$AR$20:$BV$20) | AH12: =SUMPRODUCT(Adds!$C$34:$AH$34,Curves!$AQ$20:$BV$20) | AI12: =SUMPRODUCT(Adds!$C$34:$AI$34,Curves!$AP$20:$BV$20) | AJ12: =SUMPRODUCT(Adds!$C$34:$AJ$34,Curves!$AO$20:$BV$20) | AK12: =SUMPRODUCT(Adds!$C$34:$AK$34,Curves!$AN$20:$BV$20) | AL12: =SUMPRODUCT(Adds!$C$34:$AL$34,Curves!$AM$20:$BV$20) | AM12: =SUMPRODUCT(Adds!$C$34:$AM$34,Curves!$AL$20:$BV$20) | AN12: =SUMPRODUCT(Adds!$C$34:$AN$34,Curves!$AK$20:$BV$20) | AO12: =SUMPRODUCT(Adds!$C$34:$AO$34,Curves!$AJ$20:$BV$20) | AP12: =SUMPRODUCT(Adds!$C$34:$AP$34,Curves!$AI$20:$BV$20) | AQ12: =SUMPRODUCT(Adds!$C$34:$AQ$34,Curves!$AH$20:$BV$20) | AR12: =SUMPRODUCT(Adds!$C$34:$AR$34,Curves!$AG$20:$BV$20) | AS12: =SUMPRODUCT(Adds!$C$34:$AS$34,Curves!$AF$20:$BV$20) | AT12: =SUMPRODUCT(Adds!$C$34:$AT$34,Curves!$AE$20:$BV$20) | AU12: =SUMPRODUCT(Adds!$C$34:$AU$34,Curves!$AD$20:$BV$20) | AV12: =SUMPRODUCT(Adds!$C$34:$AV$34,Curves!$AC$20:$BV$20) | AW12: =SUMPRODUCT(Adds!$C$34:$AW$34,Curves!$AB$20:$BV$20) | AX12: =SUMPRODUCT(Adds!$C$34:$AX$34,Curves!$AA$20:$BV$20) | AY12: =SUMPRODUCT(Adds!$C$34:$AY$34,Curves!$Z$20:$BV$20) | AZ12: =SUMPRODUCT(Adds!$C$34:$AZ$34,Curves!$Y$20:$BV$20) | BA12: =SUMPRODUCT(Adds!$C$34:$BA$34,Curves!$X$20:$BV$20) | BB12: =SUMPRODUCT(Adds!$C$34:$BB$34,Curves!$W$20:$BV$20) | BC12: =SUMPRODUCT(Adds!$C$34:$BC$34,Curves!$V$20:$BV$20) | BD12: =SUMPRODUCT(Adds!$C$34:$BD$34,Curves!$U$20:$BV$20) | BE12: =SUMPRODUCT(Adds!$C$34:$BE$34,Curves!$T$20:$BV$20) | BF12: =SUMPRODUCT(Adds!$C$34:$BF$34,Curves!$S$20:$BV$20) | BG12: =SUMPRODUCT(Adds!$C$34:$BG$34,Curves!$R$20:$BV$20) | BH12: =SUMPRODUCT(Adds!$C$34:$BH$34,Curves!$Q$20:$BV$20) | BI12: =SUMPRODUCT(Adds!$C$34:$BI$34,Curves!$P$20:$BV$20) | BJ12: =SUMPRODUCT(Adds!$C$34:$BJ$34,Curves!$O$20:$BV$20) | BK12: =SUMPRODUCT(Adds!$C$34:$BK$34,Curves!$N$20:$BV$20) | BL12: =SUMPRODUCT(Adds!$C$34:$BL$34,Curves!$M$20:$BV$20) | BM12: =SUMPRODUCT(Adds!$C$34:$BM$34,Curves!$L$20:$BV$20) | BN12: =SUMPRODUCT(Adds!$C$34:$BN$34,Curves!$K$20:$BV$20) | BO12: =SUMPRODUCT(Adds!$C$34:$BO$34,Curves!$J$20:$BV$20) | BP12: =SUMPRODUCT(Adds!$C$34:$BP$34,Curves!$I$20:$BV$20) | BQ12: =SUMPRODUCT(Adds!$C$34:$BQ$34,Curves!$H$20:$BV$20) | BR12: =SUMPRODUCT(Adds!$C$34:$BR$34,Curves!$G$20:$BV$20) | BS12: =SUMPRODUCT(Adds!$C$34:$BS$34,Curves!$F$20:$BV$20) | BT12: =SUMPRODUCT(Adds!$C$34:$BT$34,Curves!$E$20:$BV$20) | BU12: =SUMPRODUCT(Adds!$C$34:$BU$34,Curves!$D$20:$BV$20) | BV12: =SUMPRODUCT(Adds!$C$34:$BV$34,Curves!$C$20:$BV$20)
A13: churned | B13: US_CA|BASIC_M | C13: =Adds!$C$34*Curves!$BV$15 | D13: =SUMPRODUCT(Adds!$C$34:$D$34,Curves!$BU$15:$BV$15) | E13: =SUMPRODUCT(Adds!$C$34:$E$34,Curves!$BT$15:$BV$15) | F13: =SUMPRODUCT(Adds!$C$34:$F$34,Curves!$BS$15:$BV$15) | G13: =SUMPRODUCT(Adds!$C$34:$G$34,Curves!$BR$15:$BV$15) | H13: =SUMPRODUCT(Adds!$C$34:$H$34,Curves!$BQ$15:$BV$15) | I13: =SUMPRODUCT(Adds!$C$34:$I$34,Curves!$BP$15:$BV$15) | J13: =SUMPRODUCT(Adds!$C$34:$J$34,Curves!$BO$15:$BV$15) | K13: =SUMPRODUCT(Adds!$C$34:$K$34,Curves!$BN$15:$BV$15) | L13: =SUMPRODUCT(Adds!$C$34:$L$34,Curves!$BM$15:$BV$15) | M13: =SUMPRODUCT(Adds!$C$34:$M$34,Curves!$BL$15:$BV$15) | N13: =SUMPRODUCT(Adds!$C$34:$N$34,Curves!$BK$15:$BV$15) | O13: =SUMPRODUCT(Adds!$C$34:$O$34,Curves!$BJ$15:$BV$15) | P13: =SUMPRODUCT(Adds!$C$34:$P$34,Curves!$BI$15:$BV$15) | Q13: =SUMPRODUCT(Adds!$C$34:$Q$34,Curves!$BH$15:$BV$15) | R13: =SUMPRODUCT(Adds!$C$34:$R$34,Curves!$BG$15:$BV$15) | S13: =SUMPRODUCT(Adds!$C$34:$S$34,Curves!$BF$15:$BV$15) | T13: =SUMPRODUCT(Adds!$C$34:$T$34,Curves!$BE$15:$BV$15) | U13: =SUMPRODUCT(Adds!$C$34:$U$34,Curves!$BD$15:$BV$15) | V13: =SUMPRODUCT(Adds!$C$34:$V$34,Curves!$BC$15:$BV$15) | W13: =SUMPRODUCT(Adds!$C$34:$W$34,Curves!$BB$15:$BV$15) | X13: =SUMPRODUCT(Adds!$C$34:$X$34,Curves!$BA$15:$BV$15) | Y13: =SUMPRODUCT(Adds!$C$34:$Y$34,Curves!$AZ$15:$BV$15) | Z13: =SUMPRODUCT(Adds!$C$34:$Z$34,Curves!$AY$15:$BV$15) | AA13: =SUMPRODUCT(Adds!$C$34:$AA$34,Curves!$AX$15:$BV$15) | AB13: =SUMPRODUCT(Adds!$C$34:$AB$34,Curves!$AW$15:$BV$15) | AC13: =SUMPRODUCT(Adds!$C$34:$AC$34,Curves!$AV$15:$BV$15) | AD13: =SUMPRODUCT(Adds!$C$34:$AD$34,Curves!$AU$15:$BV$15) | AE13: =SUMPRODUCT(Adds!$C$34:$AE$34,Curves!$AT$15:$BV$15) | AF13: =SUMPRODUCT(Adds!$C$34:$AF$34,Curves!$AS$15:$BV$15) | AG13: =SUMPRODUCT(Adds!$C$34:$AG$34,Curves!$AR$15:$BV$15) | AH13: =SUMPRODUCT(Adds!$C$34:$AH$34,Curves!$AQ$15:$BV$15) | AI13: =SUMPRODUCT(Adds!$C$34:$AI$34,Curves!$AP$15:$BV$15) | AJ13: =SUMPRODUCT(Adds!$C$34:$AJ$34,Curves!$AO$15:$BV$15) | AK13: =SUMPRODUCT(Adds!$C$34:$AK$34,Curves!$AN$15:$BV$15) | AL13: =SUMPRODUCT(Adds!$C$34:$AL$34,Curves!$AM$15:$BV$15) | AM13: =SUMPRODUCT(Adds!$C$34:$AM$34,Curves!$AL$15:$BV$15) | AN13: =SUMPRODUCT(Adds!$C$34:$AN$34,Curves!$AK$15:$BV$15) | AO13: =SUMPRODUCT(Adds!$C$34:$AO$34,Curves!$AJ$15:$BV$15) | AP13: =SUMPRODUCT(Adds!$C$34:$AP$34,Curves!$AI$15:$BV$15) | AQ13: =SUMPRODUCT(Adds!$C$34:$AQ$34,Curves!$AH$15:$BV$15) | AR13: =SUMPRODUCT(Adds!$C$34:$AR$34,Curves!$AG$15:$BV$15) | AS13: =SUMPRODUCT(Adds!$C$34:$AS$34,Curves!$AF$15:$BV$15) | AT13: =SUMPRODUCT(Adds!$C$34:$AT$34,Curves!$AE$15:$BV$15) | AU13: =SUMPRODUCT(Adds!$C$34:$AU$34,Curves!$AD$15:$BV$15) | AV13: =SUMPRODUCT(Adds!$C$34:$AV$34,Curves!$AC$15:$BV$15) | AW13: =SUMPRODUCT(Adds!$C$34:$AW$34,Curves!$AB$15:$BV$15) | AX13: =SUMPRODUCT(Adds!$C$34:$AX$34,Curves!$AA$15:$BV$15) | AY13: =SUMPRODUCT(Adds!$C$34:$AY$34,Curves!$Z$15:$BV$15) | AZ13: =SUMPRODUCT(Adds!$C$34:$AZ$34,Curves!$Y$15:$BV$15) | BA13: =SUMPRODUCT(Adds!$C$34:$BA$34,Curves!$X$15:$BV$15) | BB13: =SUMPRODUCT(Adds!$C$34:$BB$34,Curves!$W$15:$BV$15) | BC13: =SUMPRODUCT(Adds!$C$34:$BC$34,Curves!$V$15:$BV$15) | BD13: =SUMPRODUCT(Adds!$C$34:$BD$34,Curves!$U$15:$BV$15) | BE13: =SUMPRODUCT(Adds!$C$34:$BE$34,Curves!$T$15:$BV$15) | BF13: =SUMPRODUCT(Adds!$C$34:$BF$34,Curves!$S$15:$BV$15) | BG13: =SUMPRODUCT(Adds!$C$34:$BG$34,Curves!$R$15:$BV$15) | BH13: =SUMPRODUCT(Adds!$C$34:$BH$34,Curves!$Q$15:$BV$15) | BI13: =SUMPRODUCT(Adds!$C$34:$BI$34,Curves!$P$15:$BV$15) | BJ13: =SUMPRODUCT(Adds!$C$34:$BJ$34,Curves!$O$15:$BV$15) | BK13: =SUMPRODUCT(Adds!$C$34:$BK$34,Curves!$N$15:$BV$15) | BL13: =SUMPRODUCT(Adds!$C$34:$BL$34,Curves!$M$15:$BV$15) | BM13: =SUMPRODUCT(Adds!$C$34:$BM$34,Curves!$L$15:$BV$15) | BN13: =SUMPRODUCT(Adds!$C$34:$BN$34,Curves!$K$15:$BV$15) | BO13: =SUMPRODUCT(Adds!$C$34:$BO$34,Curves!$J$15:$BV$15) | BP13: =SUMPRODUCT(Adds!$C$34:$BP$34,Curves!$I$15:$BV$15) | BQ13: =SUMPRODUCT(Adds!$C$34:$BQ$34,Curves!$H$15:$BV$15) | BR13: =SUMPRODUCT(Adds!$C$34:$BR$34,Curves!$G$15:$BV$15) | BS13: =SUMPRODUCT(Adds!$C$34:$BS$34,Curves!$F$15:$BV$15) | BT13: =SUMPRODUCT(Adds!$C$34:$BT$34,Curves!$E$15:$BV$15) | BU13: =SUMPRODUCT(Adds!$C$34:$BU$34,Curves!$D$15:$BV$15) | BV13: =SUMPRODUCT(Adds!$C$34:$BV$34,Curves!$C$15:$BV$15)
A15: active | B15: US_CA|BASIC_A | C15: =Adds!$C$45*Curves!$BV$14 | D15: =SUMPRODUCT(Adds!$C$45:$D$45,Curves!$BU$14:$BV$14) | E15: =SUMPRODUCT(Adds!$C$45:$E$45,Curves!$BT$14:$BV$14) | F15: =SUMPRODUCT(Adds!$C$45:$F$45,Curves!$BS$14:$BV$14) | G15: =SUMPRODUCT(Adds!$C$45:$G$45,Curves!$BR$14:$BV$14) | H15: =SUMPRODUCT(Adds!$C$45:$H$45,Curves!$BQ$14:$BV$14) | I15: =SUMPRODUCT(Adds!$C$45:$I$45,Curves!$BP$14:$BV$14) | J15: =SUMPRODUCT(Adds!$C$45:$J$45,Curves!$BO$14:$BV$14) | K15: =SUMPRODUCT(Adds!$C$45:$K$45,Curves!$BN$14:$BV$14) | L15: =SUMPRODUCT(Adds!$C$45:$L$45,Curves!$BM$14:$BV$14) | M15: =SUMPRODUCT(Adds!$C$45:$M$45,Curves!$BL$14:$BV$14) | N15: =SUMPRODUCT(Adds!$C$45:$N$45,Curves!$BK$14:$BV$14) | O15: =SUMPRODUCT(Adds!$C$45:$O$45,Curves!$BJ$14:$BV$14) | P15: =SUMPRODUCT(Adds!$C$45:$P$45,Curves!$BI$14:$BV$14) | Q15: =SUMPRODUCT(Adds!$C$45:$Q$45,Curves!$BH$14:$BV$14) | R15: =SUMPRODUCT(Adds!$C$45:$R$45,Curves!$BG$14:$BV$14) | S15: =SUMPRODUCT(Adds!$C$45:$S$45,Curves!$BF$14:$BV$14) | T15: =SUMPRODUCT(Adds!$C$45:$T$45,Curves!$BE$14:$BV$14) | U15: =SUMPRODUCT(Adds!$C$45:$U$45,Curves!$BD$14:$BV$14) | V15: =SUMPRODUCT(Adds!$C$45:$V$45,Curves!$BC$14:$BV$14) | W15: =SUMPRODUCT(Adds!$C$45:$W$45,Curves!$BB$14:$BV$14) | X15: =SUMPRODUCT(Adds!$C$45:$X$45,Curves!$BA$14:$BV$14) | Y15: =SUMPRODUCT(Adds!$C$45:$Y$45,Curves!$AZ$14:$BV$14) | Z15: =SUMPRODUCT(Adds!$C$45:$Z$45,Curves!$AY$14:$BV$14) | AA15: =SUMPRODUCT(Adds!$C$45:$AA$45,Curves!$AX$14:$BV$14) | AB15: =SUMPRODUCT(Adds!$C$45:$AB$45,Curves!$AW$14:$BV$14) | AC15: =SUMPRODUCT(Adds!$C$45:$AC$45,Curves!$AV$14:$BV$14) | AD15: =SUMPRODUCT(Adds!$C$45:$AD$45,Curves!$AU$14:$BV$14) | AE15: =SUMPRODUCT(Adds!$C$45:$AE$45,Curves!$AT$14:$BV$14) | AF15: =SUMPRODUCT(Adds!$C$45:$AF$45,Curves!$AS$14:$BV$14) | AG15: =SUMPRODUCT(Adds!$C$45:$AG$45,Curves!$AR$14:$BV$14) | AH15: =SUMPRODUCT(Adds!$C$45:$AH$45,Curves!$AQ$14:$BV$14) | AI15: =SUMPRODUCT(Adds!$C$45:$AI$45,Curves!$AP$14:$BV$14) | AJ15: =SUMPRODUCT(Adds!$C$45:$AJ$45,Curves!$AO$14:$BV$14) | AK15: =SUMPRODUCT(Adds!$C$45:$AK$45,Curves!$AN$14:$BV$14) | AL15: =SUMPRODUCT(Adds!$C$45:$AL$45,Curves!$AM$14:$BV$14) | AM15: =SUMPRODUCT(Adds!$C$45:$AM$45,Curves!$AL$14:$BV$14) | AN15: =SUMPRODUCT(Adds!$C$45:$AN$45,Curves!$AK$14:$BV$14) | AO15: =SUMPRODUCT(Adds!$C$45:$AO$45,Curves!$AJ$14:$BV$14) | AP15: =SUMPRODUCT(Adds!$C$45:$AP$45,Curves!$AI$14:$BV$14) | AQ15: =SUMPRODUCT(Adds!$C$45:$AQ$45,Curves!$AH$14:$BV$14) | AR15: =SUMPRODUCT(Adds!$C$45:$AR$45,Curves!$AG$14:$BV$14) | AS15: =SUMPRODUCT(Adds!$C$45:$AS$45,Curves!$AF$14:$BV$14) | AT15: =SUMPRODUCT(Adds!$C$45:$AT$45,Curves!$AE$14:$BV$14) | AU15: =SUMPRODUCT(Adds!$C$45:$AU$45,Curves!$AD$14:$BV$14) | AV15: =SUMPRODUCT(Adds!$C$45:$AV$45,Curves!$AC$14:$BV$14) | AW15: =SUMPRODUCT(Adds!$C$45:$AW$45,Curves!$AB$14:$BV$14) | AX15: =SUMPRODUCT(Adds!$C$45:$AX$45,Curves!$AA$14:$BV$14) | AY15: =SUMPRODUCT(Adds!$C$45:$AY$45,Curves!$Z$14:$BV$14) | AZ15: =SUMPRODUCT(Adds!$C$45:$AZ$45,Curves!$Y$14:$BV$14) | BA15: =SUMPRODUCT(Adds!$C$45:$BA$45,Curves!$X$14:$BV$14) | BB15: =SUMPRODUCT(Adds!$C$45:$BB$45,Curves!$W$14:$BV$14) | BC15: =SUMPRODUCT(Adds!$C$45:$BC$45,Curves!$V$14:$BV$14) | BD15: =SUMPRODUCT(Adds!$C$45:$BD$45,Curves!$U$14:$BV$14) | BE15: =SUMPRODUCT(Adds!$C$45:$BE$45,Curves!$T$14:$BV$14) | BF15: =SUMPRODUCT(Adds!$C$45:$BF$45,Curves!$S$14:$BV$14) | BG15: =SUMPRODUCT(Adds!$C$45:$BG$45,Curves!$R$14:$BV$14) | BH15: =SUMPRODUCT(Adds!$C$45:$BH$45,Curves!$Q$14:$BV$14) | BI15: =SUMPRODUCT(Adds!$C$45:$BI$45,Curves!$P$14:$BV$14) | BJ15: =SUMPRODUCT(Adds!$C$45:$BJ$45,Curves!$O$14:$BV$14) | BK15: =SUMPRODUCT(Adds!$C$45:$BK$45,Curves!$N$14:$BV$14) | BL15: =SUMPRODUCT(Adds!$C$45:$BL$45,Curves!$M$14:$BV$14) | BM15: =SUMPRODUCT(Adds!$C$45:$BM$45,Curves!$L$14:$BV$14) | BN15: =SUMPRODUCT(Adds!$C$45:$BN$45,Curves!$K$14:$BV$14) | BO15: =SUMPRODUCT(Adds!$C$45:$BO$45,Curves!$J$14:$BV$14) | BP15: =SUMPRODUCT(Adds!$C$45:$BP$45,Curves!$I$14:$BV$14) | BQ15: =SUMPRODUCT(Adds!$C$45:$BQ$45,Curves!$H$14:$BV$14) | BR15: =SUMPRODUCT(Adds!$C$45:$BR$45,Curves!$G$14:$BV$14) | BS15: =SUMPRODUCT(Adds!$C$45:$BS$45,Curves!$F$14:$BV$14) | BT15: =SUMPRODUCT(Adds!$C$45:$BT$45,Curves!$E$14:$BV$14) | BU15: =SUMPRODUCT(Adds!$C$45:$BU$45,Curves!$D$14:$BV$14) | BV15: =SUMPRODUCT(Adds!$C$45:$BV$45,Curves!$C$14:$BV$14)
A16: active yr 1 | B16: US_CA|BASIC_A | C16: =Adds!$C$45*Curves!$BV$21 | D16: =SUMPRODUCT(Adds!$C$45:$D$45,Curves!$BU$21:$BV$21) | E16: =SUMPRODUCT(Adds!$C$45:$E$45,Curves!$BT$21:$BV$21) | F16: =SUMPRODUCT(Adds!$C$45:$F$45,Curves!$BS$21:$BV$21) | G16: =SUMPRODUCT(Adds!$C$45:$G$45,Curves!$BR$21:$BV$21) | H16: =SUMPRODUCT(Adds!$C$45:$H$45,Curves!$BQ$21:$BV$21) | I16: =SUMPRODUCT(Adds!$C$45:$I$45,Curves!$BP$21:$BV$21) | J16: =SUMPRODUCT(Adds!$C$45:$J$45,Curves!$BO$21:$BV$21) | K16: =SUMPRODUCT(Adds!$C$45:$K$45,Curves!$BN$21:$BV$21) | L16: =SUMPRODUCT(Adds!$C$45:$L$45,Curves!$BM$21:$BV$21) | M16: =SUMPRODUCT(Adds!$C$45:$M$45,Curves!$BL$21:$BV$21) | N16: =SUMPRODUCT(Adds!$C$45:$N$45,Curves!$BK$21:$BV$21) | O16: =SUMPRODUCT(Adds!$C$45:$O$45,Curves!$BJ$21:$BV$21) | P16: =SUMPRODUCT(Adds!$C$45:$P$45,Curves!$BI$21:$BV$21) | Q16: =SUMPRODUCT(Adds!$C$45:$Q$45,Curves!$BH$21:$BV$21) | R16: =SUMPRODUCT(Adds!$C$45:$R$45,Curves!$BG$21:$BV$21) | S16: =SUMPRODUCT(Adds!$C$45:$S$45,Curves!$BF$21:$BV$21) | T16: =SUMPRODUCT(Adds!$C$45:$T$45,Curves!$BE$21:$BV$21) | U16: =SUMPRODUCT(Adds!$C$45:$U$45,Curves!$BD$21:$BV$21) | V16: =SUMPRODUCT(Adds!$C$45:$V$45,Curves!$BC$21:$BV$21) | W16: =SUMPRODUCT(Adds!$C$45:$W$45,Curves!$BB$21:$BV$21) | X16: =SUMPRODUCT(Adds!$C$45:$X$45,Curves!$BA$21:$BV$21) | Y16: =SUMPRODUCT(Adds!$C$45:$Y$45,Curves!$AZ$21:$BV$21) | Z16: =SUMPRODUCT(Adds!$C$45:$Z$45,Curves!$AY$21:$BV$21) | AA16: =SUMPRODUCT(Adds!$C$45:$AA$45,Curves!$AX$21:$BV$21) | AB16: =SUMPRODUCT(Adds!$C$45:$AB$45,Curves!$AW$21:$BV$21) | AC16: =SUMPRODUCT(Adds!$C$45:$AC$45,Curves!$AV$21:$BV$21) | AD16: =SUMPRODUCT(Adds!$C$45:$AD$45,Curves!$AU$21:$BV$21) | AE16: =SUMPRODUCT(Adds!$C$45:$AE$45,Curves!$AT$21:$BV$21) | AF16: =SUMPRODUCT(Adds!$C$45:$AF$45,Curves!$AS$21:$BV$21) | AG16: =SUMPRODUCT(Adds!$C$45:$AG$45,Curves!$AR$21:$BV$21) | AH16: =SUMPRODUCT(Adds!$C$45:$AH$45,Curves!$AQ$21:$BV$21) | AI16: =SUMPRODUCT(Adds!$C$45:$AI$45,Curves!$AP$21:$BV$21) | AJ16: =SUMPRODUCT(Adds!$C$45:$AJ$45,Curves!$AO$21:$BV$21) | AK16: =SUMPRODUCT(Adds!$C$45:$AK$45,Curves!$AN$21:$BV$21) | AL16: =SUMPRODUCT(Adds!$C$45:$AL$45,Curves!$AM$21:$BV$21) | AM16: =SUMPRODUCT(Adds!$C$45:$AM$45,Curves!$AL$21:$BV$21) | AN16: =SUMPRODUCT(Adds!$C$45:$AN$45,Curves!$AK$21:$BV$21) | AO16: =SUMPRODUCT(Adds!$C$45:$AO$45,Curves!$AJ$21:$BV$21) | AP16: =SUMPRODUCT(Adds!$C$45:$AP$45,Curves!$AI$21:$BV$21) | AQ16: =SUMPRODUCT(Adds!$C$45:$AQ$45,Curves!$AH$21:$BV$21) | AR16: =SUMPRODUCT(Adds!$C$45:$AR$45,Curves!$AG$21:$BV$21) | AS16: =SUMPRODUCT(Adds!$C$45:$AS$45,Curves!$AF$21:$BV$21) | AT16: =SUMPRODUCT(Adds!$C$45:$AT$45,Curves!$AE$21:$BV$21) | AU16: =SUMPRODUCT(Adds!$C$45:$AU$45,Curves!$AD$21:$BV$21) | AV16: =SUMPRODUCT(Adds!$C$45:$AV$45,Curves!$AC$21:$BV$21) | AW16: =SUMPRODUCT(Adds!$C$45:$AW$45,Curves!$AB$21:$BV$21) | AX16: =SUMPRODUCT(Adds!$C$45:$AX$45,Curves!$AA$21:$BV$21) | AY16: =SUMPRODUCT(Adds!$C$45:$AY$45,Curves!$Z$21:$BV$21) | AZ16: =SUMPRODUCT(Adds!$C$45:$AZ$45,Curves!$Y$21:$BV$21) | BA16: =SUMPRODUCT(Adds!$C$45:$BA$45,Curves!$X$21:$BV$21) | BB16: =SUMPRODUCT(Adds!$C$45:$BB$45,Curves!$W$21:$BV$21) | BC16: =SUMPRODUCT(Adds!$C$45:$BC$45,Curves!$V$21:$BV$21) | BD16: =SUMPRODUCT(Adds!$C$45:$BD$45,Curves!$U$21:$BV$21) | BE16: =SUMPRODUCT(Adds!$C$45:$BE$45,Curves!$T$21:$BV$21) | BF16: =SUMPRODUCT(Adds!$C$45:$BF$45,Curves!$S$21:$BV$21) | BG16: =SUMPRODUCT(Adds!$C$45:$BG$45,Curves!$R$21:$BV$21) | BH16: =SUMPRODUCT(Adds!$C$45:$BH$45,Curves!$Q$21:$BV$21) | BI16: =SUMPRODUCT(Adds!$C$45:$BI$45,Curves!$P$21:$BV$21) | BJ16: =SUMPRODUCT(Adds!$C$45:$BJ$45,Curves!$O$21:$BV$21) | BK16: =SUMPRODUCT(Adds!$C$45:$BK$45,Curves!$N$21:$BV$21) | BL16: =SUMPRODUCT(Adds!$C$45:$BL$45,Curves!$M$21:$BV$21) | BM16: =SUMPRODUCT(Adds!$C$45:$BM$45,Curves!$L$21:$BV$21) | BN16: =SUMPRODUCT(Adds!$C$45:$BN$45,Curves!$K$21:$BV$21) | BO16: =SUMPRODUCT(Adds!$C$45:$BO$45,Curves!$J$21:$BV$21) | BP16: =SUMPRODUCT(Adds!$C$45:$BP$45,Curves!$I$21:$BV$21) | BQ16: =SUMPRODUCT(Adds!$C$45:$BQ$45,Curves!$H$21:$BV$21) | BR16: =SUMPRODUCT(Adds!$C$45:$BR$45,Curves!$G$21:$BV$21) | BS16: =SUMPRODUCT(Adds!$C$45:$BS$45,Curves!$F$21:$BV$21) | BT16: =SUMPRODUCT(Adds!$C$45:$BT$45,Curves!$E$21:$BV$21) | BU16: =SUMPRODUCT(Adds!$C$45:$BU$45,Curves!$D$21:$BV$21) | BV16: =SUMPRODUCT(Adds!$C$45:$BV$45,Curves!$C$21:$BV$21)
A17: churned | B17: US_CA|BASIC_A | C17: =Adds!$C$45*Curves!$BV$16 | D17: =SUMPRODUCT(Adds!$C$45:$D$45,Curves!$BU$16:$BV$16) | E17: =SUMPRODUCT(Adds!$C$45:$E$45,Curves!$BT$16:$BV$16) | F17: =SUMPRODUCT(Adds!$C$45:$F$45,Curves!$BS$16:$BV$16) | G17: =SUMPRODUCT(Adds!$C$45:$G$45,Curves!$BR$16:$BV$16) | H17: =SUMPRODUCT(Adds!$C$45:$H$45,Curves!$BQ$16:$BV$16) | I17: =SUMPRODUCT(Adds!$C$45:$I$45,Curves!$BP$16:$BV$16) | J17: =SUMPRODUCT(Adds!$C$45:$J$45,Curves!$BO$16:$BV$16) | K17: =SUMPRODUCT(Adds!$C$45:$K$45,Curves!$BN$16:$BV$16) | L17: =SUMPRODUCT(Adds!$C$45:$L$45,Curves!$BM$16:$BV$16) | M17: =SUMPRODUCT(Adds!$C$45:$M$45,Curves!$BL$16:$BV$16) | N17: =SUMPRODUCT(Adds!$C$45:$N$45,Curves!$BK$16:$BV$16) | O17: =SUMPRODUCT(Adds!$C$45:$O$45,Curves!$BJ$16:$BV$16) | P17: =SUMPRODUCT(Adds!$C$45:$P$45,Curves!$BI$16:$BV$16) | Q17: =SUMPRODUCT(Adds!$C$45:$Q$45,Curves!$BH$16:$BV$16) | R17: =SUMPRODUCT(Adds!$C$45:$R$45,Curves!$BG$16:$BV$16) | S17: =SUMPRODUCT(Adds!$C$45:$S$45,Curves!$BF$16:$BV$16) | T17: =SUMPRODUCT(Adds!$C$45:$T$45,Curves!$BE$16:$BV$16) | U17: =SUMPRODUCT(Adds!$C$45:$U$45,Curves!$BD$16:$BV$16) | V17: =SUMPRODUCT(Adds!$C$45:$V$45,Curves!$BC$16:$BV$16) | W17: =SUMPRODUCT(Adds!$C$45:$W$45,Curves!$BB$16:$BV$16) | X17: =SUMPRODUCT(Adds!$C$45:$X$45,Curves!$BA$16:$BV$16) | Y17: =SUMPRODUCT(Adds!$C$45:$Y$45,Curves!$AZ$16:$BV$16) | Z17: =SUMPRODUCT(Adds!$C$45:$Z$45,Curves!$AY$16:$BV$16) | AA17: =SUMPRODUCT(Adds!$C$45:$AA$45,Curves!$AX$16:$BV$16) | AB17: =SUMPRODUCT(Adds!$C$45:$AB$45,Curves!$AW$16:$BV$16) | AC17: =SUMPRODUCT(Adds!$C$45:$AC$45,Curves!$AV$16:$BV$16) | AD17: =SUMPRODUCT(Adds!$C$45:$AD$45,Curves!$AU$16:$BV$16) | AE17: =SUMPRODUCT(Adds!$C$45:$AE$45,Curves!$AT$16:$BV$16) | AF17: =SUMPRODUCT(Adds!$C$45:$AF$45,Curves!$AS$16:$BV$16) | AG17: =SUMPRODUCT(Adds!$C$45:$AG$45,Curves!$AR$16:$BV$16) | AH17: =SUMPRODUCT(Adds!$C$45:$AH$45,Curves!$AQ$16:$BV$16) | AI17: =SUMPRODUCT(Adds!$C$45:$AI$45,Curves!$AP$16:$BV$16) | AJ17: =SUMPRODUCT(Adds!$C$45:$AJ$45,Curves!$AO$16:$BV$16) | AK17: =SUMPRODUCT(Adds!$C$45:$AK$45,Curves!$AN$16:$BV$16) | AL17: =SUMPRODUCT(Adds!$C$45:$AL$45,Curves!$AM$16:$BV$16) | AM17: =SUMPRODUCT(Adds!$C$45:$AM$45,Curves!$AL$16:$BV$16) | AN17: =SUMPRODUCT(Adds!$C$45:$AN$45,Curves!$AK$16:$BV$16) | AO17: =SUMPRODUCT(Adds!$C$45:$AO$45,Curves!$AJ$16:$BV$16) | AP17: =SUMPRODUCT(Adds!$C$45:$AP$45,Curves!$AI$16:$BV$16) | AQ17: =SUMPRODUCT(Adds!$C$45:$AQ$45,Curves!$AH$16:$BV$16) | AR17: =SUMPRODUCT(Adds!$C$45:$AR$45,Curves!$AG$16:$BV$16) | AS17: =SUMPRODUCT(Adds!$C$45:$AS$45,Curves!$AF$16:$BV$16) | AT17: =SUMPRODUCT(Adds!$C$45:$AT$45,Curves!$AE$16:$BV$16) | AU17: =SUMPRODUCT(Adds!$C$45:$AU$45,Curves!$AD$16:$BV$16) | AV17: =SUMPRODUCT(Adds!$C$45:$AV$45,Curves!$AC$16:$BV$16) | AW17: =SUMPRODUCT(Adds!$C$45:$AW$45,Curves!$AB$16:$BV$16) | AX17: =SUMPRODUCT(Adds!$C$45:$AX$45,Curves!$AA$16:$BV$16) | AY17: =SUMPRODUCT(Adds!$C$45:$AY$45,Curves!$Z$16:$BV$16) | AZ17: =SUMPRODUCT(Adds!$C$45:$AZ$45,Curves!$Y$16:$BV$16) | BA17: =SUMPRODUCT(Adds!$C$45:$BA$45,Curves!$X$16:$BV$16) | BB17: =SUMPRODUCT(Adds!$C$45:$BB$45,Curves!$W$16:$BV$16) | BC17: =SUMPRODUCT(Adds!$C$45:$BC$45,Curves!$V$16:$BV$16) | BD17: =SUMPRODUCT(Adds!$C$45:$BD$45,Curves!$U$16:$BV$16) | BE17: =SUMPRODUCT(Adds!$C$45:$BE$45,Curves!$T$16:$BV$16) | BF17: =SUMPRODUCT(Adds!$C$45:$BF$45,Curves!$S$16:$BV$16) | BG17: =SUMPRODUCT(Adds!$C$45:$BG$45,Curves!$R$16:$BV$16) | BH17: =SUMPRODUCT(Adds!$C$45:$BH$45,Curves!$Q$16:$BV$16) | BI17: =SUMPRODUCT(Adds!$C$45:$BI$45,Curves!$P$16:$BV$16) | BJ17: =SUMPRODUCT(Adds!$C$45:$BJ$45,Curves!$O$16:$BV$16) | BK17: =SUMPRODUCT(Adds!$C$45:$BK$45,Curves!$N$16:$BV$16) | BL17: =SUMPRODUCT(Adds!$C$45:$BL$45,Curves!$M$16:$BV$16) | BM17: =SUMPRODUCT(Adds!$C$45:$BM$45,Curves!$L$16:$BV$16) | BN17: =SUMPRODUCT(Adds!$C$45:$BN$45,Curves!$K$16:$BV$16) | BO17: =SUMPRODUCT(Adds!$C$45:$BO$45,Curves!$J$16:$BV$16) | BP17: =SUMPRODUCT(Adds!$C$45:$BP$45,Curves!$I$16:$BV$16) | BQ17: =SUMPRODUCT(Adds!$C$45:$BQ$45,Curves!$H$16:$BV$16) | BR17: =SUMPRODUCT(Adds!$C$45:$BR$45,Curves!$G$16:$BV$16) | BS17: =SUMPRODUCT(Adds!$C$45:$BS$45,Curves!$F$16:$BV$16) | BT17: =SUMPRODUCT(Adds!$C$45:$BT$45,Curves!$E$16:$BV$16) | BU17: =SUMPRODUCT(Adds!$C$45:$BU$45,Curves!$D$16:$BV$16) | BV17: =SUMPRODUCT(Adds!$C$45:$BV$45,Curves!$C$16:$BV$16)
A19: active | B19: EUROPE|NITRO_M | C19: =Adds!$C$56*Curves!$BV$13 | D19: =SUMPRODUCT(Adds!$C$56:$D$56,Curves!$BU$13:$BV$13) | E19: =SUMPRODUCT(Adds!$C$56:$E$56,Curves!$BT$13:$BV$13) | F19: =SUMPRODUCT(Adds!$C$56:$F$56,Curves!$BS$13:$BV$13) | G19: =SUMPRODUCT(Adds!$C$56:$G$56,Curves!$BR$13:$BV$13) | H19: =SUMPRODUCT(Adds!$C$56:$H$56,Curves!$BQ$13:$BV$13) | I19: =SUMPRODUCT(Adds!$C$56:$I$56,Curves!$BP$13:$BV$13) | J19: =SUMPRODUCT(Adds!$C$56:$J$56,Curves!$BO$13:$BV$13) | K19: =SUMPRODUCT(Adds!$C$56:$K$56,Curves!$BN$13:$BV$13) | L19: =SUMPRODUCT(Adds!$C$56:$L$56,Curves!$BM$13:$BV$13) | M19: =SUMPRODUCT(Adds!$C$56:$M$56,Curves!$BL$13:$BV$13) | N19: =SUMPRODUCT(Adds!$C$56:$N$56,Curves!$BK$13:$BV$13) | O19: =SUMPRODUCT(Adds!$C$56:$O$56,Curves!$BJ$13:$BV$13) | P19: =SUMPRODUCT(Adds!$C$56:$P$56,Curves!$BI$13:$BV$13) | Q19: =SUMPRODUCT(Adds!$C$56:$Q$56,Curves!$BH$13:$BV$13) | R19: =SUMPRODUCT(Adds!$C$56:$R$56,Curves!$BG$13:$BV$13) | S19: =SUMPRODUCT(Adds!$C$56:$S$56,Curves!$BF$13:$BV$13) | T19: =SUMPRODUCT(Adds!$C$56:$T$56,Curves!$BE$13:$BV$13) | U19: =SUMPRODUCT(Adds!$C$56:$U$56,Curves!$BD$13:$BV$13) | V19: =SUMPRODUCT(Adds!$C$56:$V$56,Curves!$BC$13:$BV$13) | W19: =SUMPRODUCT(Adds!$C$56:$W$56,Curves!$BB$13:$BV$13) | X19: =SUMPRODUCT(Adds!$C$56:$X$56,Curves!$BA$13:$BV$13) | Y19: =SUMPRODUCT(Adds!$C$56:$Y$56,Curves!$AZ$13:$BV$13) | Z19: =SUMPRODUCT(Adds!$C$56:$Z$56,Curves!$AY$13:$BV$13) | AA19: =SUMPRODUCT(Adds!$C$56:$AA$56,Curves!$AX$13:$BV$13) | AB19: =SUMPRODUCT(Adds!$C$56:$AB$56,Curves!$AW$13:$BV$13) | AC19: =SUMPRODUCT(Adds!$C$56:$AC$56,Curves!$AV$13:$BV$13) | AD19: =SUMPRODUCT(Adds!$C$56:$AD$56,Curves!$AU$13:$BV$13) | AE19: =SUMPRODUCT(Adds!$C$56:$AE$56,Curves!$AT$13:$BV$13) | AF19: =SUMPRODUCT(Adds!$C$56:$AF$56,Curves!$AS$13:$BV$13) | AG19: =SUMPRODUCT(Adds!$C$56:$AG$56,Curves!$AR$13:$BV$13) | AH19: =SUMPRODUCT(Adds!$C$56:$AH$56,Curves!$AQ$13:$BV$13) | AI19: =SUMPRODUCT(Adds!$C$56:$AI$56,Curves!$AP$13:$BV$13) | AJ19: =SUMPRODUCT(Adds!$C$56:$AJ$56,Curves!$AO$13:$BV$13) | AK19: =SUMPRODUCT(Adds!$C$56:$AK$56,Curves!$AN$13:$BV$13) | AL19: =SUMPRODUCT(Adds!$C$56:$AL$56,Curves!$AM$13:$BV$13) | AM19: =SUMPRODUCT(Adds!$C$56:$AM$56,Curves!$AL$13:$BV$13) | AN19: =SUMPRODUCT(Adds!$C$56:$AN$56,Curves!$AK$13:$BV$13) | AO19: =SUMPRODUCT(Adds!$C$56:$AO$56,Curves!$AJ$13:$BV$13) | AP19: =SUMPRODUCT(Adds!$C$56:$AP$56,Curves!$AI$13:$BV$13) | AQ19: =SUMPRODUCT(Adds!$C$56:$AQ$56,Curves!$AH$13:$BV$13) | AR19: =SUMPRODUCT(Adds!$C$56:$AR$56,Curves!$AG$13:$BV$13) | AS19: =SUMPRODUCT(Adds!$C$56:$AS$56,Curves!$AF$13:$BV$13) | AT19: =SUMPRODUCT(Adds!$C$56:$AT$56,Curves!$AE$13:$BV$13) | AU19: =SUMPRODUCT(Adds!$C$56:$AU$56,Curves!$AD$13:$BV$13) | AV19: =SUMPRODUCT(Adds!$C$56:$AV$56,Curves!$AC$13:$BV$13) | AW19: =SUMPRODUCT(Adds!$C$56:$AW$56,Curves!$AB$13:$BV$13) | AX19: =SUMPRODUCT(Adds!$C$56:$AX$56,Curves!$AA$13:$BV$13) | AY19: =SUMPRODUCT(Adds!$C$56:$AY$56,Curves!$Z$13:$BV$13) | AZ19: =SUMPRODUCT(Adds!$C$56:$AZ$56,Curves!$Y$13:$BV$13) | BA19: =SUMPRODUCT(Adds!$C$56:$BA$56,Curves!$X$13:$BV$13) | BB19: =SUMPRODUCT(Adds!$C$56:$BB$56,Curves!$W$13:$BV$13) | BC19: =SUMPRODUCT(Adds!$C$56:$BC$56,Curves!$V$13:$BV$13) | BD19: =SUMPRODUCT(Adds!$C$56:$BD$56,Curves!$U$13:$BV$13) | BE19: =SUMPRODUCT(Adds!$C$56:$BE$56,Curves!$T$13:$BV$13) | BF19: =SUMPRODUCT(Adds!$C$56:$BF$56,Curves!$S$13:$BV$13) | BG19: =SUMPRODUCT(Adds!$C$56:$BG$56,Curves!$R$13:$BV$13) | BH19: =SUMPRODUCT(Adds!$C$56:$BH$56,Curves!$Q$13:$BV$13) | BI19: =SUMPRODUCT(Adds!$C$56:$BI$56,Curves!$P$13:$BV$13) | BJ19: =SUMPRODUCT(Adds!$C$56:$BJ$56,Curves!$O$13:$BV$13) | BK19: =SUMPRODUCT(Adds!$C$56:$BK$56,Curves!$N$13:$BV$13) | BL19: =SUMPRODUCT(Adds!$C$56:$BL$56,Curves!$M$13:$BV$13) | BM19: =SUMPRODUCT(Adds!$C$56:$BM$56,Curves!$L$13:$BV$13) | BN19: =SUMPRODUCT(Adds!$C$56:$BN$56,Curves!$K$13:$BV$13) | BO19: =SUMPRODUCT(Adds!$C$56:$BO$56,Curves!$J$13:$BV$13) | BP19: =SUMPRODUCT(Adds!$C$56:$BP$56,Curves!$I$13:$BV$13) | BQ19: =SUMPRODUCT(Adds!$C$56:$BQ$56,Curves!$H$13:$BV$13) | BR19: =SUMPRODUCT(Adds!$C$56:$BR$56,Curves!$G$13:$BV$13) | BS19: =SUMPRODUCT(Adds!$C$56:$BS$56,Curves!$F$13:$BV$13) | BT19: =SUMPRODUCT(Adds!$C$56:$BT$56,Curves!$E$13:$BV$13) | BU19: =SUMPRODUCT(Adds!$C$56:$BU$56,Curves!$D$13:$BV$13) | BV19: =SUMPRODUCT(Adds!$C$56:$BV$56,Curves!$C$13:$BV$13)
A20: active yr 1 | B20: EUROPE|NITRO_M | C20: =Adds!$C$56*Curves!$BV$20 | D20: =SUMPRODUCT(Adds!$C$56:$D$56,Curves!$BU$20:$BV$20) | E20: =SUMPRODUCT(Adds!$C$56:$E$56,Curves!$BT$20:$BV$20) | F20: =SUMPRODUCT(Adds!$C$56:$F$56,Curves!$BS$20:$BV$20) | G20: =SUMPRODUCT(Adds!$C$56:$G$56,Curves!$BR$20:$BV$20) | H20: =SUMPRODUCT(Adds!$C$56:$H$56,Curves!$BQ$20:$BV$20) | I20: =SUMPRODUCT(Adds!$C$56:$I$56,Curves!$BP$20:$BV$20) | J20: =SUMPRODUCT(Adds!$C$56:$J$56,Curves!$BO$20:$BV$20) | K20: =SUMPRODUCT(Adds!$C$56:$K$56,Curves!$BN$20:$BV$20) | L20: =SUMPRODUCT(Adds!$C$56:$L$56,Curves!$BM$20:$BV$20) | M20: =SUMPRODUCT(Adds!$C$56:$M$56,Curves!$BL$20:$BV$20) | N20: =SUMPRODUCT(Adds!$C$56:$N$56,Curves!$BK$20:$BV$20) | O20: =SUMPRODUCT(Adds!$C$56:$O$56,Curves!$BJ$20:$BV$20) | P20: =SUMPRODUCT(Adds!$C$56:$P$56,Curves!$BI$20:$BV$20) | Q20: =SUMPRODUCT(Adds!$C$56:$Q$56,Curves!$BH$20:$BV$20) | R20: =SUMPRODUCT(Adds!$C$56:$R$56,Curves!$BG$20:$BV$20) | S20: =SUMPRODUCT(Adds!$C$56:$S$56,Curves!$BF$20:$BV$20) | T20: =SUMPRODUCT(Adds!$C$56:$T$56,Curves!$BE$20:$BV$20) | U20: =SUMPRODUCT(Adds!$C$56:$U$56,Curves!$BD$20:$BV$20) | V20: =SUMPRODUCT(Adds!$C$56:$V$56,Curves!$BC$20:$BV$20) | W20: =SUMPRODUCT(Adds!$C$56:$W$56,Curves!$BB$20:$BV$20) | X20: =SUMPRODUCT(Adds!$C$56:$X$56,Curves!$BA$20:$BV$20) | Y20: =SUMPRODUCT(Adds!$C$56:$Y$56,Curves!$AZ$20:$BV$20) | Z20: =SUMPRODUCT(Adds!$C$56:$Z$56,Curves!$AY$20:$BV$20) | AA20: =SUMPRODUCT(Adds!$C$56:$AA$56,Curves!$AX$20:$BV$20) | AB20: =SUMPRODUCT(Adds!$C$56:$AB$56,Curves!$AW$20:$BV$20) | AC20: =SUMPRODUCT(Adds!$C$56:$AC$56,Curves!$AV$20:$BV$20) | AD20: =SUMPRODUCT(Adds!$C$56:$AD$56,Curves!$AU$20:$BV$20) | AE20: =SUMPRODUCT(Adds!$C$56:$AE$56,Curves!$AT$20:$BV$20) | AF20: =SUMPRODUCT(Adds!$C$56:$AF$56,Curves!$AS$20:$BV$20) | AG20: =SUMPRODUCT(Adds!$C$56:$AG$56,Curves!$AR$20:$BV$20) | AH20: =SUMPRODUCT(Adds!$C$56:$AH$56,Curves!$AQ$20:$BV$20) | AI20: =SUMPRODUCT(Adds!$C$56:$AI$56,Curves!$AP$20:$BV$20) | AJ20: =SUMPRODUCT(Adds!$C$56:$AJ$56,Curves!$AO$20:$BV$20) | AK20: =SUMPRODUCT(Adds!$C$56:$AK$56,Curves!$AN$20:$BV$20) | AL20: =SUMPRODUCT(Adds!$C$56:$AL$56,Curves!$AM$20:$BV$20) | AM20: =SUMPRODUCT(Adds!$C$56:$AM$56,Curves!$AL$20:$BV$20) | AN20: =SUMPRODUCT(Adds!$C$56:$AN$56,Curves!$AK$20:$BV$20) | AO20: =SUMPRODUCT(Adds!$C$56:$AO$56,Curves!$AJ$20:$BV$20) | AP20: =SUMPRODUCT(Adds!$C$56:$AP$56,Curves!$AI$20:$BV$20) | AQ20: =SUMPRODUCT(Adds!$C$56:$AQ$56,Curves!$AH$20:$BV$20) | AR20: =SUMPRODUCT(Adds!$C$56:$AR$56,Curves!$AG$20:$BV$20) | AS20: =SUMPRODUCT(Adds!$C$56:$AS$56,Curves!$AF$20:$BV$20) | AT20: =SUMPRODUCT(Adds!$C$56:$AT$56,Curves!$AE$20:$BV$20) | AU20: =SUMPRODUCT(Adds!$C$56:$AU$56,Curves!$AD$20:$BV$20) | AV20: =SUMPRODUCT(Adds!$C$56:$AV$56,Curves!$AC$20:$BV$20) | AW20: =SUMPRODUCT(Adds!$C$56:$AW$56,Curves!$AB$20:$BV$20) | AX20: =SUMPRODUCT(Adds!$C$56:$AX$56,Curves!$AA$20:$BV$20) | AY20: =SUMPRODUCT(Adds!$C$56:$AY$56,Curves!$Z$20:$BV$20) | AZ20: =SUMPRODUCT(Adds!$C$56:$AZ$56,Curves!$Y$20:$BV$20) | BA20: =SUMPRODUCT(Adds!$C$56:$BA$56,Curves!$X$20:$BV$20) | BB20: =SUMPRODUCT(Adds!$C$56:$BB$56,Curves!$W$20:$BV$20) | BC20: =SUMPRODUCT(Adds!$C$56:$BC$56,Curves!$V$20:$BV$20) | BD20: =SUMPRODUCT(Adds!$C$56:$BD$56,Curves!$U$20:$BV$20) | BE20: =SUMPRODUCT(Adds!$C$56:$BE$56,Curves!$T$20:$BV$20) | BF20: =SUMPRODUCT(Adds!$C$56:$BF$56,Curves!$S$20:$BV$20) | BG20: =SUMPRODUCT(Adds!$C$56:$BG$56,Curves!$R$20:$BV$20) | BH20: =SUMPRODUCT(Adds!$C$56:$BH$56,Curves!$Q$20:$BV$20) | BI20: =SUMPRODUCT(Adds!$C$56:$BI$56,Curves!$P$20:$BV$20) | BJ20: =SUMPRODUCT(Adds!$C$56:$BJ$56,Curves!$O$20:$BV$20) | BK20: =SUMPRODUCT(Adds!$C$56:$BK$56,Curves!$N$20:$BV$20) | BL20: =SUMPRODUCT(Adds!$C$56:$BL$56,Curves!$M$20:$BV$20) | BM20: =SUMPRODUCT(Adds!$C$56:$BM$56,Curves!$L$20:$BV$20) | BN20: =SUMPRODUCT(Adds!$C$56:$BN$56,Curves!$K$20:$BV$20) | BO20: =SUMPRODUCT(Adds!$C$56:$BO$56,Curves!$J$20:$BV$20) | BP20: =SUMPRODUCT(Adds!$C$56:$BP$56,Curves!$I$20:$BV$20) | BQ20: =SUMPRODUCT(Adds!$C$56:$BQ$56,Curves!$H$20:$BV$20) | BR20: =SUMPRODUCT(Adds!$C$56:$BR$56,Curves!$G$20:$BV$20) | BS20: =SUMPRODUCT(Adds!$C$56:$BS$56,Curves!$F$20:$BV$20) | BT20: =SUMPRODUCT(Adds!$C$56:$BT$56,Curves!$E$20:$BV$20) | BU20: =SUMPRODUCT(Adds!$C$56:$BU$56,Curves!$D$20:$BV$20) | BV20: =SUMPRODUCT(Adds!$C$56:$BV$56,Curves!$C$20:$BV$20)
A21: churned | B21: EUROPE|NITRO_M | C21: =Adds!$C$56*Curves!$BV$15 | D21: =SUMPRODUCT(Adds!$C$56:$D$56,Curves!$BU$15:$BV$15) | E21: =SUMPRODUCT(Adds!$C$56:$E$56,Curves!$BT$15:$BV$15) | F21: =SUMPRODUCT(Adds!$C$56:$F$56,Curves!$BS$15:$BV$15) | G21: =SUMPRODUCT(Adds!$C$56:$G$56,Curves!$BR$15:$BV$15) | H21: =SUMPRODUCT(Adds!$C$56:$H$56,Curves!$BQ$15:$BV$15) | I21: =SUMPRODUCT(Adds!$C$56:$I$56,Curves!$BP$15:$BV$15) | J21: =SUMPRODUCT(Adds!$C$56:$J$56,Curves!$BO$15:$BV$15) | K21: =SUMPRODUCT(Adds!$C$56:$K$56,Curves!$BN$15:$BV$15) | L21: =SUMPRODUCT(Adds!$C$56:$L$56,Curves!$BM$15:$BV$15) | M21: =SUMPRODUCT(Adds!$C$56:$M$56,Curves!$BL$15:$BV$15) | N21: =SUMPRODUCT(Adds!$C$56:$N$56,Curves!$BK$15:$BV$15) | O21: =SUMPRODUCT(Adds!$C$56:$O$56,Curves!$BJ$15:$BV$15) | P21: =SUMPRODUCT(Adds!$C$56:$P$56,Curves!$BI$15:$BV$15) | Q21: =SUMPRODUCT(Adds!$C$56:$Q$56,Curves!$BH$15:$BV$15) | R21: =SUMPRODUCT(Adds!$C$56:$R$56,Curves!$BG$15:$BV$15) | S21: =SUMPRODUCT(Adds!$C$56:$S$56,Curves!$BF$15:$BV$15) | T21: =SUMPRODUCT(Adds!$C$56:$T$56,Curves!$BE$15:$BV$15) | U21: =SUMPRODUCT(Adds!$C$56:$U$56,Curves!$BD$15:$BV$15) | V21: =SUMPRODUCT(Adds!$C$56:$V$56,Curves!$BC$15:$BV$15) | W21: =SUMPRODUCT(Adds!$C$56:$W$56,Curves!$BB$15:$BV$15) | X21: =SUMPRODUCT(Adds!$C$56:$X$56,Curves!$BA$15:$BV$15) | Y21: =SUMPRODUCT(Adds!$C$56:$Y$56,Curves!$AZ$15:$BV$15) | Z21: =SUMPRODUCT(Adds!$C$56:$Z$56,Curves!$AY$15:$BV$15) | AA21: =SUMPRODUCT(Adds!$C$56:$AA$56,Curves!$AX$15:$BV$15) | AB21: =SUMPRODUCT(Adds!$C$56:$AB$56,Curves!$AW$15:$BV$15) | AC21: =SUMPRODUCT(Adds!$C$56:$AC$56,Curves!$AV$15:$BV$15) | AD21: =SUMPRODUCT(Adds!$C$56:$AD$56,Curves!$AU$15:$BV$15) | AE21: =SUMPRODUCT(Adds!$C$56:$AE$56,Curves!$AT$15:$BV$15) | AF21: =SUMPRODUCT(Adds!$C$56:$AF$56,Curves!$AS$15:$BV$15) | AG21: =SUMPRODUCT(Adds!$C$56:$AG$56,Curves!$AR$15:$BV$15) | AH21: =SUMPRODUCT(Adds!$C$56:$AH$56,Curves!$AQ$15:$BV$15) | AI21: =SUMPRODUCT(Adds!$C$56:$AI$56,Curves!$AP$15:$BV$15) | AJ21: =SUMPRODUCT(Adds!$C$56:$AJ$56,Curves!$AO$15:$BV$15) | AK21: =SUMPRODUCT(Adds!$C$56:$AK$56,Curves!$AN$15:$BV$15) | AL21: =SUMPRODUCT(Adds!$C$56:$AL$56,Curves!$AM$15:$BV$15) | AM21: =SUMPRODUCT(Adds!$C$56:$AM$56,Curves!$AL$15:$BV$15) | AN21: =SUMPRODUCT(Adds!$C$56:$AN$56,Curves!$AK$15:$BV$15) | AO21: =SUMPRODUCT(Adds!$C$56:$AO$56,Curves!$AJ$15:$BV$15) | AP21: =SUMPRODUCT(Adds!$C$56:$AP$56,Curves!$AI$15:$BV$15) | AQ21: =SUMPRODUCT(Adds!$C$56:$AQ$56,Curves!$AH$15:$BV$15) | AR21: =SUMPRODUCT(Adds!$C$56:$AR$56,Curves!$AG$15:$BV$15) | AS21: =SUMPRODUCT(Adds!$C$56:$AS$56,Curves!$AF$15:$BV$15) | AT21: =SUMPRODUCT(Adds!$C$56:$AT$56,Curves!$AE$15:$BV$15) | AU21: =SUMPRODUCT(Adds!$C$56:$AU$56,Curves!$AD$15:$BV$15) | AV21: =SUMPRODUCT(Adds!$C$56:$AV$56,Curves!$AC$15:$BV$15) | AW21: =SUMPRODUCT(Adds!$C$56:$AW$56,Curves!$AB$15:$BV$15) | AX21: =SUMPRODUCT(Adds!$C$56:$AX$56,Curves!$AA$15:$BV$15) | AY21: =SUMPRODUCT(Adds!$C$56:$AY$56,Curves!$Z$15:$BV$15) | AZ21: =SUMPRODUCT(Adds!$C$56:$AZ$56,Curves!$Y$15:$BV$15) | BA21: =SUMPRODUCT(Adds!$C$56:$BA$56,Curves!$X$15:$BV$15) | BB21: =SUMPRODUCT(Adds!$C$56:$BB$56,Curves!$W$15:$BV$15) | BC21: =SUMPRODUCT(Adds!$C$56:$BC$56,Curves!$V$15:$BV$15) | BD21: =SUMPRODUCT(Adds!$C$56:$BD$56,Curves!$U$15:$BV$15) | BE21: =SUMPRODUCT(Adds!$C$56:$BE$56,Curves!$T$15:$BV$15) | BF21: =SUMPRODUCT(Adds!$C$56:$BF$56,Curves!$S$15:$BV$15) | BG21: =SUMPRODUCT(Adds!$C$56:$BG$56,Curves!$R$15:$BV$15) | BH21: =SUMPRODUCT(Adds!$C$56:$BH$56,Curves!$Q$15:$BV$15) | BI21: =SUMPRODUCT(Adds!$C$56:$BI$56,Curves!$P$15:$BV$15) | BJ21: =SUMPRODUCT(Adds!$C$56:$BJ$56,Curves!$O$15:$BV$15) | BK21: =SUMPRODUCT(Adds!$C$56:$BK$56,Curves!$N$15:$BV$15) | BL21: =SUMPRODUCT(Adds!$C$56:$BL$56,Curves!$M$15:$BV$15) | BM21: =SUMPRODUCT(Adds!$C$56:$BM$56,Curves!$L$15:$BV$15) | BN21: =SUMPRODUCT(Adds!$C$56:$BN$56,Curves!$K$15:$BV$15) | BO21: =SUMPRODUCT(Adds!$C$56:$BO$56,Curves!$J$15:$BV$15) | BP21: =SUMPRODUCT(Adds!$C$56:$BP$56,Curves!$I$15:$BV$15) | BQ21: =SUMPRODUCT(Adds!$C$56:$BQ$56,Curves!$H$15:$BV$15) | BR21: =SUMPRODUCT(Adds!$C$56:$BR$56,Curves!$G$15:$BV$15) | BS21: =SUMPRODUCT(Adds!$C$56:$BS$56,Curves!$F$15:$BV$15) | BT21: =SUMPRODUCT(Adds!$C$56:$BT$56,Curves!$E$15:$BV$15) | BU21: =SUMPRODUCT(Adds!$C$56:$BU$56,Curves!$D$15:$BV$15) | BV21: =SUMPRODUCT(Adds!$C$56:$BV$56,Curves!$C$15:$BV$15)
A23: active | B23: EUROPE|NITRO_A | C23: =Adds!$C$67*Curves!$BV$14 | D23: =SUMPRODUCT(Adds!$C$67:$D$67,Curves!$BU$14:$BV$14) | E23: =SUMPRODUCT(Adds!$C$67:$E$67,Curves!$BT$14:$BV$14) | F23: =SUMPRODUCT(Adds!$C$67:$F$67,Curves!$BS$14:$BV$14) | G23: =SUMPRODUCT(Adds!$C$67:$G$67,Curves!$BR$14:$BV$14) | H23: =SUMPRODUCT(Adds!$C$67:$H$67,Curves!$BQ$14:$BV$14) | I23: =SUMPRODUCT(Adds!$C$67:$I$67,Curves!$BP$14:$BV$14) | J23: =SUMPRODUCT(Adds!$C$67:$J$67,Curves!$BO$14:$BV$14) | K23: =SUMPRODUCT(Adds!$C$67:$K$67,Curves!$BN$14:$BV$14) | L23: =SUMPRODUCT(Adds!$C$67:$L$67,Curves!$BM$14:$BV$14) | M23: =SUMPRODUCT(Adds!$C$67:$M$67,Curves!$BL$14:$BV$14) | N23: =SUMPRODUCT(Adds!$C$67:$N$67,Curves!$BK$14:$BV$14) | O23: =SUMPRODUCT(Adds!$C$67:$O$67,Curves!$BJ$14:$BV$14) | P23: =SUMPRODUCT(Adds!$C$67:$P$67,Curves!$BI$14:$BV$14) | Q23: =SUMPRODUCT(Adds!$C$67:$Q$67,Curves!$BH$14:$BV$14) | R23: =SUMPRODUCT(Adds!$C$67:$R$67,Curves!$BG$14:$BV$14) | S23: =SUMPRODUCT(Adds!$C$67:$S$67,Curves!$BF$14:$BV$14) | T23: =SUMPRODUCT(Adds!$C$67:$T$67,Curves!$BE$14:$BV$14) | U23: =SUMPRODUCT(Adds!$C$67:$U$67,Curves!$BD$14:$BV$14) | V23: =SUMPRODUCT(Adds!$C$67:$V$67,Curves!$BC$14:$BV$14) | W23: =SUMPRODUCT(Adds!$C$67:$W$67,Curves!$BB$14:$BV$14) | X23: =SUMPRODUCT(Adds!$C$67:$X$67,Curves!$BA$14:$BV$14) | Y23: =SUMPRODUCT(Adds!$C$67:$Y$67,Curves!$AZ$14:$BV$14) | Z23: =SUMPRODUCT(Adds!$C$67:$Z$67,Curves!$AY$14:$BV$14) | AA23: =SUMPRODUCT(Adds!$C$67:$AA$67,Curves!$AX$14:$BV$14) | AB23: =SUMPRODUCT(Adds!$C$67:$AB$67,Curves!$AW$14:$BV$14) | AC23: =SUMPRODUCT(Adds!$C$67:$AC$67,Curves!$AV$14:$BV$14) | AD23: =SUMPRODUCT(Adds!$C$67:$AD$67,Curves!$AU$14:$BV$14) | AE23: =SUMPRODUCT(Adds!$C$67:$AE$67,Curves!$AT$14:$BV$14) | AF23: =SUMPRODUCT(Adds!$C$67:$AF$67,Curves!$AS$14:$BV$14) | AG23: =SUMPRODUCT(Adds!$C$67:$AG$67,Curves!$AR$14:$BV$14) | AH23: =SUMPRODUCT(Adds!$C$67:$AH$67,Curves!$AQ$14:$BV$14) | AI23: =SUMPRODUCT(Adds!$C$67:$AI$67,Curves!$AP$14:$BV$14) | AJ23: =SUMPRODUCT(Adds!$C$67:$AJ$67,Curves!$AO$14:$BV$14) | AK23: =SUMPRODUCT(Adds!$C$67:$AK$67,Curves!$AN$14:$BV$14) | AL23: =SUMPRODUCT(Adds!$C$67:$AL$67,Curves!$AM$14:$BV$14) | AM23: =SUMPRODUCT(Adds!$C$67:$AM$67,Curves!$AL$14:$BV$14) | AN23: =SUMPRODUCT(Adds!$C$67:$AN$67,Curves!$AK$14:$BV$14) | AO23: =SUMPRODUCT(Adds!$C$67:$AO$67,Curves!$AJ$14:$BV$14) | AP23: =SUMPRODUCT(Adds!$C$67:$AP$67,Curves!$AI$14:$BV$14) | AQ23: =SUMPRODUCT(Adds!$C$67:$AQ$67,Curves!$AH$14:$BV$14) | AR23: =SUMPRODUCT(Adds!$C$67:$AR$67,Curves!$AG$14:$BV$14) | AS23: =SUMPRODUCT(Adds!$C$67:$AS$67,Curves!$AF$14:$BV$14) | AT23: =SUMPRODUCT(Adds!$C$67:$AT$67,Curves!$AE$14:$BV$14) | AU23: =SUMPRODUCT(Adds!$C$67:$AU$67,Curves!$AD$14:$BV$14) | AV23: =SUMPRODUCT(Adds!$C$67:$AV$67,Curves!$AC$14:$BV$14) | AW23: =SUMPRODUCT(Adds!$C$67:$AW$67,Curves!$AB$14:$BV$14) | AX23: =SUMPRODUCT(Adds!$C$67:$AX$67,Curves!$AA$14:$BV$14) | AY23: =SUMPRODUCT(Adds!$C$67:$AY$67,Curves!$Z$14:$BV$14) | AZ23: =SUMPRODUCT(Adds!$C$67:$AZ$67,Curves!$Y$14:$BV$14) | BA23: =SUMPRODUCT(Adds!$C$67:$BA$67,Curves!$X$14:$BV$14) | BB23: =SUMPRODUCT(Adds!$C$67:$BB$67,Curves!$W$14:$BV$14) | BC23: =SUMPRODUCT(Adds!$C$67:$BC$67,Curves!$V$14:$BV$14) | BD23: =SUMPRODUCT(Adds!$C$67:$BD$67,Curves!$U$14:$BV$14) | BE23: =SUMPRODUCT(Adds!$C$67:$BE$67,Curves!$T$14:$BV$14) | BF23: =SUMPRODUCT(Adds!$C$67:$BF$67,Curves!$S$14:$BV$14) | BG23: =SUMPRODUCT(Adds!$C$67:$BG$67,Curves!$R$14:$BV$14) | BH23: =SUMPRODUCT(Adds!$C$67:$BH$67,Curves!$Q$14:$BV$14) | BI23: =SUMPRODUCT(Adds!$C$67:$BI$67,Curves!$P$14:$BV$14) | BJ23: =SUMPRODUCT(Adds!$C$67:$BJ$67,Curves!$O$14:$BV$14) | BK23: =SUMPRODUCT(Adds!$C$67:$BK$67,Curves!$N$14:$BV$14) | BL23: =SUMPRODUCT(Adds!$C$67:$BL$67,Curves!$M$14:$BV$14) | BM23: =SUMPRODUCT(Adds!$C$67:$BM$67,Curves!$L$14:$BV$14) | BN23: =SUMPRODUCT(Adds!$C$67:$BN$67,Curves!$K$14:$BV$14) | BO23: =SUMPRODUCT(Adds!$C$67:$BO$67,Curves!$J$14:$BV$14) | BP23: =SUMPRODUCT(Adds!$C$67:$BP$67,Curves!$I$14:$BV$14) | BQ23: =SUMPRODUCT(Adds!$C$67:$BQ$67,Curves!$H$14:$BV$14) | BR23: =SUMPRODUCT(Adds!$C$67:$BR$67,Curves!$G$14:$BV$14) | BS23: =SUMPRODUCT(Adds!$C$67:$BS$67,Curves!$F$14:$BV$14) | BT23: =SUMPRODUCT(Adds!$C$67:$BT$67,Curves!$E$14:$BV$14) | BU23: =SUMPRODUCT(Adds!$C$67:$BU$67,Curves!$D$14:$BV$14) | BV23: =SUMPRODUCT(Adds!$C$67:$BV$67,Curves!$C$14:$BV$14)
A24: active yr 1 | B24: EUROPE|NITRO_A | C24: =Adds!$C$67*Curves!$BV$21 | D24: =SUMPRODUCT(Adds!$C$67:$D$67,Curves!$BU$21:$BV$21) | E24: =SUMPRODUCT(Adds!$C$67:$E$67,Curves!$BT$21:$BV$21) | F24: =SUMPRODUCT(Adds!$C$67:$F$67,Curves!$BS$21:$BV$21) | G24: =SUMPRODUCT(Adds!$C$67:$G$67,Curves!$BR$21:$BV$21) | H24: =SUMPRODUCT(Adds!$C$67:$H$67,Curves!$BQ$21:$BV$21) | I24: =SUMPRODUCT(Adds!$C$67:$I$67,Curves!$BP$21:$BV$21) | J24: =SUMPRODUCT(Adds!$C$67:$J$67,Curves!$BO$21:$BV$21) | K24: =SUMPRODUCT(Adds!$C$67:$K$67,Curves!$BN$21:$BV$21) | L24: =SUMPRODUCT(Adds!$C$67:$L$67,Curves!$BM$21:$BV$21) | M24: =SUMPRODUCT(Adds!$C$67:$M$67,Curves!$BL$21:$BV$21) | N24: =SUMPRODUCT(Adds!$C$67:$N$67,Curves!$BK$21:$BV$21) | O24: =SUMPRODUCT(Adds!$C$67:$O$67,Curves!$BJ$21:$BV$21) | P24: =SUMPRODUCT(Adds!$C$67:$P$67,Curves!$BI$21:$BV$21) | Q24: =SUMPRODUCT(Adds!$C$67:$Q$67,Curves!$BH$21:$BV$21) | R24: =SUMPRODUCT(Adds!$C$67:$R$67,Curves!$BG$21:$BV$21) | S24: =SUMPRODUCT(Adds!$C$67:$S$67,Curves!$BF$21:$BV$21) | T24: =SUMPRODUCT(Adds!$C$67:$T$67,Curves!$BE$21:$BV$21) | U24: =SUMPRODUCT(Adds!$C$67:$U$67,Curves!$BD$21:$BV$21) | V24: =SUMPRODUCT(Adds!$C$67:$V$67,Curves!$BC$21:$BV$21) | W24: =SUMPRODUCT(Adds!$C$67:$W$67,Curves!$BB$21:$BV$21) | X24: =SUMPRODUCT(Adds!$C$67:$X$67,Curves!$BA$21:$BV$21) | Y24: =SUMPRODUCT(Adds!$C$67:$Y$67,Curves!$AZ$21:$BV$21) | Z24: =SUMPRODUCT(Adds!$C$67:$Z$67,Curves!$AY$21:$BV$21) | AA24: =SUMPRODUCT(Adds!$C$67:$AA$67,Curves!$AX$21:$BV$21) | AB24: =SUMPRODUCT(Adds!$C$67:$AB$67,Curves!$AW$21:$BV$21) | AC24: =SUMPRODUCT(Adds!$C$67:$AC$67,Curves!$AV$21:$BV$21) | AD24: =SUMPRODUCT(Adds!$C$67:$AD$67,Curves!$AU$21:$BV$21) | AE24: =SUMPRODUCT(Adds!$C$67:$AE$67,Curves!$AT$21:$BV$21) | AF24: =SUMPRODUCT(Adds!$C$67:$AF$67,Curves!$AS$21:$BV$21) | AG24: =SUMPRODUCT(Adds!$C$67:$AG$67,Curves!$AR$21:$BV$21) | AH24: =SUMPRODUCT(Adds!$C$67:$AH$67,Curves!$AQ$21:$BV$21) | AI24: =SUMPRODUCT(Adds!$C$67:$AI$67,Curves!$AP$21:$BV$21) | AJ24: =SUMPRODUCT(Adds!$C$67:$AJ$67,Curves!$AO$21:$BV$21) | AK24: =SUMPRODUCT(Adds!$C$67:$AK$67,Curves!$AN$21:$BV$21) | AL24: =SUMPRODUCT(Adds!$C$67:$AL$67,Curves!$AM$21:$BV$21) | AM24: =SUMPRODUCT(Adds!$C$67:$AM$67,Curves!$AL$21:$BV$21) | AN24: =SUMPRODUCT(Adds!$C$67:$AN$67,Curves!$AK$21:$BV$21) | AO24: =SUMPRODUCT(Adds!$C$67:$AO$67,Curves!$AJ$21:$BV$21) | AP24: =SUMPRODUCT(Adds!$C$67:$AP$67,Curves!$AI$21:$BV$21) | AQ24: =SUMPRODUCT(Adds!$C$67:$AQ$67,Curves!$AH$21:$BV$21) | AR24: =SUMPRODUCT(Adds!$C$67:$AR$67,Curves!$AG$21:$BV$21) | AS24: =SUMPRODUCT(Adds!$C$67:$AS$67,Curves!$AF$21:$BV$21) | AT24: =SUMPRODUCT(Adds!$C$67:$AT$67,Curves!$AE$21:$BV$21) | AU24: =SUMPRODUCT(Adds!$C$67:$AU$67,Curves!$AD$21:$BV$21) | AV24: =SUMPRODUCT(Adds!$C$67:$AV$67,Curves!$AC$21:$BV$21) | AW24: =SUMPRODUCT(Adds!$C$67:$AW$67,Curves!$AB$21:$BV$21) | AX24: =SUMPRODUCT(Adds!$C$67:$AX$67,Curves!$AA$21:$BV$21) | AY24: =SUMPRODUCT(Adds!$C$67:$AY$67,Curves!$Z$21:$BV$21) | AZ24: =SUMPRODUCT(Adds!$C$67:$AZ$67,Curves!$Y$21:$BV$21) | BA24: =SUMPRODUCT(Adds!$C$67:$BA$67,Curves!$X$21:$BV$21) | BB24: =SUMPRODUCT(Adds!$C$67:$BB$67,Curves!$W$21:$BV$21) | BC24: =SUMPRODUCT(Adds!$C$67:$BC$67,Curves!$V$21:$BV$21) | BD24: =SUMPRODUCT(Adds!$C$67:$BD$67,Curves!$U$21:$BV$21) | BE24: =SUMPRODUCT(Adds!$C$67:$BE$67,Curves!$T$21:$BV$21) | BF24: =SUMPRODUCT(Adds!$C$67:$BF$67,Curves!$S$21:$BV$21) | BG24: =SUMPRODUCT(Adds!$C$67:$BG$67,Curves!$R$21:$BV$21) | BH24: =SUMPRODUCT(Adds!$C$67:$BH$67,Curves!$Q$21:$BV$21) | BI24: =SUMPRODUCT(Adds!$C$67:$BI$67,Curves!$P$21:$BV$21) | BJ24: =SUMPRODUCT(Adds!$C$67:$BJ$67,Curves!$O$21:$BV$21) | BK24: =SUMPRODUCT(Adds!$C$67:$BK$67,Curves!$N$21:$BV$21) | BL24: =SUMPRODUCT(Adds!$C$67:$BL$67,Curves!$M$21:$BV$21) | BM24: =SUMPRODUCT(Adds!$C$67:$BM$67,Curves!$L$21:$BV$21) | BN24: =SUMPRODUCT(Adds!$C$67:$BN$67,Curves!$K$21:$BV$21) | BO24: =SUMPRODUCT(Adds!$C$67:$BO$67,Curves!$J$21:$BV$21) | BP24: =SUMPRODUCT(Adds!$C$67:$BP$67,Curves!$I$21:$BV$21) | BQ24: =SUMPRODUCT(Adds!$C$67:$BQ$67,Curves!$H$21:$BV$21) | BR24: =SUMPRODUCT(Adds!$C$67:$BR$67,Curves!$G$21:$BV$21) | BS24: =SUMPRODUCT(Adds!$C$67:$BS$67,Curves!$F$21:$BV$21) | BT24: =SUMPRODUCT(Adds!$C$67:$BT$67,Curves!$E$21:$BV$21) | BU24: =SUMPRODUCT(Adds!$C$67:$BU$67,Curves!$D$21:$BV$21) | BV24: =SUMPRODUCT(Adds!$C$67:$BV$67,Curves!$C$21:$BV$21)
A25: churned | B25: EUROPE|NITRO_A | C25: =Adds!$C$67*Curves!$BV$16 | D25: =SUMPRODUCT(Adds!$C$67:$D$67,Curves!$BU$16:$BV$16) | E25: =SUMPRODUCT(Adds!$C$67:$E$67,Curves!$BT$16:$BV$16) | F25: =SUMPRODUCT(Adds!$C$67:$F$67,Curves!$BS$16:$BV$16) | G25: =SUMPRODUCT(Adds!$C$67:$G$67,Curves!$BR$16:$BV$16) | H25: =SUMPRODUCT(Adds!$C$67:$H$67,Curves!$BQ$16:$BV$16) | I25: =SUMPRODUCT(Adds!$C$67:$I$67,Curves!$BP$16:$BV$16) | J25: =SUMPRODUCT(Adds!$C$67:$J$67,Curves!$BO$16:$BV$16) | K25: =SUMPRODUCT(Adds!$C$67:$K$67,Curves!$BN$16:$BV$16) | L25: =SUMPRODUCT(Adds!$C$67:$L$67,Curves!$BM$16:$BV$16) | M25: =SUMPRODUCT(Adds!$C$67:$M$67,Curves!$BL$16:$BV$16) | N25: =SUMPRODUCT(Adds!$C$67:$N$67,Curves!$BK$16:$BV$16) | O25: =SUMPRODUCT(Adds!$C$67:$O$67,Curves!$BJ$16:$BV$16) | P25: =SUMPRODUCT(Adds!$C$67:$P$67,Curves!$BI$16:$BV$16) | Q25: =SUMPRODUCT(Adds!$C$67:$Q$67,Curves!$BH$16:$BV$16) | R25: =SUMPRODUCT(Adds!$C$67:$R$67,Curves!$BG$16:$BV$16) | S25: =SUMPRODUCT(Adds!$C$67:$S$67,Curves!$BF$16:$BV$16) | T25: =SUMPRODUCT(Adds!$C$67:$T$67,Curves!$BE$16:$BV$16) | U25: =SUMPRODUCT(Adds!$C$67:$U$67,Curves!$BD$16:$BV$16) | V25: =SUMPRODUCT(Adds!$C$67:$V$67,Curves!$BC$16:$BV$16) | W25: =SUMPRODUCT(Adds!$C$67:$W$67,Curves!$BB$16:$BV$16) | X25: =SUMPRODUCT(Adds!$C$67:$X$67,Curves!$BA$16:$BV$16) | Y25: =SUMPRODUCT(Adds!$C$67:$Y$67,Curves!$AZ$16:$BV$16) | Z25: =SUMPRODUCT(Adds!$C$67:$Z$67,Curves!$AY$16:$BV$16) | AA25: =SUMPRODUCT(Adds!$C$67:$AA$67,Curves!$AX$16:$BV$16) | AB25: =SUMPRODUCT(Adds!$C$67:$AB$67,Curves!$AW$16:$BV$16) | AC25: =SUMPRODUCT(Adds!$C$67:$AC$67,Curves!$AV$16:$BV$16) | AD25: =SUMPRODUCT(Adds!$C$67:$AD$67,Curves!$AU$16:$BV$16) | AE25: =SUMPRODUCT(Adds!$C$67:$AE$67,Curves!$AT$16:$BV$16) | AF25: =SUMPRODUCT(Adds!$C$67:$AF$67,Curves!$AS$16:$BV$16) | AG25: =SUMPRODUCT(Adds!$C$67:$AG$67,Curves!$AR$16:$BV$16) | AH25: =SUMPRODUCT(Adds!$C$67:$AH$67,Curves!$AQ$16:$BV$16) | AI25: =SUMPRODUCT(Adds!$C$67:$AI$67,Curves!$AP$16:$BV$16) | AJ25: =SUMPRODUCT(Adds!$C$67:$AJ$67,Curves!$AO$16:$BV$16) | AK25: =SUMPRODUCT(Adds!$C$67:$AK$67,Curves!$AN$16:$BV$16) | AL25: =SUMPRODUCT(Adds!$C$67:$AL$67,Curves!$AM$16:$BV$16) | AM25: =SUMPRODUCT(Adds!$C$67:$AM$67,Curves!$AL$16:$BV$16) | AN25: =SUMPRODUCT(Adds!$C$67:$AN$67,Curves!$AK$16:$BV$16) | AO25: =SUMPRODUCT(Adds!$C$67:$AO$67,Curves!$AJ$16:$BV$16) | AP25: =SUMPRODUCT(Adds!$C$67:$AP$67,Curves!$AI$16:$BV$16) | AQ25: =SUMPRODUCT(Adds!$C$67:$AQ$67,Curves!$AH$16:$BV$16) | AR25: =SUMPRODUCT(Adds!$C$67:$AR$67,Curves!$AG$16:$BV$16) | AS25: =SUMPRODUCT(Adds!$C$67:$AS$67,Curves!$AF$16:$BV$16) | AT25: =SUMPRODUCT(Adds!$C$67:$AT$67,Curves!$AE$16:$BV$16) | AU25: =SUMPRODUCT(Adds!$C$67:$AU$67,Curves!$AD$16:$BV$16) | AV25: =SUMPRODUCT(Adds!$C$67:$AV$67,Curves!$AC$16:$BV$16) | AW25: =SUMPRODUCT(Adds!$C$67:$AW$67,Curves!$AB$16:$BV$16) | AX25: =SUMPRODUCT(Adds!$C$67:$AX$67,Curves!$AA$16:$BV$16) | AY25: =SUMPRODUCT(Adds!$C$67:$AY$67,Curves!$Z$16:$BV$16) | AZ25: =SUMPRODUCT(Adds!$C$67:$AZ$67,Curves!$Y$16:$BV$16) | BA25: =SUMPRODUCT(Adds!$C$67:$BA$67,Curves!$X$16:$BV$16) | BB25: =SUMPRODUCT(Adds!$C$67:$BB$67,Curves!$W$16:$BV$16) | BC25: =SUMPRODUCT(Adds!$C$67:$BC$67,Curves!$V$16:$BV$16) | BD25: =SUMPRODUCT(Adds!$C$67:$BD$67,Curves!$U$16:$BV$16) | BE25: =SUMPRODUCT(Adds!$C$67:$BE$67,Curves!$T$16:$BV$16) | BF25: =SUMPRODUCT(Adds!$C$67:$BF$67,Curves!$S$16:$BV$16) | BG25: =SUMPRODUCT(Adds!$C$67:$BG$67,Curves!$R$16:$BV$16) | BH25: =SUMPRODUCT(Adds!$C$67:$BH$67,Curves!$Q$16:$BV$16) | BI25: =SUMPRODUCT(Adds!$C$67:$BI$67,Curves!$P$16:$BV$16) | BJ25: =SUMPRODUCT(Adds!$C$67:$BJ$67,Curves!$O$16:$BV$16) | BK25: =SUMPRODUCT(Adds!$C$67:$BK$67,Curves!$N$16:$BV$16) | BL25: =SUMPRODUCT(Adds!$C$67:$BL$67,Curves!$M$16:$BV$16) | BM25: =SUMPRODUCT(Adds!$C$67:$BM$67,Curves!$L$16:$BV$16) | BN25: =SUMPRODUCT(Adds!$C$67:$BN$67,Curves!$K$16:$BV$16) | BO25: =SUMPRODUCT(Adds!$C$67:$BO$67,Curves!$J$16:$BV$16) | BP25: =SUMPRODUCT(Adds!$C$67:$BP$67,Curves!$I$16:$BV$16) | BQ25: =SUMPRODUCT(Adds!$C$67:$BQ$67,Curves!$H$16:$BV$16) | BR25: =SUMPRODUCT(Adds!$C$67:$BR$67,Curves!$G$16:$BV$16) | BS25: =SUMPRODUCT(Adds!$C$67:$BS$67,Curves!$F$16:$BV$16) | BT25: =SUMPRODUCT(Adds!$C$67:$BT$67,Curves!$E$16:$BV$16) | BU25: =SUMPRODUCT(Adds!$C$67:$BU$67,Curves!$D$16:$BV$16) | BV25: =SUMPRODUCT(Adds!$C$67:$BV$67,Curves!$C$16:$BV$16)
A27: active | B27: EUROPE|BASIC_M | C27: =Adds!$C$78*Curves!$BV$13 | D27: =SUMPRODUCT(Adds!$C$78:$D$78,Curves!$BU$13:$BV$13) | E27: =SUMPRODUCT(Adds!$C$78:$E$78,Curves!$BT$13:$BV$13) | F27: =SUMPRODUCT(Adds!$C$78:$F$78,Curves!$BS$13:$BV$13) | G27: =SUMPRODUCT(Adds!$C$78:$G$78,Curves!$BR$13:$BV$13) | H27: =SUMPRODUCT(Adds!$C$78:$H$78,Curves!$BQ$13:$BV$13) | I27: =SUMPRODUCT(Adds!$C$78:$I$78,Curves!$BP$13:$BV$13) | J27: =SUMPRODUCT(Adds!$C$78:$J$78,Curves!$BO$13:$BV$13) | K27: =SUMPRODUCT(Adds!$C$78:$K$78,Curves!$BN$13:$BV$13) | L27: =SUMPRODUCT(Adds!$C$78:$L$78,Curves!$BM$13:$BV$13) | M27: =SUMPRODUCT(Adds!$C$78:$M$78,Curves!$BL$13:$BV$13) | N27: =SUMPRODUCT(Adds!$C$78:$N$78,Curves!$BK$13:$BV$13) | O27: =SUMPRODUCT(Adds!$C$78:$O$78,Curves!$BJ$13:$BV$13) | P27: =SUMPRODUCT(Adds!$C$78:$P$78,Curves!$BI$13:$BV$13) | Q27: =SUMPRODUCT(Adds!$C$78:$Q$78,Curves!$BH$13:$BV$13) | R27: =SUMPRODUCT(Adds!$C$78:$R$78,Curves!$BG$13:$BV$13) | S27: =SUMPRODUCT(Adds!$C$78:$S$78,Curves!$BF$13:$BV$13) | T27: =SUMPRODUCT(Adds!$C$78:$T$78,Curves!$BE$13:$BV$13) | U27: =SUMPRODUCT(Adds!$C$78:$U$78,Curves!$BD$13:$BV$13) | V27: =SUMPRODUCT(Adds!$C$78:$V$78,Curves!$BC$13:$BV$13) | W27: =SUMPRODUCT(Adds!$C$78:$W$78,Curves!$BB$13:$BV$13) | X27: =SUMPRODUCT(Adds!$C$78:$X$78,Curves!$BA$13:$BV$13) | Y27: =SUMPRODUCT(Adds!$C$78:$Y$78,Curves!$AZ$13:$BV$13) | Z27: =SUMPRODUCT(Adds!$C$78:$Z$78,Curves!$AY$13:$BV$13) | AA27: =SUMPRODUCT(Adds!$C$78:$AA$78,Curves!$AX$13:$BV$13) | AB27: =SUMPRODUCT(Adds!$C$78:$AB$78,Curves!$AW$13:$BV$13) | AC27: =SUMPRODUCT(Adds!$C$78:$AC$78,Curves!$AV$13:$BV$13) | AD27: =SUMPRODUCT(Adds!$C$78:$AD$78,Curves!$AU$13:$BV$13) | AE27: =SUMPRODUCT(Adds!$C$78:$AE$78,Curves!$AT$13:$BV$13) | AF27: =SUMPRODUCT(Adds!$C$78:$AF$78,Curves!$AS$13:$BV$13) | AG27: =SUMPRODUCT(Adds!$C$78:$AG$78,Curves!$AR$13:$BV$13) | AH27: =SUMPRODUCT(Adds!$C$78:$AH$78,Curves!$AQ$13:$BV$13) | AI27: =SUMPRODUCT(Adds!$C$78:$AI$78,Curves!$AP$13:$BV$13) | AJ27: =SUMPRODUCT(Adds!$C$78:$AJ$78,Curves!$AO$13:$BV$13) | AK27: =SUMPRODUCT(Adds!$C$78:$AK$78,Curves!$AN$13:$BV$13) | AL27: =SUMPRODUCT(Adds!$C$78:$AL$78,Curves!$AM$13:$BV$13) | AM27: =SUMPRODUCT(Adds!$C$78:$AM$78,Curves!$AL$13:$BV$13) | AN27: =SUMPRODUCT(Adds!$C$78:$AN$78,Curves!$AK$13:$BV$13) | AO27: =SUMPRODUCT(Adds!$C$78:$AO$78,Curves!$AJ$13:$BV$13) | AP27: =SUMPRODUCT(Adds!$C$78:$AP$78,Curves!$AI$13:$BV$13) | AQ27: =SUMPRODUCT(Adds!$C$78:$AQ$78,Curves!$AH$13:$BV$13) | AR27: =SUMPRODUCT(Adds!$C$78:$AR$78,Curves!$AG$13:$BV$13) | AS27: =SUMPRODUCT(Adds!$C$78:$AS$78,Curves!$AF$13:$BV$13) | AT27: =SUMPRODUCT(Adds!$C$78:$AT$78,Curves!$AE$13:$BV$13) | AU27: =SUMPRODUCT(Adds!$C$78:$AU$78,Curves!$AD$13:$BV$13) | AV27: =SUMPRODUCT(Adds!$C$78:$AV$78,Curves!$AC$13:$BV$13) | AW27: =SUMPRODUCT(Adds!$C$78:$AW$78,Curves!$AB$13:$BV$13) | AX27: =SUMPRODUCT(Adds!$C$78:$AX$78,Curves!$AA$13:$BV$13) | AY27: =SUMPRODUCT(Adds!$C$78:$AY$78,Curves!$Z$13:$BV$13) | AZ27: =SUMPRODUCT(Adds!$C$78:$AZ$78,Curves!$Y$13:$BV$13) | BA27: =SUMPRODUCT(Adds!$C$78:$BA$78,Curves!$X$13:$BV$13) | BB27: =SUMPRODUCT(Adds!$C$78:$BB$78,Curves!$W$13:$BV$13) | BC27: =SUMPRODUCT(Adds!$C$78:$BC$78,Curves!$V$13:$BV$13) | BD27: =SUMPRODUCT(Adds!$C$78:$BD$78,Curves!$U$13:$BV$13) | BE27: =SUMPRODUCT(Adds!$C$78:$BE$78,Curves!$T$13:$BV$13) | BF27: =SUMPRODUCT(Adds!$C$78:$BF$78,Curves!$S$13:$BV$13) | BG27: =SUMPRODUCT(Adds!$C$78:$BG$78,Curves!$R$13:$BV$13) | BH27: =SUMPRODUCT(Adds!$C$78:$BH$78,Curves!$Q$13:$BV$13) | BI27: =SUMPRODUCT(Adds!$C$78:$BI$78,Curves!$P$13:$BV$13) | BJ27: =SUMPRODUCT(Adds!$C$78:$BJ$78,Curves!$O$13:$BV$13) | BK27: =SUMPRODUCT(Adds!$C$78:$BK$78,Curves!$N$13:$BV$13) | BL27: =SUMPRODUCT(Adds!$C$78:$BL$78,Curves!$M$13:$BV$13) | BM27: =SUMPRODUCT(Adds!$C$78:$BM$78,Curves!$L$13:$BV$13) | BN27: =SUMPRODUCT(Adds!$C$78:$BN$78,Curves!$K$13:$BV$13) | BO27: =SUMPRODUCT(Adds!$C$78:$BO$78,Curves!$J$13:$BV$13) | BP27: =SUMPRODUCT(Adds!$C$78:$BP$78,Curves!$I$13:$BV$13) | BQ27: =SUMPRODUCT(Adds!$C$78:$BQ$78,Curves!$H$13:$BV$13) | BR27: =SUMPRODUCT(Adds!$C$78:$BR$78,Curves!$G$13:$BV$13) | BS27: =SUMPRODUCT(Adds!$C$78:$BS$78,Curves!$F$13:$BV$13) | BT27: =SUMPRODUCT(Adds!$C$78:$BT$78,Curves!$E$13:$BV$13) | BU27: =SUMPRODUCT(Adds!$C$78:$BU$78,Curves!$D$13:$BV$13) | BV27: =SUMPRODUCT(Adds!$C$78:$BV$78,Curves!$C$13:$BV$13)
A28: active yr 1 | B28: EUROPE|BASIC_M | C28: =Adds!$C$78*Curves!$BV$20 | D28: =SUMPRODUCT(Adds!$C$78:$D$78,Curves!$BU$20:$BV$20) | E28: =SUMPRODUCT(Adds!$C$78:$E$78,Curves!$BT$20:$BV$20) | F28: =SUMPRODUCT(Adds!$C$78:$F$78,Curves!$BS$20:$BV$20) | G28: =SUMPRODUCT(Adds!$C$78:$G$78,Curves!$BR$20:$BV$20) | H28: =SUMPRODUCT(Adds!$C$78:$H$78,Curves!$BQ$20:$BV$20) | I28: =SUMPRODUCT(Adds!$C$78:$I$78,Curves!$BP$20:$BV$20) | J28: =SUMPRODUCT(Adds!$C$78:$J$78,Curves!$BO$20:$BV$20) | K28: =SUMPRODUCT(Adds!$C$78:$K$78,Curves!$BN$20:$BV$20) | L28: =SUMPRODUCT(Adds!$C$78:$L$78,Curves!$BM$20:$BV$20) | M28: =SUMPRODUCT(Adds!$C$78:$M$78,Curves!$BL$20:$BV$20) | N28: =SUMPRODUCT(Adds!$C$78:$N$78,Curves!$BK$20:$BV$20) | O28: =SUMPRODUCT(Adds!$C$78:$O$78,Curves!$BJ$20:$BV$20) | P28: =SUMPRODUCT(Adds!$C$78:$P$78,Curves!$BI$20:$BV$20) | Q28: =SUMPRODUCT(Adds!$C$78:$Q$78,Curves!$BH$20:$BV$20) | R28: =SUMPRODUCT(Adds!$C$78:$R$78,Curves!$BG$20:$BV$20) | S28: =SUMPRODUCT(Adds!$C$78:$S$78,Curves!$BF$20:$BV$20) | T28: =SUMPRODUCT(Adds!$C$78:$T$78,Curves!$BE$20:$BV$20) | U28: =SUMPRODUCT(Adds!$C$78:$U$78,Curves!$BD$20:$BV$20) | V28: =SUMPRODUCT(Adds!$C$78:$V$78,Curves!$BC$20:$BV$20) | W28: =SUMPRODUCT(Adds!$C$78:$W$78,Curves!$BB$20:$BV$20) | X28: =SUMPRODUCT(Adds!$C$78:$X$78,Curves!$BA$20:$BV$20) | Y28: =SUMPRODUCT(Adds!$C$78:$Y$78,Curves!$AZ$20:$BV$20) | Z28: =SUMPRODUCT(Adds!$C$78:$Z$78,Curves!$AY$20:$BV$20) | AA28: =SUMPRODUCT(Adds!$C$78:$AA$78,Curves!$AX$20:$BV$20) | AB28: =SUMPRODUCT(Adds!$C$78:$AB$78,Curves!$AW$20:$BV$20) | AC28: =SUMPRODUCT(Adds!$C$78:$AC$78,Curves!$AV$20:$BV$20) | AD28: =SUMPRODUCT(Adds!$C$78:$AD$78,Curves!$AU$20:$BV$20) | AE28: =SUMPRODUCT(Adds!$C$78:$AE$78,Curves!$AT$20:$BV$20) | AF28: =SUMPRODUCT(Adds!$C$78:$AF$78,Curves!$AS$20:$BV$20) | AG28: =SUMPRODUCT(Adds!$C$78:$AG$78,Curves!$AR$20:$BV$20) | AH28: =SUMPRODUCT(Adds!$C$78:$AH$78,Curves!$AQ$20:$BV$20) | AI28: =SUMPRODUCT(Adds!$C$78:$AI$78,Curves!$AP$20:$BV$20) | AJ28: =SUMPRODUCT(Adds!$C$78:$AJ$78,Curves!$AO$20:$BV$20) | AK28: =SUMPRODUCT(Adds!$C$78:$AK$78,Curves!$AN$20:$BV$20) | AL28: =SUMPRODUCT(Adds!$C$78:$AL$78,Curves!$AM$20:$BV$20) | AM28: =SUMPRODUCT(Adds!$C$78:$AM$78,Curves!$AL$20:$BV$20) | AN28: =SUMPRODUCT(Adds!$C$78:$AN$78,Curves!$AK$20:$BV$20) | AO28: =SUMPRODUCT(Adds!$C$78:$AO$78,Curves!$AJ$20:$BV$20) | AP28: =SUMPRODUCT(Adds!$C$78:$AP$78,Curves!$AI$20:$BV$20) | AQ28: =SUMPRODUCT(Adds!$C$78:$AQ$78,Curves!$AH$20:$BV$20) | AR28: =SUMPRODUCT(Adds!$C$78:$AR$78,Curves!$AG$20:$BV$20) | AS28: =SUMPRODUCT(Adds!$C$78:$AS$78,Curves!$AF$20:$BV$20) | AT28: =SUMPRODUCT(Adds!$C$78:$AT$78,Curves!$AE$20:$BV$20) | AU28: =SUMPRODUCT(Adds!$C$78:$AU$78,Curves!$AD$20:$BV$20) | AV28: =SUMPRODUCT(Adds!$C$78:$AV$78,Curves!$AC$20:$BV$20) | AW28: =SUMPRODUCT(Adds!$C$78:$AW$78,Curves!$AB$20:$BV$20) | AX28: =SUMPRODUCT(Adds!$C$78:$AX$78,Curves!$AA$20:$BV$20) | AY28: =SUMPRODUCT(Adds!$C$78:$AY$78,Curves!$Z$20:$BV$20) | AZ28: =SUMPRODUCT(Adds!$C$78:$AZ$78,Curves!$Y$20:$BV$20) | BA28: =SUMPRODUCT(Adds!$C$78:$BA$78,Curves!$X$20:$BV$20) | BB28: =SUMPRODUCT(Adds!$C$78:$BB$78,Curves!$W$20:$BV$20) | BC28: =SUMPRODUCT(Adds!$C$78:$BC$78,Curves!$V$20:$BV$20) | BD28: =SUMPRODUCT(Adds!$C$78:$BD$78,Curves!$U$20:$BV$20) | BE28: =SUMPRODUCT(Adds!$C$78:$BE$78,Curves!$T$20:$BV$20) | BF28: =SUMPRODUCT(Adds!$C$78:$BF$78,Curves!$S$20:$BV$20) | BG28: =SUMPRODUCT(Adds!$C$78:$BG$78,Curves!$R$20:$BV$20) | BH28: =SUMPRODUCT(Adds!$C$78:$BH$78,Curves!$Q$20:$BV$20) | BI28: =SUMPRODUCT(Adds!$C$78:$BI$78,Curves!$P$20:$BV$20) | BJ28: =SUMPRODUCT(Adds!$C$78:$BJ$78,Curves!$O$20:$BV$20) | BK28: =SUMPRODUCT(Adds!$C$78:$BK$78,Curves!$N$20:$BV$20) | BL28: =SUMPRODUCT(Adds!$C$78:$BL$78,Curves!$M$20:$BV$20) | BM28: =SUMPRODUCT(Adds!$C$78:$BM$78,Curves!$L$20:$BV$20) | BN28: =SUMPRODUCT(Adds!$C$78:$BN$78,Curves!$K$20:$BV$20) | BO28: =SUMPRODUCT(Adds!$C$78:$BO$78,Curves!$J$20:$BV$20) | BP28: =SUMPRODUCT(Adds!$C$78:$BP$78,Curves!$I$20:$BV$20) | BQ28: =SUMPRODUCT(Adds!$C$78:$BQ$78,Curves!$H$20:$BV$20) | BR28: =SUMPRODUCT(Adds!$C$78:$BR$78,Curves!$G$20:$BV$20) | BS28: =SUMPRODUCT(Adds!$C$78:$BS$78,Curves!$F$20:$BV$20) | BT28: =SUMPRODUCT(Adds!$C$78:$BT$78,Curves!$E$20:$BV$20) | BU28: =SUMPRODUCT(Adds!$C$78:$BU$78,Curves!$D$20:$BV$20) | BV28: =SUMPRODUCT(Adds!$C$78:$BV$78,Curves!$C$20:$BV$20)
A29: churned | B29: EUROPE|BASIC_M | C29: =Adds!$C$78*Curves!$BV$15 | D29: =SUMPRODUCT(Adds!$C$78:$D$78,Curves!$BU$15:$BV$15) | E29: =SUMPRODUCT(Adds!$C$78:$E$78,Curves!$BT$15:$BV$15) | F29: =SUMPRODUCT(Adds!$C$78:$F$78,Curves!$BS$15:$BV$15) | G29: =SUMPRODUCT(Adds!$C$78:$G$78,Curves!$BR$15:$BV$15) | H29: =SUMPRODUCT(Adds!$C$78:$H$78,Curves!$BQ$15:$BV$15) | I29: =SUMPRODUCT(Adds!$C$78:$I$78,Curves!$BP$15:$BV$15) | J29: =SUMPRODUCT(Adds!$C$78:$J$78,Curves!$BO$15:$BV$15) | K29: =SUMPRODUCT(Adds!$C$78:$K$78,Curves!$BN$15:$BV$15) | L29: =SUMPRODUCT(Adds!$C$78:$L$78,Curves!$BM$15:$BV$15) | M29: =SUMPRODUCT(Adds!$C$78:$M$78,Curves!$BL$15:$BV$15) | N29: =SUMPRODUCT(Adds!$C$78:$N$78,Curves!$BK$15:$BV$15) | O29: =SUMPRODUCT(Adds!$C$78:$O$78,Curves!$BJ$15:$BV$15) | P29: =SUMPRODUCT(Adds!$C$78:$P$78,Curves!$BI$15:$BV$15) | Q29: =SUMPRODUCT(Adds!$C$78:$Q$78,Curves!$BH$15:$BV$15) | R29: =SUMPRODUCT(Adds!$C$78:$R$78,Curves!$BG$15:$BV$15) | S29: =SUMPRODUCT(Adds!$C$78:$S$78,Curves!$BF$15:$BV$15) | T29: =SUMPRODUCT(Adds!$C$78:$T$78,Curves!$BE$15:$BV$15) | U29: =SUMPRODUCT(Adds!$C$78:$U$78,Curves!$BD$15:$BV$15) | V29: =SUMPRODUCT(Adds!$C$78:$V$78,Curves!$BC$15:$BV$15) | W29: =SUMPRODUCT(Adds!$C$78:$W$78,Curves!$BB$15:$BV$15) | X29: =SUMPRODUCT(Adds!$C$78:$X$78,Curves!$BA$15:$BV$15) | Y29: =SUMPRODUCT(Adds!$C$78:$Y$78,Curves!$AZ$15:$BV$15) | Z29: =SUMPRODUCT(Adds!$C$78:$Z$78,Curves!$AY$15:$BV$15) | AA29: =SUMPRODUCT(Adds!$C$78:$AA$78,Curves!$AX$15:$BV$15) | AB29: =SUMPRODUCT(Adds!$C$78:$AB$78,Curves!$AW$15:$BV$15) | AC29: =SUMPRODUCT(Adds!$C$78:$AC$78,Curves!$AV$15:$BV$15) | AD29: =SUMPRODUCT(Adds!$C$78:$AD$78,Curves!$AU$15:$BV$15) | AE29: =SUMPRODUCT(Adds!$C$78:$AE$78,Curves!$AT$15:$BV$15) | AF29: =SUMPRODUCT(Adds!$C$78:$AF$78,Curves!$AS$15:$BV$15) | AG29: =SUMPRODUCT(Adds!$C$78:$AG$78,Curves!$AR$15:$BV$15) | AH29: =SUMPRODUCT(Adds!$C$78:$AH$78,Curves!$AQ$15:$BV$15) | AI29: =SUMPRODUCT(Adds!$C$78:$AI$78,Curves!$AP$15:$BV$15) | AJ29: =SUMPRODUCT(Adds!$C$78:$AJ$78,Curves!$AO$15:$BV$15) | AK29: =SUMPRODUCT(Adds!$C$78:$AK$78,Curves!$AN$15:$BV$15) | AL29: =SUMPRODUCT(Adds!$C$78:$AL$78,Curves!$AM$15:$BV$15) | AM29: =SUMPRODUCT(Adds!$C$78:$AM$78,Curves!$AL$15:$BV$15) | AN29: =SUMPRODUCT(Adds!$C$78:$AN$78,Curves!$AK$15:$BV$15) | AO29: =SUMPRODUCT(Adds!$C$78:$AO$78,Curves!$AJ$15:$BV$15) | AP29: =SUMPRODUCT(Adds!$C$78:$AP$78,Curves!$AI$15:$BV$15) | AQ29: =SUMPRODUCT(Adds!$C$78:$AQ$78,Curves!$AH$15:$BV$15) | AR29: =SUMPRODUCT(Adds!$C$78:$AR$78,Curves!$AG$15:$BV$15) | AS29: =SUMPRODUCT(Adds!$C$78:$AS$78,Curves!$AF$15:$BV$15) | AT29: =SUMPRODUCT(Adds!$C$78:$AT$78,Curves!$AE$15:$BV$15) | AU29: =SUMPRODUCT(Adds!$C$78:$AU$78,Curves!$AD$15:$BV$15) | AV29: =SUMPRODUCT(Adds!$C$78:$AV$78,Curves!$AC$15:$BV$15) | AW29: =SUMPRODUCT(Adds!$C$78:$AW$78,Curves!$AB$15:$BV$15) | AX29: =SUMPRODUCT(Adds!$C$78:$AX$78,Curves!$AA$15:$BV$15) | AY29: =SUMPRODUCT(Adds!$C$78:$AY$78,Curves!$Z$15:$BV$15) | AZ29: =SUMPRODUCT(Adds!$C$78:$AZ$78,Curves!$Y$15:$BV$15) | BA29: =SUMPRODUCT(Adds!$C$78:$BA$78,Curves!$X$15:$BV$15) | BB29: =SUMPRODUCT(Adds!$C$78:$BB$78,Curves!$W$15:$BV$15) | BC29: =SUMPRODUCT(Adds!$C$78:$BC$78,Curves!$V$15:$BV$15) | BD29: =SUMPRODUCT(Adds!$C$78:$BD$78,Curves!$U$15:$BV$15) | BE29: =SUMPRODUCT(Adds!$C$78:$BE$78,Curves!$T$15:$BV$15) | BF29: =SUMPRODUCT(Adds!$C$78:$BF$78,Curves!$S$15:$BV$15) | BG29: =SUMPRODUCT(Adds!$C$78:$BG$78,Curves!$R$15:$BV$15) | BH29: =SUMPRODUCT(Adds!$C$78:$BH$78,Curves!$Q$15:$BV$15) | BI29: =SUMPRODUCT(Adds!$C$78:$BI$78,Curves!$P$15:$BV$15) | BJ29: =SUMPRODUCT(Adds!$C$78:$BJ$78,Curves!$O$15:$BV$15) | BK29: =SUMPRODUCT(Adds!$C$78:$BK$78,Curves!$N$15:$BV$15) | BL29: =SUMPRODUCT(Adds!$C$78:$BL$78,Curves!$M$15:$BV$15) | BM29: =SUMPRODUCT(Adds!$C$78:$BM$78,Curves!$L$15:$BV$15) | BN29: =SUMPRODUCT(Adds!$C$78:$BN$78,Curves!$K$15:$BV$15) | BO29: =SUMPRODUCT(Adds!$C$78:$BO$78,Curves!$J$15:$BV$15) | BP29: =SUMPRODUCT(Adds!$C$78:$BP$78,Curves!$I$15:$BV$15) | BQ29: =SUMPRODUCT(Adds!$C$78:$BQ$78,Curves!$H$15:$BV$15) | BR29: =SUMPRODUCT(Adds!$C$78:$BR$78,Curves!$G$15:$BV$15) | BS29: =SUMPRODUCT(Adds!$C$78:$BS$78,Curves!$F$15:$BV$15) | BT29: =SUMPRODUCT(Adds!$C$78:$BT$78,Curves!$E$15:$BV$15) | BU29: =SUMPRODUCT(Adds!$C$78:$BU$78,Curves!$D$15:$BV$15) | BV29: =SUMPRODUCT(Adds!$C$78:$BV$78,Curves!$C$15:$BV$15)
A31: active | B31: EUROPE|BASIC_A | C31: =Adds!$C$89*Curves!$BV$14 | D31: =SUMPRODUCT(Adds!$C$89:$D$89,Curves!$BU$14:$BV$14) | E31: =SUMPRODUCT(Adds!$C$89:$E$89,Curves!$BT$14:$BV$14) | F31: =SUMPRODUCT(Adds!$C$89:$F$89,Curves!$BS$14:$BV$14) | G31: =SUMPRODUCT(Adds!$C$89:$G$89,Curves!$BR$14:$BV$14) | H31: =SUMPRODUCT(Adds!$C$89:$H$89,Curves!$BQ$14:$BV$14) | I31: =SUMPRODUCT(Adds!$C$89:$I$89,Curves!$BP$14:$BV$14) | J31: =SUMPRODUCT(Adds!$C$89:$J$89,Curves!$BO$14:$BV$14) | K31: =SUMPRODUCT(Adds!$C$89:$K$89,Curves!$BN$14:$BV$14) | L31: =SUMPRODUCT(Adds!$C$89:$L$89,Curves!$BM$14:$BV$14) | M31: =SUMPRODUCT(Adds!$C$89:$M$89,Curves!$BL$14:$BV$14) | N31: =SUMPRODUCT(Adds!$C$89:$N$89,Curves!$BK$14:$BV$14) | O31: =SUMPRODUCT(Adds!$C$89:$O$89,Curves!$BJ$14:$BV$14) | P31: =SUMPRODUCT(Adds!$C$89:$P$89,Curves!$BI$14:$BV$14) | Q31: =SUMPRODUCT(Adds!$C$89:$Q$89,Curves!$BH$14:$BV$14) | R31: =SUMPRODUCT(Adds!$C$89:$R$89,Curves!$BG$14:$BV$14) | S31: =SUMPRODUCT(Adds!$C$89:$S$89,Curves!$BF$14:$BV$14) | T31: =SUMPRODUCT(Adds!$C$89:$T$89,Curves!$BE$14:$BV$14) | U31: =SUMPRODUCT(Adds!$C$89:$U$89,Curves!$BD$14:$BV$14) | V31: =SUMPRODUCT(Adds!$C$89:$V$89,Curves!$BC$14:$BV$14) | W31: =SUMPRODUCT(Adds!$C$89:$W$89,Curves!$BB$14:$BV$14) | X31: =SUMPRODUCT(Adds!$C$89:$X$89,Curves!$BA$14:$BV$14) | Y31: =SUMPRODUCT(Adds!$C$89:$Y$89,Curves!$AZ$14:$BV$14) | Z31: =SUMPRODUCT(Adds!$C$89:$Z$89,Curves!$AY$14:$BV$14) | AA31: =SUMPRODUCT(Adds!$C$89:$AA$89,Curves!$AX$14:$BV$14) | AB31: =SUMPRODUCT(Adds!$C$89:$AB$89,Curves!$AW$14:$BV$14) | AC31: =SUMPRODUCT(Adds!$C$89:$AC$89,Curves!$AV$14:$BV$14) | AD31: =SUMPRODUCT(Adds!$C$89:$AD$89,Curves!$AU$14:$BV$14) | AE31: =SUMPRODUCT(Adds!$C$89:$AE$89,Curves!$AT$14:$BV$14) | AF31: =SUMPRODUCT(Adds!$C$89:$AF$89,Curves!$AS$14:$BV$14) | AG31: =SUMPRODUCT(Adds!$C$89:$AG$89,Curves!$AR$14:$BV$14) | AH31: =SUMPRODUCT(Adds!$C$89:$AH$89,Curves!$AQ$14:$BV$14) | AI31: =SUMPRODUCT(Adds!$C$89:$AI$89,Curves!$AP$14:$BV$14) | AJ31: =SUMPRODUCT(Adds!$C$89:$AJ$89,Curves!$AO$14:$BV$14) | AK31: =SUMPRODUCT(Adds!$C$89:$AK$89,Curves!$AN$14:$BV$14) | AL31: =SUMPRODUCT(Adds!$C$89:$AL$89,Curves!$AM$14:$BV$14) | AM31: =SUMPRODUCT(Adds!$C$89:$AM$89,Curves!$AL$14:$BV$14) | AN31: =SUMPRODUCT(Adds!$C$89:$AN$89,Curves!$AK$14:$BV$14) | AO31: =SUMPRODUCT(Adds!$C$89:$AO$89,Curves!$AJ$14:$BV$14) | AP31: =SUMPRODUCT(Adds!$C$89:$AP$89,Curves!$AI$14:$BV$14) | AQ31: =SUMPRODUCT(Adds!$C$89:$AQ$89,Curves!$AH$14:$BV$14) | AR31: =SUMPRODUCT(Adds!$C$89:$AR$89,Curves!$AG$14:$BV$14) | AS31: =SUMPRODUCT(Adds!$C$89:$AS$89,Curves!$AF$14:$BV$14) | AT31: =SUMPRODUCT(Adds!$C$89:$AT$89,Curves!$AE$14:$BV$14) | AU31: =SUMPRODUCT(Adds!$C$89:$AU$89,Curves!$AD$14:$BV$14) | AV31: =SUMPRODUCT(Adds!$C$89:$AV$89,Curves!$AC$14:$BV$14) | AW31: =SUMPRODUCT(Adds!$C$89:$AW$89,Curves!$AB$14:$BV$14) | AX31: =SUMPRODUCT(Adds!$C$89:$AX$89,Curves!$AA$14:$BV$14) | AY31: =SUMPRODUCT(Adds!$C$89:$AY$89,Curves!$Z$14:$BV$14) | AZ31: =SUMPRODUCT(Adds!$C$89:$AZ$89,Curves!$Y$14:$BV$14) | BA31: =SUMPRODUCT(Adds!$C$89:$BA$89,Curves!$X$14:$BV$14) | BB31: =SUMPRODUCT(Adds!$C$89:$BB$89,Curves!$W$14:$BV$14) | BC31: =SUMPRODUCT(Adds!$C$89:$BC$89,Curves!$V$14:$BV$14) | BD31: =SUMPRODUCT(Adds!$C$89:$BD$89,Curves!$U$14:$BV$14) | BE31: =SUMPRODUCT(Adds!$C$89:$BE$89,Curves!$T$14:$BV$14) | BF31: =SUMPRODUCT(Adds!$C$89:$BF$89,Curves!$S$14:$BV$14) | BG31: =SUMPRODUCT(Adds!$C$89:$BG$89,Curves!$R$14:$BV$14) | BH31: =SUMPRODUCT(Adds!$C$89:$BH$89,Curves!$Q$14:$BV$14) | BI31: =SUMPRODUCT(Adds!$C$89:$BI$89,Curves!$P$14:$BV$14) | BJ31: =SUMPRODUCT(Adds!$C$89:$BJ$89,Curves!$O$14:$BV$14) | BK31: =SUMPRODUCT(Adds!$C$89:$BK$89,Curves!$N$14:$BV$14) | BL31: =SUMPRODUCT(Adds!$C$89:$BL$89,Curves!$M$14:$BV$14) | BM31: =SUMPRODUCT(Adds!$C$89:$BM$89,Curves!$L$14:$BV$14) | BN31: =SUMPRODUCT(Adds!$C$89:$BN$89,Curves!$K$14:$BV$14) | BO31: =SUMPRODUCT(Adds!$C$89:$BO$89,Curves!$J$14:$BV$14) | BP31: =SUMPRODUCT(Adds!$C$89:$BP$89,Curves!$I$14:$BV$14) | BQ31: =SUMPRODUCT(Adds!$C$89:$BQ$89,Curves!$H$14:$BV$14) | BR31: =SUMPRODUCT(Adds!$C$89:$BR$89,Curves!$G$14:$BV$14) | BS31: =SUMPRODUCT(Adds!$C$89:$BS$89,Curves!$F$14:$BV$14) | BT31: =SUMPRODUCT(Adds!$C$89:$BT$89,Curves!$E$14:$BV$14) | BU31: =SUMPRODUCT(Adds!$C$89:$BU$89,Curves!$D$14:$BV$14) | BV31: =SUMPRODUCT(Adds!$C$89:$BV$89,Curves!$C$14:$BV$14)
A32: active yr 1 | B32: EUROPE|BASIC_A | C32: =Adds!$C$89*Curves!$BV$21 | D32: =SUMPRODUCT(Adds!$C$89:$D$89,Curves!$BU$21:$BV$21) | E32: =SUMPRODUCT(Adds!$C$89:$E$89,Curves!$BT$21:$BV$21) | F32: =SUMPRODUCT(Adds!$C$89:$F$89,Curves!$BS$21:$BV$21) | G32: =SUMPRODUCT(Adds!$C$89:$G$89,Curves!$BR$21:$BV$21) | H32: =SUMPRODUCT(Adds!$C$89:$H$89,Curves!$BQ$21:$BV$21) | I32: =SUMPRODUCT(Adds!$C$89:$I$89,Curves!$BP$21:$BV$21) | J32: =SUMPRODUCT(Adds!$C$89:$J$89,Curves!$BO$21:$BV$21) | K32: =SUMPRODUCT(Adds!$C$89:$K$89,Curves!$BN$21:$BV$21) | L32: =SUMPRODUCT(Adds!$C$89:$L$89,Curves!$BM$21:$BV$21) | M32: =SUMPRODUCT(Adds!$C$89:$M$89,Curves!$BL$21:$BV$21) | N32: =SUMPRODUCT(Adds!$C$89:$N$89,Curves!$BK$21:$BV$21) | O32: =SUMPRODUCT(Adds!$C$89:$O$89,Curves!$BJ$21:$BV$21) | P32: =SUMPRODUCT(Adds!$C$89:$P$89,Curves!$BI$21:$BV$21) | Q32: =SUMPRODUCT(Adds!$C$89:$Q$89,Curves!$BH$21:$BV$21) | R32: =SUMPRODUCT(Adds!$C$89:$R$89,Curves!$BG$21:$BV$21) | S32: =SUMPRODUCT(Adds!$C$89:$S$89,Curves!$BF$21:$BV$21) | T32: =SUMPRODUCT(Adds!$C$89:$T$89,Curves!$BE$21:$BV$21) | U32: =SUMPRODUCT(Adds!$C$89:$U$89,Curves!$BD$21:$BV$21) | V32: =SUMPRODUCT(Adds!$C$89:$V$89,Curves!$BC$21:$BV$21) | W32: =SUMPRODUCT(Adds!$C$89:$W$89,Curves!$BB$21:$BV$21) | X32: =SUMPRODUCT(Adds!$C$89:$X$89,Curves!$BA$21:$BV$21) | Y32: =SUMPRODUCT(Adds!$C$89:$Y$89,Curves!$AZ$21:$BV$21) | Z32: =SUMPRODUCT(Adds!$C$89:$Z$89,Curves!$AY$21:$BV$21) | AA32: =SUMPRODUCT(Adds!$C$89:$AA$89,Curves!$AX$21:$BV$21) | AB32: =SUMPRODUCT(Adds!$C$89:$AB$89,Curves!$AW$21:$BV$21) | AC32: =SUMPRODUCT(Adds!$C$89:$AC$89,Curves!$AV$21:$BV$21) | AD32: =SUMPRODUCT(Adds!$C$89:$AD$89,Curves!$AU$21:$BV$21) | AE32: =SUMPRODUCT(Adds!$C$89:$AE$89,Curves!$AT$21:$BV$21) | AF32: =SUMPRODUCT(Adds!$C$89:$AF$89,Curves!$AS$21:$BV$21) | AG32: =SUMPRODUCT(Adds!$C$89:$AG$89,Curves!$AR$21:$BV$21) | AH32: =SUMPRODUCT(Adds!$C$89:$AH$89,Curves!$AQ$21:$BV$21) | AI32: =SUMPRODUCT(Adds!$C$89:$AI$89,Curves!$AP$21:$BV$21) | AJ32: =SUMPRODUCT(Adds!$C$89:$AJ$89,Curves!$AO$21:$BV$21) | AK32: =SUMPRODUCT(Adds!$C$89:$AK$89,Curves!$AN$21:$BV$21) | AL32: =SUMPRODUCT(Adds!$C$89:$AL$89,Curves!$AM$21:$BV$21) | AM32: =SUMPRODUCT(Adds!$C$89:$AM$89,Curves!$AL$21:$BV$21) | AN32: =SUMPRODUCT(Adds!$C$89:$AN$89,Curves!$AK$21:$BV$21) | AO32: =SUMPRODUCT(Adds!$C$89:$AO$89,Curves!$AJ$21:$BV$21) | AP32: =SUMPRODUCT(Adds!$C$89:$AP$89,Curves!$AI$21:$BV$21) | AQ32: =SUMPRODUCT(Adds!$C$89:$AQ$89,Curves!$AH$21:$BV$21) | AR32: =SUMPRODUCT(Adds!$C$89:$AR$89,Curves!$AG$21:$BV$21) | AS32: =SUMPRODUCT(Adds!$C$89:$AS$89,Curves!$AF$21:$BV$21) | AT32: =SUMPRODUCT(Adds!$C$89:$AT$89,Curves!$AE$21:$BV$21) | AU32: =SUMPRODUCT(Adds!$C$89:$AU$89,Curves!$AD$21:$BV$21) | AV32: =SUMPRODUCT(Adds!$C$89:$AV$89,Curves!$AC$21:$BV$21) | AW32: =SUMPRODUCT(Adds!$C$89:$AW$89,Curves!$AB$21:$BV$21) | AX32: =SUMPRODUCT(Adds!$C$89:$AX$89,Curves!$AA$21:$BV$21) | AY32: =SUMPRODUCT(Adds!$C$89:$AY$89,Curves!$Z$21:$BV$21) | AZ32: =SUMPRODUCT(Adds!$C$89:$AZ$89,Curves!$Y$21:$BV$21) | BA32: =SUMPRODUCT(Adds!$C$89:$BA$89,Curves!$X$21:$BV$21) | BB32: =SUMPRODUCT(Adds!$C$89:$BB$89,Curves!$W$21:$BV$21) | BC32: =SUMPRODUCT(Adds!$C$89:$BC$89,Curves!$V$21:$BV$21) | BD32: =SUMPRODUCT(Adds!$C$89:$BD$89,Curves!$U$21:$BV$21) | BE32: =SUMPRODUCT(Adds!$C$89:$BE$89,Curves!$T$21:$BV$21) | BF32: =SUMPRODUCT(Adds!$C$89:$BF$89,Curves!$S$21:$BV$21) | BG32: =SUMPRODUCT(Adds!$C$89:$BG$89,Curves!$R$21:$BV$21) | BH32: =SUMPRODUCT(Adds!$C$89:$BH$89,Curves!$Q$21:$BV$21) | BI32: =SUMPRODUCT(Adds!$C$89:$BI$89,Curves!$P$21:$BV$21) | BJ32: =SUMPRODUCT(Adds!$C$89:$BJ$89,Curves!$O$21:$BV$21) | BK32: =SUMPRODUCT(Adds!$C$89:$BK$89,Curves!$N$21:$BV$21) | BL32: =SUMPRODUCT(Adds!$C$89:$BL$89,Curves!$M$21:$BV$21) | BM32: =SUMPRODUCT(Adds!$C$89:$BM$89,Curves!$L$21:$BV$21) | BN32: =SUMPRODUCT(Adds!$C$89:$BN$89,Curves!$K$21:$BV$21) | BO32: =SUMPRODUCT(Adds!$C$89:$BO$89,Curves!$J$21:$BV$21) | BP32: =SUMPRODUCT(Adds!$C$89:$BP$89,Curves!$I$21:$BV$21) | BQ32: =SUMPRODUCT(Adds!$C$89:$BQ$89,Curves!$H$21:$BV$21) | BR32: =SUMPRODUCT(Adds!$C$89:$BR$89,Curves!$G$21:$BV$21) | BS32: =SUMPRODUCT(Adds!$C$89:$BS$89,Curves!$F$21:$BV$21) | BT32: =SUMPRODUCT(Adds!$C$89:$BT$89,Curves!$E$21:$BV$21) | BU32: =SUMPRODUCT(Adds!$C$89:$BU$89,Curves!$D$21:$BV$21) | BV32: =SUMPRODUCT(Adds!$C$89:$BV$89,Curves!$C$21:$BV$21)
